Workbook

Sheet input
A1: Anno | B1: 2024 | C1: 2023 | D1: 2022 | E1: 2021 | F1: 2020 | G1: 2019 | H1: 2018 | I1: 2017 | J1: 2016 | K1: 2015
A2: A. CREDITI VERSO SOCI | B2: 0 | C2: 0 | D2: 0 | E2: 0 | F2: 0 | G2: 0 | H2: 0 | I2: 0 | J2: 0 | K2: 0
A3: Quota di capitale richiamata | B3: 0 | C3: 0 | D3: 0 | E3: 0 | F3: 0 | G3: 0 | H3: 0 | I3: 0 | J3: 0 | K3: 0
A4: B. TOTALE IMMOBILIZZAZIONI sep.ind. Di quelle conc. In loc. Finanz. | B4: 3738553 | C4: 3878514 | D4: 3703601 | E4: 3856913 | F4: 4103066 | G4: 2316758 | H4: 2364636 | I4: 2327351 | J4: 2514852 | K4: 2145754
A5: B.I. TOTALE IMMOB. IMMATERIALI | B5: 1282 | C5: 1712 | D5: 2744 | E5: 3344 | F5: 11317 | G5: 23177 | H5: 36257 | I5: 49156 | J5: 62552 | K5: 34512
A6: B.I.1. Costi impianto e ampl. | B6: 0 | C6: 0 | D6: 0 | E6: 0 | F6: 0 | G6: 0 | H6: 0 | I6: 0 | J6: 0 | K6: 0
A7: B.I.2. Costi ricerca e pubb. | B7: 0 | C7: 0 | D7: 0 | E7: 0 | F7: 0 | G7: 0 | H7: 0 | I7: 0 | J7: 0 | K7: 0
A8: B.I.3. Diritti brevetto ind. | B8: 661 | C8: 1049 | D8: 2040 | E8: 3157 | F8: 10942 | G8: 17523 | H8: 25323 | I8: 33879 | J8: 0 | K8: 0
A9: B.I.4. Concessioni, licenze | B9: 621 | C9: 663 | D9: 704 | E9: 0 | F9: 0 | G9: 0 | H9: 0 | I9: 0 | J9: 0 | K9: 0
A10: B.I.5. Avviamento/Differenza di consolidamento | B10: 0 | C10: 0 | D10: 0 | E10: 0 | F10: 0 | G10: 0 | H10: 0 | I10: 0 | J10: 0 | K10: 0
A11: di cui: Avviamento | B11: 0 | C11: 0 | D11: 0 | E11: 0 | F11: 0 | G11: 0 | H11: 0 | I11: 0 | J11: 0 | K11: 0
A12: B.I.6. Imm. in corso | B12: 0 | C12: 0 | D12: 0 | E12: 0 | F12: 0 | G12: 0 | H12: 0 | I12: 0 | J12: 0 | K12: 0
... A93: TOTALE ATTIVO | B93: 6479233 | C93: 6929645 | D93: 6517697 | E93: 6230020 | F93: 6320161 | G93: 4619390 | H93: 4606793 | I93: 4491663 | J93: 4514623 | K93: 4176270
A94: Passivo
A95: PATRIMONIO NETTO
A96: A. TOTALE PATRIMONIO NETTO | B96: 3395702 | C96: 3347713 | D96: 3324149 | E96: 3186130 | F96: 3095198 | G96: 1226155 | H96: 1184635 | I96: 1121927 | J96: 1091757 | K96: 1018727
A97: A.I. Capitale sociale | B97: 110000 | C97: 110000 | D97: 110000 | E97: 110000 | F97: 110000 | G97: 110000 | H97: 110000 | I97: 110000 | J97: 110000 | K97: 110000
A98: di cui: Versamenti soci in c/capitale | B98: 0 | C98: 0 | D98: 0 | E98: 0 | F98: 0 | G98: 0 | H98: 0 | I98: 0 | J98: 0 | K98: 0
A99: di cui: Versamenti in c/futuro aumento di capitale | B99: 0 | C99: 0 | D99: 0 | E99: 0 | F99: 0 | G99: 0 | H99: 0 | I99: 0 | J99: 0 | K99: 0
A100: di cui: Versamenti in c/capitale | B100: 0 | C100: 0 | D100: 0 | E100: 0 | F100: 0 | G100: 0 | H100: 0 | I100: 0 | J100: 0 | K100: 0
A101: di cui: Versamenti a copertura perdite | B101: 0 | C101: 0 | D101: 0 | E101: 0 | F101: 0 | G101: 0 | H101: 0 | I101: 0 | J101: 0 | K101: 0
A102: A.II. Riserva da sovrapprezzo | B102: 0 | C102: 0 | D102: 0 | E102: 0 | F102: 0 | G102: 0 | H102: 0 | I102: 0 | J102: 0 | K102: 0
A103: A.III. Riserva di rivalutazione | B103: 1841883 | C103: 1841883 | D103: 1841883 | E103: 1841883 | F103: 1841883 | G103: 0 | H103: 0 | I103: 0 | J103: 0 | K103: 0
A104: A.IV. Riserva legale | B104: 22000 | C104: 22000 | D104: 22000 | E104: 22000 | F104: 22000 | G104: 22000 | H104: 22000 | I104: 22000 | J104: 22000 | K104: 22000
A105: A.V. Riserva statutaria | B105: 0 | C105: 0 | D105: 0 | E105: 0 | F105: 0 | G105: 0 | H105: 0 | I105: 0 | J105: 0 | K105: 0
A106: Riserva azioni proprie | B106: 0 | C106: 0 | D106: 0 | E106: 0 | F106: 0 | G106: 0 | H106: 0 | I106: 0 | J106: 0 | K106: 0
A107: A.VI. Altre riserve | B107: 240239 | C107: 191213 | D107: 204749 | E107: 204748 | F107: 223037 | G107: 161812 | H107: 161812 | I107: 161812 | J107: 161812 | K107: 161812
... A126: C. TRATTAMENTO DI FINE RAPPORTO | B126: 254425 | C126: 218390 | D126: 277417 | E126: 260333 | F126: 214928 | G126: 226683 | H126: 206901 | I126: 178930 | J126: 182052 | K126: 155271
A127: Debiti
A128: D. TOTALE DEBITI | B128: 2784779 | C128: 3320300 | D128: 2893107 | E128: 2763325 | F128: 2983247 | G128: 3166487 | H128: 3214928 | I128: 3190806 | J128: 3240814 | K128: 2991573
A129: D.1. Obblig.ni entro | B129: 0 | C129: 0 | D129: 0 | E129: 0 | F129: 0 | G129: 0 | H129: 0 | I129: 0 | J129: 0 | K129: 0
A130: D.1. Obblig.ni oltre | B130: 0 | C130: 0 | D130: 0 | E130: 0 | F130: 0 | G130: 0 | H130: 0 | I130: 0 | J130: 0 | K130: 0
A131: D.2. Obblig.ni convert. entro | B131: 0 | C131: 0 | D131: 0 | E131: 0 | F131: 0 | G131: 0 | H131: 0 | I131: 0 | J131: 0 | K131: 0
A132: D.2. Obblig.ni convert. oltre. | B132: 0 | C132: 0 | D132: 0 | E132: 0 | F132: 0 | G132: 0 | H132: 0 | I132: 0 | J132: 0 | K132: 0
A133: D.3. Soci per Finanziamenti entro | B133: 0 | C133: 0 | D133: 0 | E133: 0 | F133: 0 | G133: 0 | H133: 0 | I133: 0 | J133: 0 | K133: 0
A134: D.3. Soci per Finanziamenti oltre | B134: 0 | C134: 0 | D134: 0 | E134: 0 | F134: 0 | G134: 0 | H134: 0 | I134: 0 | J134: 0 | K134: 0
A135: D.4. Banche entro l'esercizio | B135: 760422 | C135: 827770 | D135: 342948 | E135: 283856 | F135: 497144 | G135: 1537431 | H135: 1449053 | I135: 1177500 | J135: 1117556 | K135: 886758
A136: D.4. Banche oltre l'esercizio | B136: 761905 | C136: 1159885 | D136: 1231437 | E136: 1405442 | F136: 1760602 | G136: 787742 | H136: 1000827 | I136: 1175475 | J136: 1379696 | K136: 1316760
A137: D.5. Altri finanziatori entro | B137: 0 | C137: 0 | D137: 0 | E137: 0 | F137: 0 | G137: 0 | H137: 0 | I137: 0 | J137: 0 | K137: 0
A138: D.5. Altri finanziatori oltre | B138: 0 | C138: 0 | D138: 0 | E138: 0 | F138: 0 | G138: 0 | H138: 0 | I138: 0 | J138: 0 | K138: 0
A139: D.6. Acconti entro | B139: 1220 | C139: 1473 | D139: 448 | E139: 0 | F139: 0 | G139: 0 | H139: 0 | I139: 0 | J139: 0 | K139: 0
... A166: TOTALE CONTI D'ORDINE | B166: 0 | C166: 0 | D166: 0 | E166: 0 | F166: 0 | G166: 0 | H166: 0 | I166: 0 | J166: 0 | K166: 0
A167: Conto economico
A168: A. TOT. VAL. DELLA PRODUZIONE | B168: 10717935 | C168: 10487862 | D168: 10236022 | E168: 7860203 | F168: 7465080 | G168: 8218588 | H168: 7827812 | I168: 7629760 | J168: 7425024 | K168: 7064459
A169: A.1. Ricavi vendite e prestazioni | B169: 10748162 | C169: 10444688 | D169: 9771059 | E169: 8043227 | F169: 7320518 | G169: 8324962 | H169: 7689620 | I169: 7598634 | J169: 7383103 | K169: 6865060
A170: A.2. Var. rimanenze prodotti | B170: -64037 | C170: -33861 | D170: 390341 | E170: -226939 | F170: 114306 | G170: -152382 | H170: 100126 | I170: -48118 | J170: 581 | K170: 162630
A171: A.3. Variazione lavori | B171: 0 | C171: 0 | D171: 0 | E171: 0 | F171: 0 | G171: 0 | H171: 0 | I171: 0 | J171: 0 | K171: 0
A172: A.2. + A.3. Totale Variazioni | B172: -64037 | C172: -33861 | D172: 390341 | E172: -226939 | F172: 114306 | G172: -152382 | H172: 100126 | I172: -48118 | J172: 581 | K172: 162630
A173: A.4. Incrementi di immob. | B173: 0 | C173: 0 | D173: 0 | E173: 0 | F173: 0 | G173: 0 | H173: 0 | I173: 0 | J173: 0 | K173: 0
A174: A.5. Altri ricavi | B174: 33810 | C174: 77035 | D174: 74622 | E174: 43915 | F174: 30256 | G174: 46008 | H174: 38066 | I174: 79244 | J174: 41340 | K174: 36769
A175: Contributi in conto esercizio | B175: 0 | C175: 19472 | D175: 48345 | E175: 654 | F175: 1053 | G175: 0 | H175: 0 | I175: 0 | J175: 0 | K175: 0
A176: B. COSTI DELLA PRODUZIONE | B176: 10509139 | C176: 10330643 | D176: 9998947 | E176: 7701303 | F176: 7385766 | G176: 8117210 | H176: 7698777 | I176: 7537360 | J176: 7255191 | K176: 6502057
A177: B.6. Materie prime e consumo | B177: 8042729 | C177: 7909736 | D177: 7635079 | E177: 5561813 | F177: 5319152 | G177: 6064470 | H177: 5643875 | I177: 5648984 | J177: 5503638 | K177: 4946714
A178: B.7. Servizi | B178: 1042479 | C178: 1055045 | D178: 1049603 | E178: 888400 | F178: 790856 | G178: 817799 | H178: 794983 | I178: 788067 | J178: 755578 | K178: 611124
A179: B.8. Godimento beni di terzi | B179: 18000 | C179: 18000 | D179: 18000 | E179: 31757 | F179: 70447 | G179: 70304 | H179: 84557 | I179: 99865 | J179: 83190 | K179: 35455
... A246: UTILE/PERDITA DI ESERCIZIO di pert. di TERZI | B246: 0 | C246: 0 | D246: 0 | E246: 0 | F246: 0 | G246: 0 | H246: 0 | I246: 0 | J246: 0 | K246: 0
A247: TROCKNER SEBASTIAN S.R.L.
A248: 02495580215

Sheet case
A1: SP attivo | B1: =input!B1 -> 2024 | C1: =input!C1 -> 2023 | D1: =input!D1 -> 2022 | E1: =input!E1 -> 2021 | F1: =input!F1 -> 2020 | G1: =input!G1 -> 2019 | H1: =input!H1 -> 2018 | I1: =input!I1 -> 2017 | ... K1: =input!K1 -> 2015 | M1: Segno | N1: Riclassificazione
A2: =input!A2 -> A. CREDITI VERSO SOCI | B2: =$M2*input!B2 -> 0 | C2: =$M2*input!C2 -> 0 | D2: =$M2*input!D2 -> 0 | E2: =$M2*input!E2 -> 0 | F2: =$M2*input!F2 -> 0 | G2: =$M2*input!G2 -> 0 | H2: =$M2*input!H2 -> 0 | I2: =$M2*input!I2 -> 0 | ... K2: =$M2*input!K2 -> 0 | M2: -1 | N2: Finanziamenti netti vs soci e controllanti
A3: =input!A3 -> Quota di capitale richiamata | B3: =$M3*input!B3 -> 0 | C3: =$M3*input!C3 -> 0 | D3: =$M3*input!D3 -> 0 | E3: =$M3*input!E3 -> 0 | F3: =$M3*input!F3 -> 0 | G3: =$M3*input!G3 -> 0 | H3: =$M3*input!H3 -> 0 | I3: =$M3*input!I3 -> 0 | ... K3: =$M3*input!K3 -> 0 | M3: 1
A5: =input!A4 -> B. TOTALE IMMOBILIZZAZIONI sep.ind. Di quelle conc. In loc. Finanz. | B5: =$M5*input!B4 -> 3738553 | C5: =$M5*input!C4 -> 3878514 | D5: =$M5*input!D4 -> 3703601 | E5: =$M5*input!E4 -> 3856913 | F5: =$M5*input!F4 -> 4103066 | G5: =$M5*input!G4 -> 2316758 | H5: =$M5*input!H4 -> 2364636 | I5: =$M5*input!I4 -> 2327351 | ... K5: =$M5*input!K4 -> 2145754 | M5: 1
A6: =input!A5 -> B.I. TOTALE IMMOB. IMMATERIALI | B6: =$M6*input!B5 -> 1282 | C6: =$M6*input!C5 -> 1712 | D6: =$M6*input!D5 -> 2744 | E6: =$M6*input!E5 -> 3344 | F6: =$M6*input!F5 -> 11317 | G6: =$M6*input!G5 -> 23177 | H6: =$M6*input!H5 -> 36257 | I6: =$M6*input!I5 -> 49156 | ... K6: =$M6*input!K5 -> 34512 | M6: 1 | N6: Immobilizzazioni immateriali nette
A7: =input!A6 -> B.I.1. Costi impianto e ampl. | B7: =$M7*input!B6 -> 0 | C7: =$M7*input!C6 -> 0 | D7: =$M7*input!D6 -> 0 | E7: =$M7*input!E6 -> 0 | F7: =$M7*input!F6 -> 0 | G7: =$M7*input!G6 -> 0 | H7: =$M7*input!H6 -> 0 | I7: =$M7*input!I6 -> 0 | ... K7: =$M7*input!K6 -> 0 | M7: 1
A8: =input!A7 -> B.I.2. Costi ricerca e pubb. | B8: =$M8*input!B7 -> 0 | C8: =$M8*input!C7 -> 0 | D8: =$M8*input!D7 -> 0 | E8: =$M8*input!E7 -> 0 | F8: =$M8*input!F7 -> 0 | G8: =$M8*input!G7 -> 0 | H8: =$M8*input!H7 -> 0 | I8: =$M8*input!I7 -> 0 | ... K8: =$M8*input!K7 -> 0 | M8: 1
A9: =input!A8 -> B.I.3. Diritti brevetto ind. | B9: =$M9*input!B8 -> 661 | C9: =$M9*input!C8 -> 1049 | D9: =$M9*input!D8 -> 2040 | E9: =$M9*input!E8 -> 3157 | F9: =$M9*input!F8 -> 10942 | G9: =$M9*input!G8 -> 17523 | H9: =$M9*input!H8 -> 25323 | I9: =$M9*input!I8 -> 33879 | ... K9: =$M9*input!K8 -> 0 | M9: 1
A10: =input!A9 -> B.I.4. Concessioni, licenze | B10: =$M10*input!B9 -> 621 | C10: =$M10*input!C9 -> 663 | D10: =$M10*input!D9 -> 704 | E10: =$M10*input!E9 -> 0 | F10: =$M10*input!F9 -> 0 | G10: =$M10*input!G9 -> 0 | H10: =$M10*input!H9 -> 0 | I10: =$M10*input!I9 -> 0 | ... K10: =$M10*input!K9 -> 0 | M10: 1
A11: =input!A10 -> B.I.5. Avviamento/Differenza di consolidamento | B11: =$M11*input!B10 -> 0 | C11: =$M11*input!C10 -> 0 | D11: =$M11*input!D10 -> 0 | E11: =$M11*input!E10 -> 0 | F11: =$M11*input!F10 -> 0 | G11: =$M11*input!G10 -> 0 | H11: =$M11*input!H10 -> 0 | I11: =$M11*input!I10 -> 0 | ... K11: =$M11*input!K10 -> 0 | M11: 1
A12: =input!A11 -> di cui: Avviamento | B12: =$M12*input!B11 -> 0 | C12: =$M12*input!C11 -> 0 | D12: =$M12*input!D11 -> 0 | E12: =$M12*input!E11 -> 0 | F12: =$M12*input!F11 -> 0 | G12: =$M12*input!G11 -> 0 | H12: =$M12*input!H11 -> 0 | I12: =$M12*input!I11 -> 0 | ... K12: =$M12*input!K11 -> 0 | M12: 1
A13: =input!A12 -> B.I.6. Imm. in corso | B13: =$M13*input!B12 -> 0 | C13: =$M13*input!C12 -> 0 | D13: =$M13*input!D12 -> 0 | E13: =$M13*input!E12 -> 0 | F13: =$M13*input!F12 -> 0 | G13: =$M13*input!G12 -> 0 | H13: =$M13*input!H12 -> 0 | I13: =$M13*input!I12 -> 0 | ... K13: =$M13*input!K12 -> 0 | M13: 1
A14: =input!A13 -> B.I.7. Altre immobiliz. Immateriali | B14: =$M14*input!B13 -> 0 | C14: =$M14*input!C13 -> 0 | D14: =$M14*input!D13 -> 0 | E14: =$M14*input!E13 -> 187 | F14: =$M14*input!F13 -> 375 | G14: =$M14*input!G13 -> 5654 | H14: =$M14*input!H13 -> 10934 | I14: =$M14*input!I13 -> 15277 | ... K14: =$M14*input!K13 -> 0 | M14: 1
A15: =input!A14 -> Fondo amm.to Immob. Immateriali | B15: =$M15*input!B14 -> 0 | C15: =$M15*input!C14 -> 0 | D15: =$M15*input!D14 -> 118560 | E15: =$M15*input!E14 -> 117215 | F15: =$M15*input!F14 -> 107873 | G15: =$M15*input!G14 -> 93505 | H15: =$M15*input!H14 -> 79347 | I15: =$M15*input!I14 -> 64882 | ... K15: =$M15*input!K14 -> 42394 | M15: 1
A16: =input!A15 -> B.II. TOTALE IMMOB. MATERIALI | B16: =$M16*input!B15 -> 3603771 | C16: =$M16*input!C15 -> 3742802 | D16: =$M16*input!D15 -> 3566385 | E16: =$M16*input!E15 -> 3648169 | F16: =$M16*input!F15 -> 3886349 | G16: =$M16*input!G15 -> 2087581 | H16: =$M16*input!H15 -> 2124193 | I16: =$M16*input!I15 -> 2173291 | ... K16: =$M16*input!K15 -> 2109242 | M16: 1 | N16: Immobilizzazioni materiali nette
A17: =input!A16 -> di cui: Beni materiali concessi in locazione finanziaria | B17: =$M17*input!B16 -> 0 | C17: =$M17*input!C16 -> 0 | D17: =$M17*input!D16 -> 0 | E17: =$M17*input!E16 -> 0 | F17: =$M17*input!F16 -> 0 | G17: =$M17*input!G16 -> 0 | H17: =$M17*input!H16 -> 0 | I17: =$M17*input!I16 -> 0 | ... K17: =$M17*input!K16 -> 0 | M17: 1
A18: =input!A17 -> B.II.1. Terreni e fabbricati | B18: =$M18*input!B17 -> 2893415 | C18: =$M18*input!C17 -> 2953285 | D18: =$M18*input!D17 -> 2984293 | E18: =$M18*input!E17 -> 3092147 | F18: =$M18*input!F17 -> 3200001 | G18: =$M18*input!G17 -> 1359175 | H18: =$M18*input!H17 -> 1417257 | I18: =$M18*input!I17 -> 1475508 | ... K18: =$M18*input!K17 -> 0 | M18: 1
A19: =input!A18 -> B.II.2. Impianti | B19: =$M19*input!B18 -> 474391 | C19: =$M19*input!C18 -> 508101 | D19: =$M19*input!D18 -> 317950 | E19: =$M19*input!E18 -> 381250 | F19: =$M19*input!F18 -> 461837 | G19: =$M19*input!G18 -> 482335 | H19: =$M19*input!H18 -> 488838 | I19: =$M19*input!I18 -> 570161 | ... K19: =$M19*input!K18 -> 0 | M19: 1
A20: =input!A19 -> B.II.3. Attrez. industriali | B20: =$M20*input!B19 -> 398 | C20: =$M20*input!C19 -> 498 | D20: =$M20*input!D19 -> 697 | E20: =$M20*input!E19 -> 1552 | F20: =$M20*input!F19 -> 2030 | G20: =$M20*input!G19 -> 3465 | H20: =$M20*input!H19 -> 4900 | I20: =$M20*input!I19 -> 6335 | ... K20: =$M20*input!K19 -> 0 | M20: 1
A21: =input!A20 -> B.II.4. Altri beni | B21: =$M21*input!B20 -> 216674 | C21: =$M21*input!C20 -> 262025 | D21: =$M21*input!D20 -> 247367 | E21: =$M21*input!E20 -> 152641 | F21: =$M21*input!F20 -> 211902 | G21: =$M21*input!G20 -> 207968 | H21: =$M21*input!H20 -> 205564 | I21: =$M21*input!I20 -> 114236 | ... K21: =$M21*input!K20 -> 0 | M21: 1
A22: =input!A21 -> B.II.5. Imm. in corso/acconti | B22: =$M22*input!B21 -> 18893 | C22: =$M22*input!C21 -> 18893 | D22: =$M22*input!D21 -> 16078 | E22: =$M22*input!E21 -> 20579 | F22: =$M22*input!F21 -> 10579 | G22: =$M22*input!G21 -> 34638 | H22: =$M22*input!H21 -> 7634 | I22: =$M22*input!I21 -> 7051 | ... K22: =$M22*input!K21 -> 0 | M22: 1
A23: =input!A22 -> Fondo amm.to Immob. Materiali | B23: =$M23*input!B22 -> 0 | C23: =$M23*input!C22 -> 0 | D23: =$M23*input!D22 -> 1987737 | E23: =$M23*input!E22 -> 1727444 | F23: =$M23*input!F22 -> 1533329 | G23: =$M23*input!G22 -> 2413573 | H23: =$M23*input!H22 -> 2278310 | I23: =$M23*input!I22 -> 2040155 | ... K23: =$M23*input!K22 -> 1639566 | M23: 1
A24: =input!A23 -> B.III. TOTALE IMMOB. FINANZIARIE | B24: =$M24*input!B23 -> 133500 | C24: =$M24*input!C23 -> 134000 | D24: =$M24*input!D23 -> 134472 | E24: =$M24*input!E23 -> 205400 | F24: =$M24*input!F23 -> 205400 | G24: =$M24*input!G23 -> 206000 | H24: =$M24*input!H23 -> 204186 | I24: =$M24*input!I23 -> 104904 | ... K24: =$M24*input!K23 -> 2000 | M24: 1
A25: =input!A24 -> di cui: esigibili entro l'esercizio successivo | B25: =$M25*input!B24 -> 1500 | C25: =$M25*input!C24 -> 77000 | D25: =$M25*input!D24 -> 102472 | E25: =$M25*input!E24 -> 173400 | F25: =$M25*input!F24 -> 173400 | G25: =$M25*input!G24 -> 174000 | H25: =$M25*input!H24 -> 202186 | I25: =$M25*input!I24 -> 102904 | ... K25: =$M25*input!K24 -> 0 | M25: 1
A26: =input!A25 -> B.III.1. TOT Partecipazioni | B26: =$M26*input!B25 -> 72000 | C26: =$M26*input!C25 -> 57000 | D26: =$M26*input!D25 -> 32000 | E26: =$M26*input!E25 -> 32000 | F26: =$M26*input!F25 -> 32000 | G26: =$M26*input!G25 -> 32000 | H26: =$M26*input!H25 -> 2000 | I26: =$M26*input!I25 -> 2000 | ... K26: =$M26*input!K25 -> 2000 | M26: 1
A27: =input!A26 -> B.III.1.a. Imprese controllate | B27: =$M27*input!B26 -> 0 | C27: =$M27*input!C26 -> 0 | D27: =$M27*input!D26 -> 0 | E27: =$M27*input!E26 -> 0 | F27: =$M27*input!F26 -> 0 | G27: =$M27*input!G26 -> 0 | H27: =$M27*input!H26 -> 0 | I27: =$M27*input!I26 -> 0 | ... K27: =$M27*input!K26 -> 0 | M27: 1 | N27: Partecipazioni
A28: =input!A27 -> B.III.1.b. Imprese collegate | B28: =$M28*input!B27 -> 0 | C28: =$M28*input!C27 -> 0 | D28: =$M28*input!D27 -> 0 | E28: =$M28*input!E27 -> 0 | F28: =$M28*input!F27 -> 0 | G28: =$M28*input!G27 -> 0 | H28: =$M28*input!H27 -> 0 | I28: =$M28*input!I27 -> 0 | ... K28: =$M28*input!K27 -> 0 | M28: 1 | N28: Partecipazioni
A29: =input!A28 -> B.III.1.c. Imprese controllanti | B29: =$M29*input!B28 -> 0 | C29: =$M29*input!C28 -> 0 | D29: =$M29*input!D28 -> 0 | E29: =$M29*input!E28 -> 0 | F29: =$M29*input!F28 -> 0 | G29: =$M29*input!G28 -> 0 | H29: =$M29*input!H28 -> 0 | I29: =$M29*input!I28 -> 0 | ... K29: =$M29*input!K28 -> 0 | M29: 1 | N29: Azioni proprie e partecipazioni in controllanti
A30: =input!A29 -> B.III.1.d. In imprese sottoposte al controllo delle controllanti | B30: =$M30*input!B29 -> 0 | C30: =$M30*input!C29 -> 0 | D30: =$M30*input!D29 -> 0 | E30: =$M30*input!E29 -> 0 | F30: =$M30*input!F29 -> 0 | G30: =$M30*input!G29 -> 0 | H30: =$M30*input!H29 -> 0 | I30: =$M30*input!I29 -> 0 | ... K30: =$M30*input!K29 -> 0 | M30: 1 | N30: Azioni proprie e partecipazioni in controllanti
A31: =input!A30 -> B.III.1.d.bis. Altre imprese | B31: =$M31*input!B30 -> 72000 | C31: =$M31*input!C30 -> 57000 | D31: =$M31*input!D30 -> 32000 | E31: =$M31*input!E30 -> 32000 | F31: =$M31*input!F30 -> 32000 | G31: =$M31*input!G30 -> 32000 | H31: =$M31*input!H30 -> 2000 | I31: =$M31*input!I30 -> 2000 | ... K31: =$M31*input!K30 -> 2000 | M31: 1 | N31: Partecipazioni
A32: =input!A31 -> B.III.2. TOT CREDITI Imm. Fin. | B32: =$M32*input!B31 -> 61500 | C32: =$M32*input!C31 -> 77000 | D32: =$M32*input!D31 -> 102472 | E32: =$M32*input!E31 -> 173400 | F32: =$M32*input!F31 -> 173400 | G32: =$M32*input!G31 -> 174000 | H32: =$M32*input!H31 -> 202186 | I32: =$M32*input!I31 -> 102904 | ... K32: =$M32*input!K31 -> 0 | M32: 1
A33: =input!A32 -> B.III.2.a. Cred. vs Controllate entro | B33: =$M33*input!B32 -> 0 | C33: =$M33*input!C32 -> 0 | D33: =$M33*input!D32 -> 0 | E33: =$M33*input!E32 -> 0 | F33: =$M33*input!F32 -> 0 | G33: =$M33*input!G32 -> 0 | H33: =$M33*input!H32 -> 0 | I33: =$M33*input!I32 -> 0 | ... K33: =$M33*input!K32 -> 0 | M33: 1 | N33: Crediti vs controllate e collegate
A34: =input!A33 -> B.III.2.a. Cred. vs Controllate oltre | B34: =$M34*input!B33 -> 0 | C34: =$M34*input!C33 -> 0 | D34: =$M34*input!D33 -> 0 | E34: =$M34*input!E33 -> 0 | F34: =$M34*input!F33 -> 0 | G34: =$M34*input!G33 -> 0 | H34: =$M34*input!H33 -> 0 | I34: =$M34*input!I33 -> 0 | ... K34: =$M34*input!K33 -> 0 | M34: 1 | N34: Crediti vs controllate e collegate
A35: =input!A34 -> B.III.2.b. Cred. vs Collegate entro | B35: =$M35*input!B34 -> 0 | C35: =$M35*input!C34 -> 0 | D35: =$M35*input!D34 -> 0 | E35: =$M35*input!E34 -> 0 | F35: =$M35*input!F34 -> 0 | G35: =$M35*input!G34 -> 0 | H35: =$M35*input!H34 -> 0 | I35: =$M35*input!I34 -> 0 | ... K35: =$M35*input!K34 -> 0 | M35: 1 | N35: Crediti vs controllate e collegate
A36: =input!A35 -> B.III.2.b. Cred. vs Collegate oltre | B36: =$M36*input!B35 -> 0 | C36: =$M36*input!C35 -> 0 | D36: =$M36*input!D35 -> 0 | E36: =$M36*input!E35 -> 0 | F36: =$M36*input!F35 -> 0 | G36: =$M36*input!G35 -> 0 | H36: =$M36*input!H35 -> 0 | I36: =$M36*input!I35 -> 0 | ... K36: =$M36*input!K35 -> 0 | M36: 1 | N36: Crediti vs controllate e collegate
A37: =input!A36 -> B.III.2.c. Cred. vs Controllanti entro | B37: =$M37*input!B36 -> 0 | C37: =$M37*input!C36 -> 0 | D37: =$M37*input!D36 -> 0 | E37: =$M37*input!E36 -> 0 | F37: =$M37*input!F36 -> 0 | G37: =$M37*input!G36 -> 0 | H37: =$M37*input!H36 -> 0 | I37: =$M37*input!I36 -> 0 | ... K37: =$M37*input!K36 -> 0 | M37: -1 | N37: Finanziamenti netti vs soci e controllanti
A38: =input!A37 -> B.III.2.c. Cred. vs Controllanti oltre | B38: =$M38*input!B37 -> 0 | C38: =$M38*input!C37 -> 0 | D38: =$M38*input!D37 -> 0 | E38: =$M38*input!E37 -> 0 | F38: =$M38*input!F37 -> 0 | G38: =$M38*input!G37 -> 0 | H38: =$M38*input!H37 -> 0 | I38: =$M38*input!I37 -> 0 | ... K38: =$M38*input!K37 -> 0 | M38: -1 | N38: Finanziamenti netti vs soci e controllanti
A39: =input!A38 -> B.III.2.d. Cred. vs imprese sottoposte al controllo delle controllanti entro | B39: =$M39*input!B38 -> 0 | C39: =$M39*input!C38 -> 0 | D39: =$M39*input!D38 -> 0 | E39: =$M39*input!E38 -> 0 | F39: =$M39*input!F38 -> 0 | G39: =$M39*input!G38 -> 0 | H39: =$M39*input!H38 -> 0 | I39: =$M39*input!I38 -> 0 | ... K39: =$M39*input!K38 -> 0 | M39: -1 | N39: Finanziamenti netti vs soci e controllanti
A40: =input!A39 -> B.III.2.d. Cred. vs imprese sottoposte al controllo delle controllanti oltre | B40: =$M40*input!B39 -> 0 | C40: =$M40*input!C39 -> 0 | D40: =$M40*input!D39 -> 0 | E40: =$M40*input!E39 -> 0 | F40: =$M40*input!F39 -> 0 | G40: =$M40*input!G39 -> 0 | H40: =$M40*input!H39 -> 0 | I40: =$M40*input!I39 -> 0 | ... K40: =$M40*input!K39 -> 0 | M40: -1 | N40: Finanziamenti netti vs soci e controllanti
A41: =input!A40 -> B.III.2.d.bis. Cred. vs Altri entro | B41: =$M41*input!B40 -> 1500 | C41: =$M41*input!C40 -> 77000 | D41: =$M41*input!D40 -> 102472 | E41: =$M41*input!E40 -> 173400 | F41: =$M41*input!F40 -> 173400 | G41: =$M41*input!G40 -> 174000 | H41: =$M41*input!H40 -> 202186 | I41: =$M41*input!I40 -> 102904 | ... K41: =$M41*input!K40 -> 0 | M41: 1 | N41: Crediti diversi
A42: =input!A41 -> B.III.2.d.bis Cred. vs Altri oltre | B42: =$M42*input!B41 -> 60000 | C42: =$M42*input!C41 -> 0 | D42: =$M42*input!D41 -> 0 | E42: =$M42*input!E41 -> 0 | F42: =$M42*input!F41 -> 0 | G42: =$M42*input!G41 -> 0 | H42: =$M42*input!H41 -> 0 | I42: =$M42*input!I41 -> 0 | ... K42: =$M42*input!K41 -> 0 | M42: 1 | N42: Crediti diversi
A43: =input!A42 -> B.III. CREDITI FIN. A BREVE | B43: =$M43*input!B42 -> 1500 | C43: =$M43*input!C42 -> 77000 | D43: =$M43*input!D42 -> 102472 | E43: =$M43*input!E42 -> 173400 | F43: =$M43*input!F42 -> 173400 | G43: =$M43*input!G42 -> 174000 | H43: =$M43*input!H42 -> 202186 | I43: =$M43*input!I42 -> 102904 | ... K43: =$M43*input!K42 -> 0 | M43: 1
A44: =input!A43 -> B.III. CREDITI FIN. A OLTRE | B44: =$M44*input!B43 -> 60000 | C44: =$M44*input!C43 -> 0 | D44: =$M44*input!D43 -> 0 | E44: =$M44*input!E43 -> 0 | F44: =$M44*input!F43 -> 0 | G44: =$M44*input!G43 -> 0 | H44: =$M44*input!H43 -> 0 | I44: =$M44*input!I43 -> 0 | ... K44: =$M44*input!K43 -> 0 | M44: 1
A45: =input!A44 -> B.III.3. Altri titoli | B45: =$M45*input!B44 -> 0 | C45: =$M45*input!C44 -> 0 | D45: =$M45*input!D44 -> 0 | E45: =$M45*input!E44 -> 0 | F45: =$M45*input!F44 -> 0 | G45: =$M45*input!G44 -> 0 | H45: =$M45*input!H44 -> 0 | I45: =$M45*input!I44 -> 0 | ... K45: =$M45*input!K44 -> 0 | M45: 1 | N45: Partecipazioni
A46: =input!A45 -> B.III.3.bis. Azioni proprie | B46: =$M46*input!B45 -> 0 | C46: =$M46*input!C45 -> 0 | D46: =$M46*input!D45 -> 0 | E46: =$M46*input!E45 -> 0 | F46: =$M46*input!F45 -> 0 | G46: =$M46*input!G45 -> 0 | H46: =$M46*input!H45 -> 0 | I46: =$M46*input!I45 -> 0 | ... K46: =$M46*input!K45 -> 0 | M46: -1 | N46: Azioni proprie e partecipazioni in controllanti
A47: =input!A46 -> B.III.4. Strumenti finanziari derivati attivi | B47: =$M47*input!B46 -> 0 | C47: =$M47*input!C46 -> 0 | D47: =$M47*input!D46 -> 0 | E47: =$M47*input!E46 -> 0 | F47: =$M47*input!F46 -> 0 | G47: =$M47*input!G46 -> 0 | H47: =$M47*input!H46 -> 0 | I47: =$M47*input!I46 -> 0 | ... K47: =$M47*input!K46 -> 0 | M47: 1 | N47: Strumenti derivati attivi
A48: =input!A47 -> Azioni proprie DI CUI: Val nominale | B48: =$M48*input!B47 -> 0 | C48: =$M48*input!C47 -> 0 | D48: =$M48*input!D47 -> 0 | E48: =$M48*input!E47 -> 0 | F48: =$M48*input!F47 -> 0 | G48: =$M48*input!G47 -> 0 | H48: =$M48*input!H47 -> 0 | I48: =$M48*input!I47 -> 0 | ... K48: =$M48*input!K47 -> 0 | M48: 1
A49: inserimento manuale straordinario per assenza dati
A50: =input!A48 -> C. ATTIVO CIRCOLANTE | B50: =$M50*input!B48 -> 2694229 | C50: =$M50*input!C48 -> 3010412 | D50: =$M50*input!D48 -> 2777633 | E50: =$M50*input!E48 -> 2337885 | F50: =$M50*input!F48 -> 2169494 | G50: =$M50*input!G48 -> 2261242 | H50: =$M50*input!H48 -> 2193432 | I50: =$M50*input!I48 -> 2112044 | ... K50: =$M50*input!K48 -> 1959243 | M50: 1
A51: =input!A49 -> C.I. TOTALE RIMANENZE | B51: =$M51*input!B49 -> 1163582 | C51: =$M51*input!C49 -> 1351255 | D51: =$M51*input!D49 -> 1299305 | E51: =$M51*input!E49 -> 806408 | F51: =$M51*input!F49 -> 1008735 | G51: =$M51*input!G49 -> 996875 | H51: =$M51*input!H49 -> 1101730 | I51: =$M51*input!I49 -> 996728 | ... K51: =$M51*input!K49 -> 986831 | M51: 1
A52: =input!A50 -> C.I.1. Materie prime | B52: =$M52*input!B50 -> 72963 | C52: =$M52*input!C50 -> 120598 | D52: =$M52*input!D50 -> 187585 | E52: =$M52*input!E50 -> 156107 | F52: =$M52*input!F50 -> 172408 | G52: =$M52*input!G50 -> 208447 | H52: =$M52*input!H50 -> 177942 | I52: =$M52*input!I50 -> 183419 | ... K52: =$M52*input!K50 -> 132708 | M52: 1 | N52: Magazzino
A53: =input!A51 -> C.I.2. Prodotti semilav./in corso | B53: =$M53*input!B51 -> 0 | C53: =$M53*input!C51 -> 0 | D53: =$M53*input!D51 -> 0 | E53: =$M53*input!E51 -> 0 | F53: =$M53*input!F51 -> 0 | G53: =$M53*input!G51 -> 0 | H53: =$M53*input!H51 -> 0 | I53: =$M53*input!I51 -> 0 | ... K53: =$M53*input!K51 -> 0 | M53: 1 | N53: Magazzino
A54: =input!A52 -> C.I.3. Lavori in corso | B54: =$M54*input!B52 -> 0 | C54: =$M54*input!C52 -> 0 | D54: =$M54*input!D52 -> 0 | E54: =$M54*input!E52 -> 0 | F54: =$M54*input!F52 -> 0 | G54: =$M54*input!G52 -> 0 | H54: =$M54*input!H52 -> 0 | I54: =$M54*input!I52 -> 0 | ... K54: =$M54*input!K52 -> 0 | M54: 1 | N54: Magazzino
A55: =input!A53 -> C.I.4. Prodotti finiti | B55: =$M55*input!B53 -> 1090619 | C55: =$M55*input!C53 -> 1230657 | D55: =$M55*input!D53 -> 1111720 | E55: =$M55*input!E53 -> 649931 | F55: =$M55*input!F53 -> 836327 | G55: =$M55*input!G53 -> 788428 | H55: =$M55*input!H53 -> 923788 | I55: =$M55*input!I53 -> 813309 | ... K55: =$M55*input!K53 -> 854123 | M55: 1 | N55: Magazzino
A56: =input!A54 -> C.I.5. Acconti | B56: =$M56*input!B54 -> 0 | C56: =$M56*input!C54 -> 0 | D56: =$M56*input!D54 -> 0 | E56: =$M56*input!E54 -> 370 | F56: =$M56*input!F54 -> 0 | G56: =$M56*input!G54 -> 0 | H56: =$M56*input!H54 -> 0 | I56: =$M56*input!I54 -> 0 | ... K56: =$M56*input!K54 -> 0 | M56: 1 | N56: Altre attività operative correnti
A57: =input!A55 -> Immobilizzazioni materiali destinate alla vendita | B57: =$M57*input!B55 -> 0 | C57: =$M57*input!C55 -> 0 | D57: =$M57*input!D55 -> 0 | E57: =$M57*input!E55 -> 0 | F57: =$M57*input!F55 -> 0 | G57: =$M57*input!G55 -> 0 | H57: =$M57*input!H55 -> 0 | I57: =$M57*input!I55 -> 0 | ... K57: =$M57*input!K55 -> 0 | M57: 1 | N57: Immobilizzazioni materiali nette
A58: =input!A56 -> C.II. TOTALE CREDITI | B58: =$M58*input!B56 -> 1359755 | C58: =$M58*input!C56 -> 1536873 | D58: =$M58*input!D56 -> 1393622 | E58: =$M58*input!E56 -> 1179647 | F58: =$M58*input!F56 -> 763895 | G58: =$M58*input!G56 -> 1221276 | H58: =$M58*input!H56 -> 1052555 | I58: =$M58*input!I56 -> 1006775 | ... K58: =$M58*input!K56 -> 954150 | M58: 1
A59: =input!A57 -> C.II.1. Cred. vs Clienti entro | B59: =$M59*input!B57 -> 1351939 | C59: =$M59*input!C57 -> 1377676 | D59: =$M59*input!D57 -> 1274814 | E59: =$M59*input!E57 -> 1090084 | F59: =$M59*input!F57 -> 653537 | G59: =$M59*input!G57 -> 1131681 | H59: =$M59*input!H57 -> 945441 | I59: =$M59*input!I57 -> 876265 | ... K59: =$M59*input!K57 -> 795525 | M59: 1 | N59: Crediti verso clienti
A60: =input!A58 -> C.II.1. Cred. vs Clienti oltre | B60: =$M60*input!B58 -> 0 | C60: =$M60*input!C58 -> 0 | D60: =$M60*input!D58 -> 0 | E60: =$M60*input!E58 -> 0 | F60: =$M60*input!F58 -> 0 | G60: =$M60*input!G58 -> 0 | H60: =$M60*input!H58 -> 0 | I60: =$M60*input!I58 -> 0 | ... K60: =$M60*input!K58 -> 0 | M60: 1 | N60: Crediti verso clienti
A61: =input!A59 -> C.II.2. Cred. vs Controllate entro | B61: =$M61*input!B59 -> 0 | C61: =$M61*input!C59 -> 0 | D61: =$M61*input!D59 -> 0 | E61: =$M61*input!E59 -> 0 | F61: =$M61*input!F59 -> 0 | G61: =$M61*input!G59 -> 0 | H61: =$M61*input!H59 -> 0 | I61: =$M61*input!I59 -> 0 | ... K61: =$M61*input!K59 -> 0 | M61: 1 | N61: Crediti vs controllate e collegate
A62: =input!A60 -> C.II.2. Cred. vs Controllate oltre | B62: =$M62*input!B60 -> 0 | C62: =$M62*input!C60 -> 0 | D62: =$M62*input!D60 -> 0 | E62: =$M62*input!E60 -> 0 | F62: =$M62*input!F60 -> 0 | G62: =$M62*input!G60 -> 0 | H62: =$M62*input!H60 -> 0 | I62: =$M62*input!I60 -> 0 | ... K62: =$M62*input!K60 -> 0 | M62: 1 | N62: Crediti vs controllate e collegate
A63: =input!A61 -> C.II.3. Cred. vs Collegate entro | B63: =$M63*input!B61 -> 0 | C63: =$M63*input!C61 -> 0 | D63: =$M63*input!D61 -> 0 | E63: =$M63*input!E61 -> 0 | F63: =$M63*input!F61 -> 0 | G63: =$M63*input!G61 -> 0 | H63: =$M63*input!H61 -> 0 | I63: =$M63*input!I61 -> 0 | ... K63: =$M63*input!K61 -> 0 | M63: 1 | N63: Crediti vs controllate e collegate
A64: =input!A62 -> C.II.3. Cred. vs Collegate oltre | B64: =$M64*input!B62 -> 0 | C64: =$M64*input!C62 -> 0 | D64: =$M64*input!D62 -> 0 | E64: =$M64*input!E62 -> 0 | F64: =$M64*input!F62 -> 0 | G64: =$M64*input!G62 -> 0 | H64: =$M64*input!H62 -> 0 | I64: =$M64*input!I62 -> 0 | ... K64: =$M64*input!K62 -> 0 | M64: 1 | N64: Crediti vs controllate e collegate
A65: =input!A63 -> C.II.4. Cred. vs Controllanti entro | B65: =$M65*input!B63 -> 0 | C65: =$M65*input!C63 -> 0 | D65: =$M65*input!D63 -> 0 | E65: =$M65*input!E63 -> 0 | F65: =$M65*input!F63 -> 0 | G65: =$M65*input!G63 -> 0 | H65: =$M65*input!H63 -> 0 | I65: =$M65*input!I63 -> 0 | ... K65: =$M65*input!K63 -> 0 | M65: -1 | N65: Finanziamenti netti vs soci e controllanti
A66: =input!A64 -> C.II.4. Cred. vs Controllanti oltre | B66: =$M66*input!B64 -> 0 | C66: =$M66*input!C64 -> 0 | D66: =$M66*input!D64 -> 0 | E66: =$M66*input!E64 -> 0 | F66: =$M66*input!F64 -> 0 | G66: =$M66*input!G64 -> 0 | H66: =$M66*input!H64 -> 0 | I66: =$M66*input!I64 -> 0 | ... K66: =$M66*input!K64 -> 0 | M66: -1 | N66: Finanziamenti netti vs soci e controllanti
A67: =input!A65 -> C.II.5. Cred. vs imprese sottoposte al controllo delle controllanti entro | B67: =$M67*input!B65 -> 0 | C67: =$M67*input!C65 -> 0 | D67: =$M67*input!D65 -> 0 | E67: =$M67*input!E65 -> 0 | F67: =$M67*input!F65 -> 0 | G67: =$M67*input!G65 -> 0 | H67: =$M67*input!H65 -> 0 | I67: =$M67*input!I65 -> 0 | ... K67: =$M67*input!K65 -> 0 | M67: -1 | N67: Finanziamenti netti vs soci e controllanti
A68: =input!A66 -> C.II.5. Cred. vs imprese sottoposte al controllo delle controllanti oltre | B68: =$M68*input!B66 -> 0 | C68: =$M68*input!C66 -> 0 | D68: =$M68*input!D66 -> 0 | E68: =$M68*input!E66 -> 0 | F68: =$M68*input!F66 -> 0 | G68: =$M68*input!G66 -> 0 | H68: =$M68*input!H66 -> 0 | I68: =$M68*input!I66 -> 0 | ... K68: =$M68*input!K66 -> 0 | M68: -1 | N68: Finanziamenti netti vs soci e controllanti
A69: =input!A67 -> C.II.5.bis. Cred. tributari entro | B69: =$M69*input!B67 -> 3863 | C69: =$M69*input!C67 -> 151880 | D69: =$M69*input!D67 -> 118808 | E69: =$M69*input!E67 -> 86212 | F69: =$M69*input!F67 -> 100957 | G69: =$M69*input!G67 -> 88699 | H69: =$M69*input!H67 -> 103085 | I69: =$M69*input!I67 -> 127020 | ... K69: =$M69*input!K67 -> 55816 | M69: 1 | N69: Crediti fisco-previdenziali
A70: =input!A68 -> C.II.5.bis. Cred. tributari oltre | B70: =$M70*input!B68 -> 0 | C70: =$M70*input!C68 -> 0 | D70: =$M70*input!D68 -> 0 | E70: =$M70*input!E68 -> 3351 | F70: =$M70*input!F68 -> 0 | G70: =$M70*input!G68 -> 0 | H70: =$M70*input!H68 -> 0 | I70: =$M70*input!I68 -> 0 | ... K70: =$M70*input!K68 -> 0 | M70: 1 | N70: Crediti fisco-previdenziali
... A74: =input!A72 -> C.II.5.quater. Cred. verso altri oltre | B74: =$M74*input!B72 -> 0 | C74: =$M74*input!C72 -> 0 | D74: =$M74*input!D72 -> 0 | E74: =$M74*input!E72 -> 0 | F74: =$M74*input!F72 -> 0 | G74: =$M74*input!G72 -> 0 | H74: =$M74*input!H72 -> 0 | I74: =$M74*input!I72 -> 63 | ... K74: =$M74*input!K72 -> 0 | M74: 1 | N74: Altre attività operative correnti
A75: =input!A73 -> C.II. Crediti a breve | B75: =$M75*input!B73 -> 1359755 | C75: =$M75*input!C73 -> 1536873 | D75: =$M75*input!D73 -> 1393622 | E75: =$M75*input!E73 -> 1176296 | F75: =$M75*input!F73 -> 763895 | G75: =$M75*input!G73 -> 1221276 | H75: =$M75*input!H73 -> 1052555 | I75: =$M75*input!I73 -> 1006712 | ... K75: =$M75*input!K73 -> 954150 | M75: 1
A76: =input!A74 -> Crediti per imposte anticipate | B76: =$M76*input!B74 -> 0 | C76: =$M76*input!C74 -> 0 | D76: =$M76*input!D74 -> 0 | E76: =$M76*input!E74 -> 0 | F76: =$M76*input!F74 -> 0 | G76: =$M76*input!G74 -> 0 | H76: =$M76*input!H74 -> 0 | I76: =$M76*input!I74 -> 0 | ... K76: =$M76*input!K74 -> 0 | M76: 1
A77: =input!A75 -> C.II. Crediti a oltre | B77: =$M77*input!B75 -> 0 | C77: =$M77*input!C75 -> 0 | D77: =$M77*input!D75 -> 0 | E77: =$M77*input!E75 -> 3351 | F77: =$M77*input!F75 -> 0 | G77: =$M77*input!G75 -> 0 | H77: =$M77*input!H75 -> 0 | I77: =$M77*input!I75 -> 63 | ... K77: =$M77*input!K75 -> 0 | M77: 1
A78: =input!A76 -> C.III. TOTALE ATTIVITA' FINANZIARIE | B78: =$M78*input!B76 -> 0 | C78: =$M78*input!C76 -> 0 | D78: =$M78*input!D76 -> 0 | E78: =$M78*input!E76 -> 0 | F78: =$M78*input!F76 -> 0 | G78: =$M78*input!G76 -> 0 | H78: =$M78*input!H76 -> 0 | I78: =$M78*input!I76 -> 0 | ... K78: =$M78*input!K76 -> 0 | M78: 1
A79: =input!A77 -> C.III.1. Partec.ni in Controllate | B79: =$M79*input!B77 -> 0 | C79: =$M79*input!C77 -> 0 | D79: =$M79*input!D77 -> 0 | E79: =$M79*input!E77 -> 0 | F79: =$M79*input!F77 -> 0 | G79: =$M79*input!G77 -> 0 | H79: =$M79*input!H77 -> 0 | I79: =$M79*input!I77 -> 0 | ... K79: =$M79*input!K77 -> 0 | M79: 1 | N79: Partecipazioni
A80: =input!A78 -> C.III.2. Partec.ni in Collegate | B80: =$M80*input!B78 -> 0 | C80: =$M80*input!C78 -> 0 | D80: =$M80*input!D78 -> 0 | E80: =$M80*input!E78 -> 0 | F80: =$M80*input!F78 -> 0 | G80: =$M80*input!G78 -> 0 | H80: =$M80*input!H78 -> 0 | I80: =$M80*input!I78 -> 0 | ... K80: =$M80*input!K78 -> 0 | M80: 1 | N80: Partecipazioni
A81: =input!A79 -> C.III.3. Partec.ni in Controllanti | B81: =$M81*input!B79 -> 0 | C81: =$M81*input!C79 -> 0 | D81: =$M81*input!D79 -> 0 | E81: =$M81*input!E79 -> 0 | F81: =$M81*input!F79 -> 0 | G81: =$M81*input!G79 -> 0 | H81: =$M81*input!H79 -> 0 | I81: =$M81*input!I79 -> 0 | ... K81: =$M81*input!K79 -> 0 | M81: -1 | N81: Azioni proprie e partecipazioni in controllanti
A82: =input!A80 -> C.III.3.bis. Partec.ni in imprese sottoposte al controllo delle controllanti | B82: =$M82*input!B80 -> 0 | C82: =$M82*input!C80 -> 0 | D82: =$M82*input!D80 -> 0 | E82: =$M82*input!E80 -> 0 | F82: =$M82*input!F80 -> 0 | G82: =$M82*input!G80 -> 0 | H82: =$M82*input!H80 -> 0 | I82: =$M82*input!I80 -> 0 | ... K82: =$M82*input!K80 -> 0 | M82: -1 | N82: Azioni proprie e partecipazioni in controllanti
A83: =input!A81 -> C.III.4. Altre Partec.ni | B83: =$M83*input!B81 -> 0 | C83: =$M83*input!C81 -> 0 | D83: =$M83*input!D81 -> 0 | E83: =$M83*input!E81 -> 0 | F83: =$M83*input!F81 -> 0 | G83: =$M83*input!G81 -> 0 | H83: =$M83*input!H81 -> 0 | I83: =$M83*input!I81 -> 0 | ... K83: =$M83*input!K81 -> 0 | M83: 1 | N83: Partecipazioni
A84: =input!A82 -> C.III.4.bis. Azioni proprie | B84: =$M84*input!B82 -> 0 | C84: =$M84*input!C82 -> 0 | D84: =$M84*input!D82 -> 0 | E84: =$M84*input!E82 -> 0 | F84: =$M84*input!F82 -> 0 | G84: =$M84*input!G82 -> 0 | H84: =$M84*input!H82 -> 0 | I84: =$M84*input!I82 -> 0 | ... K84: =$M84*input!K82 -> 0 | M84: -1 | N84: Azioni proprie e partecipazioni in controllanti
A85: =input!A83 -> Azioni proprie DI CUI: Val nominale | B85: =$M85*input!B83 -> 0 | C85: =$M85*input!C83 -> 0 | D85: =$M85*input!D83 -> 0 | E85: =$M85*input!E83 -> 0 | F85: =$M85*input!F83 -> 0 | G85: =$M85*input!G83 -> 0 | H85: =$M85*input!H83 -> 0 | I85: =$M85*input!I83 -> 0 | ... K85: =$M85*input!K83 -> 0 | M85: 1
A86: =input!A84 -> C.III.5. Strumenti finanziari derivati attivi | B86: =$M86*input!B84 -> 0 | C86: =$M86*input!C84 -> 0 | D86: =$M86*input!D84 -> 0 | E86: =$M86*input!E84 -> 0 | F86: =$M86*input!F84 -> 0 | G86: =$M86*input!G84 -> 0 | H86: =$M86*input!H84 -> 0 | I86: =$M86*input!I84 -> 0 | ... K86: =$M86*input!K84 -> 0 | M86: 1 | N86: Strumenti derivati attivi
A87: =input!A85 -> C.III.6. Altri titoli | B87: =$M87*input!B85 -> 0 | C87: =$M87*input!C85 -> 0 | D87: =$M87*input!D85 -> 0 | E87: =$M87*input!E85 -> 0 | F87: =$M87*input!F85 -> 0 | G87: =$M87*input!G85 -> 0 | H87: =$M87*input!H85 -> 0 | I87: =$M87*input!I85 -> 0 | ... K87: =$M87*input!K85 -> 0 | M87: 1 | N87: Riserve strategiche di liquidità
A88: =input!A86 -> C.III.7. Attività finanziarie per la gestione accentrata della tesoreria | B88: =$M88*input!B86 -> 0 | C88: =$M88*input!C86 -> 0 | D88: =$M88*input!D86 -> 0 | E88: =$M88*input!E86 -> 0 | F88: =$M88*input!F86 -> 0 | G88: =$M88*input!G86 -> 0 | H88: =$M88*input!H86 -> 0 | I88: =$M88*input!I86 -> 0 | ... K88: =$M88*input!K86 -> 0 | M88: 1 | N88: Attività di tesoreria
A89: =input!A87 -> C.IV. TOT. DISPON. LIQUIDE | B89: =$M89*input!B87 -> 170892 | C89: =$M89*input!C87 -> 122284 | D89: =$M89*input!D87 -> 84706 | E89: =$M89*input!E87 -> 351830 | F89: =$M89*input!F87 -> 396864 | G89: =$M89*input!G87 -> 43091 | H89: =$M89*input!H87 -> 39147 | I89: =$M89*input!I87 -> 108541 | ... K89: =$M89*input!K87 -> 18262 | M89: 1
A90: =input!A88 -> C.IV.1. Depositi bancari | B90: =$M90*input!B88 -> 167409 | C90: =$M90*input!C88 -> 108944 | D90: =$M90*input!D88 -> 72765 | E90: =$M90*input!E88 -> 343595 | F90: =$M90*input!F88 -> 379984 | G90: =$M90*input!G88 -> 29839 | H90: =$M90*input!H88 -> 24599 | I90: =$M90*input!I88 -> 90063 | ... K90: =$M90*input!K88 -> 0 | M90: 1 | N90: Attività di tesoreria
A91: =input!A89 -> C.IV.2. Assegni | B91: =$M91*input!B89 -> 0 | C91: =$M91*input!C89 -> 0 | D91: =$M91*input!D89 -> 0 | E91: =$M91*input!E89 -> 0 | F91: =$M91*input!F89 -> 0 | G91: =$M91*input!G89 -> 0 | H91: =$M91*input!H89 -> 0 | I91: =$M91*input!I89 -> 0 | ... K91: =$M91*input!K89 -> 0 | M91: 1 | N91: Attività di tesoreria
A92: =input!A90 -> C.IV.3. Denaro in cassa | B92: =$M92*input!B90 -> 3483 | C92: =$M92*input!C90 -> 13340 | D92: =$M92*input!D90 -> 11941 | E92: =$M92*input!E90 -> 8235 | F92: =$M92*input!F90 -> 16880 | G92: =$M92*input!G90 -> 13252 | H92: =$M92*input!H90 -> 14548 | I92: =$M92*input!I90 -> 18478 | ... K92: =$M92*input!K90 -> 0 | M92: 1 | N92: Attività di tesoreria
A93: =input!A91 -> D. RATEI E RISCONTI | B93: =$M93*input!B91 -> 46451 | C93: =$M93*input!C91 -> 40719 | D93: =$M93*input!D91 -> 36463 | E93: =$M93*input!E91 -> 35222 | F93: =$M93*input!F91 -> 47601 | G93: =$M93*input!G91 -> 41390 | H93: =$M93*input!H91 -> 48725 | I93: =$M93*input!I91 -> 52268 | ... K93: =$M93*input!K91 -> 71273 | M93: 1 | N93: Altre attività operative correnti
A94: =input!A92 -> Disaggio su prestiti | B94: =$M94*input!B92 -> 0 | C94: =$M94*input!C92 -> 0 | D94: =$M94*input!D92 -> 0 | E94: =$M94*input!E92 -> 0 | F94: =$M94*input!F92 -> 0 | G94: =$M94*input!G92 -> 0 | H94: =$M94*input!H92 -> 0 | I94: =$M94*input!I92 -> 0 | ... K94: =$M94*input!K92 -> 0 | M94: 1
A95: =input!A93 -> TOTALE ATTIVO | B95: =$M95*input!B93 -> 6479233 | C95: =$M95*input!C93 -> 6929645 | D95: =$M95*input!D93 -> 6517697 | E95: =$M95*input!E93 -> 6230020 | F95: =$M95*input!F93 -> 6320161 | G95: =$M95*input!G93 -> 4619390 | H95: =$M95*input!H93 -> 4606793 | I95: =$M95*input!I93 -> 4491663 | ... K95: =$M95*input!K93 -> 4176270 | M95: 1
A97: =input!A94 -> Passivo
A98: =input!A95 -> PATRIMONIO NETTO | B98: =$M98*input!B95 -> 0 | C98: =$M98*input!C95 -> 0 | D98: =$M98*input!D95 -> 0 | E98: =$M98*input!E95 -> 0 | F98: =$M98*input!F95 -> 0 | G98: =$M98*input!G95 -> 0 | H98: =$M98*input!H95 -> 0 | I98: =$M98*input!I95 -> 0 | ... K98: =$M98*input!K95 -> 0 | M98: 1
A99: =input!A96 -> A. TOTALE PATRIMONIO NETTO | B99: =$M99*input!B96 -> 3395702 | C99: =$M99*input!C96 -> 3347713 | D99: =$M99*input!D96 -> 3324149 | E99: =$M99*input!E96 -> 3186130 | F99: =$M99*input!F96 -> 3095198 | G99: =$M99*input!G96 -> 1226155 | H99: =$M99*input!H96 -> 1184635 | I99: =$M99*input!I96 -> 1121927 | ... K99: =$M99*input!K96 -> 1018727 | M99: 1
A100: =input!A97 -> A.I. Capitale sociale | B100: =$M100*input!B97 -> 110000 | C100: =$M100*input!C97 -> 110000 | D100: =$M100*input!D97 -> 110000 | E100: =$M100*input!E97 -> 110000 | F100: =$M100*input!F97 -> 110000 | G100: =$M100*input!G97 -> 110000 | H100: =$M100*input!H97 -> 110000 | I100: =$M100*input!I97 -> 110000 | ... K100: =$M100*input!K97 -> 110000 | M100: 1 | N100: Capitale conferito dai soci
A101: =input!A98 -> di cui: Versamenti soci in c/capitale | B101: =$M101*input!B98 -> 0 | C101: =$M101*input!C98 -> 0 | D101: =$M101*input!D98 -> 0 | E101: =$M101*input!E98 -> 0 | F101: =$M101*input!F98 -> 0 | G101: =$M101*input!G98 -> 0 | H101: =$M101*input!H98 -> 0 | I101: =$M101*input!I98 -> 0 | ... K101: =$M101*input!K98 -> 0 | M101: 1
A102: =input!A99 -> di cui: Versamenti in c/futuro aumento di capitale | B102: =$M102*input!B99 -> 0 | C102: =$M102*input!C99 -> 0 | D102: =$M102*input!D99 -> 0 | E102: =$M102*input!E99 -> 0 | F102: =$M102*input!F99 -> 0 | G102: =$M102*input!G99 -> 0 | H102: =$M102*input!H99 -> 0 | I102: =$M102*input!I99 -> 0 | ... K102: =$M102*input!K99 -> 0 | M102: 1
A103: =input!A100 -> di cui: Versamenti in c/capitale | B103: =$M103*input!B100 -> 0 | C103: =$M103*input!C100 -> 0 | D103: =$M103*input!D100 -> 0 | E103: =$M103*input!E100 -> 0 | F103: =$M103*input!F100 -> 0 | G103: =$M103*input!G100 -> 0 | H103: =$M103*input!H100 -> 0 | I103: =$M103*input!I100 -> 0 | ... K103: =$M103*input!K100 -> 0 | M103: 1
A104: =input!A101 -> di cui: Versamenti a copertura perdite | B104: =$M104*input!B101 -> 0 | C104: =$M104*input!C101 -> 0 | D104: =$M104*input!D101 -> 0 | E104: =$M104*input!E101 -> 0 | F104: =$M104*input!F101 -> 0 | G104: =$M104*input!G101 -> 0 | H104: =$M104*input!H101 -> 0 | I104: =$M104*input!I101 -> 0 | ... K104: =$M104*input!K101 -> 0 | M104: 1
A105: =input!A102 -> A.II. Riserva da sovrapprezzo | B105: =$M105*input!B102 -> 0 | C105: =$M105*input!C102 -> 0 | D105: =$M105*input!D102 -> 0 | E105: =$M105*input!E102 -> 0 | F105: =$M105*input!F102 -> 0 | G105: =$M105*input!G102 -> 0 | H105: =$M105*input!H102 -> 0 | I105: =$M105*input!I102 -> 0 | ... K105: =$M105*input!K102 -> 0 | M105: 1 | N105: Capitale conferito dai soci
...

Sheet RC
B1: =case!B1 -> 2024 | C1: =case!C1 -> 2023 | D1: =case!D1 -> 2022 | E1: =case!E1 -> 2021 | F1: =case!F1 -> 2020 | G1: =case!G1 -> 2019 | H1: =case!H1 -> 2018 | I1: =case!I1 -> 2017 | ... K1: =case!K1 -> 2015
A2: Stato Patrimoniale Attivo
A3: Attività operative
A4: Attività operative correnti
A5: Crediti verso clienti | B5: =SUMIF(case!$N:$N,$A5,case!B:B) -> 1351939 | C5: =SUMIF(case!$N:$N,$A5,case!C:C) -> 1377676 | D5: =SUMIF(case!$N:$N,$A5,case!D:D) -> 1274814 | E5: =SUMIF(case!$N:$N,$A5,case!E:E) -> 1090084 | F5: =SUMIF(case!$N:$N,$A5,case!F:F) -> 653537 | G5: =SUMIF(case!$N:$N,$A5,case!G:G) -> 1131681 | H5: =SUMIF(case!$N:$N,$A5,case!H:H) -> 945441 | I5: =SUMIF(case!$N:$N,$A5,case!I:I) -> 876265 | J5: =SUMIF(case!$N:$N,$A5,case!J:J) -> 738505 | K5: =SUMIF(case!$N:$N,$A5,case!K:K) -> 795525
A6: Magazzino | B6: =SUMIF(case!$N:$N,$A6,case!B:B) -> 1163582 | C6: =SUMIF(case!$N:$N,$A6,case!C:C) -> 1351255 | D6: =SUMIF(case!$N:$N,$A6,case!D:D) -> 1299305 | E6: =SUMIF(case!$N:$N,$A6,case!E:E) -> 806038 | F6: =SUMIF(case!$N:$N,$A6,case!F:F) -> 1008735 | G6: =SUMIF(case!$N:$N,$A6,case!G:G) -> 996875 | H6: =SUMIF(case!$N:$N,$A6,case!H:H) -> 1101730 | I6: =SUMIF(case!$N:$N,$A6,case!I:I) -> 996728 | J6: =SUMIF(case!$N:$N,$A6,case!J:J) -> 0 | K6: =SUMIF(case!$N:$N,$A6,case!K:K) -> 986831
A7: Altre attività operative correnti | B7: =SUMIF(case!$N:$N,$A7,case!B:B) -> 50404 | C7: =SUMIF(case!$N:$N,$A7,case!C:C) -> 48036 | D7: =SUMIF(case!$N:$N,$A7,case!D:D) -> 36463 | E7: =SUMIF(case!$N:$N,$A7,case!E:E) -> 35592 | F7: =SUMIF(case!$N:$N,$A7,case!F:F) -> 50265 | G7: =SUMIF(case!$N:$N,$A7,case!G:G) -> 42286 | H7: =SUMIF(case!$N:$N,$A7,case!H:H) -> 52754 | I7: =SUMIF(case!$N:$N,$A7,case!I:I) -> 55758 | J7: =SUMIF(case!$N:$N,$A7,case!J:J) -> 61672 | K7: =SUMIF(case!$N:$N,$A7,case!K:K) -> 174082
A8: Totale attività operative correnti | B8: =SUM(B5:B7) -> 2565925 | C8: =SUM(C5:C7) -> 2776967 | D8: =SUM(D5:D7) -> 2610582 | E8: =SUM(E5:E7) -> 1931714 | F8: =SUM(F5:F7) -> 1712537 | G8: =SUM(G5:G7) -> 2170842 | H8: =SUM(H5:H7) -> 2099925 | I8: =SUM(I5:I7) -> 1928751 | ... K8: =SUM(K5:K7) -> 1956438
A9: Immobilizzazioni operative nette
A10: Immobilizzazioni materiali nette | B10: =SUMIF(case!$N:$N,$A10,case!B:B) -> 3603771 | C10: =SUMIF(case!$N:$N,$A10,case!C:C) -> 3742802 | D10: =SUMIF(case!$N:$N,$A10,case!D:D) -> 3566385 | E10: =SUMIF(case!$N:$N,$A10,case!E:E) -> 3648169 | F10: =SUMIF(case!$N:$N,$A10,case!F:F) -> 3886349 | G10: =SUMIF(case!$N:$N,$A10,case!G:G) -> 2087581 | H10: =SUMIF(case!$N:$N,$A10,case!H:H) -> 2124193 | I10: =SUMIF(case!$N:$N,$A10,case!I:I) -> 2173291 | J10: =SUMIF(case!$N:$N,$A10,case!J:J) -> 2247633 | K10: =SUMIF(case!$N:$N,$A10,case!K:K) -> 2109242
A11: Immobilizzazioni immateriali nette | B11: =SUMIF(case!$N:$N,$A11,case!B:B) -> 1282 | C11: =SUMIF(case!$N:$N,$A11,case!C:C) -> 1712 | D11: =SUMIF(case!$N:$N,$A11,case!D:D) -> 2744 | E11: =SUMIF(case!$N:$N,$A11,case!E:E) -> 3344 | F11: =SUMIF(case!$N:$N,$A11,case!F:F) -> 11317 | G11: =SUMIF(case!$N:$N,$A11,case!G:G) -> 23177 | H11: =SUMIF(case!$N:$N,$A11,case!H:H) -> 36257 | I11: =SUMIF(case!$N:$N,$A11,case!I:I) -> 49156 | J11: =SUMIF(case!$N:$N,$A11,case!J:J) -> 62552 | K11: =SUMIF(case!$N:$N,$A11,case!K:K) -> 34512
A12: Totale immobilizzazioni operative nette | B12: =SUM(B10:B11) -> 3605053 | C12: =SUM(C10:C11) -> 3744514 | D12: =SUM(D10:D11) -> 3569129 | E12: =SUM(E10:E11) -> 3651513 | F12: =SUM(F10:F11) -> 3897666 | G12: =SUM(G10:G11) -> 2110758 | H12: =SUM(H10:H11) -> 2160450 | I12: =SUM(I10:I11) -> 2222447 | ... K12: =SUM(K10:K11) -> 2143754
A13: Altre attività operative immobilizzate
A14: Crediti diversi | B14: =SUMIF(case!$N:$N,$A14,case!B:B) -> 61500 | C14: =SUMIF(case!$N:$N,$A14,case!C:C) -> 77000 | D14: =SUMIF(case!$N:$N,$A14,case!D:D) -> 102472 | E14: =SUMIF(case!$N:$N,$A14,case!E:E) -> 173400 | F14: =SUMIF(case!$N:$N,$A14,case!F:F) -> 173400 | G14: =SUMIF(case!$N:$N,$A14,case!G:G) -> 174000 | H14: =SUMIF(case!$N:$N,$A14,case!H:H) -> 202186 | I14: =SUMIF(case!$N:$N,$A14,case!I:I) -> 102904 | J14: =SUMIF(case!$N:$N,$A14,case!J:J) -> 202667 | K14: =SUMIF(case!$N:$N,$A14,case!K:K) -> 0
A15: Totale altre attività operative immobilizzate | B15: =SUM(B14) -> 61500 | C15: =SUM(C14) -> 77000 | D15: =SUM(D14) -> 102472 | E15: =SUM(E14) -> 173400 | F15: =SUM(F14) -> 173400 | G15: =SUM(G14) -> 174000 | H15: =SUM(H14) -> 202186 | I15: =SUM(I14) -> 102904 | ... K15: =SUM(K14) -> 0
A16: Totale attività operative | B16: =B8+B12+B15 -> 6232478 | C16: =C8+C12+C15 -> 6598481 | D16: =D8+D12+D15 -> 6282183 | E16: =E8+E12+E15 -> 5756627 | F16: =F8+F12+F15 -> 5783603 | G16: =G8+G12+G15 -> 4455600 | H16: =H8+H12+H15 -> 4462561 | I16: =I8+I12+I15 -> 4254102 | ... K16: =K8+K12+K15 -> 4100192
A18: Attività fiscali
A19: Crediti fisco-previdenziali | B19: =SUMIF(case!$N:$N,$A19,case!B:B) -> 3863 | C19: =SUMIF(case!$N:$N,$A19,case!C:C) -> 151880 | D19: =SUMIF(case!$N:$N,$A19,case!D:D) -> 118808 | E19: =SUMIF(case!$N:$N,$A19,case!E:E) -> 89563 | F19: =SUMIF(case!$N:$N,$A19,case!F:F) -> 100957 | G19: =SUMIF(case!$N:$N,$A19,case!G:G) -> 88699 | H19: =SUMIF(case!$N:$N,$A19,case!H:H) -> 103085 | I19: =SUMIF(case!$N:$N,$A19,case!I:I) -> 127020 | J19: =SUMIF(case!$N:$N,$A19,case!J:J) -> 133161 | K19: =SUMIF(case!$N:$N,$A19,case!K:K) -> 55816
A20: Attività per imposte anticipate | B20: =SUMIF(case!$N:$N,$A20,case!B:B) -> 0 | C20: =SUMIF(case!$N:$N,$A20,case!C:C) -> 0 | D20: =SUMIF(case!$N:$N,$A20,case!D:D) -> 0 | E20: =SUMIF(case!$N:$N,$A20,case!E:E) -> 0 | F20: =SUMIF(case!$N:$N,$A20,case!F:F) -> 6737 | G20: =SUMIF(case!$N:$N,$A20,case!G:G) -> 0 | H20: =SUMIF(case!$N:$N,$A20,case!H:H) -> 0 | I20: =SUMIF(case!$N:$N,$A20,case!I:I) -> 0 | J20: =SUMIF(case!$N:$N,$A20,case!J:J) -> 0 | K20: =SUMIF(case!$N:$N,$A20,case!K:K) -> 0
A21: Totale attività fiscali | B21: =SUM(B19:B20) -> 3863 | C21: =SUM(C19:C20) -> 151880 | D21: =SUM(D19:D20) -> 118808 | E21: =SUM(E19:E20) -> 89563 | F21: =SUM(F19:F20) -> 107694 | G21: =SUM(G19:G20) -> 88699 | H21: =SUM(H19:H20) -> 103085 | I21: =SUM(I19:I20) -> 127020 | ... K21: =SUM(K19:K20) -> 55816
A23: Attività accessorie
A24: Immobilizzazioni extra-operative | B24: =SUMIF(case!$N:$N,$A24,case!B:B) -> 0 | C24: =SUMIF(case!$N:$N,$A24,case!C:C) -> 0 | D24: =SUMIF(case!$N:$N,$A24,case!D:D) -> 0 | E24: =SUMIF(case!$N:$N,$A24,case!E:E) -> 0 | F24: =SUMIF(case!$N:$N,$A24,case!F:F) -> 0 | G24: =SUMIF(case!$N:$N,$A24,case!G:G) -> 0 | H24: =SUMIF(case!$N:$N,$A24,case!H:H) -> 0 | I24: =SUMIF(case!$N:$N,$A24,case!I:I) -> 0 | J24: =SUMIF(case!$N:$N,$A24,case!J:J) -> 0 | K24: =SUMIF(case!$N:$N,$A24,case!K:K) -> 0
A25: Partecipazioni | B25: =SUMIF(case!$N:$N,$A25,case!B:B) -> 72000 | C25: =SUMIF(case!$N:$N,$A25,case!C:C) -> 57000 | D25: =SUMIF(case!$N:$N,$A25,case!D:D) -> 32000 | E25: =SUMIF(case!$N:$N,$A25,case!E:E) -> 32000 | F25: =SUMIF(case!$N:$N,$A25,case!F:F) -> 32000 | G25: =SUMIF(case!$N:$N,$A25,case!G:G) -> 32000 | H25: =SUMIF(case!$N:$N,$A25,case!H:H) -> 2000 | I25: =SUMIF(case!$N:$N,$A25,case!I:I) -> 2000 | J25: =SUMIF(case!$N:$N,$A25,case!J:J) -> 2000 | K25: =SUMIF(case!$N:$N,$A25,case!K:K) -> 2000
A26: Crediti vs controllate e collegate | B26: =SUMIF(case!$N:$N,$A26,case!B:B) -> 0 | C26: =SUMIF(case!$N:$N,$A26,case!C:C) -> 0 | D26: =SUMIF(case!$N:$N,$A26,case!D:D) -> 0 | E26: =SUMIF(case!$N:$N,$A26,case!E:E) -> 0 | F26: =SUMIF(case!$N:$N,$A26,case!F:F) -> 0 | G26: =SUMIF(case!$N:$N,$A26,case!G:G) -> 0 | H26: =SUMIF(case!$N:$N,$A26,case!H:H) -> 0 | I26: =SUMIF(case!$N:$N,$A26,case!I:I) -> 0 | J26: =SUMIF(case!$N:$N,$A26,case!J:J) -> 0 | K26: =SUMIF(case!$N:$N,$A26,case!K:K) -> 0
A27: Totale attività accessorie | B27: =SUM(B24:B26) -> 72000 | C27: =SUM(C24:C26) -> 57000 | D27: =SUM(D24:D26) -> 32000 | E27: =SUM(E24:E26) -> 32000 | F27: =SUM(F24:F26) -> 32000 | G27: =SUM(G24:G26) -> 32000 | H27: =SUM(H24:H26) -> 2000 | I27: =SUM(I24:I26) -> 2000 | ... K27: =SUM(K24:K26) -> 2000
A29: Attività finanziarie
A30: Riserve strategiche di liquidità | B30: =SUMIF(case!$N:$N,$A30,case!B:B) -> 0 | C30: =SUMIF(case!$N:$N,$A30,case!C:C) -> 0 | D30: =SUMIF(case!$N:$N,$A30,case!D:D) -> 0 | E30: =SUMIF(case!$N:$N,$A30,case!E:E) -> 0 | F30: =SUMIF(case!$N:$N,$A30,case!F:F) -> 0 | G30: =SUMIF(case!$N:$N,$A30,case!G:G) -> 0 | H30: =SUMIF(case!$N:$N,$A30,case!H:H) -> 0 | I30: =SUMIF(case!$N:$N,$A30,case!I:I) -> 0 | J30: =SUMIF(case!$N:$N,$A30,case!J:J) -> 0 | K30: =SUMIF(case!$N:$N,$A30,case!K:K) -> 0
A31: Attività di tesoreria | B31: =SUMIF(case!$N:$N,$A31,case!B:B) -> 170892 | C31: =SUMIF(case!$N:$N,$A31,case!C:C) -> 122284 | D31: =SUMIF(case!$N:$N,$A31,case!D:D) -> 84706 | E31: =SUMIF(case!$N:$N,$A31,case!E:E) -> 351830 | F31: =SUMIF(case!$N:$N,$A31,case!F:F) -> 396864 | G31: =SUMIF(case!$N:$N,$A31,case!G:G) -> 43091 | H31: =SUMIF(case!$N:$N,$A31,case!H:H) -> 39147 | I31: =SUMIF(case!$N:$N,$A31,case!I:I) -> 108541 | J31: =SUMIF(case!$N:$N,$A31,case!J:J) -> 0 | K31: =SUMIF(case!$N:$N,$A31,case!K:K) -> 0
A32: Strumenti derivati attivi | B32: =SUMIF(case!$N:$N,$A32,case!B:B) -> 0 | C32: =SUMIF(case!$N:$N,$A32,case!C:C) -> 0 | D32: =SUMIF(case!$N:$N,$A32,case!D:D) -> 0 | E32: =SUMIF(case!$N:$N,$A32,case!E:E) -> 0 | F32: =SUMIF(case!$N:$N,$A32,case!F:F) -> 0 | G32: =SUMIF(case!$N:$N,$A32,case!G:G) -> 0 | H32: =SUMIF(case!$N:$N,$A32,case!H:H) -> 0 | I32: =SUMIF(case!$N:$N,$A32,case!I:I) -> 0 | J32: =SUMIF(case!$N:$N,$A32,case!J:J) -> 0 | K32: =SUMIF(case!$N:$N,$A32,case!K:K) -> 0
A33: Totale attività finanziarie | B33: =SUM(B30:B32) -> 170892 | C33: =SUM(C30:C32) -> 122284 | D33: =SUM(D30:D32) -> 84706 | E33: =SUM(E30:E32) -> 351830 | F33: =SUM(F30:F32) -> 396864 | G33: =SUM(G30:G32) -> 43091 | H33: =SUM(H30:H32) -> 39147 | I33: =SUM(I30:I32) -> 108541 | ... K33: =SUM(K30:K32) -> 0
A35: Totale attivo | B35: =B16+B21+B27+B33 -> 6479233 | C35: =C16+C21+C27+C33 -> 6929645 | D35: =D16+D21+D27+D33 -> 6517697 | E35: =E16+E21+E27+E33 -> 6230020 | F35: =F16+F21+F27+F33 -> 6320161 | G35: =G16+G21+G27+G33 -> 4619390 | H35: =H16+H21+H27+H33 -> 4606793 | I35: =I16+I21+I27+I33 -> 4491663 | ... K35: =K16+K21+K27+K33 -> 4158008
A37: Check con totale attivo AIDA | B37: =case!B95 -> 6479233 | C37: =case!C95 -> 6929645 | D37: =case!D95 -> 6517697 | E37: =case!E95 -> 6230020 | F37: =case!F95 -> 6320161 | G37: =case!G95 -> 4619390 | H37: =case!H95 -> 4606793 | I37: =case!I95 -> 4491663 | ... K37: =case!K95 -> 4176270
A38: Differenza tra totale attivo e totale attivo AIDA | B38: =B37-B35 -> 0 | C38: =C37-C35 -> 0 | D38: =D37-D35 -> 0 | E38: =E37-E35 -> 0 | F38: =F37-F35 -> 0 | G38: =G37-G35 -> 0 | H38: =H37-H35 -> 0 | I38: =I37-I35 -> 0 | ... K38: =K37-K35 -> 18262
A39: Somma voci spostate nel passivo | B39: =case!B2+case!B46 -> 0 | C39: =case!C2+case!C46 -> 0 | D39: =case!D2+case!D46 -> 0 | E39: =case!E2+case!E46 -> 0 | F39: =case!F2+case!F46 -> 0 | G39: =case!G2+case!G46 -> 0 | H39: =case!H2+case!H46 -> 0 | I39: =case!I2+case!I46 -> 0 | ... K39: =case!K2+case!K46 -> 0
A40: Sbilancio | B40: =B38+B39 -> 0 | C40: =C38+C39 -> 0 | D40: =D38+D39 -> 0 | E40: =E38+E39 -> 0 | F40: =F38+F39 -> 0 | G40: =G38+G39 -> 0 | H40: =H38+H39 -> 0 | I40: =I38+I39 -> 0 | ... K40: =K38+K39 -> 18262
B44: =B1 -> 2024 | C44: =C1 -> 2023 | D44: =D1 -> 2022 | E44: =E1 -> 2021 | F44: =F1 -> 2020 | G44: =G1 -> 2019 | H44: =H1 -> 2018 | I44: =I1 -> 2017 | ... K44: =K1 -> 2015
A45: Stato Patrimoniale Passivo
A46: Passività operative
A47: Passività operative correnti | B47: =SUMIF(case!$N:$N,$A47,case!B:B) -> 0 | C47: =SUMIF(case!$N:$N,$A47,case!C:C) -> 0 | D47: =SUMIF(case!$N:$N,$A47,case!D:D) -> 0 | E47: =SUMIF(case!$N:$N,$A47,case!E:E) -> 0 | F47: =SUMIF(case!$N:$N,$A47,case!F:F) -> 0 | G47: =SUMIF(case!$N:$N,$A47,case!G:G) -> 0 | H47: =SUMIF(case!$N:$N,$A47,case!H:H) -> 0 | I47: =SUMIF(case!$N:$N,$A47,case!I:I) -> 0 | J47: =SUMIF(case!$N:$N,$A47,case!J:J) -> 0 | K47: =SUMIF(case!$N:$N,$A47,case!K:K) -> 0
A48: Debiti vs fornitori | B48: =SUMIF(case!$N:$N,$A48,case!B:B) -> 1001425 | C48: =SUMIF(case!$N:$N,$A48,case!C:C) -> 1022720 | D48: =SUMIF(case!$N:$N,$A48,case!D:D) -> 1073141 | E48: =SUMIF(case!$N:$N,$A48,case!E:E) -> 819126 | F48: =SUMIF(case!$N:$N,$A48,case!F:F) -> 460830 | G48: =SUMIF(case!$N:$N,$A48,case!G:G) -> 618053 | H48: =SUMIF(case!$N:$N,$A48,case!H:H) -> 558934 | I48: =SUMIF(case!$N:$N,$A48,case!I:I) -> 671844 | J48: =SUMIF(case!$N:$N,$A48,case!J:J) -> 578800 | K48: =SUMIF(case!$N:$N,$A48,case!K:K) -> 622035
A49: Debiti vs dipendenti | B49: =SUMIF(case!$N:$N,$A49,case!B:B) -> 0 | C49: =SUMIF(case!$N:$N,$A49,case!C:C) -> 0 | D49: =SUMIF(case!$N:$N,$A49,case!D:D) -> 0 | E49: =SUMIF(case!$N:$N,$A49,case!E:E) -> 0 | F49: =SUMIF(case!$N:$N,$A49,case!F:F) -> 0 | G49: =SUMIF(case!$N:$N,$A49,case!G:G) -> 0 | H49: =SUMIF(case!$N:$N,$A49,case!H:H) -> 0 | I49: =SUMIF(case!$N:$N,$A49,case!I:I) -> 0 | J49: =SUMIF(case!$N:$N,$A49,case!J:J) -> 0 | K49: =SUMIF(case!$N:$N,$A49,case!K:K) -> 0
A50: Altre passività operative correnti | B50: =SUMIF(case!$N:$N,$A50,case!B:B) -> 161463 | C50: =SUMIF(case!$N:$N,$A50,case!C:C) -> 194348 | D50: =SUMIF(case!$N:$N,$A50,case!D:D) -> 129291 | E50: =SUMIF(case!$N:$N,$A50,case!E:E) -> 131009 | F50: =SUMIF(case!$N:$N,$A50,case!F:F) -> 137555 | G50: =SUMIF(case!$N:$N,$A50,case!G:G) -> 127601 | H50: =SUMIF(case!$N:$N,$A50,case!H:H) -> 115842 | I50: =SUMIF(case!$N:$N,$A50,case!I:I) -> 91406 | J50: =SUMIF(case!$N:$N,$A50,case!J:J) -> 85453 | K50: =SUMIF(case!$N:$N,$A50,case!K:K) -> 10699
A51: Totale passività operative correnti | B51: =SUM(B48:B50) -> 1162888 | C51: =SUM(C48:C50) -> 1217068 | D51: =SUM(D48:D50) -> 1202432 | E51: =SUM(E48:E50) -> 950135 | F51: =SUM(F48:F50) -> 598385 | G51: =SUM(G48:G50) -> 745654 | H51: =SUM(H48:H50) -> 674776 | I51: =SUM(I48:I50) -> 763250 | ... K51: =SUM(K48:K50) -> 632734
A52: Passività operative consolidate | B52: =SUMIF(case!$N:$N,$A52,case!B:B) -> 0 | C52: =SUMIF(case!$N:$N,$A52,case!C:C) -> 0 | D52: =SUMIF(case!$N:$N,$A52,case!D:D) -> 0 | E52: =SUMIF(case!$N:$N,$A52,case!E:E) -> 0 | F52: =SUMIF(case!$N:$N,$A52,case!F:F) -> 0 | G52: =SUMIF(case!$N:$N,$A52,case!G:G) -> 0 | H52: =SUMIF(case!$N:$N,$A52,case!H:H) -> 0 | I52: =SUMIF(case!$N:$N,$A52,case!I:I) -> 0 | J52: =SUMIF(case!$N:$N,$A52,case!J:J) -> 0 | K52: =SUMIF(case!$N:$N,$A52,case!K:K) -> 0
A53: Fondo TFR | B53: =SUMIF(case!$N:$N,$A53,case!B:B) -> 254425 | C53: =SUMIF(case!$N:$N,$A53,case!C:C) -> 218390 | D53: =SUMIF(case!$N:$N,$A53,case!D:D) -> 277417 | E53: =SUMIF(case!$N:$N,$A53,case!E:E) -> 260333 | F53: =SUMIF(case!$N:$N,$A53,case!F:F) -> 214928 | G53: =SUMIF(case!$N:$N,$A53,case!G:G) -> 226683 | H53: =SUMIF(case!$N:$N,$A53,case!H:H) -> 206901 | I53: =SUMIF(case!$N:$N,$A53,case!I:I) -> 178930 | J53: =SUMIF(case!$N:$N,$A53,case!J:J) -> 182052 | K53: =SUMIF(case!$N:$N,$A53,case!K:K) -> 155271
A54: Altre passività operative consolidate | B54: =SUMIF(case!$N:$N,$A54,case!B:B) -> 1000 | C54: =SUMIF(case!$N:$N,$A54,case!C:C) -> 1000 | D54: =SUMIF(case!$N:$N,$A54,case!D:D) -> 1000 | E54: =SUMIF(case!$N:$N,$A54,case!E:E) -> 1000 | F54: =SUMIF(case!$N:$N,$A54,case!F:F) -> 1000 | G54: =SUMIF(case!$N:$N,$A54,case!G:G) -> 1000 | H54: =SUMIF(case!$N:$N,$A54,case!H:H) -> 1000 | I54: =SUMIF(case!$N:$N,$A54,case!I:I) -> 1000 | J54: =SUMIF(case!$N:$N,$A54,case!J:J) -> 1000 | K54: =SUMIF(case!$N:$N,$A54,case!K:K) -> 93230
A55: Totale passività operative consolidate | B55: =SUM(B53:B54) -> 255425 | C55: =SUM(C53:C54) -> 219390 | D55: =SUM(D53:D54) -> 278417 | E55: =SUM(E53:E54) -> 261333 | F55: =SUM(F53:F54) -> 215928 | G55: =SUM(G53:G54) -> 227683 | H55: =SUM(H53:H54) -> 207901 | I55: =SUM(I53:I54) -> 179930 | ... K55: =SUM(K53:K54) -> 248501
A56: Totale passività operative | B56: =B51+B55 -> 1418313 | C56: =C51+C55 -> 1436458 | D56: =D51+D55 -> 1480849 | E56: =E51+E55 -> 1211468 | F56: =F51+F55 -> 814313 | G56: =G51+G55 -> 973337 | H56: =H51+H55 -> 882677 | I56: =I51+I55 -> 943180 | ... K56: =K51+K55 -> 881235
A58: Passività fiscali e fondi
A59: Debiti fisco previdenziali | B59: =SUMIF(case!$N:$N,$A59,case!B:B) -> 136276 | C59: =SUMIF(case!$N:$N,$A59,case!C:C) -> 149793 | D59: =SUMIF(case!$N:$N,$A59,case!D:D) -> 126858 | E59: =SUMIF(case!$N:$N,$A59,case!E:E) -> 131668 | F59: =SUMIF(case!$N:$N,$A59,case!F:F) -> 136594 | G59: =SUMIF(case!$N:$N,$A59,case!G:G) -> 94725 | H59: =SUMIF(case!$N:$N,$A59,case!H:H) -> 89601 | I59: =SUMIF(case!$N:$N,$A59,case!I:I) -> 73581 | J59: =SUMIF(case!$N:$N,$A59,case!J:J) -> 78309 | K59: =SUMIF(case!$N:$N,$A59,case!K:K) -> 72790
A60: Passività per imposte differite | B60: =SUMIF(case!$N:$N,$A60,case!B:B) -> 6615 | C60: =SUMIF(case!$N:$N,$A60,case!C:C) -> 8026 | D60: =SUMIF(case!$N:$N,$A60,case!D:D) -> 11456 | E60: =SUMIF(case!$N:$N,$A60,case!E:E) -> 11456 | F60: =SUMIF(case!$N:$N,$A60,case!F:F) -> 16310 | G60: =SUMIF(case!$N:$N,$A60,case!G:G) -> 0 | H60: =SUMIF(case!$N:$N,$A60,case!H:H) -> 0 | I60: =SUMIF(case!$N:$N,$A60,case!I:I) -> 0 | J60: =SUMIF(case!$N:$N,$A60,case!J:J) -> 0 | K60: =SUMIF(case!$N:$N,$A60,case!K:K) -> 0
A61: Altri fondi | B61: =SUMIF(case!$N:$N,$A61,case!B:B) -> 0 | C61: =SUMIF(case!$N:$N,$A61,case!C:C) -> 0 | D61: =SUMIF(case!$N:$N,$A61,case!D:D) -> 0 | E61: =SUMIF(case!$N:$N,$A61,case!E:E) -> 0 | F61: =SUMIF(case!$N:$N,$A61,case!F:F) -> 0 | G61: =SUMIF(case!$N:$N,$A61,case!G:G) -> 0 | H61: =SUMIF(case!$N:$N,$A61,case!H:H) -> 0 | I61: =SUMIF(case!$N:$N,$A61,case!I:I) -> 0 | J61: =SUMIF(case!$N:$N,$A61,case!J:J) -> 0 | K61: =SUMIF(case!$N:$N,$A61,case!K:K) -> 0
A62: Totale passività fiscali e fondi | B62: =SUM(B59:B61) -> 142891 | C62: =SUM(C59:C61) -> 157819 | D62: =SUM(D59:D61) -> 138314 | E62: =SUM(E59:E61) -> 143124 | F62: =SUM(F59:F61) -> 152904 | G62: =SUM(G59:G61) -> 94725 | H62: =SUM(H59:H61) -> 89601 | I62: =SUM(I59:I61) -> 73581 | ... K62: =SUM(K59:K61) -> 72790
A64: Passività accessorie
A65: Debiti verso controllate e collegate | B65: =SUMIF(case!$N:$N,$A65,case!B:B) -> 0 | C65: =SUMIF(case!$N:$N,$A65,case!C:C) -> 0 | D65: =SUMIF(case!$N:$N,$A65,case!D:D) -> 0 | E65: =SUMIF(case!$N:$N,$A65,case!E:E) -> 0 | F65: =SUMIF(case!$N:$N,$A65,case!F:F) -> 0 | G65: =SUMIF(case!$N:$N,$A65,case!G:G) -> 0 | H65: =SUMIF(case!$N:$N,$A65,case!H:H) -> 0 | I65: =SUMIF(case!$N:$N,$A65,case!I:I) -> 0 | J65: =SUMIF(case!$N:$N,$A65,case!J:J) -> 0 | K65: =SUMIF(case!$N:$N,$A65,case!K:K) -> 0
A66: Totale passività accessorie | B66: =B65 -> 0 | C66: =C65 -> 0 | D66: =D65 -> 0 | E66: =E65 -> 0 | F66: =F65 -> 0 | G66: =G65 -> 0 | H66: =H65 -> 0 | I66: =I65 -> 0 | ... K66: =K65 -> 0
A68: Passività finanziarie
A69: Debiti strutturali a m/l termine | B69: =SUMIF(case!$N:$N,$A69,case!B:B) -> 761905 | C69: =SUMIF(case!$N:$N,$A69,case!C:C) -> 1159885 | D69: =SUMIF(case!$N:$N,$A69,case!D:D) -> 1231437 | E69: =SUMIF(case!$N:$N,$A69,case!E:E) -> 1405442 | F69: =SUMIF(case!$N:$N,$A69,case!F:F) -> 1760602 | G69: =SUMIF(case!$N:$N,$A69,case!G:G) -> 787742 | H69: =SUMIF(case!$N:$N,$A69,case!H:H) -> 1000827 | I69: =SUMIF(case!$N:$N,$A69,case!I:I) -> 1175475 | J69: =SUMIF(case!$N:$N,$A69,case!J:J) -> 1379696 | K69: =SUMIF(case!$N:$N,$A69,case!K:K) -> 1316760
A70: Debiti strutturali a breve termine | B70: =SUMIF(case!$N:$N,$A70,case!B:B) -> 760422 | C70: =SUMIF(case!$N:$N,$A70,case!C:C) -> 827770 | D70: =SUMIF(case!$N:$N,$A70,case!D:D) -> 342948 | E70: =SUMIF(case!$N:$N,$A70,case!E:E) -> 283856 | F70: =SUMIF(case!$N:$N,$A70,case!F:F) -> 497144 | G70: =SUMIF(case!$N:$N,$A70,case!G:G) -> 1537431 | H70: =SUMIF(case!$N:$N,$A70,case!H:H) -> 1449053 | I70: =SUMIF(case!$N:$N,$A70,case!I:I) -> 1177500 | J70: =SUMIF(case!$N:$N,$A70,case!J:J) -> 1117556 | K70: =SUMIF(case!$N:$N,$A70,case!K:K) -> 886758
A71: Debiti di tesoreria | B71: =SUMIF(case!$N:$N,$A71,case!B:B) -> 0 | C71: =SUMIF(case!$N:$N,$A71,case!C:C) -> 0 | D71: =SUMIF(case!$N:$N,$A71,case!D:D) -> 0 | E71: =SUMIF(case!$N:$N,$A71,case!E:E) -> 0 | F71: =SUMIF(case!$N:$N,$A71,case!F:F) -> 0 | G71: =SUMIF(case!$N:$N,$A71,case!G:G) -> 0 | H71: =SUMIF(case!$N:$N,$A71,case!H:H) -> 0 | I71: =SUMIF(case!$N:$N,$A71,case!I:I) -> 0 | J71: =SUMIF(case!$N:$N,$A71,case!J:J) -> 0 | K71: =SUMIF(case!$N:$N,$A71,case!K:K) -> 0
A72: Strumenti derivati passivi | B72: =SUMIF(case!$N:$N,$A72,case!B:B) -> 0 | C72: =SUMIF(case!$N:$N,$A72,case!C:C) -> 0 | D72: =SUMIF(case!$N:$N,$A72,case!D:D) -> 0 | E72: =SUMIF(case!$N:$N,$A72,case!E:E) -> 0 | F72: =SUMIF(case!$N:$N,$A72,case!F:F) -> 0 | G72: =SUMIF(case!$N:$N,$A72,case!G:G) -> 0 | H72: =SUMIF(case!$N:$N,$A72,case!H:H) -> 0 | I72: =SUMIF(case!$N:$N,$A72,case!I:I) -> 0 | J72: =SUMIF(case!$N:$N,$A72,case!J:J) -> 0 | K72: =SUMIF(case!$N:$N,$A72,case!K:K) -> 0
A73: Totale passività finanziarie | B73: =SUM(B69:B72) -> 1522327 | C73: =SUM(C69:C72) -> 1987655 | D73: =SUM(D69:D72) -> 1574385 | E73: =SUM(E69:E72) -> 1689298 | F73: =SUM(F69:F72) -> 2257746 | G73: =SUM(G69:G72) -> 2325173 | H73: =SUM(H69:H72) -> 2449880 | I73: =SUM(I69:I72) -> 2352975 | ... K73: =SUM(K69:K72) -> 2203518
A75: Capitale proprio
A76: Finanziamenti netti vs soci e controllanti | B76: =SUMIF(case!$N:$N,$A76,case!B:B) -> 0 | C76: =SUMIF(case!$N:$N,$A76,case!C:C) -> 0 | D76: =SUMIF(case!$N:$N,$A76,case!D:D) -> 0 | E76: =SUMIF(case!$N:$N,$A76,case!E:E) -> 0 | F76: =SUMIF(case!$N:$N,$A76,case!F:F) -> 0 | G76: =SUMIF(case!$N:$N,$A76,case!G:G) -> 0 | H76: =SUMIF(case!$N:$N,$A76,case!H:H) -> 0 | I76: =SUMIF(case!$N:$N,$A76,case!I:I) -> 0 | J76: =SUMIF(case!$N:$N,$A76,case!J:J) -> 0 | K76: =SUMIF(case!$N:$N,$A76,case!K:K) -> 0
A77: Capitale netto | B77: =SUM(B78:B82) -> 3395702 | C77: =SUM(C78:C82) -> 3347713 | D77: =SUM(D78:D82) -> 3324149 | E77: =SUM(E78:E82) -> 3186130 | F77: =SUM(F78:F82) -> 3095198 | G77: =SUM(G78:G82) -> 1226155 | H77: =SUM(H78:H82) -> 1184635 | I77: =SUM(I78:I82) -> 1121927 | ... K77: =SUM(K78:K82) -> 1018727
A78: Capitale conferito dai soci | B78: =SUMIF(case!$N:$N,$A78,case!B:B) -> 110000 | C78: =SUMIF(case!$N:$N,$A78,case!C:C) -> 110000 | D78: =SUMIF(case!$N:$N,$A78,case!D:D) -> 110000 | E78: =SUMIF(case!$N:$N,$A78,case!E:E) -> 110000 | F78: =SUMIF(case!$N:$N,$A78,case!F:F) -> 110000 | G78: =SUMIF(case!$N:$N,$A78,case!G:G) -> 110000 | H78: =SUMIF(case!$N:$N,$A78,case!H:H) -> 110000 | I78: =SUMIF(case!$N:$N,$A78,case!I:I) -> 110000 | J78: =SUMIF(case!$N:$N,$A78,case!J:J) -> 110000 | K78: =SUMIF(case!$N:$N,$A78,case!K:K) -> 110000
A79: Utili non distribuiti | B79: =SUMIF(case!$N:$N,$A79,case!B:B) -> 1395828 | C79: =SUMIF(case!$N:$N,$A79,case!C:C) -> 1372267 | D79: =SUMIF(case!$N:$N,$A79,case!D:D) -> 1234248 | E79: =SUMIF(case!$N:$N,$A79,case!E:E) -> 1143314 | F79: =SUMIF(case!$N:$N,$A79,case!F:F) -> 1116155 | G79: =SUMIF(case!$N:$N,$A79,case!G:G) -> 1074635 | H79: =SUMIF(case!$N:$N,$A79,case!H:H) -> 1011927 | I79: =SUMIF(case!$N:$N,$A79,case!I:I) -> 981757 | J79: =SUMIF(case!$N:$N,$A79,case!J:J) -> 908727 | K79: =SUMIF(case!$N:$N,$A79,case!K:K) -> 571453
A80: Riserve da rivalutazione | B80: =SUMIF(case!$N:$N,$A80,case!B:B) -> 1841883 | C80: =SUMIF(case!$N:$N,$A80,case!C:C) -> 1841883 | D80: =SUMIF(case!$N:$N,$A80,case!D:D) -> 1841883 | E80: =SUMIF(case!$N:$N,$A80,case!E:E) -> 1841883 | F80: =SUMIF(case!$N:$N,$A80,case!F:F) -> 1841883 | G80: =SUMIF(case!$N:$N,$A80,case!G:G) -> 0 | H80: =SUMIF(case!$N:$N,$A80,case!H:H) -> 0 | I80: =SUMIF(case!$N:$N,$A80,case!I:I) -> 0 | J80: =SUMIF(case!$N:$N,$A80,case!J:J) -> 0 | K80: =SUMIF(case!$N:$N,$A80,case!K:K) -> 0
A81: Azioni proprie e partecipazioni in controllanti | B81: =SUMIF(case!$N:$N,$A81,case!B:B) -> 0 | C81: =SUMIF(case!$N:$N,$A81,case!C:C) -> 0 | D81: =SUMIF(case!$N:$N,$A81,case!D:D) -> 0 | E81: =SUMIF(case!$N:$N,$A81,case!E:E) -> 0 | F81: =SUMIF(case!$N:$N,$A81,case!F:F) -> 0 | G81: =SUMIF(case!$N:$N,$A81,case!G:G) -> 0 | H81: =SUMIF(case!$N:$N,$A81,case!H:H) -> 0 | I81: =SUMIF(case!$N:$N,$A81,case!I:I) -> 0 | J81: =SUMIF(case!$N:$N,$A81,case!J:J) -> 0 | K81: =SUMIF(case!$N:$N,$A81,case!K:K) -> 0
A82: Reddito dell’esercizio | B82: =SUMIF(case!$N:$N,$A82,case!B:B) -> 47991 | C82: =SUMIF(case!$N:$N,$A82,case!C:C) -> 23563 | D82: =SUMIF(case!$N:$N,$A82,case!D:D) -> 138018 | E82: =SUMIF(case!$N:$N,$A82,case!E:E) -> 90933 | F82: =SUMIF(case!$N:$N,$A82,case!F:F) -> 27160 | G82: =SUMIF(case!$N:$N,$A82,case!G:G) -> 41520 | H82: =SUMIF(case!$N:$N,$A82,case!H:H) -> 62708 | I82: =SUMIF(case!$N:$N,$A82,case!I:I) -> 30170 | J82: =SUMIF(case!$N:$N,$A82,case!J:J) -> 73030 | K82: =SUMIF(case!$N:$N,$A82,case!K:K) -> 337274
A83: Capitale proprio di pertinenza di terzi | B83: =SUMIF(case!$N:$N,$A83,case!B:B) -> 0 | C83: =SUMIF(case!$N:$N,$A83,case!C:C) -> 0 | D83: =SUMIF(case!$N:$N,$A83,case!D:D) -> 0 | E83: =SUMIF(case!$N:$N,$A83,case!E:E) -> 0 | F83: =SUMIF(case!$N:$N,$A83,case!F:F) -> 0 | G83: =SUMIF(case!$N:$N,$A83,case!G:G) -> 0 | H83: =SUMIF(case!$N:$N,$A83,case!H:H) -> 0 | I83: =SUMIF(case!$N:$N,$A83,case!I:I) -> 0 | J83: =SUMIF(case!$N:$N,$A83,case!J:J) -> 0 | K83: =SUMIF(case!$N:$N,$A83,case!K:K) -> 0
A84: Totale capitale proprio | B84: =B76+B77+B83 -> 3395702 | C84: =C76+C77+C83 -> 3347713 | D84: =D76+D77+D83 -> 3324149 | E84: =E76+E77+E83 -> 3186130 | F84: =F76+F77+F83 -> 3095198 | G84: =G76+G77+G83 -> 1226155 | H84: =H76+H77+H83 -> 1184635 | I84: =I76+I77+I83 -> 1121927 | ... K84: =K76+K77+K83 -> 1018727
A86: Totale passivo | B86: =B56+B62+B66+B73+B84 -> 6479233 | C86: =C56+C62+C66+C73+C84 -> 6929645 | D86: =D56+D62+D66+D73+D84 -> 6517697 | E86: =E56+E62+E66+E73+E84 -> 6230020 | F86: =F56+F62+F66+F73+F84 -> 6320161 | G86: =G56+G62+G66+G73+G84 -> 4619390 | H86: =H56+H62+H66+H73+H84 -> 4606793 | I86: =I56+I62+I66+I73+I84 -> 4491663 | ... K86: =K56+K62+K66+K73+K84 -> 4176270
A88: Check con totale attivo AIDA | B88: =case!B168 -> 6479233 | C88: =case!C168 -> 6929645 | D88: =case!D168 -> 6517697 | E88: =case!E168 -> 6230020 | F88: =case!F168 -> 6320161 | G88: =case!G168 -> 4619390 | H88: =case!H168 -> 4606793 | I88: =case!I168 -> 4491663 | ... K88: =case!K168 -> 4176270
A89: diff da AIDA | B89: =B88-B86 -> 0 | C89: =C88-C86 -> 0 | D89: =D88-D86 -> 0 | E89: =E88-E86 -> 0 | F89: =F88-F86 -> 0 | G89: =G88-G86 -> 0 | H89: =H88-H86 -> 0 | I89: =I88-I86 -> 0 | ... K89: =K88-K86 -> 0
A90: Check Tot.Attivo - Tot.Passivo | B90: =B35-B86 -> 0 | C90: =C35-C86 -> 0 | D90: =D35-D86 -> 0 | E90: =E35-E86 -> 0 | F90: =F35-F86 -> 0 | G90: =G35-G86 -> 0 | H90: =H35-H86 -> 0 | I90: =I35-I86 -> 0 | ... K90: =K35-K86 -> -18262
A92: Relazione fondamentale fonti/impieghi:
A93: Attività Operative Nette Estese (AON*) | B93: =B16-B56+B21-B62 -> 4675137 | C93: =C16-C56+C21-C62 -> 5156084 | D93: =D16-D56+D21-D62 -> 4781828 | E93: =E16-E56+E21-E62 -> 4491598 | F93: =F16-F56+F21-F62 -> 4924080 | G93: =G16-G56+G21-G62 -> 3476237 | H93: =H16-H56+H21-H62 -> 3593368 | I93: =I16-I56+I21-I62 -> 3364361 | ... K93: =K16-K56+K21-K62 -> 3201983
A94: Attività Accessorie Nette (AACCN) | B94: =B27-B66 -> 72000 | C94: =C27-C66 -> 57000 | D94: =D27-D66 -> 32000 | E94: =E27-E66 -> 32000 | F94: =F27-F66 -> 32000 | G94: =G27-G66 -> 32000 | H94: =H27-H66 -> 2000 | I94: =I27-I66 -> 2000 | ... K94: =K27-K66 -> 2000
A95: Posizione Finanziaria Netta (+Liquidità - Debito) | B95: =B33-B73 -> -1351435 | C95: =C33-C73 -> -1865371 | D95: =D33-D73 -> -1489679 | E95: =E33-E73 -> -1337468 | F95: =F33-F73 -> -1860882 | G95: =G33-G73 -> -2282082 | H95: =H33-H73 -> -2410733 | I95: =I33-I73 -> -2244434 | ... K95: =K33-K73 -> -2203518
A96: Capitale Proprio | B96: =B84 -> 3395702 | C96: =C84 -> 3347713 | D96: =D84 -> 3324149 | E96: =E84 -> 3186130 | F96: =F84 -> 3095198 | G96: =G84 -> 1226155 | H96: =H84 -> 1184635 | I96: =I84 -> 1121927 | ... K96: =K84 -> 1018727
A97: Totale Attivo | B97: =B35 -> 6479233 | C97: =C35 -> 6929645 | D97: =D35 -> 6517697 | E97: =E35 -> 6230020 | F97: =F35 -> 6320161 | G97: =G35 -> 4619390 | H97: =H35 -> 4606793 | I97: =I35 -> 4491663 | ... K97: =K35 -> 4158008
A98: Totale Passivo | B98: =B86 -> 6479233 | C98: =C86 -> 6929645 | D98: =D86 -> 6517697 | E98: =E86 -> 6230020 | F98: =F86 -> 6320161 | G98: =G86 -> 4619390 | H98: =H86 -> 4606793 | I98: =I86 -> 4491663 | ... K98: =K86 -> 4176270
A99: Sbilancio | B99: =B97-B98 -> 0 | C99: =C97-C98 -> 0 | D99: =D97-D98 -> 0 | E99: =E97-E98 -> 0 | F99: =F97-F98 -> 0 | G99: =G97-G98 -> 0 | H99: =H97-H98 -> 0 | I99: =I97-I98 -> 0 | ... K99: =K97-K98 -> -18262
A101: CCON | B101: =B8-B51 -> 1403037 | C101: =C8-C51 -> 1559899 | D101: =D8-D51 -> 1408150 | E101: =E8-E51 -> 981579 | F101: =F8-F51 -> 1114152 | G101: =G8-G51 -> 1425188 | H101: =H8-H51 -> 1425149 | I101: =I8-I51 -> 1165501 | ... K101: =K8-K51 -> 1323704
A102: AON -> | B102: =B16-B56 -> 4814165 | C102: =C16-C56 -> 5162023 | D102: =D16-D56 -> 4801334 | E102: =E16-E56 -> 4545159 | F102: =F16-F56 -> 4969290 | G102: =G16-G56 -> 3482263 | H102: =H16-H56 -> 3579884 | I102: =I16-I56 -> 3310922 | ... K102: =K16-K56 -> 3218957
A103: debito netto, se neg è liq netta -> | B103: =-B95 -> 1351435 | C103: =-C95 -> 1865371 | D103: =-D95 -> 1489679 | E103: =-E95 -> 1337468 | F103: =-F95 -> 1860882 | G103: =-G95 -> 2282082 | H103: =-H95 -> 2410733 | I103: =-I95 -> 2244434 | ... K103: =-K95 -> 2203518
A104: AON*+ att.gestione accessoria | B104: =B93+B94 -> 4747137 | C104: =C93+C94 -> 5213084 | D104: =D93+D94 -> 4813828 | E104: =E93+E94 -> 4523598 | F104: =F93+F94 -> 4956080 | G104: =G93+G94 -> 3508237 | H104: =H93+H94 -> 3595368 | I104: =I93+I94 -> 3366361 | ... K104: =K93+K94 -> 3203983
A105: capitale proprio + debito netto | B105: =B96+B103 -> 4747137 | C105: =C96+C103 -> 5213084 | D105: =D96+D103 -> 4813828 | E105: =E96+E103 -> 4523598 | F105: =F96+F103 -> 4956080 | G105: =G96+G103 -> 3508237 | H105: =H96+H103 -> 3595368 | I105: =I96+I103 -> 3366361 | ... K105: =K96+K103 -> 3222245
A106: Relazione fonti/impieghi | B106: =B104-B105 -> 0 | C106: =C104-C105 -> 0 | D106: =D104-D105 -> 0 | E106: =E104-E105 -> 0 | F106: =F104-F105 -> 0 | G106: =G104-G105 -> 0 | H106: =H104-H105 -> 0 | I106: =I104-I105 -> 0 | ... K106: =K104-K105 -> -18262
B108: =B1 -> 2024 | C108: =C1 -> 2023 | D108: =D1 -> 2022 | E108: =E1 -> 2021 | F108: =F1 -> 2020 | G108: =G1 -> 2019 | H108: =H1 -> 2018 | I108: =I1 -> 2017 | ... K108: =K1 -> 2015
A109: Conto Economico
A110: Gestione operativa
A111: (A) Ricavi di vendita | B111: =SUMIF(case!$N:$N,$A111,case!B:B)-B127 -> 10781972 | C111: =SUMIF(case!$N:$N,$A111,case!C:C)-C127 -> 10502251 | D111: =SUMIF(case!$N:$N,$A111,case!D:D)-D127 -> 9797336 | E111: =SUMIF(case!$N:$N,$A111,case!E:E)-E127 -> 8086488 | F111: =SUMIF(case!$N:$N,$A111,case!F:F)-F127 -> 7349721 | G111: =SUMIF(case!$N:$N,$A111,case!G:G)-G127 -> 8370970 | H111: =SUMIF(case!$N:$N,$A111,case!H:H)-H127 -> 7727686 | I111: =SUMIF(case!$N:$N,$A111,case!I:I)-I127 -> 7677878 | J111: =SUMIF(case!$N:$N,$A111,case!J:J)-J127 -> 7424443 | K111: =SUMIF(case!$N:$N,$A111,case!K:K)-K127 -> 6901829
A112: Acquisti
A113: − Materie prime e merci | B113: =SUMIF(case!$N:$N,$A113,case!B:B) -> -8042729 | C113: =SUMIF(case!$N:$N,$A113,case!C:C) -> -7909736 | D113: =SUMIF(case!$N:$N,$A113,case!D:D) -> -7635079 | E113: =SUMIF(case!$N:$N,$A113,case!E:E) -> -5561813 | F113: =SUMIF(case!$N:$N,$A113,case!F:F) -> -5319152 | G113: =SUMIF(case!$N:$N,$A113,case!G:G) -> -6064470 | H113: =SUMIF(case!$N:$N,$A113,case!H:H) -> -5643875 | I113: =SUMIF(case!$N:$N,$A113,case!I:I) -> -5648984 | J113: =SUMIF(case!$N:$N,$A113,case!J:J) -> -5503638 | K113: =SUMIF(case!$N:$N,$A113,case!K:K) -> -4946714
A114: − Servizi | B114: =SUMIF(case!$N:$N,$A114,case!B:B) -> -1042479 | C114: =SUMIF(case!$N:$N,$A114,case!C:C) -> -1055045 | D114: =SUMIF(case!$N:$N,$A114,case!D:D) -> -1049603 | E114: =SUMIF(case!$N:$N,$A114,case!E:E) -> -888400 | F114: =SUMIF(case!$N:$N,$A114,case!F:F) -> -790856 | G114: =SUMIF(case!$N:$N,$A114,case!G:G) -> -817799 | H114: =SUMIF(case!$N:$N,$A114,case!H:H) -> -794983 | I114: =SUMIF(case!$N:$N,$A114,case!I:I) -> -788067 | J114: =SUMIF(case!$N:$N,$A114,case!J:J) -> -755578 | K114: =SUMIF(case!$N:$N,$A114,case!K:K) -> -611124
A115: − Godimento beni di terzi | B115: =SUMIF(case!$N:$N,$A115,case!B:B) -> -18000 | C115: =SUMIF(case!$N:$N,$A115,case!C:C) -> -18000 | D115: =SUMIF(case!$N:$N,$A115,case!D:D) -> -18000 | E115: =SUMIF(case!$N:$N,$A115,case!E:E) -> -31757 | F115: =SUMIF(case!$N:$N,$A115,case!F:F) -> -70447 | G115: =SUMIF(case!$N:$N,$A115,case!G:G) -> -70304 | H115: =SUMIF(case!$N:$N,$A115,case!H:H) -> -84557 | I115: =SUMIF(case!$N:$N,$A115,case!I:I) -> -99865 | J115: =SUMIF(case!$N:$N,$A115,case!J:J) -> -83190 | K115: =SUMIF(case!$N:$N,$A115,case!K:K) -> -35455
A116: = − Totale acquisti MP, merci e servizi | B116: =SUM(B113:B115) -> -9103208 | C116: =SUM(C113:C115) -> -8982781 | D116: =SUM(D113:D115) -> -8702682 | E116: =SUM(E113:E115) -> -6481970 | F116: =SUM(F113:F115) -> -6180455 | G116: =SUM(G113:G115) -> -6952573 | H116: =SUM(H113:H115) -> -6523415 | I116: =SUM(I113:I115) -> -6536916 | ... K116: =SUM(K113:K115) -> -5593293
A117: + Variazione rimanenze di MP e merci | B117: =SUMIF(case!$N:$N,$A117,case!B:B) -> -123637 | C117: =SUMIF(case!$N:$N,$A117,case!C:C) -> 85812 | D117: =SUMIF(case!$N:$N,$A117,case!D:D) -> 102926 | E117: =SUMIF(case!$N:$N,$A117,case!E:E) -> 24242 | F117: =SUMIF(case!$N:$N,$A117,case!F:F) -> -102446 | G117: =SUMIF(case!$N:$N,$A117,case!G:G) -> 47527 | H117: =SUMIF(case!$N:$N,$A117,case!H:H) -> 4875 | I117: =SUMIF(case!$N:$N,$A117,case!I:I) -> 18872 | J117: =SUMIF(case!$N:$N,$A117,case!J:J) -> 38563 | K117: =SUMIF(case!$N:$N,$A117,case!K:K) -> 82592
...

Sheet RF
B1: Rendiconto finanziario | C1: =case!B1 -> 2024 | D1: =case!C1 -> 2023 | E1: =case!D1 -> 2022 | F1: =case!E1 -> 2021 | G1: =case!F1 -> 2020 | H1: =case!G1 -> 2019 | I1: =case!H1 -> 2018 | J1: =case!I1 -> 2017 | ... L1: =case!K1 -> 2015
B2: Flussi di cassa della gestione operativa e accessoria
B3: Flussi di cassa della gestione operativa corrente
A4: + | B4: Reddito operativo | C4: =RC!B131 -> 208796 | D4: =RC!C131 -> 157219 | E4: =RC!D131 -> 237075 | F4: =RC!E131 -> 158900 | G4: =RC!F131 -> 79314 | H4: =RC!G131 -> 101378 | I4: =RC!H131 -> 129035 | J4: =RC!I131 -> 92400 | ... L4: =RC!K131 -> 562402
A5: ± | B5: Reddito gestioni accessoria e straordinaria | C5: =RC!B146 -> 0 | D5: =RC!C146 -> 0 | E5: =RC!D146 -> 0 | F5: =RC!E146 -> 0 | G5: =RC!F146 -> 0 | H5: =RC!G146 -> 0 | I5: =RC!H146 -> 0 | J5: =RC!I146 -> 0 | ... L5: =RC!K146 -> 0
A6: + | B6: Riaggiunta ammortamenti | C6: =-RC!B124 -> 178212 | D6: =-RC!C124 -> 262884 | E6: =-RC!D124 -> 284679 | F6: =-RC!E124 -> 291427 | G6: =-RC!F124 -> 207100 | H6: =-RC!G124 -> 250219 | I6: =-RC!H124 -> 254982 | J6: =-RC!I124 -> 237401 | ... L6: =-RC!K124 -> 190385
A7: - | B7: (Imposte + Risparmio fiscale interessi netti) | C7: =-(RC!B149+RC!B157) -> -4522.7903 | D7: =-(RC!C149+RC!C157) -> -24688.921 | E7: =-(RC!D149+RC!D157) -> 56410.184 | F7: =-(RC!E149+RC!E157) -> 31360.089 | G7: =-(RC!F149+RC!F157) -> 711.47551 | H7: =-(RC!G149+RC!G157) -> 7210.7077 | I7: =-(RC!H149+RC!H157) -> 15690.71 | J7: =-(RC!I149+RC!I157) -> -2098.5248 | ... L7: =-(RC!K149+RC!K157) -> 144205.21
A8: = | B8: EBITDA al netto delle imposte | C8: =C4+C5+C6-C7 -> 391530.79 | D8: =D4+D5+D6-D7 -> 444791.92 | E8: =E4+E5+E6-E7 -> 465343.82 | F8: =F4+F5+F6-F7 -> 418966.91 | G8: =G4+G5+G6-G7 -> 285702.52 | H8: =H4+H5+H6-H7 -> 344386.29 | I8: =I4+I5+I6-I7 -> 368326.29 | J8: =J4+J5+J6-J7 -> 331899.52 | ... L8: =L4+L5+L6-L7 -> 608581.79
B9: Rettifiche per determinare il flusso di cassa
B10: Variazione del CCON*
A11: - | B11: (Aumento) diminuzione crediti verso clienti | C11: =-1*(RC!B5-RC!C5) -> 25737 | D11: =-1*(RC!C5-RC!D5) -> -102862 | E11: =-1*(RC!D5-RC!E5) -> -184730 | F11: =-1*(RC!E5-RC!F5) -> -436547 | G11: =-1*(RC!F5-RC!G5) -> 478144 | H11: =-1*(RC!G5-RC!H5) -> -186240 | I11: =-1*(RC!H5-RC!I5) -> -69176 | J11: =-1*(RC!I5-RC!J5) -> -137760 | ... L11: =-1*(RC!K5-RC!L5) -> -795525
A12: - | B12: (Aumento) diminuzione scorte magazzino | C12: =-1*(RC!B6-RC!C6) -> 187673 | D12: =-1*(RC!C6-RC!D6) -> -51950 | E12: =-1*(RC!D6-RC!E6) -> -493267 | F12: =-1*(RC!E6-RC!F6) -> 202697 | G12: =-1*(RC!F6-RC!G6) -> -11860 | H12: =-1*(RC!G6-RC!H6) -> 104855 | I12: =-1*(RC!H6-RC!I6) -> -105002 | J12: =-1*(RC!I6-RC!J6) -> -996728 | ... L12: =-1*(RC!K6-RC!L6) -> -986831
A13: - | B13: (Aumento) diminuzione altre attività correnti | C13: =-1*(RC!B7-RC!C7) -> -2368 | D13: =-1*(RC!C7-RC!D7) -> -11573 | E13: =-1*(RC!D7-RC!E7) -> -871 | F13: =-1*(RC!E7-RC!F7) -> 14673 | G13: =-1*(RC!F7-RC!G7) -> -7979 | H13: =-1*(RC!G7-RC!H7) -> 10468 | I13: =-1*(RC!H7-RC!I7) -> 3004 | J13: =-1*(RC!I7-RC!J7) -> 5914 | ... L13: =-1*(RC!K7-RC!L7) -> -174082
A14: + | B14: Aumento (diminuzione) debiti verso fornitori | C14: =RC!B48-RC!C48 -> -21295 | D14: =RC!C48-RC!D48 -> -50421 | E14: =RC!D48-RC!E48 -> 254015 | F14: =RC!E48-RC!F48 -> 358296 | G14: =RC!F48-RC!G48 -> -157223 | H14: =RC!G48-RC!H48 -> 59119 | I14: =RC!H48-RC!I48 -> -112910 | J14: =RC!I48-RC!J48 -> 93044 | ... L14: =RC!K48-RC!L48 -> 622035
A15: + | B15: Aumento (diminuzione) altre passività correnti | C15: =RC!B50-RC!C50 -> -32885 | D15: =RC!C50-RC!D50 -> 65057 | E15: =RC!D50-RC!E50 -> -1718 | F15: =RC!E50-RC!F50 -> -6546 | G15: =RC!F50-RC!G50 -> 9954 | H15: =RC!G50-RC!H50 -> 11759 | I15: =RC!H50-RC!I50 -> 24436 | J15: =RC!I50-RC!J50 -> 5953 | ... L15: =RC!K50-RC!L50 -> 10699
A16: - | B16: (Aumento) diminuzione attività fiscali | C16: =-1*(RC!B21-RC!C21) -> 148017 | D16: =-1*(RC!C21-RC!D21) -> -33072 | E16: =-1*(RC!D21-RC!E21) -> -29245 | F16: =-1*(RC!E21-RC!F21) -> 18131 | G16: =-1*(RC!F21-RC!G21) -> -18995 | H16: =-1*(RC!G21-RC!H21) -> 14386 | I16: =-1*(RC!H21-RC!I21) -> 23935 | J16: =-1*(RC!I21-RC!J21) -> 6141 | ... L16: =-1*(RC!K21-RC!L21) -> -55816
A17: + | B17: Aumento (diminuzione) passività fiscali | C17: =RC!B62-RC!C62 -> -14928 | D17: =RC!C62-RC!D62 -> 19505 | E17: =RC!D62-RC!E62 -> -4810 | F17: =RC!E62-RC!F62 -> -9780 | G17: =RC!F62-RC!G62 -> 58179 | H17: =RC!G62-RC!H62 -> 5124 | I17: =RC!H62-RC!I62 -> 16020 | J17: =RC!I62-RC!J62 -> -4728 | ... L17: =RC!K62-RC!L62 -> 72790
A18: = | B18: (Aumento) diminuzione CCON* | C18: =SUM(C11:C17) -> 289951 | D18: =SUM(D11:D17) -> -165316 | E18: =SUM(E11:E17) -> -460626 | F18: =SUM(F11:F17) -> 140924 | G18: =SUM(G11:G17) -> 350220 | H18: =SUM(H11:H17) -> 19471 | I18: =SUM(I11:I17) -> -219693 | J18: =SUM(J11:J17) -> -1028164 | ... L18: =SUM(L11:L17) -> -1306730
A19: + | B19: Aumento (diminuzione) fondo TFR | C19: =RC!B53-RC!C53 -> 36035 | D19: =RC!C53-RC!D53 -> -59027 | E19: =RC!D53-RC!E53 -> 17084 | F19: =RC!E53-RC!F53 -> 45405 | G19: =RC!F53-RC!G53 -> -11755 | H19: =RC!G53-RC!H53 -> 19782 | I19: =RC!H53-RC!I53 -> 27971 | J19: =RC!I53-RC!J53 -> -3122 | ... L19: =RC!K53-RC!L53 -> 155271
A20: - | B20: (Aumento) diminuzione altre attività operative immobilizzate | C20: =-1*(RC!B15-RC!C15) -> 15500 | D20: =-1*(RC!C15-RC!D15) -> 25472 | E20: =-1*(RC!D15-RC!E15) -> 70928 | F20: =-1*(RC!E15-RC!F15) -> 0 | G20: =-1*(RC!F15-RC!G15) -> 600 | H20: =-1*(RC!G15-RC!H15) -> 28186 | I20: =-1*(RC!H15-RC!I15) -> -99282 | J20: =-1*(RC!I15-RC!J15) -> 99763 | ... L20: =-1*(RC!K15-RC!L15) -> 0
A21: + | B21: Aumento (diminuzione) altre passività operative consolidate | C21: =RC!B54-RC!C54 -> 0 | D21: =RC!C54-RC!D54 -> 0 | E21: =RC!D54-RC!E54 -> 0 | F21: =RC!E54-RC!F54 -> 0 | G21: =RC!F54-RC!G54 -> 0 | H21: =RC!G54-RC!H54 -> 0 | I21: =RC!H54-RC!I54 -> 0 | J21: =RC!I54-RC!J54 -> 0 | ... L21: =RC!K54-RC!L54 -> 93230
A22: = | B22: Totale rettifiche | C22: =SUM(C18:C21) -> 341486 | D22: =SUM(D18:D21) -> -198871 | E22: =SUM(E18:E21) -> -372614 | F22: =SUM(F18:F21) -> 186329 | G22: =SUM(G18:G21) -> 339065 | H22: =SUM(H18:H21) -> 67439 | I22: =SUM(I18:I21) -> -291004 | J22: =SUM(J18:J21) -> -931523 | ... L22: =SUM(L18:L21) -> -1058229
A23: = | B23: Flussi di cassa netti gestione operativa corrente, acc e straord. | C23: =C8+C22 -> 733016.79 | D23: =D8+D22 -> 245920.92 | E23: =E8+E22 -> 92729.816 | F23: =F8+F22 -> 605295.91 | G23: =G8+G22 -> 624767.52 | H23: =H8+H22 -> 411825.29 | I23: =I8+I22 -> 77322.29 | J23: =J8+J22 -> -599623.48 | ... L23: =L8+L22 -> -449647.21
B24: Flussi di cassa della gestione investimenti
A25: - | B25: (Aumento) diminuzione Immobilizzazioni operative nette | C25: =-1*(RC!B12-RC!C12) -> 139461 | D25: =-1*(RC!C12-RC!D12) -> -175385 | E25: =-1*(RC!D12-RC!E12) -> 82384 | F25: =-1*(RC!E12-RC!F12) -> 246153 | G25: =-1*(RC!F12-RC!G12) -> -1786908 | H25: =-1*(RC!G12-RC!H12) -> 49692 | I25: =-1*(RC!H12-RC!I12) -> 61997 | J25: =-1*(RC!I12-RC!J12) -> 87738 | ... L25: =-1*(RC!K12-RC!L12) -> -2143754
A26: - | B26: (Aumento) diminuzione attività accessorie | C26: =-1*(RC!B27-RC!C27) -> -15000 | D26: =-1*(RC!C27-RC!D27) -> -25000 | E26: =-1*(RC!D27-RC!E27) -> 0 | F26: =-1*(RC!E27-RC!F27) -> 0 | G26: =-1*(RC!F27-RC!G27) -> 0 | H26: =-1*(RC!G27-RC!H27) -> -30000 | I26: =-1*(RC!H27-RC!I27) -> 0 | J26: =-1*(RC!I27-RC!J27) -> 0 | ... L26: =-1*(RC!K27-RC!L27) -> -2000
A27: + | B27: Aumento (diminuzione) debiti vs controllate e collegate | C27: =RC!B66-RC!C66 -> 0 | D27: =RC!C66-RC!D66 -> 0 | E27: =RC!D66-RC!E66 -> 0 | F27: =RC!E66-RC!F66 -> 0 | G27: =RC!F66-RC!G66 -> 0 | H27: =RC!G66-RC!H66 -> 0 | I27: =RC!H66-RC!I66 -> 0 | J27: =RC!I66-RC!J66 -> 0 | ... L27: =RC!K66-RC!L66 -> 0
A28: - | B28: (Ammortamenti) | C28: =RC!B124 -> -178212 | D28: =RC!C124 -> -262884 | E28: =RC!D124 -> -284679 | F28: =RC!E124 -> -291427 | G28: =RC!F124 -> -207100 | H28: =RC!G124 -> -250219 | I28: =RC!H124 -> -254982 | J28: =RC!I124 -> -237401 | ... L28: =RC!K124 -> -190385
A29: + | B29: Aumento (diminuzione) riserve da rivalutazione | C29: =RC!B80-RC!C80 -> 0 | D29: =RC!C80-RC!D80 -> 0 | E29: =RC!D80-RC!E80 -> 0 | F29: =RC!E80-RC!F80 -> 0 | G29: =RC!F80-RC!G80 -> 1841883 | H29: =RC!G80-RC!H80 -> 0 | I29: =RC!H80-RC!I80 -> 0 | J29: =RC!I80-RC!J80 -> 0 | ... L29: =RC!K80-RC!L80 -> 0
A30: = | B30: Flussi di cassa netti della gestione investimenti | C30: =SUM(C25:C29) -> -53751 | D30: =SUM(D25:D29) -> -463269 | E30: =SUM(E25:E29) -> -202295 | F30: =SUM(F25:F29) -> -45274 | G30: =SUM(G25:G29) -> -152125 | H30: =SUM(H25:H29) -> -230527 | I30: =SUM(I25:I29) -> -192985 | J30: =SUM(J25:J29) -> -149663 | ... L30: =SUM(L25:L29) -> -2336139
A31: = | B31: Free cash flow to the firm (FCFF) | C31: =C23+C30 -> 679265.79 | D31: =D23+D30 -> -217348.08 | E31: =E23+E30 -> -109565.18 | F31: =F23+F30 -> 560021.91 | G31: =G23+G30 -> 472642.52 | H31: =H23+H30 -> 181298.29 | I31: =I23+I30 -> -115662.71 | J31: =J23+J30 -> -749286.48 | ... L31: =L23+L30 -> -2785786.2
B32: Flussi di cassa della gestione finanziaria
B33: Debito e attività finanziarie (esclusa tesoreria)
A34: - | B34: (Oneri finanziari netti) | C34: =RC!B140 -> -108744 | D34: =RC!C140 -> -99460 | E34: =RC!D140 -> -32150 | F34: =RC!E140 -> -28050 | G34: =RC!F140 -> -38589 | H34: =RC!G140 -> -39669 | I34: =RC!H140 -> -38800 | J34: =RC!I140 -> -49795 | ... L34: =RC!K140 -> -60964
A35: + | B35: Risparmio fiscale interessi netti | C35: =-RC!B157 -> -56583.79 | D35: =-RC!C157 -> -58884.921 | E35: =-RC!D157 -> -10496.816 | F35: =-RC!E157 -> -8556.9113 | G35: =-RC!F157 -> -12853.524 | H35: =-RC!G157 -> -12978.292 | I35: =-RC!H157 -> -11836.29 | J35: =-RC!I157 -> -14533.525 | ... L35: =-RC!K157 -> -19958.787
A36: + | B36: Strumenti derivati: (aumento) diminuzione attivi + aumento (diminuzione) passivi | C36: =-(RC!B32-RC!C32)+(RC!B72-RC!C72) -> 0 | D36: =-(RC!C32-RC!D32)+(RC!C72-RC!D72) -> 0 | E36: =-(RC!D32-RC!E32)+(RC!D72-RC!E72) -> 0 | F36: =-(RC!E32-RC!F32)+(RC!E72-RC!F72) -> 0 | G36: =-(RC!F32-RC!G32)+(RC!F72-RC!G72) -> 0 | H36: =-(RC!G32-RC!H32)+(RC!G72-RC!H72) -> 0 | I36: =-(RC!H32-RC!I32)+(RC!H72-RC!I72) -> 0 | J36: =-(RC!I32-RC!J32)+(RC!I72-RC!J72) -> 0 | ... L36: =-(RC!K32-RC!L32)+(RC!K72-RC!L72) -> 0
A37: + | B37: Aumento (diminuzione) debiti struttturali a medio-lungo | C37: =RC!B69-RC!C69 -> -397980 | D37: =RC!C69-RC!D69 -> -71552 | E37: =RC!D69-RC!E69 -> -174005 | F37: =RC!E69-RC!F69 -> -355160 | G37: =RC!F69-RC!G69 -> 972860 | H37: =RC!G69-RC!H69 -> -213085 | I37: =RC!H69-RC!I69 -> -174648 | J37: =RC!I69-RC!J69 -> -204221 | ... L37: =RC!K69-RC!L69 -> 1316760
A38: + | B38: Aumento (diminuzione) debiti strutturali a breve | C38: =RC!B70-RC!C70 -> -67348 | D38: =RC!C70-RC!D70 -> 484822 | E38: =RC!D70-RC!E70 -> 59092 | F38: =RC!E70-RC!F70 -> -213288 | G38: =RC!F70-RC!G70 -> -1040287 | H38: =RC!G70-RC!H70 -> 88378 | I38: =RC!H70-RC!I70 -> 271553 | J38: =RC!I70-RC!J70 -> 59944 | ... L38: =RC!K70-RC!L70 -> 886758
A39: - | B39: (Aumento) diminuzione riserve strategiche di liquidità | C39: =-(RC!B30-RC!C30) -> 0 | D39: =-(RC!C30-RC!D30) -> 0 | E39: =-(RC!D30-RC!E30) -> 0 | F39: =-(RC!E30-RC!F30) -> 0 | G39: =-(RC!F30-RC!G30) -> 0 | H39: =-(RC!G30-RC!H30) -> 0 | I39: =-(RC!H30-RC!I30) -> 0 | J39: =-(RC!I30-RC!J30) -> 0 | ... L39: =-(RC!K30-RC!L30) -> 0
A40: = | B40: Flussi di cassa netti sul debito netto (esclusa tesoreria) (FCDN) | C40: =SUM(C34:C39) -> -630655.79 | D40: =SUM(D34:D39) -> 254925.08 | E40: =SUM(E34:E39) -> -157559.82 | F40: =SUM(F34:F39) -> -605054.91 | G40: =SUM(G34:G39) -> -118869.52 | H40: =SUM(H34:H39) -> -177354.29 | I40: =SUM(I34:I39) -> 46268.71 | J40: =SUM(J34:J39) -> -208605.52 | ... L40: =SUM(L34:L39) -> 2122595.2
A41: = | B41: Free cash flow to equity (FCFE) | C41: =C31+C40 -> 48610 | D41: =D31+D40 -> 37577 | E41: =E31+E40 -> -267125 | F41: =F31+F40 -> -45033 | G41: =G31+G40 -> 353773 | H41: =H31+H40 -> 3944 | I41: =I31+I40 -> -69394 | J41: =J31+J40 -> -957892 | ... L41: =L31+L40 -> -663191
B42: Capitale proprio
A43: - | B43: (Stima utili distribuiti) | C43: =RC!B79 -> 1395828 | D43: =RC!C79 -> 1372267 | E43: =RC!D79 -> 1234248 | F43: =RC!E79 -> 1143314 | G43: =RC!F79 -> 1116155 | H43: =RC!G79 -> 1074635 | I43: =RC!H79 -> 1011927 | J43: =RC!I79 -> 981757 | ... L43: =RC!K79 -> 571453
A44: - | B44: (Aumento) diminuzione azioni proprie e partec in controllanti | C44: =-(RC!B81-RC!C81) -> 0 | D44: =-(RC!C81-RC!D81) -> 0 | E44: =-(RC!D81-RC!E81) -> 0 | F44: =-(RC!E81-RC!F81) -> 0 | G44: =-(RC!F81-RC!G81) -> 0 | H44: =-(RC!G81-RC!H81) -> 0 | I44: =-(RC!H81-RC!I81) -> 0 | J44: =-(RC!I81-RC!J81) -> 0 | ... L44: =-(RC!K81-RC!L81) -> 0
A45: + | B45: Aumento (diminuzione) finanziamenti netti da soci e controllanti | C45: =RC!B76-RC!C76 -> 0 | D45: =RC!C76-RC!D76 -> 0 | E45: =RC!D76-RC!E76 -> 0 | F45: =RC!E76-RC!F76 -> 0 | G45: =RC!F76-RC!G76 -> 0 | H45: =RC!G76-RC!H76 -> 0 | I45: =RC!H76-RC!I76 -> 0 | J45: =RC!I76-RC!J76 -> 0 | ... L45: =RC!K76-RC!L76 -> 0
A46: + | B46: Aumento (diminuzione) di capitale conferito dai soci | C46: =RC!B78-RC!C78 -> 0 | D46: =RC!C78-RC!D78 -> 0 | E46: =RC!D78-RC!E78 -> 0 | F46: =RC!E78-RC!F78 -> 0 | G46: =RC!F78-RC!G78 -> 0 | H46: =RC!G78-RC!H78 -> 0 | I46: =RC!H78-RC!I78 -> 0 | J46: =RC!I78-RC!J78 -> 0 | ... L46: =RC!K78-RC!L78 -> 110000
A47: + | B47: Aumento (diminuzione) capitale proprio di pertinenza di terzi | C47: =RC!B83-RC!C83 -> 0 | D47: =RC!C83-RC!D83 -> 0 | E47: =RC!D83-RC!E83 -> 0 | F47: =RC!E83-RC!F83 -> 0 | G47: =RC!F83-RC!G83 -> 0 | H47: =RC!G83-RC!H83 -> 0 | I47: =RC!H83-RC!I83 -> 0 | J47: =RC!I83-RC!J83 -> 0 | ... L47: =RC!K83-RC!L83 -> 0
A48: = | B48: Flussi di cassa effettivi sul capitale proprio (FCCP) | C48: =SUM(C43:C47) -> 1395828 | D48: =SUM(D43:D47) -> 1372267 | E48: =SUM(E43:E47) -> 1234248 | F48: =SUM(F43:F47) -> 1143314 | G48: =SUM(G43:G47) -> 1116155 | H48: =SUM(H43:H47) -> 1074635 | I48: =SUM(I43:I47) -> 1011927 | J48: =SUM(J43:J47) -> 981757 | ... L48: =SUM(L43:L47) -> 681453
A49: = | B49: Flusso di cassa netto (NCF) | C49: =C41+C48 -> 1444438 | D49: =D41+D48 -> 1409844 | E49: =E41+E48 -> 967123 | F49: =F41+F48 -> 1098281 | G49: =G41+G48 -> 1469928 | H49: =H41+H48 -> 1078579 | I49: =I41+I48 -> 942533 | J49: =J41+J48 -> 23865 | ... L49: =L41+L48 -> 18262
B51: Check NCF
A52: + | B52: Aumento (diminuzione) attività di tesoreria | C52: =RC!B31-RC!C31 -> 48608 | D52: =RC!C31-RC!D31 -> 37578 | E52: =RC!D31-RC!E31 -> -267124 | F52: =RC!E31-RC!F31 -> -45034 | G52: =RC!F31-RC!G31 -> 353773 | H52: =RC!G31-RC!H31 -> 3944 | I52: =RC!H31-RC!I31 -> -69394 | J52: =RC!I31-RC!J31 -> 108541 | ... L52: =RC!K31-RC!L31 -> 0
A53: - | B53: (Aumento) diminuzione debiti di tesoreria | C53: =-(RC!B71-RC!C71) -> 0 | D53: =-(RC!C71-RC!D71) -> 0 | E53: =-(RC!D71-RC!E71) -> 0 | F53: =-(RC!E71-RC!F71) -> 0 | G53: =-(RC!F71-RC!G71) -> 0 | H53: =-(RC!G71-RC!H71) -> 0 | I53: =-(RC!H71-RC!I71) -> 0 | J53: =-(RC!I71-RC!J71) -> 0 | ... L53: =-(RC!K71-RC!L71) -> 0
A54: = | B54: Variazione posizione netta di tesoreria | C54: =C52+C53 -> 48608 | D54: =D52+D53 -> 37578 | E54: =E52+E53 -> -267124 | F54: =F52+F53 -> -45034 | G54: =G52+G53 -> 353773 | H54: =H52+H53 -> 3944 | I54: =I52+I53 -> -69394 | J54: =J52+J53 -> 108541 | ... L54: =L52+L53 -> 0
A55: = | B55: NCF | C55: =C49 -> 1444438 | D55: =D49 -> 1409844 | E55: =E49 -> 967123 | F55: =F49 -> 1098281 | G55: =G49 -> 1469928 | H55: =H49 -> 1078579 | I55: =I49 -> 942533 | J55: =J49 -> 23865 | ... L55: =L49 -> 18262
B56: Sbilancio check NCF | C56: =C54-C55 -> -1395830 | D56: =D54-D55 -> -1372266 | E56: =E54-E55 -> -1234247 | F56: =F54-F55 -> -1143315 | G56: =G54-G55 -> -1116155 | H56: =H54-H55 -> -1074635 | I56: =I54-I55 -> -1011927 | J56: =J54-J55 -> 84676 | ... L56: =L54-L55 -> -18262
B57: Check FCFF
A58: + | B58: EBITDA al netto delle imposte check | C58: =C8 -> 391530.79 | D58: =D8 -> 444791.92 | E58: =E8 -> 465343.82 | F58: =F8 -> 418966.91 | G58: =G8 -> 285702.52 | H58: =H8 -> 344386.29 | I58: =I8 -> 368326.29 | J58: =J8 -> 331899.52 | ... L58: =L8 -> 608581.79
A59: - | B59: -Ammortamenti check | C59: =-C6 -> -178212 | D59: =-D6 -> -262884 | E59: =-E6 -> -284679 | F59: =-F6 -> -291427 | G59: =-G6 -> -207100 | H59: =-H6 -> -250219 | I59: =-I6 -> -254982 | J59: =-J6 -> -237401 | ... L59: =-L6 -> -190385
A60: - | B60: -VAR AON* | C60: =(RC!B162-RC!C162)*-1 -> 480947 | D60: =(RC!C162-RC!D162)*-1 -> -374256 | E60: =(RC!D162-RC!E162)*-1 -> -290230 | F60: =(RC!E162-RC!F162)*-1 -> 432482 | G60: =(RC!F162-RC!G162)*-1 -> -1447843 | H60: =(RC!G162-RC!H162)*-1 -> 117131 | I60: =(RC!H162-RC!I162)*-1 -> -229007 | J60: =(RC!I162-RC!J162)*-1 -> -843785 | ... L60: =(RC!K162-RC!L162)*-1 -> -3201983
A61: - | B61: -VAR AACC | C61: =(RC!B27-RC!C27)*-1 -> -15000 | D61: =(RC!C27-RC!D27)*-1 -> -25000 | E61: =(RC!D27-RC!E27)*-1 -> 0 | F61: =(RC!E27-RC!F27)*-1 -> 0 | G61: =(RC!F27-RC!G27)*-1 -> 0 | H61: =(RC!G27-RC!H27)*-1 -> -30000 | I61: =(RC!H27-RC!I27)*-1 -> 0 | J61: =(RC!I27-RC!J27)*-1 -> 0 | ... L61: =(RC!K27-RC!L27)*-1 -> -2000
A62: + | B62: +VAR P.ACC | C62: =RC!B66-RC!C66 -> 0 | D62: =RC!C66-RC!D66 -> 0 | E62: =RC!D66-RC!E66 -> 0 | F62: =RC!E66-RC!F66 -> 0 | G62: =RC!F66-RC!G66 -> 0 | H62: =RC!G66-RC!H66 -> 0 | I62: =RC!H66-RC!I66 -> 0 | J62: =RC!I66-RC!J66 -> 0 | ... L62: =RC!K66-RC!L66 -> 0
A63: + | B63: +Var. Ris. rivalutazione | C63: =RC!B80-RC!C80 -> 0 | D63: =RC!C80-RC!D80 -> 0 | E63: =RC!D80-RC!E80 -> 0 | F63: =RC!E80-RC!F80 -> 0 | G63: =RC!F80-RC!G80 -> 1841883 | H63: =RC!G80-RC!H80 -> 0 | I63: =RC!H80-RC!I80 -> 0 | J63: =RC!I80-RC!J80 -> 0 | ... L63: =RC!K80-RC!L80 -> 0
A64: = | B64: = Risultato | C64: =SUM(C58:C63) -> 679265.79 | D64: =SUM(D58:D63) -> -217348.08 | E64: =SUM(E58:E63) -> -109565.18 | F64: =SUM(F58:F63) -> 560021.91 | G64: =SUM(G58:G63) -> 472642.52 | H64: =SUM(H58:H63) -> 181298.29 | I64: =SUM(I58:I63) -> -115662.71 | J64: =SUM(J58:J63) -> -749286.48 | ... L64: =SUM(L58:L63) -> -2785786.2
A65: = | B65: = FCFF ceck | C65: =C31 -> 679265.79 | D65: =D31 -> -217348.08 | E65: =E31 -> -109565.18 | F65: =F31 -> 560021.91 | G65: =G31 -> 472642.52 | H65: =H31 -> 181298.29 | I65: =I31 -> -115662.71 | J65: =J31 -> -749286.48 | ... L65: =L31 -> -2785786.2
B66: Sbilancio check FCFF | C66: =C64-C65 -> 0 | D66: =D64-D65 -> 0 | E66: =E64-E65 -> 0 | F66: =F64-F65 -> 0 | G66: =G64-G65 -> 0 | H66: =H64-H65 -> 0 | I66: =I64-I65 -> 0 | J66: =J64-J65 -> 0 | ... L66: =L64-L65 -> 0
B67: Check FCFE
A68: + | B68: Reddito netto check | C68: =RC!B150 -> 47991 | D68: =RC!C150 -> 23563 | E68: =RC!D150 -> 138018 | F68: =RC!E150 -> 90933 | G68: =RC!F150 -> 27160 | H68: =RC!G150 -> 41520 | I68: =RC!H150 -> 62708 | J68: =RC!I150 -> 30170 | ... L68: =RC!K150 -> 337274
A69: - | B69: - Var (AON* + Att acc - Deb contr coll - Ris riv.) check 2 | C69: =SUM(C60:C63) -> 465947 | D69: =SUM(D60:D63) -> -399256 | E69: =SUM(E60:E63) -> -290230 | F69: =SUM(F60:F63) -> 432482 | G69: =SUM(G60:G63) -> 394040 | H69: =SUM(H60:H63) -> 87131 | I69: =SUM(I60:I63) -> -229007 | J69: =SUM(J60:J63) -> -843785 | ... L69: =SUM(L60:L63) -> -3203983
B70: + Var (Debito strutt + deriv pass - ris strat liq - deriv att ) check | C70: =SUM(C71:C74) -> -465328 | D70: =SUM(D71:D74) -> 413270 | E70: =SUM(E71:E74) -> -114913 | F70: =SUM(F71:F74) -> -568448 | G70: =SUM(G71:G74) -> -67427 | H70: =SUM(H71:H74) -> -124707 | I70: =SUM(I71:I74) -> 96905 | J70: =SUM(J71:J74) -> -144277 | ... L70: =SUM(L71:L74) -> 2203518
B71: +VAR deb strutt m/l + bt | C71: =RC!B69+RC!B70-RC!C69-RC!C70 -> -465328 | D71: =RC!C69+RC!C70-RC!D69-RC!D70 -> 413270 | E71: =RC!D69+RC!D70-RC!E69-RC!E70 -> -114913 | F71: =RC!E69+RC!E70-RC!F69-RC!F70 -> -568448 | G71: =RC!F69+RC!F70-RC!G69-RC!G70 -> -67427 | H71: =RC!G69+RC!G70-RC!H69-RC!H70 -> -124707 | I71: =RC!H69+RC!H70-RC!I69-RC!I70 -> 96905 | J71: =RC!I69+RC!I70-RC!J69-RC!J70 -> -144277 | ... L71: =RC!K69+RC!K70-RC!L69-RC!L70 -> 2203518
B72: +VAR deriv pass | C72: =RC!B72-RC!C72 -> 0 | D72: =RC!C72-RC!D72 -> 0 | E72: =RC!D72-RC!E72 -> 0 | F72: =RC!E72-RC!F72 -> 0 | G72: =RC!F72-RC!G72 -> 0 | H72: =RC!G72-RC!H72 -> 0 | I72: =RC!H72-RC!I72 -> 0 | J72: =RC!I72-RC!J72 -> 0 | ... L72: =RC!K72-RC!L72 -> 0
B73: -VAR deriv att | C73: =-(RC!B32-RC!C32) -> 0 | D73: =-(RC!C32-RC!D32) -> 0 | E73: =-(RC!D32-RC!E32) -> 0 | F73: =-(RC!E32-RC!F32) -> 0 | G73: =-(RC!F32-RC!G32) -> 0 | H73: =-(RC!G32-RC!H32) -> 0 | I73: =-(RC!H32-RC!I32) -> 0 | J73: =-(RC!I32-RC!J32) -> 0 | ... L73: =-(RC!K32-RC!L32) -> 0
A74: + | B74: -VAR AON*
B75: = Risultato | C75: =SUM(C68:C70) -> 48610 | D75: =SUM(D68:D70) -> 37577 | E75: =SUM(E68:E70) -> -267125 | F75: =SUM(F68:F70) -> -45033 | G75: =SUM(G68:G70) -> 353773 | H75: =SUM(H68:H70) -> 3944 | I75: =SUM(I68:I70) -> -69394 | J75: =SUM(J68:J70) -> -957892 | ... L75: =SUM(L68:L70) -> -663191
A76: = | B76: = FCFE check | C76: =C41 -> 48610 | D76: =D41 -> 37577 | E76: =E41 -> -267125 | F76: =F41 -> -45033 | G76: =G41 -> 353773 | H76: =H41 -> 3944 | I76: =I41 -> -69394 | J76: =J41 -> -957892 | ... L76: =L41 -> -663191
B77: Sbilancio check FCFE | C77: =C75-C76 -> 0 | D77: =D75-D76 -> 0 | E77: =E75-E76 -> 0 | F77: =F75-F76 -> 0 | G77: =G75-G76 -> 0 | H77: =H75-H76 -> -2.910383e-11 | I77: =I75-I76 -> 0 | J77: =J75-J76 -> 0 | ... L77: =L75-L76 -> 0

Sheet ind
A1: INDICATORI FINANZIARI | B1: =RF!C1 -> 2024 | C1: =RF!D1 -> 2023 | D1: =RF!E1 -> 2022 | E1: =RF!F1 -> 2021 | F1: =RF!G1 -> 2020 | G1: =RF!H1 -> 2019 | H1: =RF!I1 -> 2018 | I1: =RF!J1 -> 2017 | ... K1: =RF!L1 -> 2015
A2: valori patrimoniali medie t-1 per attenuare variazioni significativi
A3: RLA (redd. gest OFA) | B3: =RC!B131+RC!B140+RC!B144 -> 100052 | C3: =RC!C131+RC!C140+RC!C144 -> 57759 | D3: =RC!D131+RC!D140+RC!D144 -> 204925 | E3: =RC!E131+RC!E140+RC!E144 -> 130850 | F3: =RC!F131+RC!F140+RC!F144 -> 40725 | G3: =RC!G131+RC!G140+RC!G144 -> 61709 | H3: =RC!H131+RC!H140+RC!H144 -> 90235 | I3: =RC!I131+RC!I140+RC!I144 -> 42605 | ... K3: =RC!K131+RC!K140+RC!K144 -> 501438
A4: Reddito operativo | B4: =RC!B131 -> 208796 | C4: =RC!C131 -> 157219 | D4: =RC!D131 -> 237075 | E4: =RC!E131 -> 158900 | F4: =RC!F131 -> 79314 | G4: =RC!G131 -> 101378 | H4: =RC!H131 -> 129035 | I4: =RC!I131 -> 92400 | ... K4: =RC!K131 -> 562402
A5: EBITDA(MOL) | B5: =RC!B123 -> 425646 | C5: =RC!C123 -> 478043 | D5: =RC!D123 -> 508402 | E5: =RC!E123 -> 485379 | F5: =RC!F123 -> 323613 | G5: =RC!G123 -> 392247 | H5: =RC!H123 -> 423438 | I5: =RC!I123 -> 355258 | ... K5: =RC!K123 -> 792171
A6: Reddito netto | B6: =RC!B150 -> 47991 | C6: =RC!C150 -> 23563 | D6: =RC!D150 -> 138018 | E6: =RC!E150 -> 90933 | F6: =RC!F150 -> 27160 | G6: =RC!G150 -> 41520 | H6: =RC!H150 -> 62708 | I6: =RC!I150 -> 30170 | ... K6: =RC!K150 -> 337274
A7: Ricavi | B7: =RC!B111 -> 10781972 | C7: =RC!C111 -> 10502251 | D7: =RC!D111 -> 9797336 | E7: =RC!E111 -> 8086488 | F7: =RC!F111 -> 7349721 | G7: =RC!G111 -> 8370970 | H7: =RC!H111 -> 7727686 | I7: =RC!I111 -> 7677878 | ... K7: =RC!K111 -> 6901829
A8: Ricavi t-1 | B8: =RC!C111 -> 10502251 | C8: =RC!D111 -> 9797336 | D8: =RC!E111 -> 8086488 | E8: =RC!F111 -> 7349721 | F8: =RC!G111 -> 8370970 | G8: =RC!H111 -> 7727686 | H8: =RC!I111 -> 7677878 | I8: =RC!J111 -> 7424443 | ... K8: =RC!L111 -> 0
A9: Ricavi con IVA gg | B9: =B7*1.22/365 -> 36038.372 | C9: =C7*1.22/365 -> 35103.414 | D9: =D7*1.22/365 -> 32747.26 | E9: =E7*1.22/365 -> 27028.809 | F9: =F7*1.22/365 -> 24566.191 | G9: =G7*1.22/365 -> 27979.681 | H9: =H7*1.22/365 -> 25829.526 | I9: =I7*1.22/365 -> 25663.044 | ... K9: =K7*1.22/365 -> 23069.127
A10: Acquisti | B10: =RC!B116 -> -9103208 | C10: =RC!C116 -> -8982781 | D10: =RC!D116 -> -8702682 | E10: =RC!E116 -> -6481970 | F10: =RC!F116 -> -6180455 | G10: =RC!G116 -> -6952573 | H10: =RC!H116 -> -6523415 | I10: =RC!I116 -> -6536916 | ... K10: =RC!K116 -> -5593293
A11: Acquisti con IVA gg | B11: =RC!B116*1.22/365 -> -30427.161 | C11: =RC!C116*1.22/365 -> -30024.638 | D11: =RC!D116*1.22/365 -> -29088.417 | E11: =RC!E116*1.22/365 -> -21665.763 | F11: =RC!F116*1.22/365 -> -20657.959 | G11: =RC!G116*1.22/365 -> -23238.737 | H11: =RC!H116*1.22/365 -> -21804.291 | I11: =RC!I116*1.22/365 -> -21849.418 | ... K11: =RC!K116*1.22/365 -> -18695.39
A12: Costo del venduto gg medio | B12: =AVERAGE(RC!B120:C120)/365 -> -24961.249 | C12: =AVERAGE(RC!C120:D120)/365 -> -23479.788 | D12: =AVERAGE(RC!D120:E120)/365 -> -20402.852 | E12: =AVERAGE(RC!E120:F120)/365 -> -17607.208 | F12: =AVERAGE(RC!F120:G120)/365 -> -18117.84 | G12: =AVERAGE(RC!G120:H120)/365 -> -18460.058 | H12: =AVERAGE(RC!H120:I120)/365 -> -17787.09 | I12: =AVERAGE(RC!I120:J120)/365 -> -17629.348 | ... K12: =AVERAGE(RC!K120:L120)/365 -> -14652.249
A13: Costo del personale gg medio | B13: =AVERAGE(RC!B122:C122)/365 -> -2957.2904 | C13: =AVERAGE(RC!C122:D122)/365 -> -2976.5712 | D13: =AVERAGE(RC!D122:E122)/365 -> -2734.1932 | E13: =AVERAGE(RC!E122:F122)/365 -> -2430.0753 | F13: =AVERAGE(RC!F122:G122)/365 -> -2436.7233 | G13: =AVERAGE(RC!G122:H122)/365 -> -2475.5192 | H13: =AVERAGE(RC!H122:I122)/365 -> -2249.7151 | I13: =AVERAGE(RC!I122:J122)/365 -> -1997.2849 | ... K13: =AVERAGE(RC!K122:L122)/365 -> -2086.5397
A14: AON* medio | B14: =AVERAGE(RC!B93,RC!C93) -> 4915610.5 | C14: =AVERAGE(RC!C93,RC!D93) -> 4968956 | D14: =AVERAGE(RC!D93,RC!E93) -> 4636713 | E14: =AVERAGE(RC!E93,RC!F93) -> 4707839 | F14: =AVERAGE(RC!F93,RC!G93) -> 4200158.5 | G14: =AVERAGE(RC!G93,RC!H93) -> 3534802.5 | H14: =AVERAGE(RC!H93,RC!I93) -> 3478864.5 | I14: =AVERAGE(RC!I93,RC!J93) -> 2942468.5 | ... K14: =AVERAGE(RC!K93,RC!L93) -> 3201983
A15: AON* init | B15: =RC!C93 -> 5156084 | C15: =RC!D93 -> 4781828 | D15: =RC!E93 -> 4491598 | E15: =RC!F93 -> 4924080 | F15: =RC!G93 -> 3476237 | G15: =RC!H93 -> 3593368 | H15: =RC!I93 -> 3364361 | I15: =RC!J93 -> 2520576 | ... K15: =RC!L93 -> 0
A16: AON* fin | B16: =RC!B93 -> 4675137 | C16: =RC!C93 -> 5156084 | D16: =RC!D93 -> 4781828 | E16: =RC!E93 -> 4491598 | F16: =RC!F93 -> 4924080 | G16: =RC!G93 -> 3476237 | H16: =RC!H93 -> 3593368 | I16: =RC!I93 -> 3364361 | ... K16: =RC!K93 -> 3201983
A17: Reddito att.acc (prov-oneri acc) | B17: =RC!B144 -> 0 | C17: =RC!C144 -> 0 | D17: =RC!D144 -> 0 | E17: =RC!E144 -> 0 | F17: =RC!F144 -> 0 | G17: =RC!G144 -> 0 | H17: =RC!H144 -> 0 | I17: =RC!I144 -> 0 | ... K17: =RC!K144 -> 0
A18: AACCN media(ris gest acc) | B18: =AVERAGE(RC!B94,RC!C94) -> 64500 | C18: =AVERAGE(RC!C94,RC!D94) -> 44500 | D18: =AVERAGE(RC!D94,RC!E94) -> 32000 | E18: =AVERAGE(RC!E94,RC!F94) -> 32000 | F18: =AVERAGE(RC!F94,RC!G94) -> 32000 | G18: =AVERAGE(RC!G94,RC!H94) -> 17000 | H18: =AVERAGE(RC!H94,RC!I94) -> 2000 | I18: =AVERAGE(RC!I94,RC!J94) -> 2000 | ... K18: =AVERAGE(RC!K94,RC!L94) -> 2000
A19: AACC medie(solo attività) | B19: =AVERAGE(RC!B27,RC!C27) -> 64500 | C19: =AVERAGE(RC!C27,RC!D27) -> 44500 | D19: =AVERAGE(RC!D27,RC!E27) -> 32000 | E19: =AVERAGE(RC!E27,RC!F27) -> 32000 | F19: =AVERAGE(RC!F27,RC!G27) -> 32000 | G19: =AVERAGE(RC!G27,RC!H27) -> 17000 | H19: =AVERAGE(RC!H27,RC!I27) -> 2000 | I19: =AVERAGE(RC!I27,RC!J27) -> 2000 | ... K19: =AVERAGE(RC!K27,RC!L27) -> 2000
A20: AACC finali | B20: =RC!B27 -> 72000 | C20: =RC!C27 -> 57000 | D20: =RC!D27 -> 32000 | E20: =RC!E27 -> 32000 | F20: =RC!F27 -> 32000 | G20: =RC!G27 -> 32000 | H20: =RC!H27 -> 2000 | I20: =RC!I27 -> 2000 | ... K20: =RC!K27 -> 2000
A21: PACC medie (solo passivo) | B21: =AVERAGE(RC!B66,RC!C66) -> 0 | C21: =AVERAGE(RC!C66,RC!D66) -> 0 | D21: =AVERAGE(RC!D66,RC!E66) -> 0 | E21: =AVERAGE(RC!E66,RC!F66) -> 0 | F21: =AVERAGE(RC!F66,RC!G66) -> 0 | G21: =AVERAGE(RC!G66,RC!H66) -> 0 | H21: =AVERAGE(RC!H66,RC!I66) -> 0 | I21: =AVERAGE(RC!I66,RC!J66) -> 0 | ... K21: =AVERAGE(RC!K66,RC!L66) -> 0
A22: PACC finali (solo passivo) | B22: =RC!B66 -> 0 | C22: =RC!C66 -> 0 | D22: =RC!D66 -> 0 | E22: =RC!E66 -> 0 | F22: =RC!F66 -> 0 | G22: =RC!G66 -> 0 | H22: =RC!H66 -> 0 | I22: =RC!I66 -> 0 | ... K22: =RC!K66 -> 0
A23: ris gest str | B23: =RC!B145 -> 0 | C23: =RC!C145 -> 0 | D23: =RC!D145 -> 0 | E23: =RC!E145 -> 0 | F23: =RC!F145 -> 0 | G23: =RC!G145 -> 0 | H23: =RC!H145 -> 0 | I23: =RC!I145 -> 0 | ... K23: =RC!K145 -> 0
A24: PFN (ris gest fin) | B24: =B30-B31 -> 1608403 | C24: =C30-C31 -> 1677525 | D24: =D30-D31 -> 1413573.5 | E24: =E30-E31 -> 1599175 | F24: =F30-F31 -> 2071482 | G24: =G30-G31 -> 2346407.5 | H24: =H30-H31 -> 2327583.5 | I24: =I30-I31 -> 2370843 | ... K24: =K30-K31 -> 2203518
A25: DEBn | B25: =IF(B24>0, B24, 0) -> 1608403 | C25: =IF(C24>0, C24, 0) -> 1677525 | D25: =IF(D24>0, D24, 0) -> 1413573.5 | E25: =IF(E24>0, E24, 0) -> 1599175 | F25: =IF(F24>0, F24, 0) -> 2071482 | G25: =IF(G24>0, G24, 0) -> 2346407.5 | H25: =IF(H24>0, H24, 0) -> 2327583.5 | I25: =IF(I24>0, I24, 0) -> 2370843 | ... K25: =IF(K24>0, K24, 0) -> 2203518
A26: LIQn | B26: =IF(B24<0, -B24, 0) -> 0 | C26: =IF(C24<0, C24, 0) -> 0 | D26: =IF(D24<0, D24, 0) -> 0 | E26: =IF(E24<0, E24, 0) -> 0 | F26: =IF(F24<0, F24, 0) -> 0 | G26: =IF(G24<0, G24, 0) -> 0 | H26: =IF(H24<0, H24, 0) -> 0 | I26: =IF(I24<0, I24, 0) -> 0 | J26: =IF(J24<0, J24, 0) -> 0 | K26: =IF(K24<0, K24, 0) -> 0
A27: oneri finanziari | B27: =RC!B138 -> -110269 | C27: =RC!C138 -> -101600 | D27: =RC!D138 -> -34715 | E27: =RC!E138 -> -32939 | F27: =RC!F138 -> -42003 | G27: =RC!G138 -> -43669 | H27: =RC!H138 -> -40987 | I27: =RC!I138 -> -52706 | ... K27: =RC!K138 -> -60976
A28: interessi attivi | B28: =RC!B137 -> 1525 | C28: =RC!C137 -> 2140 | D28: =RC!D137 -> 2565 | E28: =RC!E137 -> 4889 | F28: =RC!F137 -> 3414 | G28: =RC!G137 -> 4000 | H28: =RC!H137 -> 2187 | I28: =RC!I137 -> 2911 | ... K28: =RC!K137 -> 12
A29: imposta | B29: =RC!B149 -> -52061 | C29: =RC!C149 -> -34196 | D29: =RC!D149 -> -66907 | E29: =RC!E149 -> -39917 | F29: =RC!F149 -> -13565 | G29: =RC!G149 -> -20189 | H29: =RC!H149 -> -27527 | I29: =RC!I149 -> -12435 | ... K29: =RC!K149 -> -164164
A30: Debito lordo medio(pass. gest. fin) | B30: =AVERAGE(RC!B73,RC!C73) -> 1754991 | C30: =AVERAGE(RC!C73,RC!D73) -> 1781020 | D30: =AVERAGE(RC!D73,RC!E73) -> 1631841.5 | E30: =AVERAGE(RC!E73,RC!F73) -> 1973522 | F30: =AVERAGE(RC!F73,RC!G73) -> 2291459.5 | G30: =AVERAGE(RC!G73,RC!H73) -> 2387526.5 | H30: =AVERAGE(RC!H73,RC!I73) -> 2401427.5 | I30: =AVERAGE(RC!I73,RC!J73) -> 2425113.5 | ... K30: =AVERAGE(RC!K73,RC!L73) -> 2203518
A31: Liq. lorda media(att. gest fin) | B31: =AVERAGE(RC!B33,RC!C33) -> 146588 | C31: =AVERAGE(RC!C33,RC!D33) -> 103495 | D31: =AVERAGE(RC!D33,RC!E33) -> 218268 | E31: =AVERAGE(RC!E33,RC!F33) -> 374347 | F31: =AVERAGE(RC!F33,RC!G33) -> 219977.5 | G31: =AVERAGE(RC!G33,RC!H33) -> 41119 | H31: =AVERAGE(RC!H33,RC!I33) -> 73844 | I31: =AVERAGE(RC!I33,RC!J33) -> 54270.5 | ... K31: =AVERAGE(RC!K33,RC!L33) -> 0
A32: Crediti commerciali medi | B32: =AVERAGE(RC!B5:C5) -> 1364807.5 | C32: =AVERAGE(RC!C5:D5) -> 1326245 | D32: =AVERAGE(RC!D5:E5) -> 1182449 | E32: =AVERAGE(RC!E5:F5) -> 871810.5 | F32: =AVERAGE(RC!F5:G5) -> 892609 | G32: =AVERAGE(RC!G5:H5) -> 1038561 | H32: =AVERAGE(RC!H5:I5) -> 910853 | I32: =AVERAGE(RC!I5:J5) -> 807385 | ... K32: =AVERAGE(RC!K5:L5) -> 795525
A33: Debiti commerciali medi | B33: =AVERAGE(RC!B48,RC!C48) -> 1012072.5 | C33: =AVERAGE(RC!C48,RC!D48) -> 1047930.5 | D33: =AVERAGE(RC!D48,RC!E48) -> 946133.5 | E33: =AVERAGE(RC!E48,RC!F48) -> 639978 | F33: =AVERAGE(RC!F48,RC!G48) -> 539441.5 | G33: =AVERAGE(RC!G48,RC!H48) -> 588493.5 | H33: =AVERAGE(RC!H48,RC!I48) -> 615389 | I33: =AVERAGE(RC!I48,RC!J48) -> 625322 | ... K33: =AVERAGE(RC!K48,RC!L48) -> 622035
A34: Rimanenze magazzino medie | B34: =AVERAGE(RC!B6,RC!C6) -> 1257418.5 | C34: =AVERAGE(RC!C6,RC!D6) -> 1325280 | D34: =AVERAGE(RC!D6,RC!E6) -> 1052671.5 | E34: =AVERAGE(RC!E6,RC!F6) -> 907386.5 | F34: =AVERAGE(RC!F6,RC!G6) -> 1002805 | G34: =AVERAGE(RC!G6,RC!H6) -> 1049302.5 | H34: =AVERAGE(RC!H6,RC!I6) -> 1049229 | I34: =AVERAGE(RC!I6,RC!J6) -> 498364 | ... K34: =AVERAGE(RC!K6,RC!L6) -> 986831
A35: Rimanenze magazzino finali | B35: =RC!B6 -> 1163582 | C35: =RC!C6 -> 1351255 | D35: =RC!D6 -> 1299305 | E35: =RC!E6 -> 806038 | F35: =RC!F6 -> 1008735 | G35: =RC!G6 -> 996875 | H35: =RC!H6 -> 1101730 | I35: =RC!I6 -> 996728 | ... K35: =RC!K6 -> 986831
A36: Attività a BT | B36: =AVERAGE(RC!B8:C8)+AVERAGE(RC!B19:C19)+AVERAGE(RC!B30:C30) -> 2749317.5 | C36: =AVERAGE(RC!C8:D8)+AVERAGE(RC!C19:D19)+AVERAGE(RC!C30:D30) -> 2829118.5 | D36: =AVERAGE(RC!D8:E8)+AVERAGE(RC!D19:E19)+AVERAGE(RC!D30:E30) -> 2375333.5 | E36: =AVERAGE(RC!E8:F8)+AVERAGE(RC!E19:F19)+AVERAGE(RC!E30:F30) -> 1917385.5 | F36: =AVERAGE(RC!F8:G8)+AVERAGE(RC!F19:G19)+AVERAGE(RC!F30:G30) -> 2036517.5 | G36: =AVERAGE(RC!G8:H8)+AVERAGE(RC!G19:H19)+AVERAGE(RC!G30:H30) -> 2231275.5 | H36: =AVERAGE(RC!H8:I8)+AVERAGE(RC!H19:I19)+AVERAGE(RC!H30:I30) -> 2129390.5 | I36: =AVERAGE(RC!I8:J8)+AVERAGE(RC!I19:J19)+AVERAGE(RC!I30:J30) -> 1494554.5 | ... K36: =AVERAGE(RC!K8:L8)+AVERAGE(RC!K19:L19)+AVERAGE(RC!K30:L30) -> 2012254
A37: Attività a BT finali | B37: =RC!B8+RC!B19+RC!B30 -> 2569788 | C37: =RC!C8+RC!C19+RC!C30 -> 2928847 | D37: =RC!D8+RC!D19+RC!D30 -> 2729390 | E37: =RC!E8+RC!E19+RC!E30 -> 2021277 | F37: =RC!F8+RC!F19+RC!F30 -> 1813494 | G37: =RC!G8+RC!G19+RC!G30 -> 2259541 | H37: =RC!H8+RC!H19+RC!H30 -> 2203010 | I37: =RC!I8+RC!I19+RC!I30 -> 2055771 | ... K37: =RC!K8+RC!K19+RC!K30 -> 2012254
A38: Passività a BT medie | B38: =AVERAGE(RC!B51:C51)+AVERAGE(RC!B59:C59)+AVERAGE(RC!B70:C70) -> 2127108.5 | C38: =AVERAGE(RC!C51:D51)+AVERAGE(RC!C59:D59)+AVERAGE(RC!C70:D70) -> 1933434.5 | D38: =AVERAGE(RC!D51:E51)+AVERAGE(RC!D59:E59)+AVERAGE(RC!D70:E70) -> 1518948.5 | E38: =AVERAGE(RC!E51:F51)+AVERAGE(RC!E59:F59)+AVERAGE(RC!E70:F70) -> 1298891 | F38: =AVERAGE(RC!F51:G51)+AVERAGE(RC!F59:G59)+AVERAGE(RC!F70:G70) -> 1804966.5 | G38: =AVERAGE(RC!G51:H51)+AVERAGE(RC!G59:H59)+AVERAGE(RC!G70:H70) -> 2295620 | H38: =AVERAGE(RC!H51:I51)+AVERAGE(RC!H59:I59)+AVERAGE(RC!H70:I70) -> 2113880.5 | I38: =AVERAGE(RC!I51:J51)+AVERAGE(RC!I59:J59)+AVERAGE(RC!I70:J70) -> 1937224.5 | ... K38: =AVERAGE(RC!K51:L51)+AVERAGE(RC!K59:L59)+AVERAGE(RC!K70:L70) -> 1592282
A39: Passività a BT finali | B39: =RC!B51+RC!B59+RC!B70 -> 2059586 | C39: =RC!C51+RC!C59+RC!C70 -> 2194631 | D39: =RC!D51+RC!D59+RC!D70 -> 1672238 | E39: =RC!E51+RC!E59+RC!E70 -> 1365659 | F39: =RC!F51+RC!F59+RC!F70 -> 1232123 | G39: =RC!G51+RC!G59+RC!G70 -> 2377810 | H39: =RC!H51+RC!H59+RC!H70 -> 2213430 | I39: =RC!I51+RC!I59+RC!I70 -> 2014331 | ... K39: =RC!K51+RC!K59+RC!K70 -> 1592282
A40: Passività operative consolidate medie | B40: =AVERAGE(RC!B52,RC!C52) -> 0 | C40: =AVERAGE(RC!C52,RC!D52) -> 0 | D40: =AVERAGE(RC!D52,RC!E52) -> 0 | E40: =AVERAGE(RC!E52,RC!F52) -> 0 | F40: =AVERAGE(RC!F52,RC!G52) -> 0 | G40: =AVERAGE(RC!G52,RC!H52) -> 0 | H40: =AVERAGE(RC!H52,RC!I52) -> 0 | I40: =AVERAGE(RC!I52,RC!J52) -> 0 | ... K40: =AVERAGE(RC!K52,RC!L52) -> 0
A41: Passività operative consolidate finali | B41: =RC!B52 -> 0 | C41: =RC!C52 -> 0 | D41: =RC!D52 -> 0 | E41: =RC!E52 -> 0 | F41: =RC!F52 -> 0 | G41: =RC!G52 -> 0 | H41: =RC!H52 -> 0 | I41: =RC!I52 -> 0 | ... K41: =RC!K52 -> 0
A42: debiti strutturali m/l medi | B42: =AVERAGE(RC!B69,RC!C69) -> 960895 | C42: =AVERAGE(RC!C69,RC!D69) -> 1195661 | D42: =AVERAGE(RC!D69,RC!E69) -> 1318439.5 | E42: =AVERAGE(RC!E69,RC!F69) -> 1583022 | F42: =AVERAGE(RC!F69,RC!G69) -> 1274172 | G42: =AVERAGE(RC!G69,RC!H69) -> 894284.5 | H42: =AVERAGE(RC!H69,RC!I69) -> 1088151 | I42: =AVERAGE(RC!I69,RC!J69) -> 1277585.5 | ... K42: =AVERAGE(RC!K69,RC!L69) -> 1316760
A43: debiti strutturali m/l finali | B43: =RC!B69 -> 761905 | C43: =RC!C69 -> 1159885 | D43: =RC!D69 -> 1231437 | E43: =RC!E69 -> 1405442 | F43: =RC!F69 -> 1760602 | G43: =RC!G69 -> 787742 | H43: =RC!H69 -> 1000827 | I43: =RC!I69 -> 1175475 | ... K43: =RC!K69 -> 1316760
A44: immobilizzazioni operative | B44: =((RC!B12+RC!B15)+RC!C12+RC!C15)/2 -> 3744033.5 | C44: =((RC!C12+RC!C15)+RC!D12+RC!D15)/2 -> 3746557.5 | D44: =((RC!D12+RC!D15)+RC!E12+RC!E15)/2 -> 3748257 | E44: =((RC!E12+RC!E15)+RC!F12+RC!F15)/2 -> 3947989.5 | F44: =((RC!F12+RC!F15)+RC!G12+RC!G15)/2 -> 3177912 | G44: =((RC!G12+RC!G15)+RC!H12+RC!H15)/2 -> 2323697 | H44: =((RC!H12+RC!H15)+RC!I12+RC!I15)/2 -> 2343993.5 | I44: =((RC!I12+RC!I15)+RC!J12+RC!J15)/2 -> 2419101.5 | ... K44: =((RC!K12+RC!K15)+RC!L12+RC!L15)/2 -> 1071877
A45: immobilizzazioni operative finali | B45: =RC!B12 -> 3605053 | C45: =RC!C12 -> 3744514 | D45: =RC!D12 -> 3569129 | E45: =RC!E12 -> 3651513 | F45: =RC!F12 -> 3897666 | G45: =RC!G12 -> 2110758 | H45: =RC!H12 -> 2160450 | I45: =RC!I12 -> 2222447 | ... K45: =RC!K12 -> 2143754
A46: CP capitale proprio medio | B46: =AVERAGE(RC!B84,RC!C84) -> 3371707.5 | C46: =AVERAGE(RC!C84,RC!D84) -> 3335931 | D46: =AVERAGE(RC!D84,RC!E84) -> 3255139.5 | E46: =AVERAGE(RC!E84,RC!F84) -> 3140664 | F46: =AVERAGE(RC!F84,RC!G84) -> 2160676.5 | G46: =AVERAGE(RC!G84,RC!H84) -> 1205395 | H46: =AVERAGE(RC!H84,RC!I84) -> 1153281 | I46: =AVERAGE(RC!I84,RC!J84) -> 1106842 | ... K46: =AVERAGE(RC!K84,RC!L84) -> 1018727
A47: CP init | B47: =RC!C84 -> 3347713 | C47: =RC!D84 -> 3324149 | D47: =RC!E84 -> 3186130 | E47: =RC!F84 -> 3095198 | F47: =RC!G84 -> 1226155 | G47: =RC!H84 -> 1184635 | H47: =RC!I84 -> 1121927 | I47: =RC!J84 -> 1091757 | ... K47: =RC!L84 -> 0
A48: CP fin | B48: =RC!B84 -> 3395702 | C48: =RC!C84 -> 3347713 | D48: =RC!D84 -> 3324149 | E48: =RC!E84 -> 3186130 | F48: =RC!F84 -> 3095198 | G48: =RC!G84 -> 1226155 | H48: =RC!H84 -> 1184635 | I48: =RC!I84 -> 1121927 | ... K48: =RC!K84 -> 1018727
A49: DIV t | B49: =RC!C82+RC!C79-RC!B79 -> 2 | C49: =RC!D82+RC!D79-RC!C79 -> -1 | D49: =RC!E82+RC!E79-RC!D79 -> -1 | E49: =RC!F82+RC!F79-RC!E79 -> 1 | F49: =RC!G82+RC!G79-RC!F79 -> 0 | G49: =RC!H82+RC!H79-RC!G79 -> 0 | H49: =RC!I82+RC!I79-RC!H79 -> 0 | I49: =RC!J82+RC!J79-RC!I79 -> 0 | ... K49: =RC!L82+RC!L79-RC!K79 -> -571453
A50: Aumento finanziamenti netti da soci e controllanti t e t-1 | B50: =RC!B76-RC!C76 -> 0 | C50: =RC!C76-RC!D76 -> 0 | D50: =RC!D76-RC!E76 -> 0 | E50: =RC!E76-RC!F76 -> 0 | F50: =RC!F76-RC!G76 -> 0 | G50: =RC!G76-RC!H76 -> 0 | H50: =RC!H76-RC!I76 -> 0 | I50: =RC!I76-RC!J76 -> 0 | ... K50: =RC!K76-RC!L76 -> 0
A51: Aumento accantonamenti e perdite precedenti (se neg aumento utile) | B51: =RF!C43-RF!D43 -> 23561 | C51: =RF!D43-RF!E43 -> 138019 | D51: =RF!E43-RF!F43 -> 90934 | E51: =RF!F43-RF!G43 -> 27159 | F51: =RF!G43-RF!H43 -> 41520 | G51: =RF!H43-RF!I43 -> 62708 | H51: =RF!I43-RF!J43 -> 30170 | I51: =RF!J43-RF!K43 -> 73030 | ... K51: =RF!L43-RF!M43 -> 571453
A52: var reddito di esercizio | B52: =RC!B82-RC!C82 -> 24428 | C52: =RC!C82-RC!D82 -> -114455 | D52: =RC!D82-RC!E82 -> 47085 | E52: =RC!E82-RC!F82 -> 63773 | F52: =RC!F82-RC!G82 -> -14360 | G52: =RC!G82-RC!H82 -> -21188 | H52: =RC!H82-RC!I82 -> 32538 | I52: =RC!I82-RC!J82 -> -42860 | ... K52: =RC!K82-RC!L82 -> 337274
A53: var CPn | B53: =RC!B77-RC!C77 -> 47989 | C53: =RC!C77-RC!D77 -> 23564 | D53: =RC!D77-RC!E77 -> 138019 | E53: =RC!E77-RC!F77 -> 90932 | F53: =RC!F77-RC!G77 -> 1869043 | G53: =RC!G77-RC!H77 -> 41520 | H53: =RC!H77-RC!I77 -> 62708 | I53: =RC!I77-RC!J77 -> 30170 | ... K53: =RC!K77-RC!L77 -> 1018727
A56: INDICATORI FINANZIARI | B56: =B1 -> 2024 | C56: =C1 -> 2023 | D56: =D1 -> 2022 | E56: =E1 -> 2021 | F56: =F1 -> 2020 | G56: =G1 -> 2019 | H56: =H1 -> 2018 | I56: =I1 -> 2017 | ... K56: =K1 -> 2015
A57: Quozienti di redditività
A58: Reddito operativo | B58: =B4 -> 208796 | C58: =C4 -> 157219 | D58: =D4 -> 237075 | E58: =E4 -> 158900 | F58: =F4 -> 79314 | G58: =G4 -> 101378 | H58: =H4 -> 129035 | I58: =I4 -> 92400 | ... K58: =K4 -> 562402
A59: /Ricavi | B59: =B7 -> 10781972 | C59: =C7 -> 10502251 | D59: =D7 -> 9797336 | E59: =E7 -> 8086488 | F59: =F7 -> 7349721 | G59: =G7 -> 8370970 | H59: =H7 -> 7727686 | I59: =I7 -> 7677878 | ... K59: =K7 -> 6901829
A60: ROS | B60: =B58/B59 -> 0.019365289 | C60: =C58/C59 -> 0.014970029 | D60: =D58/D59 -> 0.024197904 | E60: =E58/E59 -> 0.019650063 | F60: =F58/F59 -> 0.01079143 | G60: =G58/G59 -> 0.012110663 | H60: =H58/H59 -> 0.016697754 | I60: =I58/I59 -> 0.012034575 | ... K60: =K58/K59 -> 0.081485937
A62: Reddito operativo | B62: =B4 -> 208796 | C62: =C4 -> 157219 | D62: =D4 -> 237075 | E62: =E4 -> 158900 | F62: =F4 -> 79314 | G62: =G4 -> 101378 | H62: =H4 -> 129035 | I62: =I4 -> 92400 | ... K62: =K4 -> 562402
A63: /AON* | B63: =B14 -> 4915610.5 | C63: =C14 -> 4968956 | D63: =D14 -> 4636713 | E63: =E14 -> 4707839 | F63: =F14 -> 4200158.5 | G63: =G14 -> 3534802.5 | H63: =H14 -> 3478864.5 | I63: =I14 -> 2942468.5 | ... K63: =K14 -> 3201983
A64: ROI | B64: =B62/B63 -> 0.042476107 | C64: =C62/C63 -> 0.031640248 | D64: =D62/D63 -> 0.051129971 | E64: =E62/E63 -> 0.033752216 | F64: =F62/F63 -> 0.018883573 | G64: =G62/G63 -> 0.028679962 | H64: =H62/H63 -> 0.037091126 | I64: =I62/I63 -> 0.031402205 | ... K64: =K62/K63 -> 0.17564178
A66: Oneri finanziari | B66: =-B27 -> 110269 | C66: =-C27 -> 101600 | D66: =-D27 -> 34715 | E66: =-E27 -> 32939 | F66: =-F27 -> 42003 | G66: =-G27 -> 43669 | H66: =-H27 -> 40987 | I66: =-I27 -> 52706 | ... K66: =-K27 -> 60976
A67: /Debito lordo | B67: =B30 -> 1754991 | C67: =C30 -> 1781020 | D67: =D30 -> 1631841.5 | E67: =E30 -> 1973522 | F67: =F30 -> 2291459.5 | G67: =G30 -> 2387526.5 | H67: =H30 -> 2401427.5 | I67: =I30 -> 2425113.5 | ... K67: =K30 -> 2203518
A68: ROD | B68: =B66/B67 -> 0.062831661 | C68: =C66/C67 -> 0.057045962 | D68: =D66/D67 -> 0.021273512 | E68: =E66/E67 -> 0.016690465 | F68: =F66/F67 -> 0.018330239 | G68: =G66/G67 -> 0.018290478 | H68: =H66/H67 -> 0.017067765 | I68: =I66/I67 -> 0.021733416 | ... K68: =K66/K67 -> 0.027672113
A70: Interessi attivi | B70: =B28 -> 1525 | C70: =C28 -> 2140 | D70: =D28 -> 2565 | E70: =E28 -> 4889 | F70: =F28 -> 3414 | G70: =G28 -> 4000 | H70: =H28 -> 2187 | I70: =I28 -> 2911 | ... K70: =K28 -> 12
A71: /Liquidità lorda | B71: =B31 -> 146588 | C71: =C31 -> 103495 | D71: =D31 -> 218268 | E71: =E31 -> 374347 | F71: =F31 -> 219977.5 | G71: =G31 -> 41119 | H71: =H31 -> 73844 | I71: =I31 -> 54270.5 | ... K71: =K31 -> 0
A72: ROL | B72: =B70/B71 -> 0.010403307 | C72: =C70/C71 -> 0.020677327 | D72: =D70/D71 -> 0.011751608 | E72: =E70/E71 -> 0.013060075 | F72: =F70/F71 -> 0.015519769 | G72: =G70/G71 -> 0.09727863 | H72: =H70/H71 -> 0.029616489 | I72: =I70/I71 -> 0.053638717 | ... K72: =K70/K71 -> #DIV/0!
A74: Reddittività att.acc | B74: =B17 -> 0 | C74: =C17 -> 0 | D74: =D17 -> 0 | E74: =E17 -> 0 | F74: =F17 -> 0 | G74: =G17 -> 0 | H74: =H17 -> 0 | I74: =I17 -> 0 | ... K74: =K17 -> 0
A75: /AACCn | B75: =B18 -> 64500 | C75: =C18 -> 44500 | D75: =D18 -> 32000 | E75: =E18 -> 32000 | F75: =F18 -> 32000 | G75: =G18 -> 17000 | H75: =H18 -> 2000 | I75: =I18 -> 2000 | ... K75: =K18 -> 2000
A76: ROAACC | B76: =B74/B75 -> 0 | C76: =C74/C75 -> 0 | D76: =D74/D75 -> 0 | E76: =E74/E75 -> 0 | F76: =F74/F75 -> 0 | G76: =G74/G75 -> 0 | H76: =H74/H75 -> 0 | I76: =I74/I75 -> 0 | ... K76: =K74/K75 -> 0
A78: Reddito netto | B78: =B6 -> 47991 | C78: =C6 -> 23563 | D78: =D6 -> 138018 | E78: =E6 -> 90933 | F78: =F6 -> 27160 | G78: =G6 -> 41520 | H78: =H6 -> 62708 | I78: =I6 -> 30170 | ... K78: =K6 -> 337274
A79: /CP | B79: =B46 -> 3371707.5 | C79: =C46 -> 3335931 | D79: =D46 -> 3255139.5 | E79: =E46 -> 3140664 | F79: =F46 -> 2160676.5 | G79: =G46 -> 1205395 | H79: =H46 -> 1153281 | I79: =I46 -> 1106842 | ... K79: =K46 -> 1018727
A80: ROE netto | B80: =B78/B79 -> 0.014233441 | C80: =C78/C79 -> 0.0070633955 | D80: =D78/D79 -> 0.042400026 | E80: =E78/E79 -> 0.028953432 | F80: =F78/F79 -> 0.012570137 | G80: =G78/G79 -> 0.03444514 | H80: =H78/H79 -> 0.054373566 | I80: =I78/I79 -> 0.02725773 | ... K80: =K78/K79 -> 0.33107398
A82: RLA | B82: =B3 -> 100052 | C82: =C3 -> 57759 | D82: =D3 -> 204925 | E82: =E3 -> 130850 | F82: =F3 -> 40725 | G82: =G3 -> 61709 | H82: =H3 -> 90235 | I82: =I3 -> 42605 | ... K82: =K3 -> 501438
A83: /CP | B83: =B46 -> 3371707.5 | C83: =C46 -> 3335931 | D83: =D46 -> 3255139.5 | E83: =E46 -> 3140664 | F83: =F46 -> 2160676.5 | G83: =G46 -> 1205395 | H83: =H46 -> 1153281 | I83: =I46 -> 1106842 | ... K83: =K46 -> 1018727
A84: ROE lordo | B84: =B82/B83 -> 0.029673986 | C84: =C82/C83 -> 0.017314207 | D84: =D82/D83 -> 0.062954291 | E84: =E82/E83 -> 0.041663164 | F84: =F82/F83 -> 0.018848263 | G84: =G82/G83 -> 0.051194007 | H84: =H82/H83 -> 0.07824199 | I84: =I82/I83 -> 0.038492395 | ... K84: =K82/K83 -> 0.49222019
A86: Prima scomposizione ROE lordo:
A87: ROI | B87: =B64 -> 0.042476107 | C87: =C64 -> 0.031640248 | D87: =D64 -> 0.051129971 | E87: =E64 -> 0.033752216 | F87: =F64 -> 0.018883573 | G87: =G64 -> 0.028679962 | H87: =H64 -> 0.037091126 | I87: =I64 -> 0.031402205 | ... K87: =K64 -> 0.17564178
A88: +effetto Leva finanziaria | B88: =(B87-B68)*(B30/B46) -> -0.01059517 | C88: =(C87-C68)*(C30/C46) -> -0.013563855 | D88: =(D87-D68)*(D30/D46) -> 0.01496741 | E88: =(E87-E68)*(E30/E46) -> 0.010721217 | F88: =(F87-F68)*(F30/F46) -> 0.00058682683 | G88: =(G87-G68)*(G30/G46) -> 0.020578456 | H88: =(H87-H68)*(H30/H46) -> 0.041693784 | I88: =(I87-I68)*(I30/I46) -> 0.021184516 | ... K88: =(K87-K68)*(K30/K46) -> 0.32006006
A89: +effetto Liquidità | B89: =(B72-B87)*(B31/B46) -> -0.0013943937 | C89: =(C72-C87)*(C31/C46) -> -0.00034011719 | D89: =(D72-D87)*(D31/D46) -> -0.002640451 | E89: =(E72-E87)*(E31/E46) -> -0.0024663705 | F89: =(F72-F87)*(F31/F46) -> -0.00034246737 | G89: =(G72-G87)*(G31/G46) -> 0.00234007 | H89: =(H72-H87)*(H31/H46) -> -0.00047859722 | I89: =(I72-I87)*(I31/I46) -> 0.0010902971 | ... K89: =(K72-K87)*(K31/K46) -> #DIV/0!
A90: +effetto Attività accessorie | B90: =(B76-B87)*(B75/B46) -> -0.00081255831 | C90: =(C76-C87)*(C75/C46) -> -0.00042206839 | D90: =(D76-D87)*(D75/D46) -> -0.00050263869 | E90: =(E76-E87)*(E75/E46) -> -0.00034389891 | F90: =(F76-F87)*(F75/F46) -> -0.00027966905 | G90: =(G76-G87)*(G75/G46) -> -0.00040448098 | H90: =(H76-H87)*(H75/H46) -> -6.432279e-05 | I90: =(I76-I87)*(I75/I46) -> -5.6741984e-05 | ... K90: =(K76-K87)*(K75/K46) -> -0.00034482601
A91: ROE lordo | B91: =SUM(B87:B90) -> 0.029673986 | C91: =SUM(C87:C90) -> 0.017314207 | D91: =SUM(D87:D90) -> 0.062954291 | E91: =SUM(E87:E90) -> 0.041663164 | F91: =SUM(F87:F90) -> 0.018848263 | G91: =SUM(G87:G90) -> 0.051194007 | H91: =SUM(H87:H90) -> 0.07824199 | I91: =SUM(I87:I90) -> 0.053620276 | ... K91: =SUM(K87:K90) -> #DIV/0!
A93: Seconda scomposizione ROE lordo:
A94: +rendimento AON* | B94: =B64*(B14/B46) -> 0.061925894 | C94: =C64*(C14/C46) -> 0.047128972 | D94: =D64*(D14/D46) -> 0.07283098 | E94: =E64*(E14/E46) -> 0.050594397 | F94: =F64*(F14/F46) -> 0.036707948 | G94: =G64*(G14/G46) -> 0.084103551 | H94: =H64*(H14/H46) -> 0.11188513 | I94: =I64*(I14/I46) -> 0.08348075 | ... K94: =K64*(K14/K46) -> 0.55206351
A95: +effetto costo del debito | B95: =-B68*(B30/B46) -> -0.032704201 | C95: =-C68*(C30/C46) -> -0.030456265 | D95: =-D68*(D30/D46) -> -0.010664674 | E95: =-E68*(E30/E46) -> -0.01048791 | F95: =-F68*(F30/F46) -> -0.019439745 | G95: =-G68*(G30/G46) -> -0.036227958 | H95: =-H68*(H30/H46) -> -0.035539474 | I95: =-I68*(I30/I46) -> -0.047618359 | ... K95: =-K68*(K30/K46) -> -0.059855094
A96: +rendimento liquidità | B96: =B72*(B31/B46) -> 0.00045229309 | C96: =C72*(C31/C46) -> 0.00064150008 | D96: =D72*(D31/D46) -> 0.00078798466 | E96: =E72*(E31/E46) -> 0.0015566772 | F96: =F72*(F31/F46) -> 0.0015800607 | G96: =G72*(G31/G46) -> 0.0033184143 | H96: =H72*(H31/H46) -> 0.0018963288 | I96: =I72*(I31/I46) -> 0.002630005 | ... K96: =K72*(K31/K46) -> #DIV/0!
A97: +rendimento att.accessorie | B97: =B76*(B18/B46) -> 0 | C97: =C76*(C18/C46) -> 0 | D97: =D76*(D18/D46) -> 0 | E97: =E76*(E18/E46) -> 0 | F97: =F76*(F18/F46) -> 0 | G97: =G76*(G18/G46) -> 0 | H97: =H76*(H18/H46) -> 0 | I97: =I76*(I18/I46) -> 0 | ... K97: =K76*(K18/K46) -> 0
A98: ROE lordo | B98: =SUM(B94:B97) -> 0.029673986 | C98: =SUM(C94:C97) -> 0.017314207 | D98: =SUM(D94:D97) -> 0.062954291 | E98: =SUM(E94:E97) -> 0.041663164 | F98: =SUM(F94:F97) -> 0.018848263 | G98: =SUM(G94:G97) -> 0.051194007 | H98: =SUM(H94:H97) -> 0.07824199 | I98: =SUM(I94:I97) -> 0.038492395 | ... K98: =SUM(K94:K97) -> #DIV/0!
A100: check ROE lordo 1: | B100: =B84-B91 -> 0 | C100: =C84-C91 -> 0 | D100: =D84-D91 -> 0 | E100: =E84-E91 -> 0 | F100: =F84-F91 -> 0 | G100: =G84-G91 -> 0 | H100: =H84-H91 -> 0 | I100: =I84-I91 -> -0.015127881 | ... K100: =K84-K91 -> #DIV/0!
A101: check ROE lordo 2: | B101: =B84-B98 -> 0 | C101: =C84-C98 -> 0 | D101: =D84-D98 -> 0 | E101: =E84-E98 -> 0 | F101: =F84-F98 -> 0 | G101: =G84-G98 -> 0 | H101: =H84-H98 -> 0 | I101: =I84-I98 -> 0 | ... K101: =K84-K98 -> #DIV/0!
A103: Da lordo a netto:
A104: RLA | B104: =B3 -> 100052 | C104: =C3 -> 57759 | D104: =D3 -> 204925 | E104: =E3 -> 130850 | F104: =F3 -> 40725 | G104: =G3 -> 61709 | H104: =H3 -> 90235 | I104: =I3 -> 42605 | ... K104: =K3 -> 501438
A105: /CP | B105: =B46 -> 3371707.5 | C105: =C46 -> 3335931 | D105: =D46 -> 3255139.5 | E105: =E46 -> 3140664 | F105: =F46 -> 2160676.5 | G105: =G46 -> 1205395 | H105: =H46 -> 1153281 | I105: =I46 -> 1106842 | ... K105: =K46 -> 1018727
A106: x (RLA+ris str)/RLA | B106: =(B104+B23)/B104 -> 1 | C106: =(C104+C23)/C104 -> 1 | D106: =(D104+D23)/D104 -> 1 | E106: =(E104+E23)/E104 -> 1 | F106: =(F104+F23)/F104 -> 1 | G106: =(G104+G23)/G104 -> 1 | H106: =(H104+H23)/H104 -> 1 | I106: =(I104+I23)/I104 -> 1 | ... K106: =(K104+K23)/K104 -> 1
A107: x (RL+tax)/RL | B107: =(B3+B23+B29)/(B3+B23) -> 0.47966058 | C107: =(C3+C23+C29)/(C3+C23) -> 0.40795374 | D107: =(D3+D23+D29)/(D3+D23) -> 0.67350494 | E107: =(E3+E23+E29)/(E3+E23) -> 0.69494077 | F107: =(F3+F23+F29)/(F3+F23) -> 0.66691222 | G107: =(G3+G23+G29)/(G3+G23) -> 0.6728354 | H107: =(H3+H23+H29)/(H3+H23) -> 0.69494099 | I107: =(I3+I23+I29)/(I3+I23) -> 0.70813285 | ... K107: =(K3+K23+K29)/(K3+K23) -> 0.67261356
A108: '= Reddito netto/CP check | B108: =B6/B46 -> 0.014233441 | C108: =C6/C46 -> 0.0070633955 | D108: =D6/D46 -> 0.042400026 | E108: =E6/E46 -> 0.028953432 | F108: =F6/F46 -> 0.012570137 | G108: =G6/G46 -> 0.03444514 | H108: =H6/H46 -> 0.054373566 | I108: =I6/I46 -> 0.02725773 | ... K108: =K6/K46 -> 0.33107398
A109: ROE netto | B109: =(B104/B105)*B106*B107 -> 0.014233441 | C109: =(C104/C105)*C106*C107 -> 0.0070633955 | D109: =(D104/D105)*D106*D107 -> 0.042400026 | E109: =(E104/E105)*E106*E107 -> 0.028953432 | F109: =(F104/F105)*F106*F107 -> 0.012570137 | G109: =(G104/G105)*G106*G107 -> 0.03444514 | H109: =(H104/H105)*H106*H107 -> 0.054373566 | I109: =(I104/I105)*I106*I107 -> 0.02725773 | ... K109: =(K104/K105)*K106*K107 -> 0.33107398
A110: check ROE netto | B110: =B109-B80 -> 0 | C110: =C109-C80 -> 0 | D110: =D109-D80 -> 0 | E110: =E109-E80 -> 0 | F110: =F109-F80 -> 0 | G110: =G109-G80 -> 0 | H110: =H109-H80 -> 0 | I110: =I109-I80 -> 0 | ... K110: =K109-K80 -> 0
A113: INDICATORI FINANZIARI
A114: Quozienti di rotazione dell'attivo netto
...

Sheet grph
B3: Quozienti di redditività
B80: Quozienti di rotazione dell'attivo netto
B135: Quozienti di liquidità ed equilibrio fonti/impieghi
B218: Indicatori di robustezza
