Workbook

Sheet input
A1: Anno | B1: 31/12/2024 | C1: 31/12/2023 | D1: 31/12/2022 | E1: 31/12/2021 | F1: 31/12/2020 | G1: 31/12/2019 | H1: 31/12/2018 | I1: 31/12/2017 | J1: 31/12/2016 | K1: 31/12/2015
A2: A. CREDITI VERSO SOCI | B2: 0 | C2: 0 | D2: 0 | E2: 0 | F2: 0 | G2: 0 | H2: 0 | I2: 0 | J2: 0 | K2: 0
A3: Quota di capitale richiamata | B3: 0 | C3: 0 | D3: 0 | E3: 0 | F3: 0 | G3: 0 | H3: 0 | I3: 0 | J3: 0 | K3: 0
A4: B. TOTALE IMMOBILIZZAZIONI sep.ind. Di quelle conc. In loc. Finanz. | B4: 2855833 | C4: 870568 | D4: 1067260.9 | E4: 891346.47 | F4: 906632.62 | G4: 378046.95 | H4: 394745.36 | I4: 421605.02 | J4: 421402.53 | K4: 422213.42
A5: B.I. TOTALE IMMOB. IMMATERIALI | B5: 1592262 | C5: 90098 | D5: 86779.886 | E5: 89055.322 | F5: 87656.701 | G5: 13306.33 | H5: 11674.413 | I5: 12394.555 | J5: 14257.563 | K5: 16231.349
A6: B.I.1. Costi impianto e ampl. | B6: 0 | C6: 0 | D6: 0 | E6: 0 | F6: 0 | G6: 0 | H6: 0 | I6: 0 | J6: 0 | K6: 0
A7: B.I.2. Costi ricerca e pubb. | B7: 0 | C7: 0 | D7: 770.608 | E7: 1105.122 | F7: 0 | G7: 0 | H7: 0 | I7: 0 | J7: 0 | K7: 0
A8: B.I.3. Diritti brevetto ind. | B8: 0 | C8: 0 | D8: 12189.851 | E8: 11548.739 | F8: 4441.959 | G8: 4819.24 | H8: 1058.732 | I8: 1177.061 | J8: 1355.297 | K8: 1568.018
A9: B.I.4. Concessioni, licenze | B9: 0 | C9: 0 | D9: 37175.784 | E9: 39674.967 | F9: 42112.582 | G9: 8248.91 | H9: 9568.06 | I9: 11008.448 | J9: 12605.625 | K9: 14213.551
A10: B.I.5. Avviamento/Differenza di consolidamento | B10: 0 | C10: 0 | D10: 29953.918 | E10: 31715.913 | F10: 33477.908 | G10: 0 | H10: 0 | I10: 0 | J10: 0 | K10: 14.688
A11: di cui: Avviamento | B11: 0 | C11: 0 | D11: 29953.918 | E11: 31715.913 | F11: 33477.908 | G11: 0 | H11: 0 | I11: 0 | J11: 0 | K11: 14.688
A12: B.I.6. Imm. in corso | B12: 0 | C12: 0 | D12: 4575.518 | E12: 2874.101 | F12: 5851.812 | G12: 116.543 | H12: 884.224 | I12: 0 | J12: 0 | K12: 0
A13: B.I.7. Altre immobiliz. Immateriali | B13: 1592262 | C13: 90098 | D13: 2114.207 | E13: 2136.48 | F13: 1772.44 | G13: 121.637 | H13: 163.397 | I13: 209.046 | J13: 296.641 | K13: 435.092
... A93: TOTALE ATTIVO | B93: 3790320 | C93: 1675063 | D93: 1536537 | E93: 1308756.7 | F93: 1311132.3 | G93: 741974.82 | H93: 792683.74 | I93: 788836.85 | J93: 778185.57 | K93: 780383.29
A94: Passivo
A95: PATRIMONIO NETTO
A96: A. TOTALE PATRIMONIO NETTO | B96: 852247 | C96: 88219 | D96: 136548.72 | E96: 117108.52 | F96: 124862.24 | G96: 344954.71 | H96: 348518.46 | I96: 370611.09 | J96: 351645.83 | K96: 318992.28
A97: A.I. Capitale sociale | B97: 40000 | C97: 40000 | D97: 40000.22 | E97: 40000.22 | F97: 40000.22 | G97: 40000.22 | H97: 40000.22 | I97: 40000.22 | J97: 40000.22 | K97: 40000.22
A98: di cui: Versamenti soci in c/capitale | B98: 0 | C98: 0 | D98: 4500 | E98: 0 | F98: 0 | G98: 0.098 | H98: 0.098 | I98: 0.098 | J98: 0.098 | K98: 0.098
A99: di cui: Versamenti in c/futuro aumento di capitale | B99: 0 | C99: 0 | D99: 0 | E99: 0 | F99: 0 | G99: 0 | H99: 0 | I99: 0 | J99: 0 | K99: 0
A100: di cui: Versamenti in c/capitale | B100: 0 | C100: 0 | D100: 0 | E100: 0 | F100: 0 | G100: 0 | H100: 0 | I100: 0 | J100: 0 | K100: 0
A101: di cui: Versamenti a copertura perdite | B101: 0 | C101: 0 | D101: 0 | E101: 0 | F101: 0 | G101: 0 | H101: 0 | I101: 0 | J101: 0 | K101: 0
A102: A.II. Riserva da sovrapprezzo | B102: 60241 | C102: 60241 | D102: 60241.454 | E102: 60241.454 | F102: 60241.454 | G102: 51829.138 | H102: 51829.138 | I102: 51829.138 | J102: 51829.138 | K102: 51829.138
A103: A.III. Riserva di rivalutazione | B103: 0 | C103: 0 | D103: 15471.903 | E103: 15471.903 | F103: 15471.903 | G103: 15471.903 | H103: 15471.903 | I103: 15471.903 | J103: 15471.903 | K103: 15471.903
A104: A.IV. Riserva legale | B104: 8000 | C104: 8000 | D104: 8000.044 | E104: 8000.044 | F104: 8000.044 | G104: 8000.044 | H104: 8000.044 | I104: 8000.044 | J104: 8000.044 | K104: 8000.044
A105: A.V. Riserva statutaria | B105: 0 | C105: 0 | D105: 0 | E105: 0 | F105: 0 | G105: 0 | H105: 0 | I105: 0 | J105: 0 | K105: 0
A106: Riserva azioni proprie | B106: 0 | C106: 0 | D106: 0 | E106: 0 | F106: 0 | G106: 0 | H106: 0 | I106: 0 | J106: 0 | K106: 0
A107: A.VI. Altre riserve | B107: 1178691 | C107: 96414 | D107: 62110.595 | E107: 57610.595 | F107: 57610.595 | G107: 229217.16 | H107: 227309.63 | I107: 206344.36 | J107: 181690.86 | K107: 164816.55
... A126: C. TRATTAMENTO DI FINE RAPPORTO | B126: 6126 | C126: 7190 | D126: 9844.145 | E126: 9804.363 | F126: 11127.204 | G126: 13315.664 | H126: 14615.308 | I126: 15818.5 | J126: 16934.442 | K126: 17851.924
A127: Debiti
A128: D. TOTALE DEBITI | B128: 2796886 | C128: 1522481 | D128: 1327820.1 | E128: 1136860.7 | F128: 1126282.8 | G128: 348491.19 | H128: 397384.07 | I128: 375606.9 | J128: 392361.16 | K128: 433764.15
A129: D.1. Obblig.ni entro | B129: 6783 | C129: 0 | D129: 0 | E129: 0 | F129: 0 | G129: 0 | H129: 0 | I129: 0 | J129: 0 | K129: 0
A130: D.1. Obblig.ni oltre | B130: 1069074 | C130: 0 | D130: 0 | E130: 0 | F130: 0 | G130: 0 | H130: 0 | I130: 0 | J130: 0 | K130: 0
A131: D.2. Obblig.ni convert. entro | B131: 0 | C131: 0 | D131: 0 | E131: 0 | F131: 0 | G131: 0 | H131: 0 | I131: 0 | J131: 0 | K131: 0
A132: D.2. Obblig.ni convert. oltre. | B132: 0 | C132: 0 | D132: 0 | E132: 0 | F132: 0 | G132: 0 | H132: 0 | I132: 0 | J132: 0 | K132: 0
A133: D.3. Soci per Finanziamenti entro | B133: 0 | C133: 0 | D133: 0 | E133: 0 | F133: 0 | G133: 0 | H133: 0 | I133: 0 | J133: 0 | K133: 0
A134: D.3. Soci per Finanziamenti oltre | B134: 322056 | C134: 0 | D134: 0 | E134: 0 | F134: 0 | G134: 0 | H134: 0 | I134: 0 | J134: 0 | K134: 0
A135: D.4. Banche entro l'esercizio | B135: 82489 | C135: 48202 | D135: 10000 | E135: 0.499 | F135: 1.807 | G135: 4.922 | H135: 20464.468 | I135: 99547.086 | J135: 79477.82 | K135: 100222.99
A136: D.4. Banche oltre l'esercizio | B136: 178111 | C136: 614866 | D136: 0 | E136: 0 | F136: 0 | G136: 0 | H136: 0 | I136: 55779.956 | J136: 79869.756 | K136: 103275.9
A137: D.5. Altri finanziatori entro | B137: 17028 | C137: 14288 | D137: 15075.841 | E137: 12408.767 | F137: 18709.528 | G137: 0 | H137: 0 | I137: 428.265 | J137: 0 | K137: 282.108
A138: D.5. Altri finanziatori oltre | B138: 171661 | C138: 88653 | D138: 0 | E138: 725617.18 | F138: 780492.17 | G138: 0 | H138: 0 | I138: 0 | J138: 0 | K138: 0
A139: D.6. Acconti entro | B139: 0 | C139: 0 | D139: 0 | E139: 0 | F139: 0 | G139: 6.24 | H139: 34.835 | I139: 20.253 | J139: 3.22 | K139: 5.222
... A166: TOTALE CONTI D'ORDINE | B166: 0 | C166: 0 | D166: 0 | E166: 0 | F166: 0 | G166: 0 | H166: 0 | I166: 0 | J166: 0 | K166: 60357.982
A167: Conto economico
A168: A. TOT. VAL. DELLA PRODUZIONE | B168: 716833 | C168: 561438 | D168: 778513.33 | E168: 588825.8 | F168: 474425.01 | G168: 593075.31 | H168: 607222.65 | I168: 653117.46 | J168: 653243.7 | K168: 618272.34
A169: A.1. Ricavi vendite e prestazioni | B169: 563394 | C169: 465805 | D169: 686052.74 | E169: 541259.54 | F169: 452166.67 | G169: 593117.57 | H169: 593723.92 | I169: 634079.11 | J169: 642254.5 | K169: 608857.85
A170: A.2. Var. rimanenze prodotti | B170: 9700 | C170: -18892 | D170: 25197.522 | E170: 12046.266 | F170: 1685.122 | G170: -7328.635 | H170: 3923.395 | I170: -6827.493 | J170: 3840.038 | K170: -246
A171: A.3. Variazione lavori | B171: 0 | C171: 0 | D171: 0 | E171: 0 | F171: 0 | G171: 0 | H171: 0 | I171: 0 | J171: 0 | K171: 0
A172: A.2. + A.3. Totale Variazioni | B172: 9700 | C172: -18892 | D172: 25197.522 | E172: 12046.266 | F172: 1685.122 | G172: -7328.635 | H172: 3923.395 | I172: -6827.493 | J172: 3840.038 | K172: -246
A173: A.4. Incrementi di immob. | B173: 4659 | C173: 3685 | D173: 809.382 | E173: 1326.432 | F173: 1595.667 | G173: 909.429 | H173: 1371.615 | I173: 784.825 | J173: 317.248 | K173: 535.277
A174: A.5. Altri ricavi | B174: 139080 | C174: 110840 | D174: 66453.687 | E174: 34193.564 | F174: 18977.553 | G174: 6376.945 | H174: 8203.722 | I174: 25081.017 | J174: 6831.908 | K174: 9125.217
A175: Contributi in conto esercizio | B175: 2123 | C175: 9121 | D175: 20889.058 | E175: 143.677 | F175: 377.922 | G175: 141.162 | H175: 816.357 | I175: 703.749 | J175: 70.303 | K175: 85.563
A176: B. COSTI DELLA PRODUZIONE | B176: 656297 | C176: 504248 | D176: 767219.05 | E176: 579536.99 | F176: 471160.83 | G176: 562411.53 | H176: 573505.08 | I176: 575818.75 | J176: 582390.41 | K176: 566338.5
A177: B.6. Materie prime e consumo | B177: 294635 | C177: 233853 | D177: 369324.92 | E177: 286223.42 | F177: 212362.42 | G177: 251077.6 | H177: 354468.09 | I177: 310414.15 | J177: 308669.76 | K177: 314184.4
A178: B.7. Servizi | B178: 186379 | C178: 150974 | D178: 233037.5 | E178: 152791.56 | F178: 136499.39 | G178: 138892.42 | H178: 130598.71 | I178: 123574.19 | J178: 132183.03 | K178: 134109.94
A179: B.8. Godimento beni di terzi | B179: 0 | C179: 0 | D179: 9817.73 | E179: 10480.972 | F179: 9122.456 | G179: 10345.315 | H179: 9457.312 | I179: 15010.612 | J179: 14467.256 | K179: 5282.061
... A246: UTILE/PERDITA DI ESERCIZIO di pert. di TERZI | B246: 0 | C246: 0 | D246: 0 | E246: 0 | F246: 0 | G246: 0 | H246: 0 | I246: 0 | J246: 0 | K246: 0
A247: FEDRIGONI S.P.A.
A248: 01664630223

Sheet case
A1: SP attivo | B1: =input!B1 -> 31/12/2024 | C1: =input!C1 -> 31/12/2023 | D1: =input!D1 -> 31/12/2022 | E1: =input!E1 -> 31/12/2021 | F1: =input!F1 -> 31/12/2020 | G1: =input!G1 -> 31/12/2019 | H1: =input!H1 -> 31/12/2018 | I1: =input!I1 -> 31/12/2017 | ... K1: =input!K1 -> 31/12/2015 | M1: Segno | N1: Riclassificazione
A2: =input!A2 -> A. CREDITI VERSO SOCI | B2: =$M2*input!B2 -> 0 | C2: =$M2*input!C2 -> 0 | D2: =$M2*input!D2 -> 0 | E2: =$M2*input!E2 -> 0 | F2: =$M2*input!F2 -> 0 | G2: =$M2*input!G2 -> 0 | H2: =$M2*input!H2 -> 0 | I2: =$M2*input!I2 -> 0 | ... K2: =$M2*input!K2 -> 0 | M2: -1 | N2: Finanziamenti netti vs soci e controllanti
A3: =input!A3 -> Quota di capitale richiamata | B3: =$M3*input!B3 -> 0 | C3: =$M3*input!C3 -> 0 | D3: =$M3*input!D3 -> 0 | E3: =$M3*input!E3 -> 0 | F3: =$M3*input!F3 -> 0 | G3: =$M3*input!G3 -> 0 | H3: =$M3*input!H3 -> 0 | I3: =$M3*input!I3 -> 0 | ... K3: =$M3*input!K3 -> 0 | M3: 1
A5: =input!A4 -> B. TOTALE IMMOBILIZZAZIONI sep.ind. Di quelle conc. In loc. Finanz. | B5: =$M5*input!B4 -> 2855833 | C5: =$M5*input!C4 -> 870568 | D5: =$M5*input!D4 -> 1067260.9 | E5: =$M5*input!E4 -> 891346.47 | F5: =$M5*input!F4 -> 906632.62 | G5: =$M5*input!G4 -> 378046.95 | H5: =$M5*input!H4 -> 394745.36 | I5: =$M5*input!I4 -> 421605.02 | ... K5: =$M5*input!K4 -> 422213.42 | M5: 1
A6: =input!A5 -> B.I. TOTALE IMMOB. IMMATERIALI | B6: =$M6*input!B5 -> 1592262 | C6: =$M6*input!C5 -> 90098 | D6: =$M6*input!D5 -> 86779.886 | E6: =$M6*input!E5 -> 89055.322 | F6: =$M6*input!F5 -> 87656.701 | G6: =$M6*input!G5 -> 13306.33 | H6: =$M6*input!H5 -> 11674.413 | I6: =$M6*input!I5 -> 12394.555 | ... K6: =$M6*input!K5 -> 16231.349 | M6: 1 | N6: Immobilizzazioni immateriali nette
A7: =input!A6 -> B.I.1. Costi impianto e ampl. | B7: =$M7*input!B6 -> 0 | C7: =$M7*input!C6 -> 0 | D7: =$M7*input!D6 -> 0 | E7: =$M7*input!E6 -> 0 | F7: =$M7*input!F6 -> 0 | G7: =$M7*input!G6 -> 0 | H7: =$M7*input!H6 -> 0 | I7: =$M7*input!I6 -> 0 | ... K7: =$M7*input!K6 -> 0 | M7: 1
A8: =input!A7 -> B.I.2. Costi ricerca e pubb. | B8: =$M8*input!B7 -> 0 | C8: =$M8*input!C7 -> 0 | D8: =$M8*input!D7 -> 770.608 | E8: =$M8*input!E7 -> 1105.122 | F8: =$M8*input!F7 -> 0 | G8: =$M8*input!G7 -> 0 | H8: =$M8*input!H7 -> 0 | I8: =$M8*input!I7 -> 0 | ... K8: =$M8*input!K7 -> 0 | M8: 1
A9: =input!A8 -> B.I.3. Diritti brevetto ind. | B9: =$M9*input!B8 -> 0 | C9: =$M9*input!C8 -> 0 | D9: =$M9*input!D8 -> 12189.851 | E9: =$M9*input!E8 -> 11548.739 | F9: =$M9*input!F8 -> 4441.959 | G9: =$M9*input!G8 -> 4819.24 | H9: =$M9*input!H8 -> 1058.732 | I9: =$M9*input!I8 -> 1177.061 | ... K9: =$M9*input!K8 -> 1568.018 | M9: 1
A10: =input!A9 -> B.I.4. Concessioni, licenze | B10: =$M10*input!B9 -> 0 | C10: =$M10*input!C9 -> 0 | D10: =$M10*input!D9 -> 37175.784 | E10: =$M10*input!E9 -> 39674.967 | F10: =$M10*input!F9 -> 42112.582 | G10: =$M10*input!G9 -> 8248.91 | H10: =$M10*input!H9 -> 9568.06 | I10: =$M10*input!I9 -> 11008.448 | ... K10: =$M10*input!K9 -> 14213.551 | M10: 1
A11: =input!A10 -> B.I.5. Avviamento/Differenza di consolidamento | B11: =$M11*input!B10 -> 0 | C11: =$M11*input!C10 -> 0 | D11: =$M11*input!D10 -> 29953.918 | E11: =$M11*input!E10 -> 31715.913 | F11: =$M11*input!F10 -> 33477.908 | G11: =$M11*input!G10 -> 0 | H11: =$M11*input!H10 -> 0 | I11: =$M11*input!I10 -> 0 | ... K11: =$M11*input!K10 -> 14.688 | M11: 1
A12: =input!A11 -> di cui: Avviamento | B12: =$M12*input!B11 -> 0 | C12: =$M12*input!C11 -> 0 | D12: =$M12*input!D11 -> 29953.918 | E12: =$M12*input!E11 -> 31715.913 | F12: =$M12*input!F11 -> 33477.908 | G12: =$M12*input!G11 -> 0 | H12: =$M12*input!H11 -> 0 | I12: =$M12*input!I11 -> 0 | ... K12: =$M12*input!K11 -> 14.688 | M12: 1
A13: =input!A12 -> B.I.6. Imm. in corso | B13: =$M13*input!B12 -> 0 | C13: =$M13*input!C12 -> 0 | D13: =$M13*input!D12 -> 4575.518 | E13: =$M13*input!E12 -> 2874.101 | F13: =$M13*input!F12 -> 5851.812 | G13: =$M13*input!G12 -> 116.543 | H13: =$M13*input!H12 -> 884.224 | I13: =$M13*input!I12 -> 0 | ... K13: =$M13*input!K12 -> 0 | M13: 1
A14: =input!A13 -> B.I.7. Altre immobiliz. Immateriali | B14: =$M14*input!B13 -> 1592262 | C14: =$M14*input!C13 -> 90098 | D14: =$M14*input!D13 -> 2114.207 | E14: =$M14*input!E13 -> 2136.48 | F14: =$M14*input!F13 -> 1772.44 | G14: =$M14*input!G13 -> 121.637 | H14: =$M14*input!H13 -> 163.397 | I14: =$M14*input!I13 -> 209.046 | ... K14: =$M14*input!K13 -> 435.092 | M14: 1
A15: =input!A14 -> Fondo amm.to Immob. Immateriali | B15: =$M15*input!B14 -> 0 | C15: =$M15*input!C14 -> 0 | D15: =$M15*input!D14 -> 0 | E15: =$M15*input!E14 -> 0 | F15: =$M15*input!F14 -> 0 | G15: =$M15*input!G14 -> 0 | H15: =$M15*input!H14 -> 0 | I15: =$M15*input!I14 -> 0 | ... K15: =$M15*input!K14 -> 0 | M15: 1
A16: =input!A15 -> B.II. TOTALE IMMOB. MATERIALI | B16: =$M16*input!B15 -> 247743 | C16: =$M16*input!C15 -> 220617 | D16: =$M16*input!D15 -> 223741.13 | E16: =$M16*input!E15 -> 217974.81 | F16: =$M16*input!F15 -> 220394.5 | G16: =$M16*input!G15 -> 154055.72 | H16: =$M16*input!H15 -> 149620.66 | I16: =$M16*input!I15 -> 148980.38 | ... K16: =$M16*input!K15 -> 152948.57 | M16: 1 | N16: Immobilizzazioni materiali nette
A17: =input!A16 -> di cui: Beni materiali concessi in locazione finanziaria | B17: =$M17*input!B16 -> 0 | C17: =$M17*input!C16 -> 0 | D17: =$M17*input!D16 -> 0 | E17: =$M17*input!E16 -> 0 | F17: =$M17*input!F16 -> 0 | G17: =$M17*input!G16 -> 0 | H17: =$M17*input!H16 -> 0 | I17: =$M17*input!I16 -> 0 | ... K17: =$M17*input!K16 -> 0 | M17: 1
A18: =input!A17 -> B.II.1. Terreni e fabbricati | B18: =$M18*input!B17 -> 14339 | C18: =$M18*input!C17 -> 46689 | D18: =$M18*input!D17 -> 76679.059 | E18: =$M18*input!E17 -> 79327.474 | F18: =$M18*input!F17 -> 87475.546 | G18: =$M18*input!G17 -> 51009.244 | H18: =$M18*input!H17 -> 52883.326 | I18: =$M18*input!I17 -> 53993.851 | ... K18: =$M18*input!K17 -> 59775.425 | M18: 1
A19: =input!A18 -> B.II.2. Impianti | B19: =$M19*input!B18 -> 125344 | C19: =$M19*input!C18 -> 100960 | D19: =$M19*input!D18 -> 125560.36 | E19: =$M19*input!E18 -> 128183.84 | F19: =$M19*input!F18 -> 124380.4 | G19: =$M19*input!G18 -> 86311.778 | H19: =$M19*input!H18 -> 88171.71 | I19: =$M19*input!I18 -> 82537.405 | ... K19: =$M19*input!K18 -> 89532.66 | M19: 1
A20: =input!A19 -> B.II.3. Attrez. industriali | B20: =$M20*input!B19 -> 249 | C20: =$M20*input!C19 -> 315 | D20: =$M20*input!D19 -> 458.76 | E20: =$M20*input!E19 -> 498 | F20: =$M20*input!F19 -> 434.511 | G20: =$M20*input!G19 -> 430.921 | H20: =$M20*input!H19 -> 503.653 | I20: =$M20*input!I19 -> 633.098 | ... K20: =$M20*input!K19 -> 906.995 | M20: 1
A21: =input!A20 -> B.II.4. Altri beni | B21: =$M21*input!B20 -> 91805 | C21: =$M21*input!C20 -> 58021 | D21: =$M21*input!D20 -> 489.163 | E21: =$M21*input!E20 -> 441.528 | F21: =$M21*input!F20 -> 511.287 | G21: =$M21*input!G20 -> 603.536 | H21: =$M21*input!H20 -> 653.076 | I21: =$M21*input!I20 -> 735.094 | ... K21: =$M21*input!K20 -> 906.335 | M21: 1
A22: =input!A21 -> B.II.5. Imm. in corso/acconti | B22: =$M22*input!B21 -> 16006 | C22: =$M22*input!C21 -> 14632 | D22: =$M22*input!D21 -> 20553.787 | E22: =$M22*input!E21 -> 9523.963 | F22: =$M22*input!F21 -> 7592.753 | G22: =$M22*input!G21 -> 15700.24 | H22: =$M22*input!H21 -> 7408.897 | I22: =$M22*input!I21 -> 11080.927 | ... K22: =$M22*input!K21 -> 1827.151 | M22: 1
A23: =input!A22 -> Fondo amm.to Immob. Materiali | B23: =$M23*input!B22 -> 0 | C23: =$M23*input!C22 -> 0 | D23: =$M23*input!D22 -> 0 | E23: =$M23*input!E22 -> 0 | F23: =$M23*input!F22 -> 0 | G23: =$M23*input!G22 -> 0 | H23: =$M23*input!H22 -> 0 | I23: =$M23*input!I22 -> 0 | ... K23: =$M23*input!K22 -> 0 | M23: 1
A24: =input!A23 -> B.III. TOTALE IMMOB. FINANZIARIE | B24: =$M24*input!B23 -> 1015828 | C24: =$M24*input!C23 -> 559853 | D24: =$M24*input!D23 -> 756739.9 | E24: =$M24*input!E23 -> 584316.34 | F24: =$M24*input!F23 -> 598581.42 | G24: =$M24*input!G23 -> 210684.9 | H24: =$M24*input!H23 -> 233450.29 | I24: =$M24*input!I23 -> 260230.09 | ... K24: =$M24*input!K23 -> 253033.51 | M24: 1
A25: =input!A24 -> di cui: esigibili entro l'esercizio successivo | B25: =$M25*input!B24 -> 0 | C25: =$M25*input!C24 -> 0 | D25: =$M25*input!D24 -> 10782.128 | E25: =$M25*input!E24 -> 343.435 | F25: =$M25*input!F24 -> 370.685 | G25: =$M25*input!G24 -> 324.796 | H25: =$M25*input!H24 -> 281.976 | I25: =$M25*input!I24 -> 278.258 | ... K25: =$M25*input!K24 -> 286.84 | M25: 1
A26: =input!A25 -> B.III.1. TOT Partecipazioni | B26: =$M26*input!B25 -> 1015828 | C26: =$M26*input!C25 -> 559853 | D26: =$M26*input!D25 -> 556283.77 | E26: =$M26*input!E25 -> 484337.02 | F26: =$M26*input!F25 -> 436771.36 | G26: =$M26*input!G25 -> 185287.81 | H26: =$M26*input!H25 -> 205707.91 | I26: =$M26*input!I25 -> 232021.82 | ... K26: =$M26*input!K25 -> 248664.75 | M26: 1
A27: =input!A26 -> B.III.1.a. Imprese controllate | B27: =$M27*input!B26 -> 1012239 | C27: =$M27*input!C26 -> 557430 | D27: =$M27*input!D26 -> 555588.13 | E27: =$M27*input!E26 -> 483640.37 | F27: =$M27*input!F26 -> 436074.72 | G27: =$M27*input!G26 -> 184591.17 | H27: =$M27*input!H26 -> 205011.27 | I27: =$M27*input!I26 -> 231325.17 | ... K27: =$M27*input!K26 -> 247968.1 | M27: 1 | N27: Partecipazioni
A28: =input!A27 -> B.III.1.b. Imprese collegate | B28: =$M28*input!B27 -> 0 | C28: =$M28*input!C27 -> 0 | D28: =$M28*input!D27 -> 695.516 | E28: =$M28*input!E27 -> 695.516 | F28: =$M28*input!F27 -> 695.516 | G28: =$M28*input!G27 -> 695.516 | H28: =$M28*input!H27 -> 695.516 | I28: =$M28*input!I27 -> 695.516 | ... K28: =$M28*input!K27 -> 695.516 | M28: 1 | N28: Partecipazioni
A29: =input!A28 -> B.III.1.c. Imprese controllanti | B29: =$M29*input!B28 -> 0 | C29: =$M29*input!C28 -> 0 | D29: =$M29*input!D28 -> 0 | E29: =$M29*input!E28 -> 0 | F29: =$M29*input!F28 -> 0 | G29: =$M29*input!G28 -> 0 | H29: =$M29*input!H28 -> 0 | I29: =$M29*input!I28 -> 0 | ... K29: =$M29*input!K28 -> 0 | M29: 1 | N29: Azioni proprie e partecipazioni in controllanti
A30: =input!A29 -> B.III.1.d. In imprese sottoposte al controllo delle controllanti | B30: =$M30*input!B29 -> 0 | C30: =$M30*input!C29 -> 0 | D30: =$M30*input!D29 -> 0 | E30: =$M30*input!E29 -> 0 | F30: =$M30*input!F29 -> 0 | G30: =$M30*input!G29 -> 0 | H30: =$M30*input!H29 -> 0 | I30: =$M30*input!I29 -> 0 | ... K30: =$M30*input!K29 -> 0 | M30: 1 | N30: Azioni proprie e partecipazioni in controllanti
A31: =input!A30 -> B.III.1.d.bis. Altre imprese | B31: =$M31*input!B30 -> 3589 | C31: =$M31*input!C30 -> 2423 | D31: =$M31*input!D30 -> 0.129 | E31: =$M31*input!E30 -> 1.129 | F31: =$M31*input!F30 -> 1.129 | G31: =$M31*input!G30 -> 1.129 | H31: =$M31*input!H30 -> 1.129 | I31: =$M31*input!I30 -> 1.129 | ... K31: =$M31*input!K30 -> 1.129 | M31: 1 | N31: Partecipazioni
A32: =input!A31 -> B.III.2. TOT CREDITI Imm. Fin. | B32: =$M32*input!B31 -> 0 | C32: =$M32*input!C31 -> 0 | D32: =$M32*input!D31 -> 200456.12 | E32: =$M32*input!E31 -> 99979.325 | F32: =$M32*input!F31 -> 161810.06 | G32: =$M32*input!G31 -> 25397.088 | H32: =$M32*input!H31 -> 27742.372 | I32: =$M32*input!I31 -> 28208.271 | ... K32: =$M32*input!K31 -> 4368.757 | M32: 1
A33: =input!A32 -> B.III.2.a. Cred. vs Controllate entro | B33: =$M33*input!B32 -> 0 | C33: =$M33*input!C32 -> 0 | D33: =$M33*input!D32 -> 0 | E33: =$M33*input!E32 -> 0 | F33: =$M33*input!F32 -> 0 | G33: =$M33*input!G32 -> 0 | H33: =$M33*input!H32 -> 0 | I33: =$M33*input!I32 -> 0 | ... K33: =$M33*input!K32 -> 0 | M33: 1 | N33: Crediti vs controllate e collegate
A34: =input!A33 -> B.III.2.a. Cred. vs Controllate oltre | B34: =$M34*input!B33 -> 0 | C34: =$M34*input!C33 -> 0 | D34: =$M34*input!D33 -> 189673.99 | E34: =$M34*input!E33 -> 99635.89 | F34: =$M34*input!F33 -> 161439.38 | G34: =$M34*input!G33 -> 25072.292 | H34: =$M34*input!H33 -> 27460.396 | I34: =$M34*input!I33 -> 27930.013 | ... K34: =$M34*input!K33 -> 4081.917 | M34: 1 | N34: Crediti vs controllate e collegate
A35: =input!A34 -> B.III.2.b. Cred. vs Collegate entro | B35: =$M35*input!B34 -> 0 | C35: =$M35*input!C34 -> 0 | D35: =$M35*input!D34 -> 0 | E35: =$M35*input!E34 -> 0 | F35: =$M35*input!F34 -> 0 | G35: =$M35*input!G34 -> 0 | H35: =$M35*input!H34 -> 0 | I35: =$M35*input!I34 -> 0 | ... K35: =$M35*input!K34 -> 0 | M35: 1 | N35: Crediti vs controllate e collegate
A36: =input!A35 -> B.III.2.b. Cred. vs Collegate oltre | B36: =$M36*input!B35 -> 0 | C36: =$M36*input!C35 -> 0 | D36: =$M36*input!D35 -> 0 | E36: =$M36*input!E35 -> 0 | F36: =$M36*input!F35 -> 0 | G36: =$M36*input!G35 -> 0 | H36: =$M36*input!H35 -> 0 | I36: =$M36*input!I35 -> 0 | ... K36: =$M36*input!K35 -> 0 | M36: 1 | N36: Crediti vs controllate e collegate
A37: =input!A36 -> B.III.2.c. Cred. vs Controllanti entro | B37: =$M37*input!B36 -> 0 | C37: =$M37*input!C36 -> 0 | D37: =$M37*input!D36 -> 0 | E37: =$M37*input!E36 -> 0 | F37: =$M37*input!F36 -> 0 | G37: =$M37*input!G36 -> 0 | H37: =$M37*input!H36 -> 0 | I37: =$M37*input!I36 -> 0 | ... K37: =$M37*input!K36 -> 0 | M37: -1 | N37: Finanziamenti netti vs soci e controllanti
A38: =input!A37 -> B.III.2.c. Cred. vs Controllanti oltre | B38: =$M38*input!B37 -> 0 | C38: =$M38*input!C37 -> 0 | D38: =$M38*input!D37 -> 0 | E38: =$M38*input!E37 -> 0 | F38: =$M38*input!F37 -> 0 | G38: =$M38*input!G37 -> 0 | H38: =$M38*input!H37 -> 0 | I38: =$M38*input!I37 -> 0 | ... K38: =$M38*input!K37 -> 0 | M38: -1 | N38: Finanziamenti netti vs soci e controllanti
A39: =input!A38 -> B.III.2.d. Cred. vs imprese sottoposte al controllo delle controllanti entro | B39: =$M39*input!B38 -> 0 | C39: =$M39*input!C38 -> 0 | D39: =$M39*input!D38 -> 0 | E39: =$M39*input!E38 -> 0 | F39: =$M39*input!F38 -> 0 | G39: =$M39*input!G38 -> 0 | H39: =$M39*input!H38 -> 0 | I39: =$M39*input!I38 -> 0 | ... K39: =$M39*input!K38 -> 0 | M39: -1 | N39: Finanziamenti netti vs soci e controllanti
A40: =input!A39 -> B.III.2.d. Cred. vs imprese sottoposte al controllo delle controllanti oltre | B40: =$M40*input!B39 -> 0 | C40: =$M40*input!C39 -> 0 | D40: =$M40*input!D39 -> 0 | E40: =$M40*input!E39 -> 0 | F40: =$M40*input!F39 -> 0 | G40: =$M40*input!G39 -> 0 | H40: =$M40*input!H39 -> 0 | I40: =$M40*input!I39 -> 0 | ... K40: =$M40*input!K39 -> 0 | M40: -1 | N40: Finanziamenti netti vs soci e controllanti
A41: =input!A40 -> B.III.2.d.bis. Cred. vs Altri entro | B41: =$M41*input!B40 -> 0 | C41: =$M41*input!C40 -> 0 | D41: =$M41*input!D40 -> 10782.128 | E41: =$M41*input!E40 -> 343.435 | F41: =$M41*input!F40 -> 370.685 | G41: =$M41*input!G40 -> 324.796 | H41: =$M41*input!H40 -> 281.976 | I41: =$M41*input!I40 -> 278.258 | ... K41: =$M41*input!K40 -> 286.84 | M41: 1 | N41: Crediti diversi
A42: =input!A41 -> B.III.2.d.bis Cred. vs Altri oltre | B42: =$M42*input!B41 -> 0 | C42: =$M42*input!C41 -> 0 | D42: =$M42*input!D41 -> 0 | E42: =$M42*input!E41 -> 0 | F42: =$M42*input!F41 -> 0 | G42: =$M42*input!G41 -> 0 | H42: =$M42*input!H41 -> 0 | I42: =$M42*input!I41 -> 0 | ... K42: =$M42*input!K41 -> 0 | M42: 1 | N42: Crediti diversi
A43: =input!A42 -> B.III. CREDITI FIN. A BREVE | B43: =$M43*input!B42 -> 0 | C43: =$M43*input!C42 -> 0 | D43: =$M43*input!D42 -> 10782.128 | E43: =$M43*input!E42 -> 343.435 | F43: =$M43*input!F42 -> 370.685 | G43: =$M43*input!G42 -> 324.796 | H43: =$M43*input!H42 -> 281.976 | I43: =$M43*input!I42 -> 278.258 | ... K43: =$M43*input!K42 -> 286.84 | M43: 1
A44: =input!A43 -> B.III. CREDITI FIN. A OLTRE | B44: =$M44*input!B43 -> 0 | C44: =$M44*input!C43 -> 0 | D44: =$M44*input!D43 -> 189673.99 | E44: =$M44*input!E43 -> 99635.89 | F44: =$M44*input!F43 -> 161439.38 | G44: =$M44*input!G43 -> 25072.292 | H44: =$M44*input!H43 -> 27460.396 | I44: =$M44*input!I43 -> 27930.013 | ... K44: =$M44*input!K43 -> 4081.917 | M44: 1
A45: =input!A44 -> B.III.3. Altri titoli | B45: =$M45*input!B44 -> 0 | C45: =$M45*input!C44 -> 0 | D45: =$M45*input!D44 -> 0 | E45: =$M45*input!E44 -> 0 | F45: =$M45*input!F44 -> 0 | G45: =$M45*input!G44 -> 0 | H45: =$M45*input!H44 -> 0 | I45: =$M45*input!I44 -> 0 | ... K45: =$M45*input!K44 -> 0 | M45: 1 | N45: Partecipazioni
A46: =input!A45 -> B.III.3.bis. Azioni proprie | B46: =$M46*input!B45 -> 0 | C46: =$M46*input!C45 -> 0 | D46: =$M46*input!D45 -> 0 | E46: =$M46*input!E45 -> 0 | F46: =$M46*input!F45 -> 0 | G46: =$M46*input!G45 -> 0 | H46: =$M46*input!H45 -> 0 | I46: =$M46*input!I45 -> 0 | ... K46: =$M46*input!K45 -> 0 | M46: -1 | N46: Azioni proprie e partecipazioni in controllanti
A47: =input!A46 -> B.III.4. Strumenti finanziari derivati attivi | B47: =$M47*input!B46 -> 0 | C47: =$M47*input!C46 -> 0 | D47: =$M47*input!D46 -> 0 | E47: =$M47*input!E46 -> 0 | F47: =$M47*input!F46 -> 0 | G47: =$M47*input!G46 -> 0 | H47: =$M47*input!H46 -> 0 | I47: =$M47*input!I46 -> 0 | ... K47: =$M47*input!K46 -> 0 | M47: 1 | N47: Strumenti derivati attivi
A48: =input!A47 -> Azioni proprie DI CUI: Val nominale | B48: =$M48*input!B47 -> 0 | C48: =$M48*input!C47 -> 0 | D48: =$M48*input!D47 -> 0 | E48: =$M48*input!E47 -> 0 | F48: =$M48*input!F47 -> 0 | G48: =$M48*input!G47 -> 0 | H48: =$M48*input!H47 -> 0 | I48: =$M48*input!I47 -> 0 | ... K48: =$M48*input!K47 -> 0 | M48: 1
A49: inserimento manuale straordinario per assenza dati
A50: =input!A48 -> C. ATTIVO CIRCOLANTE | B50: =$M50*input!B48 -> 928992 | C50: =$M50*input!C48 -> 800575 | D50: =$M50*input!D48 -> 465473.07 | E50: =$M50*input!E48 -> 414787.23 | F50: =$M50*input!F48 -> 402157.7 | G50: =$M50*input!G48 -> 362440.91 | H50: =$M50*input!H48 -> 397058.58 | I50: =$M50*input!I48 -> 366357.24 | ... K50: =$M50*input!K48 -> 356907.61 | M50: 1
A51: =input!A49 -> C.I. TOTALE RIMANENZE | B51: =$M51*input!B49 -> 131166 | C51: =$M51*input!C49 -> 118064 | D51: =$M51*input!D49 -> 153759.14 | E51: =$M51*input!E49 -> 132482.19 | F51: =$M51*input!F49 -> 122437.38 | G51: =$M51*input!G49 -> 119385.93 | H51: =$M51*input!H49 -> 165935.34 | I51: =$M51*input!I49 -> 122521.08 | ... K51: =$M51*input!K49 -> 127191.34 | M51: 1
A52: =input!A50 -> C.I.1. Materie prime | B52: =$M52*input!B50 -> 36228 | C52: =$M52*input!C50 -> 28765 | D52: =$M52*input!D50 -> 51100.075 | E52: =$M52*input!E50 -> 55036.616 | F52: =$M52*input!F50 -> 56441.392 | G52: =$M52*input!G50 -> 55075.056 | H52: =$M52*input!H50 -> 94295.833 | I52: =$M52*input!I50 -> 54804.973 | ... K52: =$M52*input!K50 -> 56487.773 | M52: 1 | N52: Magazzino
A53: =input!A51 -> C.I.2. Prodotti semilav./in corso | B53: =$M53*input!B51 -> 21392 | C53: =$M53*input!C51 -> 17346 | D53: =$M53*input!D51 -> 18137.727 | E53: =$M53*input!E51 -> 20388.608 | F53: =$M53*input!F51 -> 15941.976 | G53: =$M53*input!G51 -> 13231.563 | H53: =$M53*input!H51 -> 17396.257 | I53: =$M53*input!I51 -> 14002.516 | ... K53: =$M53*input!K51 -> 21028.982 | M53: 1 | N53: Magazzino
A54: =input!A52 -> C.I.3. Lavori in corso | B54: =$M54*input!B52 -> 0 | C54: =$M54*input!C52 -> 0 | D54: =$M54*input!D52 -> 0 | E54: =$M54*input!E52 -> 0 | F54: =$M54*input!F52 -> 0 | G54: =$M54*input!G52 -> 0 | H54: =$M54*input!H52 -> 0 | I54: =$M54*input!I52 -> 0 | ... K54: =$M54*input!K52 -> 0 | M54: 1 | N54: Magazzino
A55: =input!A53 -> C.I.4. Prodotti finiti | B55: =$M55*input!B53 -> 73546 | C55: =$M55*input!C53 -> 71953 | D55: =$M55*input!D53 -> 84521.341 | E55: =$M55*input!E53 -> 57056.969 | F55: =$M55*input!F53 -> 50054.017 | G55: =$M55*input!G53 -> 51079.308 | H55: =$M55*input!H53 -> 54243.249 | I55: =$M55*input!I53 -> 53713.595 | ... K55: =$M55*input!K53 -> 49674.584 | M55: 1 | N55: Magazzino
A56: =input!A54 -> C.I.5. Acconti | B56: =$M56*input!B54 -> 0 | C56: =$M56*input!C54 -> 0 | D56: =$M56*input!D54 -> 0 | E56: =$M56*input!E54 -> 0 | F56: =$M56*input!F54 -> 0 | G56: =$M56*input!G54 -> 0 | H56: =$M56*input!H54 -> 0 | I56: =$M56*input!I54 -> 0 | ... K56: =$M56*input!K54 -> 0 | M56: 1 | N56: Altre attività operative correnti
A57: =input!A55 -> Immobilizzazioni materiali destinate alla vendita | B57: =$M57*input!B55 -> 0 | C57: =$M57*input!C55 -> 0 | D57: =$M57*input!D55 -> 510 | E57: =$M57*input!E55 -> 2484.427 | F57: =$M57*input!F55 -> 0 | G57: =$M57*input!G55 -> 0 | H57: =$M57*input!H55 -> 0 | I57: =$M57*input!I55 -> 9544.279 | ... K57: =$M57*input!K55 -> 0 | M57: 1 | N57: Immobilizzazioni materiali nette
A58: =input!A56 -> C.II. TOTALE CREDITI | B58: =$M58*input!B56 -> 466516 | C58: =$M58*input!C56 -> 385746 | D58: =$M58*input!D56 -> 201829.77 | E58: =$M58*input!E56 -> 172658.69 | F58: =$M58*input!F56 -> 141122.55 | G58: =$M58*input!G56 -> 135002.11 | H58: =$M58*input!H56 -> 210872.06 | I58: =$M58*input!I56 -> 184547.51 | ... K58: =$M58*input!K56 -> 221173.32 | M58: 1
A59: =input!A57 -> C.II.1. Cred. vs Clienti entro | B59: =$M59*input!B57 -> 101879 | C59: =$M59*input!C57 -> 90210 | D59: =$M59*input!D57 -> 23706.719 | E59: =$M59*input!E57 -> 29714.413 | F59: =$M59*input!F57 -> 49086.977 | G59: =$M59*input!G57 -> 70085.629 | H59: =$M59*input!H57 -> 136291.51 | I59: =$M59*input!I57 -> 129228.82 | ... K59: =$M59*input!K57 -> 142030.01 | M59: 1 | N59: Crediti verso clienti
A60: =input!A58 -> C.II.1. Cred. vs Clienti oltre | B60: =$M60*input!B58 -> 0 | C60: =$M60*input!C58 -> 0 | D60: =$M60*input!D58 -> 0 | E60: =$M60*input!E58 -> 0 | F60: =$M60*input!F58 -> 0 | G60: =$M60*input!G58 -> 0 | H60: =$M60*input!H58 -> 0 | I60: =$M60*input!I58 -> 0 | ... K60: =$M60*input!K58 -> 0 | M60: 1 | N60: Crediti verso clienti
A61: =input!A59 -> C.II.2. Cred. vs Controllate entro | B61: =$M61*input!B59 -> 0 | C61: =$M61*input!C59 -> 0 | D61: =$M61*input!D59 -> 94483.737 | E61: =$M61*input!E59 -> 84671.502 | F61: =$M61*input!F59 -> 42783.246 | G61: =$M61*input!G59 -> 43410.699 | H61: =$M61*input!H59 -> 49179.387 | I61: =$M61*input!I59 -> 35369.92 | ... K61: =$M61*input!K59 -> 49767.019 | M61: 1 | N61: Crediti vs controllate e collegate
A62: =input!A60 -> C.II.2. Cred. vs Controllate oltre | B62: =$M62*input!B60 -> 0 | C62: =$M62*input!C60 -> 0 | D62: =$M62*input!D60 -> 0 | E62: =$M62*input!E60 -> 0 | F62: =$M62*input!F60 -> 0 | G62: =$M62*input!G60 -> 0 | H62: =$M62*input!H60 -> 0 | I62: =$M62*input!I60 -> 0 | ... K62: =$M62*input!K60 -> 0 | M62: 1 | N62: Crediti vs controllate e collegate
A63: =input!A61 -> C.II.3. Cred. vs Collegate entro | B63: =$M63*input!B61 -> 0 | C63: =$M63*input!C61 -> 0 | D63: =$M63*input!D61 -> 0 | E63: =$M63*input!E61 -> 0 | F63: =$M63*input!F61 -> 0 | G63: =$M63*input!G61 -> 0 | H63: =$M63*input!H61 -> 0 | I63: =$M63*input!I61 -> 0.114 | ... K63: =$M63*input!K61 -> 0 | M63: 1 | N63: Crediti vs controllate e collegate
A64: =input!A62 -> C.II.3. Cred. vs Collegate oltre | B64: =$M64*input!B62 -> 0 | C64: =$M64*input!C62 -> 0 | D64: =$M64*input!D62 -> 0 | E64: =$M64*input!E62 -> 0 | F64: =$M64*input!F62 -> 0 | G64: =$M64*input!G62 -> 0 | H64: =$M64*input!H62 -> 0 | I64: =$M64*input!I62 -> 0 | ... K64: =$M64*input!K62 -> 0 | M64: 1 | N64: Crediti vs controllate e collegate
A65: =input!A63 -> C.II.4. Cred. vs Controllanti entro | B65: =$M65*input!B63 -> 0 | C65: =$M65*input!C63 -> 0 | D65: =$M65*input!D63 -> 0 | E65: =$M65*input!E63 -> -2347.699 | F65: =$M65*input!F63 -> -150.154 | G65: =$M65*input!G63 -> -60.784 | H65: =$M65*input!H63 -> 0 | I65: =$M65*input!I63 -> -17.433 | ... K65: =$M65*input!K63 -> -8499.321 | M65: -1 | N65: Finanziamenti netti vs soci e controllanti
A66: =input!A64 -> C.II.4. Cred. vs Controllanti oltre | B66: =$M66*input!B64 -> 0 | C66: =$M66*input!C64 -> 0 | D66: =$M66*input!D64 -> 0 | E66: =$M66*input!E64 -> 0 | F66: =$M66*input!F64 -> 0 | G66: =$M66*input!G64 -> 0 | H66: =$M66*input!H64 -> 0 | I66: =$M66*input!I64 -> 0 | ... K66: =$M66*input!K64 -> -3363.959 | M66: -1 | N66: Finanziamenti netti vs soci e controllanti
A67: =input!A65 -> C.II.5. Cred. vs imprese sottoposte al controllo delle controllanti entro | B67: =$M67*input!B65 -> 0 | C67: =$M67*input!C65 -> 0 | D67: =$M67*input!D65 -> 0 | E67: =$M67*input!E65 -> 0 | F67: =$M67*input!F65 -> 0 | G67: =$M67*input!G65 -> -104.127 | H67: =$M67*input!H65 -> -1719.228 | I67: =$M67*input!I65 -> 0 | ... K67: =$M67*input!K65 -> 0 | M67: -1 | N67: Finanziamenti netti vs soci e controllanti
A68: =input!A66 -> C.II.5. Cred. vs imprese sottoposte al controllo delle controllanti oltre | B68: =$M68*input!B66 -> 0 | C68: =$M68*input!C66 -> 0 | D68: =$M68*input!D66 -> 0 | E68: =$M68*input!E66 -> 0 | F68: =$M68*input!F66 -> 0 | G68: =$M68*input!G66 -> 0 | H68: =$M68*input!H66 -> 0 | I68: =$M68*input!I66 -> 0 | ... K68: =$M68*input!K66 -> 0 | M68: -1 | N68: Finanziamenti netti vs soci e controllanti
A69: =input!A67 -> C.II.5.bis. Cred. tributari entro | B69: =$M69*input!B67 -> 10412 | C69: =$M69*input!C67 -> 8555 | D69: =$M69*input!D67 -> 33563.234 | E69: =$M69*input!E67 -> 3849.21 | F69: =$M69*input!F67 -> 5238.225 | G69: =$M69*input!G67 -> 2425.476 | H69: =$M69*input!H67 -> 3415.281 | I69: =$M69*input!I67 -> 1617.122 | ... K69: =$M69*input!K67 -> 1914.91 | M69: 1 | N69: Crediti fisco-previdenziali
A70: =input!A68 -> C.II.5.bis. Cred. tributari oltre | B70: =$M70*input!B68 -> 0 | C70: =$M70*input!C68 -> 0 | D70: =$M70*input!D68 -> 17289.35 | E70: =$M70*input!E68 -> 21476.191 | F70: =$M70*input!F68 -> 21275.683 | G70: =$M70*input!G68 -> 1476.219 | H70: =$M70*input!H68 -> 1476.219 | I70: =$M70*input!I68 -> 1476.219 | ... K70: =$M70*input!K68 -> 0 | M70: 1 | N70: Crediti fisco-previdenziali
... A74: =input!A72 -> C.II.5.quater. Cred. verso altri oltre | B74: =$M74*input!B72 -> 8314 | C74: =$M74*input!C72 -> 13104 | D74: =$M74*input!D72 -> 40.953 | E74: =$M74*input!E72 -> 81.906 | F74: =$M74*input!F72 -> 139.577 | G74: =$M74*input!G72 -> 1.103 | H74: =$M74*input!H72 -> 50.156 | I74: =$M74*input!I72 -> 96.893 | ... K74: =$M74*input!K72 -> 105.532 | M74: 1 | N74: Altre attività operative correnti
A75: =input!A73 -> C.II. Crediti a breve | B75: =$M75*input!B73 -> 420418 | C75: =$M75*input!C73 -> 349516 | D75: =$M75*input!D73 -> 184499.46 | E75: =$M75*input!E73 -> 151100.59 | F75: =$M75*input!F73 -> 119707.29 | G75: =$M75*input!G73 -> 133524.79 | H75: =$M75*input!H73 -> 209345.68 | I75: =$M75*input!I73 -> 182974.4 | ... K75: =$M75*input!K73 -> 211653.72 | M75: 1
A76: =input!A74 -> Crediti per imposte anticipate | B76: =$M76*input!B74 -> 0 | C76: =$M76*input!C74 -> 0 | D76: =$M76*input!D74 -> 0 | E76: =$M76*input!E74 -> 0 | F76: =$M76*input!F74 -> 0 | G76: =$M76*input!G74 -> 0 | H76: =$M76*input!H74 -> 0 | I76: =$M76*input!I74 -> 0 | ... K76: =$M76*input!K74 -> 0 | M76: 1
A77: =input!A75 -> C.II. Crediti a oltre | B77: =$M77*input!B75 -> 46098 | C77: =$M77*input!C75 -> 36230 | D77: =$M77*input!D75 -> 17330.303 | E77: =$M77*input!E75 -> 21558.097 | F77: =$M77*input!F75 -> 21415.26 | G77: =$M77*input!G75 -> 1477.322 | H77: =$M77*input!H75 -> 1526.375 | I77: =$M77*input!I75 -> 1573.112 | ... K77: =$M77*input!K75 -> 9519.6 | M77: 1
A78: =input!A76 -> C.III. TOTALE ATTIVITA' FINANZIARIE | B78: =$M78*input!B76 -> 179600 | C78: =$M78*input!C76 -> 78779 | D78: =$M78*input!D76 -> 24977.574 | E78: =$M78*input!E76 -> 7277.777 | F78: =$M78*input!F76 -> 3815.003 | G78: =$M78*input!G76 -> 5346.81 | H78: =$M78*input!H76 -> 10708.029 | I78: =$M78*input!I76 -> 38218.805 | ... K78: =$M78*input!K76 -> 0 | M78: 1
A79: =input!A77 -> C.III.1. Partec.ni in Controllate | B79: =$M79*input!B77 -> 0 | C79: =$M79*input!C77 -> 0 | D79: =$M79*input!D77 -> 0 | E79: =$M79*input!E77 -> 0 | F79: =$M79*input!F77 -> 0 | G79: =$M79*input!G77 -> 0 | H79: =$M79*input!H77 -> 0 | I79: =$M79*input!I77 -> 0 | ... K79: =$M79*input!K77 -> 0 | M79: 1 | N79: Partecipazioni
A80: =input!A78 -> C.III.2. Partec.ni in Collegate | B80: =$M80*input!B78 -> 0 | C80: =$M80*input!C78 -> 0 | D80: =$M80*input!D78 -> 0 | E80: =$M80*input!E78 -> 0 | F80: =$M80*input!F78 -> 0 | G80: =$M80*input!G78 -> 0 | H80: =$M80*input!H78 -> 0 | I80: =$M80*input!I78 -> 0 | ... K80: =$M80*input!K78 -> 0 | M80: 1 | N80: Partecipazioni
A81: =input!A79 -> C.III.3. Partec.ni in Controllanti | B81: =$M81*input!B79 -> 0 | C81: =$M81*input!C79 -> 0 | D81: =$M81*input!D79 -> 0 | E81: =$M81*input!E79 -> 0 | F81: =$M81*input!F79 -> 0 | G81: =$M81*input!G79 -> 0 | H81: =$M81*input!H79 -> 0 | I81: =$M81*input!I79 -> 0 | ... K81: =$M81*input!K79 -> 0 | M81: -1 | N81: Azioni proprie e partecipazioni in controllanti
A82: =input!A80 -> C.III.3.bis. Partec.ni in imprese sottoposte al controllo delle controllanti | B82: =$M82*input!B80 -> 0 | C82: =$M82*input!C80 -> 0 | D82: =$M82*input!D80 -> 0 | E82: =$M82*input!E80 -> 0 | F82: =$M82*input!F80 -> 0 | G82: =$M82*input!G80 -> 0 | H82: =$M82*input!H80 -> 0 | I82: =$M82*input!I80 -> 0 | ... K82: =$M82*input!K80 -> 0 | M82: -1 | N82: Azioni proprie e partecipazioni in controllanti
A83: =input!A81 -> C.III.4. Altre Partec.ni | B83: =$M83*input!B81 -> 0 | C83: =$M83*input!C81 -> 0 | D83: =$M83*input!D81 -> 0 | E83: =$M83*input!E81 -> 0 | F83: =$M83*input!F81 -> 0 | G83: =$M83*input!G81 -> 0 | H83: =$M83*input!H81 -> 0 | I83: =$M83*input!I81 -> 0 | ... K83: =$M83*input!K81 -> 0 | M83: 1 | N83: Partecipazioni
A84: =input!A82 -> C.III.4.bis. Azioni proprie | B84: =$M84*input!B82 -> 0 | C84: =$M84*input!C82 -> 0 | D84: =$M84*input!D82 -> 0 | E84: =$M84*input!E82 -> 0 | F84: =$M84*input!F82 -> 0 | G84: =$M84*input!G82 -> 0 | H84: =$M84*input!H82 -> 0 | I84: =$M84*input!I82 -> 0 | ... K84: =$M84*input!K82 -> 0 | M84: -1 | N84: Azioni proprie e partecipazioni in controllanti
A85: =input!A83 -> Azioni proprie DI CUI: Val nominale | B85: =$M85*input!B83 -> 0 | C85: =$M85*input!C83 -> 0 | D85: =$M85*input!D83 -> 0 | E85: =$M85*input!E83 -> 0 | F85: =$M85*input!F83 -> 0 | G85: =$M85*input!G83 -> 0 | H85: =$M85*input!H83 -> 0 | I85: =$M85*input!I83 -> 0 | ... K85: =$M85*input!K83 -> 0 | M85: 1
A86: =input!A84 -> C.III.5. Strumenti finanziari derivati attivi | B86: =$M86*input!B84 -> 6904 | C86: =$M86*input!C84 -> 0 | D86: =$M86*input!D84 -> 1696.644 | E86: =$M86*input!E84 -> 5609.937 | F86: =$M86*input!F84 -> 623.72 | G86: =$M86*input!G84 -> 68.101 | H86: =$M86*input!H84 -> 347.477 | I86: =$M86*input!I84 -> 30.892 | ... K86: =$M86*input!K84 -> 0 | M86: 1 | N86: Strumenti derivati attivi
A87: =input!A85 -> C.III.6. Altri titoli | B87: =$M87*input!B85 -> 0 | C87: =$M87*input!C85 -> 0 | D87: =$M87*input!D85 -> 0 | E87: =$M87*input!E85 -> 0 | F87: =$M87*input!F85 -> 0 | G87: =$M87*input!G85 -> 0 | H87: =$M87*input!H85 -> 0 | I87: =$M87*input!I85 -> 0 | ... K87: =$M87*input!K85 -> 0 | M87: 1 | N87: Riserve strategiche di liquidità
A88: =input!A86 -> C.III.7. Attività finanziarie per la gestione accentrata della tesoreria | B88: =$M88*input!B86 -> 172696 | C88: =$M88*input!C86 -> 78779 | D88: =$M88*input!D86 -> 23280.93 | E88: =$M88*input!E86 -> 1667.84 | F88: =$M88*input!F86 -> 3191.283 | G88: =$M88*input!G86 -> 5278.709 | H88: =$M88*input!H86 -> 10360.552 | I88: =$M88*input!I86 -> 38187.913 | ... K88: =$M88*input!K86 -> 0 | M88: 1 | N88: Attività di tesoreria
A89: =input!A87 -> C.IV. TOT. DISPON. LIQUIDE | B89: =$M89*input!B87 -> 151710 | C89: =$M89*input!C87 -> 217986 | D89: =$M89*input!D87 -> 84396.581 | E89: =$M89*input!E87 -> 99884.146 | F89: =$M89*input!F87 -> 134782.76 | G89: =$M89*input!G87 -> 102706.06 | H89: =$M89*input!H87 -> 9543.148 | I89: =$M89*input!I87 -> 11525.562 | ... K89: =$M89*input!K87 -> 8542.951 | M89: 1
A90: =input!A88 -> C.IV.1. Depositi bancari | B90: =$M90*input!B88 -> 151686 | C90: =$M90*input!C88 -> 217926 | D90: =$M90*input!D88 -> 84346.945 | E90: =$M90*input!E88 -> 99824.346 | F90: =$M90*input!F88 -> 134694.24 | G90: =$M90*input!G88 -> 102618.29 | H90: =$M90*input!H88 -> 9451.376 | I90: =$M90*input!I88 -> 11392.256 | ... K90: =$M90*input!K88 -> 8449.194 | M90: 1 | N90: Attività di tesoreria
A91: =input!A89 -> C.IV.2. Assegni | B91: =$M91*input!B89 -> 0 | C91: =$M91*input!C89 -> 0 | D91: =$M91*input!D89 -> 0 | E91: =$M91*input!E89 -> 1.255 | F91: =$M91*input!F89 -> 30.017 | G91: =$M91*input!G89 -> 0 | H91: =$M91*input!H89 -> 0 | I91: =$M91*input!I89 -> 1.639 | ... K91: =$M91*input!K89 -> 0 | M91: 1 | N91: Attività di tesoreria
A92: =input!A90 -> C.IV.3. Denaro in cassa | B92: =$M92*input!B90 -> 24 | C92: =$M92*input!C90 -> 60 | D92: =$M92*input!D90 -> 49.636 | E92: =$M92*input!E90 -> 58.545 | F92: =$M92*input!F90 -> 58.507 | G92: =$M92*input!G90 -> 87.767 | H92: =$M92*input!H90 -> 91.772 | I92: =$M92*input!I90 -> 131.667 | ... K92: =$M92*input!K90 -> 93.757 | M92: 1 | N92: Attività di tesoreria
A93: =input!A91 -> D. RATEI E RISCONTI | B93: =$M93*input!B91 -> 5495 | C93: =$M93*input!C91 -> 3920 | D93: =$M93*input!D91 -> 3803.008 | E93: =$M93*input!E91 -> 2622.996 | F93: =$M93*input!F91 -> 2341.983 | G93: =$M93*input!G91 -> 1486.968 | H93: =$M93*input!H91 -> 879.808 | I93: =$M93*input!I91 -> 874.591 | ... K93: =$M93*input!K91 -> 1262.259 | M93: 1 | N93: Altre attività operative correnti
A94: =input!A92 -> Disaggio su prestiti | B94: =$M94*input!B92 -> 0 | C94: =$M94*input!C92 -> 0 | D94: =$M94*input!D92 -> 0 | E94: =$M94*input!E92 -> 0 | F94: =$M94*input!F92 -> 0 | G94: =$M94*input!G92 -> 0 | H94: =$M94*input!H92 -> 0 | I94: =$M94*input!I92 -> 0 | ... K94: =$M94*input!K92 -> 0 | M94: 1
A95: =input!A93 -> TOTALE ATTIVO | B95: =$M95*input!B93 -> 3790320 | C95: =$M95*input!C93 -> 1675063 | D95: =$M95*input!D93 -> 1536537 | E95: =$M95*input!E93 -> 1308756.7 | F95: =$M95*input!F93 -> 1311132.3 | G95: =$M95*input!G93 -> 741974.82 | H95: =$M95*input!H93 -> 792683.74 | I95: =$M95*input!I93 -> 788836.85 | ... K95: =$M95*input!K93 -> 780383.29 | M95: 1
A97: =input!A94 -> Passivo
A98: =input!A95 -> PATRIMONIO NETTO | B98: =$M98*input!B95 -> 0 | C98: =$M98*input!C95 -> 0 | D98: =$M98*input!D95 -> 0 | E98: =$M98*input!E95 -> 0 | F98: =$M98*input!F95 -> 0 | G98: =$M98*input!G95 -> 0 | H98: =$M98*input!H95 -> 0 | I98: =$M98*input!I95 -> 0 | ... K98: =$M98*input!K95 -> 0 | M98: 1
A99: =input!A96 -> A. TOTALE PATRIMONIO NETTO | B99: =$M99*input!B96 -> 852247 | C99: =$M99*input!C96 -> 88219 | D99: =$M99*input!D96 -> 136548.72 | E99: =$M99*input!E96 -> 117108.52 | F99: =$M99*input!F96 -> 124862.24 | G99: =$M99*input!G96 -> 344954.71 | H99: =$M99*input!H96 -> 348518.46 | I99: =$M99*input!I96 -> 370611.09 | ... K99: =$M99*input!K96 -> 318992.28 | M99: 1
A100: =input!A97 -> A.I. Capitale sociale | B100: =$M100*input!B97 -> 40000 | C100: =$M100*input!C97 -> 40000 | D100: =$M100*input!D97 -> 40000.22 | E100: =$M100*input!E97 -> 40000.22 | F100: =$M100*input!F97 -> 40000.22 | G100: =$M100*input!G97 -> 40000.22 | H100: =$M100*input!H97 -> 40000.22 | I100: =$M100*input!I97 -> 40000.22 | ... K100: =$M100*input!K97 -> 40000.22 | M100: 1 | N100: Capitale conferito dai soci
A101: =input!A98 -> di cui: Versamenti soci in c/capitale | B101: =$M101*input!B98 -> 0 | C101: =$M101*input!C98 -> 0 | D101: =$M101*input!D98 -> 4500 | E101: =$M101*input!E98 -> 0 | F101: =$M101*input!F98 -> 0 | G101: =$M101*input!G98 -> 0.098 | H101: =$M101*input!H98 -> 0.098 | I101: =$M101*input!I98 -> 0.098 | ... K101: =$M101*input!K98 -> 0.098 | M101: 1
A102: =input!A99 -> di cui: Versamenti in c/futuro aumento di capitale | B102: =$M102*input!B99 -> 0 | C102: =$M102*input!C99 -> 0 | D102: =$M102*input!D99 -> 0 | E102: =$M102*input!E99 -> 0 | F102: =$M102*input!F99 -> 0 | G102: =$M102*input!G99 -> 0 | H102: =$M102*input!H99 -> 0 | I102: =$M102*input!I99 -> 0 | ... K102: =$M102*input!K99 -> 0 | M102: 1
A103: =input!A100 -> di cui: Versamenti in c/capitale | B103: =$M103*input!B100 -> 0 | C103: =$M103*input!C100 -> 0 | D103: =$M103*input!D100 -> 0 | E103: =$M103*input!E100 -> 0 | F103: =$M103*input!F100 -> 0 | G103: =$M103*input!G100 -> 0 | H103: =$M103*input!H100 -> 0 | I103: =$M103*input!I100 -> 0 | ... K103: =$M103*input!K100 -> 0 | M103: 1
A104: =input!A101 -> di cui: Versamenti a copertura perdite | B104: =$M104*input!B101 -> 0 | C104: =$M104*input!C101 -> 0 | D104: =$M104*input!D101 -> 0 | E104: =$M104*input!E101 -> 0 | F104: =$M104*input!F101 -> 0 | G104: =$M104*input!G101 -> 0 | H104: =$M104*input!H101 -> 0 | I104: =$M104*input!I101 -> 0 | ... K104: =$M104*input!K101 -> 0 | M104: 1
A105: =input!A102 -> A.II. Riserva da sovrapprezzo | B105: =$M105*input!B102 -> 60241 | C105: =$M105*input!C102 -> 60241 | D105: =$M105*input!D102 -> 60241.454 | E105: =$M105*input!E102 -> 60241.454 | F105: =$M105*input!F102 -> 60241.454 | G105: =$M105*input!G102 -> 51829.138 | H105: =$M105*input!H102 -> 51829.138 | I105: =$M105*input!I102 -> 51829.138 | ... K105: =$M105*input!K102 -> 51829.138 | M105: 1 | N105: Capitale conferito dai soci
...

Sheet RC
B1: =case!B1 -> 31/12/2024 | C1: =case!C1 -> 31/12/2023 | D1: =case!D1 -> 31/12/2022 | E1: =case!E1 -> 31/12/2021 | F1: =case!F1 -> 31/12/2020 | G1: =case!G1 -> 31/12/2019 | H1: =case!H1 -> 31/12/2018 | I1: =case!I1 -> 31/12/2017 | ... K1: =case!K1 -> 31/12/2015
A2: Stato Patrimoniale Attivo
A3: Attività operative
A4: Attività operative correnti
A5: Crediti verso clienti | B5: =SUMIF(case!$N:$N,$A5,case!B:B) -> 101879 | C5: =SUMIF(case!$N:$N,$A5,case!C:C) -> 90210 | D5: =SUMIF(case!$N:$N,$A5,case!D:D) -> 23706.719 | E5: =SUMIF(case!$N:$N,$A5,case!E:E) -> 29714.413 | F5: =SUMIF(case!$N:$N,$A5,case!F:F) -> 49086.977 | G5: =SUMIF(case!$N:$N,$A5,case!G:G) -> 70085.629 | H5: =SUMIF(case!$N:$N,$A5,case!H:H) -> 136291.51 | I5: =SUMIF(case!$N:$N,$A5,case!I:I) -> 129228.82 | J5: =SUMIF(case!$N:$N,$A5,case!J:J) -> 138605.74 | K5: =SUMIF(case!$N:$N,$A5,case!K:K) -> 142030.01
A6: Magazzino | B6: =SUMIF(case!$N:$N,$A6,case!B:B) -> 131166 | C6: =SUMIF(case!$N:$N,$A6,case!C:C) -> 118064 | D6: =SUMIF(case!$N:$N,$A6,case!D:D) -> 153759.14 | E6: =SUMIF(case!$N:$N,$A6,case!E:E) -> 132482.19 | F6: =SUMIF(case!$N:$N,$A6,case!F:F) -> 122437.39 | G6: =SUMIF(case!$N:$N,$A6,case!G:G) -> 119385.93 | H6: =SUMIF(case!$N:$N,$A6,case!H:H) -> 165935.34 | I6: =SUMIF(case!$N:$N,$A6,case!I:I) -> 122521.08 | J6: =SUMIF(case!$N:$N,$A6,case!J:J) -> 131111.25 | K6: =SUMIF(case!$N:$N,$A6,case!K:K) -> 127191.34
A7: Altre attività operative correnti | B7: =SUMIF(case!$N:$N,$A7,case!B:B) -> 321936 | C7: =SUMIF(case!$N:$N,$A7,case!C:C) -> 267775 | D7: =SUMIF(case!$N:$N,$A7,case!D:D) -> 17604.266 | E7: =SUMIF(case!$N:$N,$A7,case!E:E) -> 18782.062 | F7: =SUMIF(case!$N:$N,$A7,case!F:F) -> 8428.457 | G7: =SUMIF(case!$N:$N,$A7,case!G:G) -> 2544.949 | H7: =SUMIF(case!$N:$N,$A7,case!H:H) -> 4712.925 | I7: =SUMIF(case!$N:$N,$A7,case!I:I) -> 4013.273 | J7: =SUMIF(case!$N:$N,$A7,case!J:J) -> 2973.346 | K7: =SUMIF(case!$N:$N,$A7,case!K:K) -> 9881.25
A8: Totale attività operative correnti | B8: =SUM(B5:B7) -> 554981 | C8: =SUM(C5:C7) -> 476049 | D8: =SUM(D5:D7) -> 195070.13 | E8: =SUM(E5:E7) -> 180978.67 | F8: =SUM(F5:F7) -> 179952.82 | G8: =SUM(G5:G7) -> 192016.5 | H8: =SUM(H5:H7) -> 306939.78 | I8: =SUM(I5:I7) -> 255763.17 | ... K8: =SUM(K5:K7) -> 279102.59
A9: Immobilizzazioni operative nette
A10: Immobilizzazioni materiali nette | B10: =SUMIF(case!$N:$N,$A10,case!B:B) -> 247743 | C10: =SUMIF(case!$N:$N,$A10,case!C:C) -> 220617 | D10: =SUMIF(case!$N:$N,$A10,case!D:D) -> 224251.13 | E10: =SUMIF(case!$N:$N,$A10,case!E:E) -> 220459.24 | F10: =SUMIF(case!$N:$N,$A10,case!F:F) -> 220394.5 | G10: =SUMIF(case!$N:$N,$A10,case!G:G) -> 154055.72 | H10: =SUMIF(case!$N:$N,$A10,case!H:H) -> 149620.66 | I10: =SUMIF(case!$N:$N,$A10,case!I:I) -> 158524.65 | J10: =SUMIF(case!$N:$N,$A10,case!J:J) -> 145157.72 | K10: =SUMIF(case!$N:$N,$A10,case!K:K) -> 152948.57
A11: Immobilizzazioni immateriali nette | B11: =SUMIF(case!$N:$N,$A11,case!B:B) -> 1592262 | C11: =SUMIF(case!$N:$N,$A11,case!C:C) -> 90098 | D11: =SUMIF(case!$N:$N,$A11,case!D:D) -> 86779.886 | E11: =SUMIF(case!$N:$N,$A11,case!E:E) -> 89055.322 | F11: =SUMIF(case!$N:$N,$A11,case!F:F) -> 87656.701 | G11: =SUMIF(case!$N:$N,$A11,case!G:G) -> 13306.33 | H11: =SUMIF(case!$N:$N,$A11,case!H:H) -> 11674.413 | I11: =SUMIF(case!$N:$N,$A11,case!I:I) -> 12394.555 | J11: =SUMIF(case!$N:$N,$A11,case!J:J) -> 14257.563 | K11: =SUMIF(case!$N:$N,$A11,case!K:K) -> 16231.349
A12: Totale immobilizzazioni operative nette | B12: =SUM(B10:B11) -> 1840005 | C12: =SUM(C10:C11) -> 310715 | D12: =SUM(D10:D11) -> 311031.01 | E12: =SUM(E10:E11) -> 309514.56 | F12: =SUM(F10:F11) -> 308051.2 | G12: =SUM(G10:G11) -> 167362.05 | H12: =SUM(H10:H11) -> 161295.08 | I12: =SUM(I10:I11) -> 170919.21 | ... K12: =SUM(K10:K11) -> 169179.91
A13: Altre attività operative immobilizzate
A14: Crediti diversi | B14: =SUMIF(case!$N:$N,$A14,case!B:B) -> 0 | C14: =SUMIF(case!$N:$N,$A14,case!C:C) -> 0 | D14: =SUMIF(case!$N:$N,$A14,case!D:D) -> 10782.128 | E14: =SUMIF(case!$N:$N,$A14,case!E:E) -> 343.435 | F14: =SUMIF(case!$N:$N,$A14,case!F:F) -> 370.685 | G14: =SUMIF(case!$N:$N,$A14,case!G:G) -> 324.796 | H14: =SUMIF(case!$N:$N,$A14,case!H:H) -> 281.976 | I14: =SUMIF(case!$N:$N,$A14,case!I:I) -> 278.258 | J14: =SUMIF(case!$N:$N,$A14,case!J:J) -> 291.076 | K14: =SUMIF(case!$N:$N,$A14,case!K:K) -> 286.84
A15: Totale altre attività operative immobilizzate | B15: =SUM(B14) -> 0 | C15: =SUM(C14) -> 0 | D15: =SUM(D14) -> 10782.128 | E15: =SUM(E14) -> 343.435 | F15: =SUM(F14) -> 370.685 | G15: =SUM(G14) -> 324.796 | H15: =SUM(H14) -> 281.976 | I15: =SUM(I14) -> 278.258 | ... K15: =SUM(K14) -> 286.84
A16: Totale attività operative | B16: =B8+B12+B15 -> 2394986 | C16: =C8+C12+C15 -> 786764 | D16: =D8+D12+D15 -> 516883.27 | E16: =E8+E12+E15 -> 490836.66 | F16: =F8+F12+F15 -> 488374.71 | G16: =G8+G12+G15 -> 359703.35 | H16: =H8+H12+H15 -> 468516.83 | I16: =I8+I12+I15 -> 426960.64 | ... K16: =K8+K12+K15 -> 448569.35
A18: Attività fiscali
A19: Crediti fisco-previdenziali | B19: =SUMIF(case!$N:$N,$A19,case!B:B) -> 10412 | C19: =SUMIF(case!$N:$N,$A19,case!C:C) -> 8555 | D19: =SUMIF(case!$N:$N,$A19,case!D:D) -> 50852.584 | E19: =SUMIF(case!$N:$N,$A19,case!E:E) -> 25325.401 | F19: =SUMIF(case!$N:$N,$A19,case!F:F) -> 26513.908 | G19: =SUMIF(case!$N:$N,$A19,case!G:G) -> 3901.695 | H19: =SUMIF(case!$N:$N,$A19,case!H:H) -> 4891.5 | I19: =SUMIF(case!$N:$N,$A19,case!I:I) -> 3093.341 | J19: =SUMIF(case!$N:$N,$A19,case!J:J) -> 1080.503 | K19: =SUMIF(case!$N:$N,$A19,case!K:K) -> 1914.91
A20: Attività per imposte anticipate | B20: =SUMIF(case!$N:$N,$A20,case!B:B) -> 37784 | C20: =SUMIF(case!$N:$N,$A20,case!C:C) -> 23126 | D20: =SUMIF(case!$N:$N,$A20,case!D:D) -> 18985.47 | E20: =SUMIF(case!$N:$N,$A20,case!E:E) -> 14440.609 | F20: =SUMIF(case!$N:$N,$A20,case!F:F) -> 16501.79 | G20: =SUMIF(case!$N:$N,$A20,case!G:G) -> 16381.2 | H20: =SUMIF(case!$N:$N,$A20,case!H:H) -> 14957.316 | I20: =SUMIF(case!$N:$N,$A20,case!I:I) -> 13699.206 | J20: =SUMIF(case!$N:$N,$A20,case!J:J) -> 9127.07 | K20: =SUMIF(case!$N:$N,$A20,case!K:K) -> 6979.118
A21: Totale attività fiscali | B21: =SUM(B19:B20) -> 48196 | C21: =SUM(C19:C20) -> 31681 | D21: =SUM(D19:D20) -> 69838.054 | E21: =SUM(E19:E20) -> 39766.01 | F21: =SUM(F19:F20) -> 43015.698 | G21: =SUM(G19:G20) -> 20282.895 | H21: =SUM(H19:H20) -> 19848.816 | I21: =SUM(I19:I20) -> 16792.547 | ... K21: =SUM(K19:K20) -> 8894.028
A23: Attività accessorie
A24: Immobilizzazioni extra-operative | B24: =SUMIF(case!$N:$N,$A24,case!B:B) -> 0 | C24: =SUMIF(case!$N:$N,$A24,case!C:C) -> 0 | D24: =SUMIF(case!$N:$N,$A24,case!D:D) -> 0 | E24: =SUMIF(case!$N:$N,$A24,case!E:E) -> 0 | F24: =SUMIF(case!$N:$N,$A24,case!F:F) -> 0 | G24: =SUMIF(case!$N:$N,$A24,case!G:G) -> 0 | H24: =SUMIF(case!$N:$N,$A24,case!H:H) -> 0 | I24: =SUMIF(case!$N:$N,$A24,case!I:I) -> 0 | J24: =SUMIF(case!$N:$N,$A24,case!J:J) -> 0 | K24: =SUMIF(case!$N:$N,$A24,case!K:K) -> 0
A25: Partecipazioni | B25: =SUMIF(case!$N:$N,$A25,case!B:B) -> 1015828 | C25: =SUMIF(case!$N:$N,$A25,case!C:C) -> 559853 | D25: =SUMIF(case!$N:$N,$A25,case!D:D) -> 556283.77 | E25: =SUMIF(case!$N:$N,$A25,case!E:E) -> 484337.02 | F25: =SUMIF(case!$N:$N,$A25,case!F:F) -> 436771.36 | G25: =SUMIF(case!$N:$N,$A25,case!G:G) -> 185287.81 | H25: =SUMIF(case!$N:$N,$A25,case!H:H) -> 205707.91 | I25: =SUMIF(case!$N:$N,$A25,case!I:I) -> 232021.82 | J25: =SUMIF(case!$N:$N,$A25,case!J:J) -> 249459.61 | K25: =SUMIF(case!$N:$N,$A25,case!K:K) -> 248664.75
A26: Crediti vs controllate e collegate | B26: =SUMIF(case!$N:$N,$A26,case!B:B) -> 0 | C26: =SUMIF(case!$N:$N,$A26,case!C:C) -> 0 | D26: =SUMIF(case!$N:$N,$A26,case!D:D) -> 284157.73 | E26: =SUMIF(case!$N:$N,$A26,case!E:E) -> 184307.39 | F26: =SUMIF(case!$N:$N,$A26,case!F:F) -> 204222.62 | G26: =SUMIF(case!$N:$N,$A26,case!G:G) -> 68482.991 | H26: =SUMIF(case!$N:$N,$A26,case!H:H) -> 76639.783 | I26: =SUMIF(case!$N:$N,$A26,case!I:I) -> 63300.047 | J26: =SUMIF(case!$N:$N,$A26,case!J:J) -> 53087.503 | K26: =SUMIF(case!$N:$N,$A26,case!K:K) -> 53848.936
A27: Totale attività accessorie | B27: =SUM(B24:B26) -> 1015828 | C27: =SUM(C24:C26) -> 559853 | D27: =SUM(D24:D26) -> 840441.5 | E27: =SUM(E24:E26) -> 668644.41 | F27: =SUM(F24:F26) -> 640993.98 | G27: =SUM(G24:G26) -> 253770.8 | H27: =SUM(H24:H26) -> 282347.7 | I27: =SUM(I24:I26) -> 295321.87 | ... K27: =SUM(K24:K26) -> 302513.68
A29: Attività finanziarie
A30: Riserve strategiche di liquidità | B30: =SUMIF(case!$N:$N,$A30,case!B:B) -> 0 | C30: =SUMIF(case!$N:$N,$A30,case!C:C) -> 0 | D30: =SUMIF(case!$N:$N,$A30,case!D:D) -> 0 | E30: =SUMIF(case!$N:$N,$A30,case!E:E) -> 0 | F30: =SUMIF(case!$N:$N,$A30,case!F:F) -> 0 | G30: =SUMIF(case!$N:$N,$A30,case!G:G) -> 0 | H30: =SUMIF(case!$N:$N,$A30,case!H:H) -> 0 | I30: =SUMIF(case!$N:$N,$A30,case!I:I) -> 0 | J30: =SUMIF(case!$N:$N,$A30,case!J:J) -> 0 | K30: =SUMIF(case!$N:$N,$A30,case!K:K) -> 0
A31: Attività di tesoreria | B31: =SUMIF(case!$N:$N,$A31,case!B:B) -> 324406 | C31: =SUMIF(case!$N:$N,$A31,case!C:C) -> 296765 | D31: =SUMIF(case!$N:$N,$A31,case!D:D) -> 107677.51 | E31: =SUMIF(case!$N:$N,$A31,case!E:E) -> 101551.99 | F31: =SUMIF(case!$N:$N,$A31,case!F:F) -> 137974.04 | G31: =SUMIF(case!$N:$N,$A31,case!G:G) -> 107984.77 | H31: =SUMIF(case!$N:$N,$A31,case!H:H) -> 19903.7 | I31: =SUMIF(case!$N:$N,$A31,case!I:I) -> 49713.475 | J31: =SUMIF(case!$N:$N,$A31,case!J:J) -> 28066.97 | K31: =SUMIF(case!$N:$N,$A31,case!K:K) -> 8542.951
A32: Strumenti derivati attivi | B32: =SUMIF(case!$N:$N,$A32,case!B:B) -> 6904 | C32: =SUMIF(case!$N:$N,$A32,case!C:C) -> 0 | D32: =SUMIF(case!$N:$N,$A32,case!D:D) -> 1696.644 | E32: =SUMIF(case!$N:$N,$A32,case!E:E) -> 5609.937 | F32: =SUMIF(case!$N:$N,$A32,case!F:F) -> 623.72 | G32: =SUMIF(case!$N:$N,$A32,case!G:G) -> 68.101 | H32: =SUMIF(case!$N:$N,$A32,case!H:H) -> 347.477 | I32: =SUMIF(case!$N:$N,$A32,case!I:I) -> 30.892 | J32: =SUMIF(case!$N:$N,$A32,case!J:J) -> 1597.017 | K32: =SUMIF(case!$N:$N,$A32,case!K:K) -> 0
A33: Totale attività finanziarie | B33: =SUM(B30:B32) -> 331310 | C33: =SUM(C30:C32) -> 296765 | D33: =SUM(D30:D32) -> 109374.15 | E33: =SUM(E30:E32) -> 107161.92 | F33: =SUM(F30:F32) -> 138597.76 | G33: =SUM(G30:G32) -> 108052.87 | H33: =SUM(H30:H32) -> 20251.177 | I33: =SUM(I30:I32) -> 49744.367 | ... K33: =SUM(K30:K32) -> 8542.951
A35: Totale attivo | B35: =B16+B21+B27+B33 -> 3790320 | C35: =C16+C21+C27+C33 -> 1675063 | D35: =D16+D21+D27+D33 -> 1536537 | E35: =E16+E21+E27+E33 -> 1306409 | F35: =F16+F21+F27+F33 -> 1310982.1 | G35: =G16+G21+G27+G33 -> 741809.91 | H35: =H16+H21+H27+H33 -> 790964.52 | I35: =I16+I21+I27+I33 -> 788819.42 | ... K35: =K16+K21+K27+K33 -> 768520.01
A37: Check con totale attivo AIDA | B37: =case!B95 -> 3790320 | C37: =case!C95 -> 1675063 | D37: =case!D95 -> 1536537 | E37: =case!E95 -> 1308756.7 | F37: =case!F95 -> 1311132.3 | G37: =case!G95 -> 741974.82 | H37: =case!H95 -> 792683.74 | I37: =case!I95 -> 788836.85 | ... K37: =case!K95 -> 780383.29
A38: Differenza tra totale attivo e totale attivo AIDA | B38: =B37-B35 -> 0 | C38: =C37-C35 -> 0 | D38: =D37-D35 -> 0 | E38: =E37-E35 -> 2347.699 | F38: =F37-F35 -> 150.154 | G38: =G37-G35 -> 164.911 | H38: =H37-H35 -> 1719.228 | I38: =I37-I35 -> 17.433 | ... K38: =K37-K35 -> 11863.28
A39: Somma voci spostate nel passivo | B39: =case!B2+case!B46 -> 0 | C39: =case!C2+case!C46 -> 0 | D39: =case!D2+case!D46 -> 0 | E39: =case!E2+case!E46 -> 0 | F39: =case!F2+case!F46 -> 0 | G39: =case!G2+case!G46 -> 0 | H39: =case!H2+case!H46 -> 0 | I39: =case!I2+case!I46 -> 0 | ... K39: =case!K2+case!K46 -> 0
A40: Sbilancio | B40: =B38+B39 -> 0 | C40: =C38+C39 -> 0 | D40: =D38+D39 -> 0 | E40: =E38+E39 -> 2347.699 | F40: =F38+F39 -> 150.154 | G40: =G38+G39 -> 164.911 | H40: =H38+H39 -> 1719.228 | I40: =I38+I39 -> 17.433 | ... K40: =K38+K39 -> 11863.28
B44: =B1 -> 31/12/2024 | C44: =C1 -> 31/12/2023 | D44: =D1 -> 31/12/2022 | E44: =E1 -> 31/12/2021 | F44: =F1 -> 31/12/2020 | G44: =G1 -> 31/12/2019 | H44: =H1 -> 31/12/2018 | I44: =I1 -> 31/12/2017 | ... K44: =K1 -> 31/12/2015
A45: Stato Patrimoniale Passivo
A46: Passività operative
A47: Passività operative correnti | B47: =SUMIF(case!$N:$N,$A47,case!B:B) -> 0 | C47: =SUMIF(case!$N:$N,$A47,case!C:C) -> 0 | D47: =SUMIF(case!$N:$N,$A47,case!D:D) -> 0 | E47: =SUMIF(case!$N:$N,$A47,case!E:E) -> 0 | F47: =SUMIF(case!$N:$N,$A47,case!F:F) -> 0 | G47: =SUMIF(case!$N:$N,$A47,case!G:G) -> 0 | H47: =SUMIF(case!$N:$N,$A47,case!H:H) -> 0 | I47: =SUMIF(case!$N:$N,$A47,case!I:I) -> 0 | J47: =SUMIF(case!$N:$N,$A47,case!J:J) -> 0 | K47: =SUMIF(case!$N:$N,$A47,case!K:K) -> 0
A48: Debiti vs fornitori | B48: =SUMIF(case!$N:$N,$A48,case!B:B) -> 250274 | C48: =SUMIF(case!$N:$N,$A48,case!C:C) -> 182261 | D48: =SUMIF(case!$N:$N,$A48,case!D:D) -> 252136.23 | E48: =SUMIF(case!$N:$N,$A48,case!E:E) -> 190182.36 | F48: =SUMIF(case!$N:$N,$A48,case!F:F) -> 134849.12 | G48: =SUMIF(case!$N:$N,$A48,case!G:G) -> 139771.21 | H48: =SUMIF(case!$N:$N,$A48,case!H:H) -> 197078.86 | I48: =SUMIF(case!$N:$N,$A48,case!I:I) -> 142429.71 | J48: =SUMIF(case!$N:$N,$A48,case!J:J) -> 140877.26 | K48: =SUMIF(case!$N:$N,$A48,case!K:K) -> 154222
A49: Debiti vs dipendenti | B49: =SUMIF(case!$N:$N,$A49,case!B:B) -> 0 | C49: =SUMIF(case!$N:$N,$A49,case!C:C) -> 0 | D49: =SUMIF(case!$N:$N,$A49,case!D:D) -> 0 | E49: =SUMIF(case!$N:$N,$A49,case!E:E) -> 0 | F49: =SUMIF(case!$N:$N,$A49,case!F:F) -> 0 | G49: =SUMIF(case!$N:$N,$A49,case!G:G) -> 0 | H49: =SUMIF(case!$N:$N,$A49,case!H:H) -> 0 | I49: =SUMIF(case!$N:$N,$A49,case!I:I) -> 0 | J49: =SUMIF(case!$N:$N,$A49,case!J:J) -> 0 | K49: =SUMIF(case!$N:$N,$A49,case!K:K) -> 0
A50: Altre passività operative correnti | B50: =SUMIF(case!$N:$N,$A50,case!B:B) -> 31095 | C50: =SUMIF(case!$N:$N,$A50,case!C:C) -> 22830 | D50: =SUMIF(case!$N:$N,$A50,case!D:D) -> 19799.218 | E50: =SUMIF(case!$N:$N,$A50,case!E:E) -> 19242.403 | F50: =SUMIF(case!$N:$N,$A50,case!F:F) -> 13505.011 | G50: =SUMIF(case!$N:$N,$A50,case!G:G) -> 14249.11 | H50: =SUMIF(case!$N:$N,$A50,case!H:H) -> 11492.701 | I50: =SUMIF(case!$N:$N,$A50,case!I:I) -> 12174.005 | J50: =SUMIF(case!$N:$N,$A50,case!J:J) -> 13103.067 | K50: =SUMIF(case!$N:$N,$A50,case!K:K) -> 11889.772
A51: Totale passività operative correnti | B51: =SUM(B48:B50) -> 281369 | C51: =SUM(C48:C50) -> 205091 | D51: =SUM(D48:D50) -> 271935.45 | E51: =SUM(E48:E50) -> 209424.77 | F51: =SUM(F48:F50) -> 148354.14 | G51: =SUM(G48:G50) -> 154020.32 | H51: =SUM(H48:H50) -> 208571.56 | I51: =SUM(I48:I50) -> 154603.72 | ... K51: =SUM(K48:K50) -> 166111.77
A52: Passività operative consolidate | B52: =SUMIF(case!$N:$N,$A52,case!B:B) -> 0 | C52: =SUMIF(case!$N:$N,$A52,case!C:C) -> 0 | D52: =SUMIF(case!$N:$N,$A52,case!D:D) -> 0 | E52: =SUMIF(case!$N:$N,$A52,case!E:E) -> 0 | F52: =SUMIF(case!$N:$N,$A52,case!F:F) -> 0 | G52: =SUMIF(case!$N:$N,$A52,case!G:G) -> 0 | H52: =SUMIF(case!$N:$N,$A52,case!H:H) -> 0 | I52: =SUMIF(case!$N:$N,$A52,case!I:I) -> 0 | J52: =SUMIF(case!$N:$N,$A52,case!J:J) -> 0 | K52: =SUMIF(case!$N:$N,$A52,case!K:K) -> 0
A53: Fondo TFR | B53: =SUMIF(case!$N:$N,$A53,case!B:B) -> 6126 | C53: =SUMIF(case!$N:$N,$A53,case!C:C) -> 7190 | D53: =SUMIF(case!$N:$N,$A53,case!D:D) -> 9844.145 | E53: =SUMIF(case!$N:$N,$A53,case!E:E) -> 9804.363 | F53: =SUMIF(case!$N:$N,$A53,case!F:F) -> 11127.204 | G53: =SUMIF(case!$N:$N,$A53,case!G:G) -> 13315.664 | H53: =SUMIF(case!$N:$N,$A53,case!H:H) -> 14615.308 | I53: =SUMIF(case!$N:$N,$A53,case!I:I) -> 15818.5 | J53: =SUMIF(case!$N:$N,$A53,case!J:J) -> 16934.442 | K53: =SUMIF(case!$N:$N,$A53,case!K:K) -> 17851.924
A54: Altre passività operative consolidate | B54: =SUMIF(case!$N:$N,$A54,case!B:B) -> 0 | C54: =SUMIF(case!$N:$N,$A54,case!C:C) -> 0 | D54: =SUMIF(case!$N:$N,$A54,case!D:D) -> 0 | E54: =SUMIF(case!$N:$N,$A54,case!E:E) -> 0 | F54: =SUMIF(case!$N:$N,$A54,case!F:F) -> 0 | G54: =SUMIF(case!$N:$N,$A54,case!G:G) -> 0 | H54: =SUMIF(case!$N:$N,$A54,case!H:H) -> 0 | I54: =SUMIF(case!$N:$N,$A54,case!I:I) -> 0 | J54: =SUMIF(case!$N:$N,$A54,case!J:J) -> 0 | K54: =SUMIF(case!$N:$N,$A54,case!K:K) -> 0
A55: Totale passività operative consolidate | B55: =SUM(B53:B54) -> 6126 | C55: =SUM(C53:C54) -> 7190 | D55: =SUM(D53:D54) -> 9844.145 | E55: =SUM(E53:E54) -> 9804.363 | F55: =SUM(F53:F54) -> 11127.204 | G55: =SUM(G53:G54) -> 13315.664 | H55: =SUM(H53:H54) -> 14615.308 | I55: =SUM(I53:I54) -> 15818.5 | ... K55: =SUM(K53:K54) -> 17851.924
A56: Totale passività operative | B56: =B51+B55 -> 287495 | C56: =C51+C55 -> 212281 | D56: =D51+D55 -> 281779.59 | E56: =E51+E55 -> 219229.13 | F56: =F51+F55 -> 159481.34 | G56: =G51+G55 -> 167335.98 | H56: =H51+H55 -> 223186.87 | I56: =I51+I55 -> 170422.22 | ... K56: =K51+K55 -> 183963.69
A58: Passività fiscali e fondi
A59: Debiti fisco previdenziali | B59: =SUMIF(case!$N:$N,$A59,case!B:B) -> 1795 | C59: =SUMIF(case!$N:$N,$A59,case!C:C) -> 780 | D59: =SUMIF(case!$N:$N,$A59,case!D:D) -> 16209.305 | E59: =SUMIF(case!$N:$N,$A59,case!E:E) -> 15299.373 | F59: =SUMIF(case!$N:$N,$A59,case!F:F) -> 37137.14 | G59: =SUMIF(case!$N:$N,$A59,case!G:G) -> 13404.492 | H59: =SUMIF(case!$N:$N,$A59,case!H:H) -> 14882.096 | I59: =SUMIF(case!$N:$N,$A59,case!I:I) -> 15285.431 | J59: =SUMIF(case!$N:$N,$A59,case!J:J) -> 25003.618 | K59: =SUMIF(case!$N:$N,$A59,case!K:K) -> 14389.177
A60: Passività per imposte differite | B60: =SUMIF(case!$N:$N,$A60,case!B:B) -> 80578 | C60: =SUMIF(case!$N:$N,$A60,case!C:C) -> 24669 | D60: =SUMIF(case!$N:$N,$A60,case!D:D) -> 17588.982 | E60: =SUMIF(case!$N:$N,$A60,case!E:E) -> 16566.299 | F60: =SUMIF(case!$N:$N,$A60,case!F:F) -> 16422.797 | G60: =SUMIF(case!$N:$N,$A60,case!G:G) -> 0 | H60: =SUMIF(case!$N:$N,$A60,case!H:H) -> 0 | I60: =SUMIF(case!$N:$N,$A60,case!I:I) -> 0 | J60: =SUMIF(case!$N:$N,$A60,case!J:J) -> 0 | K60: =SUMIF(case!$N:$N,$A60,case!K:K) -> 0
A61: Altri fondi | B61: =SUMIF(case!$N:$N,$A61,case!B:B) -> 52524 | C61: =SUMIF(case!$N:$N,$A61,case!C:C) -> 16494 | D61: =SUMIF(case!$N:$N,$A61,case!D:D) -> 30000.27 | E61: =SUMIF(case!$N:$N,$A61,case!E:E) -> 27563.206 | F61: =SUMIF(case!$N:$N,$A61,case!F:F) -> 30289.56 | G61: =SUMIF(case!$N:$N,$A61,case!G:G) -> 35059.685 | H61: =SUMIF(case!$N:$N,$A61,case!H:H) -> 32071.222 | I61: =SUMIF(case!$N:$N,$A61,case!I:I) -> 26043.48 | J61: =SUMIF(case!$N:$N,$A61,case!J:J) -> 16890.149 | K61: =SUMIF(case!$N:$N,$A61,case!K:K) -> 9555.965
A62: Totale passività fiscali e fondi | B62: =SUM(B59:B61) -> 134897 | C62: =SUM(C59:C61) -> 41943 | D62: =SUM(D59:D61) -> 63798.557 | E62: =SUM(E59:E61) -> 59428.878 | F62: =SUM(F59:F61) -> 83849.497 | G62: =SUM(G59:G61) -> 48464.177 | H62: =SUM(H59:H61) -> 46953.318 | I62: =SUM(I59:I61) -> 41328.911 | ... K62: =SUM(K59:K61) -> 23945.142
A64: Passività accessorie
A65: Debiti verso controllate e collegate | B65: =SUMIF(case!$N:$N,$A65,case!B:B) -> 0 | C65: =SUMIF(case!$N:$N,$A65,case!C:C) -> 0 | D65: =SUMIF(case!$N:$N,$A65,case!D:D) -> 395029.19 | E65: =SUMIF(case!$N:$N,$A65,case!E:E) -> 174280.43 | F65: =SUMIF(case!$N:$N,$A65,case!F:F) -> 141526.41 | G65: =SUMIF(case!$N:$N,$A65,case!G:G) -> 103931.45 | H65: =SUMIF(case!$N:$N,$A65,case!H:H) -> 67952.994 | I65: =SUMIF(case!$N:$N,$A65,case!I:I) -> 46501.775 | J65: =SUMIF(case!$N:$N,$A65,case!J:J) -> 54122.252 | K65: =SUMIF(case!$N:$N,$A65,case!K:K) -> 49593.984
A66: Totale passività accessorie | B66: =B65 -> 0 | C66: =C65 -> 0 | D66: =D65 -> 395029.19 | E66: =E65 -> 174280.43 | F66: =F65 -> 141526.41 | G66: =G65 -> 103931.45 | H66: =H65 -> 67952.994 | I66: =I65 -> 46501.775 | ... K66: =K65 -> 49593.984
A68: Passività finanziarie
A69: Debiti strutturali a m/l termine | B69: =SUMIF(case!$N:$N,$A69,case!B:B) -> 1425629 | C69: =SUMIF(case!$N:$N,$A69,case!C:C) -> 703519 | D69: =SUMIF(case!$N:$N,$A69,case!D:D) -> 0 | E69: =SUMIF(case!$N:$N,$A69,case!E:E) -> 725617.18 | F69: =SUMIF(case!$N:$N,$A69,case!F:F) -> 780492.17 | G69: =SUMIF(case!$N:$N,$A69,case!G:G) -> 0 | H69: =SUMIF(case!$N:$N,$A69,case!H:H) -> 0 | I69: =SUMIF(case!$N:$N,$A69,case!I:I) -> 55779.956 | J69: =SUMIF(case!$N:$N,$A69,case!J:J) -> 79869.756 | K69: =SUMIF(case!$N:$N,$A69,case!K:K) -> 103275.9
A70: Debiti strutturali a breve termine | B70: =SUMIF(case!$N:$N,$A70,case!B:B) -> 99517 | C70: =SUMIF(case!$N:$N,$A70,case!C:C) -> 62490 | D70: =SUMIF(case!$N:$N,$A70,case!D:D) -> 25075.841 | E70: =SUMIF(case!$N:$N,$A70,case!E:E) -> 12409.266 | F70: =SUMIF(case!$N:$N,$A70,case!F:F) -> 18711.335 | G70: =SUMIF(case!$N:$N,$A70,case!G:G) -> 4.922 | H70: =SUMIF(case!$N:$N,$A70,case!H:H) -> 20464.468 | I70: =SUMIF(case!$N:$N,$A70,case!I:I) -> 99975.351 | J70: =SUMIF(case!$N:$N,$A70,case!J:J) -> 79477.82 | K70: =SUMIF(case!$N:$N,$A70,case!K:K) -> 100505.1
A71: Debiti di tesoreria | B71: =SUMIF(case!$N:$N,$A71,case!B:B) -> 0 | C71: =SUMIF(case!$N:$N,$A71,case!C:C) -> 0 | D71: =SUMIF(case!$N:$N,$A71,case!D:D) -> 0 | E71: =SUMIF(case!$N:$N,$A71,case!E:E) -> 0 | F71: =SUMIF(case!$N:$N,$A71,case!F:F) -> 0 | G71: =SUMIF(case!$N:$N,$A71,case!G:G) -> 0 | H71: =SUMIF(case!$N:$N,$A71,case!H:H) -> 0 | I71: =SUMIF(case!$N:$N,$A71,case!I:I) -> 0 | J71: =SUMIF(case!$N:$N,$A71,case!J:J) -> 0 | K71: =SUMIF(case!$N:$N,$A71,case!K:K) -> 0
A72: Strumenti derivati passivi | B72: =SUMIF(case!$N:$N,$A72,case!B:B) -> 1959 | C72: =SUMIF(case!$N:$N,$A72,case!C:C) -> 16010 | D72: =SUMIF(case!$N:$N,$A72,case!D:D) -> 14734.732 | E72: =SUMIF(case!$N:$N,$A72,case!E:E) -> 620.458 | F72: =SUMIF(case!$N:$N,$A72,case!F:F) -> 2147.741 | G72: =SUMIF(case!$N:$N,$A72,case!G:G) -> 136.013 | H72: =SUMIF(case!$N:$N,$A72,case!H:H) -> 12.057 | I72: =SUMIF(case!$N:$N,$A72,case!I:I) -> 532.534 | J72: =SUMIF(case!$N:$N,$A72,case!J:J) -> 157.472 | K72: =SUMIF(case!$N:$N,$A72,case!K:K) -> 0
A73: Totale passività finanziarie | B73: =SUM(B69:B72) -> 1527105 | C73: =SUM(C69:C72) -> 782019 | D73: =SUM(D69:D72) -> 39810.573 | E73: =SUM(E69:E72) -> 738646.9 | F73: =SUM(F69:F72) -> 801351.24 | G73: =SUM(G69:G72) -> 140.935 | H73: =SUM(H69:H72) -> 20476.525 | I73: =SUM(I69:I72) -> 156287.84 | ... K73: =SUM(K69:K72) -> 203780.99
A75: Capitale proprio
A76: Finanziamenti netti vs soci e controllanti | B76: =SUMIF(case!$N:$N,$A76,case!B:B) -> 988576 | C76: =SUMIF(case!$N:$N,$A76,case!C:C) -> 550601 | D76: =SUMIF(case!$N:$N,$A76,case!D:D) -> 619570.35 | E76: =SUMIF(case!$N:$N,$A76,case!E:E) -> -2284.853 | F76: =SUMIF(case!$N:$N,$A76,case!F:F) -> -88.58 | G76: =SUMIF(case!$N:$N,$A76,case!G:G) -> 76982.659 | H76: =SUMIF(case!$N:$N,$A76,case!H:H) -> 83876.349 | I76: =SUMIF(case!$N:$N,$A76,case!I:I) -> 3667.587 | J76: =SUMIF(case!$N:$N,$A76,case!J:J) -> -3266.301 | K76: =SUMIF(case!$N:$N,$A76,case!K:K) -> -11756.08
A77: Capitale netto | B77: =SUM(B78:B82) -> 852247 | C77: =SUM(C78:C82) -> 88219 | D77: =SUM(D78:D82) -> 136548.72 | E77: =SUM(E78:E82) -> 117108.52 | F77: =SUM(F78:F82) -> 124862.24 | G77: =SUM(G78:G82) -> 344954.71 | H77: =SUM(H78:H82) -> 348518.46 | I77: =SUM(I78:I82) -> 370611.09 | ... K77: =SUM(K78:K82) -> 318992.28
A78: Capitale conferito dai soci | B78: =SUMIF(case!$N:$N,$A78,case!B:B) -> 100241 | C78: =SUMIF(case!$N:$N,$A78,case!C:C) -> 100241 | D78: =SUMIF(case!$N:$N,$A78,case!D:D) -> 100241.67 | E78: =SUMIF(case!$N:$N,$A78,case!E:E) -> 100241.67 | F78: =SUMIF(case!$N:$N,$A78,case!F:F) -> 100241.67 | G78: =SUMIF(case!$N:$N,$A78,case!G:G) -> 91829.358 | H78: =SUMIF(case!$N:$N,$A78,case!H:H) -> 91829.358 | I78: =SUMIF(case!$N:$N,$A78,case!I:I) -> 91829.358 | J78: =SUMIF(case!$N:$N,$A78,case!J:J) -> 91829.358 | K78: =SUMIF(case!$N:$N,$A78,case!K:K) -> 91829.358
A79: Utili non distribuiti | B79: =SUMIF(case!$N:$N,$A79,case!B:B) -> 1076923 | C79: =SUMIF(case!$N:$N,$A79,case!C:C) -> 52270 | D79: =SUMIF(case!$N:$N,$A79,case!D:D) -> 3345.615 | E79: =SUMIF(case!$N:$N,$A79,case!E:E) -> 10181.987 | F79: =SUMIF(case!$N:$N,$A79,case!F:F) -> 65610.639 | G79: =SUMIF(case!$N:$N,$A79,case!G:G) -> 237217.2 | H79: =SUMIF(case!$N:$N,$A79,case!H:H) -> 235309.67 | I79: =SUMIF(case!$N:$N,$A79,case!I:I) -> 214344.4 | J79: =SUMIF(case!$N:$N,$A79,case!J:J) -> 189690.9 | K79: =SUMIF(case!$N:$N,$A79,case!K:K) -> 172816.59
A80: Riserve da rivalutazione | B80: =SUMIF(case!$N:$N,$A80,case!B:B) -> 0 | C80: =SUMIF(case!$N:$N,$A80,case!C:C) -> 0 | D80: =SUMIF(case!$N:$N,$A80,case!D:D) -> 15208.961 | E80: =SUMIF(case!$N:$N,$A80,case!E:E) -> 18021.232 | F80: =SUMIF(case!$N:$N,$A80,case!F:F) -> 14438.58 | G80: =SUMIF(case!$N:$N,$A80,case!G:G) -> 15471.903 | H80: =SUMIF(case!$N:$N,$A80,case!H:H) -> 15471.903 | I80: =SUMIF(case!$N:$N,$A80,case!I:I) -> 15471.903 | J80: =SUMIF(case!$N:$N,$A80,case!J:J) -> 15471.903 | K80: =SUMIF(case!$N:$N,$A80,case!K:K) -> 15471.903
A81: Azioni proprie e partecipazioni in controllanti | B81: =SUMIF(case!$N:$N,$A81,case!B:B) -> 0 | C81: =SUMIF(case!$N:$N,$A81,case!C:C) -> 0 | D81: =SUMIF(case!$N:$N,$A81,case!D:D) -> 0 | E81: =SUMIF(case!$N:$N,$A81,case!E:E) -> 0 | F81: =SUMIF(case!$N:$N,$A81,case!F:F) -> 0 | G81: =SUMIF(case!$N:$N,$A81,case!G:G) -> 0 | H81: =SUMIF(case!$N:$N,$A81,case!H:H) -> 0 | I81: =SUMIF(case!$N:$N,$A81,case!I:I) -> 0 | J81: =SUMIF(case!$N:$N,$A81,case!J:J) -> 0 | K81: =SUMIF(case!$N:$N,$A81,case!K:K) -> 0
A82: Reddito dell’esercizio | B82: =SUMIF(case!$N:$N,$A82,case!B:B) -> -324917 | C82: =SUMIF(case!$N:$N,$A82,case!C:C) -> -64292 | D82: =SUMIF(case!$N:$N,$A82,case!D:D) -> 17752.471 | E82: =SUMIF(case!$N:$N,$A82,case!E:E) -> -11336.372 | F82: =SUMIF(case!$N:$N,$A82,case!F:F) -> -55428.652 | G82: =SUMIF(case!$N:$N,$A82,case!G:G) -> 436.251 | H82: =SUMIF(case!$N:$N,$A82,case!H:H) -> 5907.529 | I82: =SUMIF(case!$N:$N,$A82,case!I:I) -> 48965.423 | J82: =SUMIF(case!$N:$N,$A82,case!J:J) -> 54653.67 | K82: =SUMIF(case!$N:$N,$A82,case!K:K) -> 38874.43
A83: Capitale proprio di pertinenza di terzi | B83: =SUMIF(case!$N:$N,$A83,case!B:B) -> 0 | C83: =SUMIF(case!$N:$N,$A83,case!C:C) -> 0 | D83: =SUMIF(case!$N:$N,$A83,case!D:D) -> 0 | E83: =SUMIF(case!$N:$N,$A83,case!E:E) -> 0 | F83: =SUMIF(case!$N:$N,$A83,case!F:F) -> 0 | G83: =SUMIF(case!$N:$N,$A83,case!G:G) -> 0 | H83: =SUMIF(case!$N:$N,$A83,case!H:H) -> 0 | I83: =SUMIF(case!$N:$N,$A83,case!I:I) -> 0 | J83: =SUMIF(case!$N:$N,$A83,case!J:J) -> 0 | K83: =SUMIF(case!$N:$N,$A83,case!K:K) -> 0
A84: Totale capitale proprio | B84: =B76+B77+B83 -> 1840823 | C84: =C76+C77+C83 -> 638820 | D84: =D76+D77+D83 -> 756119.07 | E84: =E76+E77+E83 -> 114823.67 | F84: =F76+F77+F83 -> 124773.66 | G84: =G76+G77+G83 -> 421937.37 | H84: =H76+H77+H83 -> 432394.81 | I84: =I76+I77+I83 -> 374278.67 | ... K84: =K76+K77+K83 -> 307236.2
A86: Totale passivo | B86: =B56+B62+B66+B73+B84 -> 3790320 | C86: =C56+C62+C66+C73+C84 -> 1675063 | D86: =D56+D62+D66+D73+D84 -> 1536537 | E86: =E56+E62+E66+E73+E84 -> 1306409 | F86: =F56+F62+F66+F73+F84 -> 1310982.1 | G86: =G56+G62+G66+G73+G84 -> 741809.91 | H86: =H56+H62+H66+H73+H84 -> 790964.52 | I86: =I56+I62+I66+I73+I84 -> 788819.42 | ... K86: =K56+K62+K66+K73+K84 -> 768520.01
A88: Check con totale attivo AIDA | B88: =case!B168 -> 3790320 | C88: =case!C168 -> 1675063 | D88: =case!D168 -> 1536537 | E88: =case!E168 -> 1308756.7 | F88: =case!F168 -> 1311132.3 | G88: =case!G168 -> 741974.82 | H88: =case!H168 -> 792683.74 | I88: =case!I168 -> 788836.85 | ... K88: =case!K168 -> 780383.29
A89: diff da AIDA | B89: =B88-B86 -> 0 | C89: =C88-C86 -> 0 | D89: =D88-D86 -> 0 | E89: =E88-E86 -> 2347.699 | F89: =F88-F86 -> 150.154 | G89: =G88-G86 -> 164.911 | H89: =H88-H86 -> 1719.228 | I89: =I88-I86 -> 17.433 | ... K89: =K88-K86 -> 11863.28
A90: Check Tot.Attivo - Tot.Passivo | B90: =B35-B86 -> 0 | C90: =C35-C86 -> 0 | D90: =D35-D86 -> 0 | E90: =E35-E86 -> 0 | F90: =F35-F86 -> 0 | G90: =G35-G86 -> 0 | H90: =H35-H86 -> 0 | I90: =I35-I86 -> 0 | ... K90: =K35-K86 -> 0
A92: Relazione fondamentale fonti/impieghi:
A93: Attività Operative Nette Estese (AON*) | B93: =B16-B56+B21-B62 -> 2020790 | C93: =C16-C56+C21-C62 -> 564221 | D93: =D16-D56+D21-D62 -> 241143.17 | E93: =E16-E56+E21-E62 -> 251944.66 | F93: =F16-F56+F21-F62 -> 288059.57 | G93: =G16-G56+G21-G62 -> 164186.08 | H93: =H16-H56+H21-H62 -> 218225.46 | I93: =I16-I56+I21-I62 -> 232002.06 | ... K93: =K16-K56+K21-K62 -> 249554.54
A94: Attività Accessorie Nette (AACCN) | B94: =B27-B66 -> 1015828 | C94: =C27-C66 -> 559853 | D94: =D27-D66 -> 445412.32 | E94: =E27-E66 -> 494363.98 | F94: =F27-F66 -> 499467.58 | G94: =G27-G66 -> 149839.35 | H94: =H27-H66 -> 214394.7 | I94: =I27-I66 -> 248820.09 | ... K94: =K27-K66 -> 252919.7
A95: Posizione Finanziaria Netta (+Liquidità - Debito) | B95: =B33-B73 -> -1195795 | C95: =C33-C73 -> -485254 | D95: =D33-D73 -> 69563.582 | E95: =E33-E73 -> -631484.98 | F95: =F33-F73 -> -662753.48 | G95: =G33-G73 -> 107911.93 | H95: =H33-H73 -> -225.348 | I95: =I33-I73 -> -106543.47 | ... K95: =K33-K73 -> -195238.04
A96: Capitale Proprio | B96: =B84 -> 1840823 | C96: =C84 -> 638820 | D96: =D84 -> 756119.07 | E96: =E84 -> 114823.67 | F96: =F84 -> 124773.66 | G96: =G84 -> 421937.37 | H96: =H84 -> 432394.81 | I96: =I84 -> 374278.67 | ... K96: =K84 -> 307236.2
A97: Totale Attivo | B97: =B35 -> 3790320 | C97: =C35 -> 1675063 | D97: =D35 -> 1536537 | E97: =E35 -> 1306409 | F97: =F35 -> 1310982.1 | G97: =G35 -> 741809.91 | H97: =H35 -> 790964.52 | I97: =I35 -> 788819.42 | ... K97: =K35 -> 768520.01
A98: Totale Passivo | B98: =B86 -> 3790320 | C98: =C86 -> 1675063 | D98: =D86 -> 1536537 | E98: =E86 -> 1306409 | F98: =F86 -> 1310982.1 | G98: =G86 -> 741809.91 | H98: =H86 -> 790964.52 | I98: =I86 -> 788819.42 | ... K98: =K86 -> 768520.01
A99: Sbilancio | B99: =B97-B98 -> 0 | C99: =C97-C98 -> 0 | D99: =D97-D98 -> 0 | E99: =E97-E98 -> 0 | F99: =F97-F98 -> 0 | G99: =G97-G98 -> 0 | H99: =H97-H98 -> 0 | I99: =I97-I98 -> 0 | ... K99: =K97-K98 -> 0
A101: CCON | B101: =B8-B51 -> 273612 | C101: =C8-C51 -> 270958 | D101: =D8-D51 -> -76865.32 | E101: =E8-E51 -> -28446.098 | F101: =F8-F51 -> 31598.684 | G101: =G8-G51 -> 37996.186 | H101: =H8-H51 -> 98368.217 | I101: =I8-I51 -> 101159.45 | ... K101: =K8-K51 -> 112990.83
A102: AON -> | B102: =B16-B56 -> 2107491 | C102: =C16-C56 -> 574483 | D102: =D16-D56 -> 235103.68 | E102: =E16-E56 -> 271607.53 | F102: =F16-F56 -> 328893.37 | G102: =G16-G56 -> 192367.37 | H102: =H16-H56 -> 245329.96 | I102: =I16-I56 -> 256538.42 | ... K102: =K16-K56 -> 264605.66
A103: debito netto, se neg è liq netta -> | B103: =-B95 -> 1195795 | C103: =-C95 -> 485254 | D103: =-D95 -> -69563.582 | E103: =-E95 -> 631484.98 | F103: =-F95 -> 662753.48 | G103: =-G95 -> -107911.93 | H103: =-H95 -> 225.348 | I103: =-I95 -> 106543.47 | ... K103: =-K95 -> 195238.04
A104: AON*+ att.gestione accessoria | B104: =B93+B94 -> 3036618 | C104: =C93+C94 -> 1124074 | D104: =D93+D94 -> 686555.49 | E104: =E93+E94 -> 746308.65 | F104: =F93+F94 -> 787527.14 | G104: =G93+G94 -> 314025.44 | H104: =H93+H94 -> 432620.16 | I104: =I93+I94 -> 480822.15 | ... K104: =K93+K94 -> 502474.24
A105: capitale proprio + debito netto | B105: =B96+B103 -> 3036618 | C105: =C96+C103 -> 1124074 | D105: =D96+D103 -> 686555.49 | E105: =E96+E103 -> 746308.65 | F105: =F96+F103 -> 787527.14 | G105: =G96+G103 -> 314025.44 | H105: =H96+H103 -> 432620.16 | I105: =I96+I103 -> 480822.15 | ... K105: =K96+K103 -> 502474.24
A106: Relazione fonti/impieghi | B106: =B104-B105 -> 0 | C106: =C104-C105 -> 0 | D106: =D104-D105 -> 0 | E106: =E104-E105 -> 0 | F106: =F104-F105 -> 0 | G106: =G104-G105 -> 0 | H106: =H104-H105 -> 0 | I106: =I104-I105 -> 0 | ... K106: =K104-K105 -> 0
B108: =B1 -> 31/12/2024 | C108: =C1 -> 31/12/2023 | D108: =D1 -> 31/12/2022 | E108: =E1 -> 31/12/2021 | F108: =F1 -> 31/12/2020 | G108: =G1 -> 31/12/2019 | H108: =H1 -> 31/12/2018 | I108: =I1 -> 31/12/2017 | ... K108: =K1 -> 31/12/2015
A109: Conto Economico
A110: Gestione operativa
A111: (A) Ricavi di vendita | B111: =SUMIF(case!$N:$N,$A111,case!B:B)-B127 -> 700351 | C111: =SUMIF(case!$N:$N,$A111,case!C:C)-C127 -> 567524 | D111: =SUMIF(case!$N:$N,$A111,case!D:D)-D127 -> 731617.37 | E111: =SUMIF(case!$N:$N,$A111,case!E:E)-E127 -> 575309.43 | F111: =SUMIF(case!$N:$N,$A111,case!F:F)-F127 -> 470766.3 | G111: =SUMIF(case!$N:$N,$A111,case!G:G)-G127 -> 599353.35 | H111: =SUMIF(case!$N:$N,$A111,case!H:H)-H127 -> 601111.28 | I111: =SUMIF(case!$N:$N,$A111,case!I:I)-I127 -> 658456.38 | J111: =SUMIF(case!$N:$N,$A111,case!J:J)-J127 -> 649016.11 | K111: =SUMIF(case!$N:$N,$A111,case!K:K)-K127 -> 617897.5
A112: Acquisti
A113: − Materie prime e merci | B113: =SUMIF(case!$N:$N,$A113,case!B:B) -> -294635 | C113: =SUMIF(case!$N:$N,$A113,case!C:C) -> -233853 | D113: =SUMIF(case!$N:$N,$A113,case!D:D) -> -369324.92 | E113: =SUMIF(case!$N:$N,$A113,case!E:E) -> -286223.42 | F113: =SUMIF(case!$N:$N,$A113,case!F:F) -> -212362.42 | G113: =SUMIF(case!$N:$N,$A113,case!G:G) -> -251077.6 | H113: =SUMIF(case!$N:$N,$A113,case!H:H) -> -354468.09 | I113: =SUMIF(case!$N:$N,$A113,case!I:I) -> -310414.15 | J113: =SUMIF(case!$N:$N,$A113,case!J:J) -> -308669.76 | K113: =SUMIF(case!$N:$N,$A113,case!K:K) -> -314184.4
A114: − Servizi | B114: =SUMIF(case!$N:$N,$A114,case!B:B) -> -186379 | C114: =SUMIF(case!$N:$N,$A114,case!C:C) -> -150974 | D114: =SUMIF(case!$N:$N,$A114,case!D:D) -> -233037.5 | E114: =SUMIF(case!$N:$N,$A114,case!E:E) -> -152791.56 | F114: =SUMIF(case!$N:$N,$A114,case!F:F) -> -136499.39 | G114: =SUMIF(case!$N:$N,$A114,case!G:G) -> -138892.42 | H114: =SUMIF(case!$N:$N,$A114,case!H:H) -> -130598.71 | I114: =SUMIF(case!$N:$N,$A114,case!I:I) -> -123574.19 | J114: =SUMIF(case!$N:$N,$A114,case!J:J) -> -132183.03 | K114: =SUMIF(case!$N:$N,$A114,case!K:K) -> -134109.94
A115: − Godimento beni di terzi | B115: =SUMIF(case!$N:$N,$A115,case!B:B) -> 0 | C115: =SUMIF(case!$N:$N,$A115,case!C:C) -> 0 | D115: =SUMIF(case!$N:$N,$A115,case!D:D) -> -9817.73 | E115: =SUMIF(case!$N:$N,$A115,case!E:E) -> -10480.972 | F115: =SUMIF(case!$N:$N,$A115,case!F:F) -> -9122.456 | G115: =SUMIF(case!$N:$N,$A115,case!G:G) -> -10345.315 | H115: =SUMIF(case!$N:$N,$A115,case!H:H) -> -9457.312 | I115: =SUMIF(case!$N:$N,$A115,case!I:I) -> -15010.612 | J115: =SUMIF(case!$N:$N,$A115,case!J:J) -> -14467.256 | K115: =SUMIF(case!$N:$N,$A115,case!K:K) -> -5282.061
A116: = − Totale acquisti MP, merci e servizi | B116: =SUM(B113:B115) -> -481014 | C116: =SUM(C113:C115) -> -384827 | D116: =SUM(D113:D115) -> -612180.15 | E116: =SUM(E113:E115) -> -449495.95 | F116: =SUM(F113:F115) -> -357984.27 | G116: =SUM(G113:G115) -> -400315.34 | H116: =SUM(H113:H115) -> -494524.11 | I116: =SUM(I113:I115) -> -448998.95 | ... K116: =SUM(K113:K115) -> -453576.4
A117: + Variazione rimanenze di MP e merci | B117: =SUMIF(case!$N:$N,$A117,case!B:B) -> 0 | C117: =SUMIF(case!$N:$N,$A117,case!C:C) -> 0 | D117: =SUMIF(case!$N:$N,$A117,case!D:D) -> -3920.572 | E117: =SUMIF(case!$N:$N,$A117,case!E:E) -> 7298.458 | F117: =SUMIF(case!$N:$N,$A117,case!F:F) -> 1366.336 | G117: =SUMIF(case!$N:$N,$A117,case!G:G) -> -39220.777 | H117: =SUMIF(case!$N:$N,$A117,case!H:H) -> 39490.86 | I117: =SUMIF(case!$N:$N,$A117,case!I:I) -> -1762.672 | J117: =SUMIF(case!$N:$N,$A117,case!J:J) -> 79.873 | K117: =SUMIF(case!$N:$N,$A117,case!K:K) -> 3289.332
...

Sheet RF
B1: Rendiconto finanziario | C1: =case!B1 -> 31/12/2024 | D1: =case!C1 -> 31/12/2023 | E1: =case!D1 -> 31/12/2022 | F1: =case!E1 -> 31/12/2021 | G1: =case!F1 -> 31/12/2020 | H1: =case!G1 -> 31/12/2019 | I1: =case!H1 -> 31/12/2018 | J1: =case!I1 -> 31/12/2017 | ... L1: =case!K1 -> 31/12/2015
B2: Flussi di cassa della gestione operativa e accessoria
B3: Flussi di cassa della gestione operativa corrente
A4: + | B4: Reddito operativo | C4: ='RC'!B131 -> 60536 | D4: ='RC'!C131 -> 57190 | E4: ='RC'!D131 -> 11294.284 | F4: ='RC'!E131 -> 9288.812 | G4: ='RC'!F131 -> 3264.182 | H4: ='RC'!G131 -> 30663.78 | I4: ='RC'!H131 -> 33717.566 | J4: ='RC'!I131 -> 77298.709 | ... L4: ='RC'!K131 -> 51933.84
A5: ± | B5: Reddito gestioni accessoria e straordinaria | C5: ='RC'!B146 -> -43154 | D5: ='RC'!C146 -> -6813 | E5: ='RC'!D146 -> 39318.078 | F5: ='RC'!E146 -> 15698.284 | G5: ='RC'!F146 -> 7043.277 | H5: ='RC'!G146 -> -13924.696 | I5: ='RC'!H146 -> -19712.91 | J5: ='RC'!I146 -> -10378.498 | ... L5: ='RC'!K146 -> 6656.506
A6: + | B6: Riaggiunta ammortamenti | C6: =-'RC'!B124 -> 51303 | D6: =-'RC'!C124 -> 32661 | E6: =-'RC'!D124 -> 35625.263 | F6: =-'RC'!E124 -> 31971.207 | G6: =-'RC'!F124 -> 26000.365 | H6: =-'RC'!G124 -> 21147.856 | I6: =-'RC'!H124 -> 26935.278 | J6: =-'RC'!I124 -> 31141.093 | ... L6: =-'RC'!K124 -> 22820.98
A7: - | B7: (Imposte + Risparmio fiscale interessi netti) | C7: =-('RC'!B149+'RC'!B157) -> 17288.031 | D7: =-('RC'!C149+'RC'!C157) -> 4014.4472 | E7: =-('RC'!D149+'RC'!D157) -> 30410.509 | F7: =-('RC'!E149+'RC'!E157) -> 14134.253 | G7: =-('RC'!F149+'RC'!F157) -> 637.06043 | H7: =-('RC'!G149+'RC'!G157) -> 8050.9647 | I7: =-('RC'!H149+'RC'!H157) -> 3216.6355 | J7: =-('RC'!I149+'RC'!I157) -> 11187.544 | ... L7: =-('RC'!K149+'RC'!K157) -> 15271.082
A8: = | B8: EBITDA al netto delle imposte | C8: =C4+C5+C6-C7 -> 51396.969 | D8: =D4+D5+D6-D7 -> 79023.553 | E8: =E4+E5+E6-E7 -> 55827.116 | F8: =F4+F5+F6-F7 -> 42824.05 | G8: =G4+G5+G6-G7 -> 35670.764 | H8: =H4+H5+H6-H7 -> 29835.975 | I8: =I4+I5+I6-I7 -> 37723.299 | J8: =J4+J5+J6-J7 -> 86873.76 | ... L8: =L4+L5+L6-L7 -> 66140.244
B9: Rettifiche per determinare il flusso di cassa
B10: Variazione del CCON*
A11: - | B11: (Aumento) diminuzione crediti verso clienti | C11: =-1*('RC'!B5-'RC'!C5) -> -11669 | D11: =-1*('RC'!C5-'RC'!D5) -> -66503.281 | E11: =-1*('RC'!D5-'RC'!E5) -> 6007.694 | F11: =-1*('RC'!E5-'RC'!F5) -> 19372.564 | G11: =-1*('RC'!F5-'RC'!G5) -> 20998.652 | H11: =-1*('RC'!G5-'RC'!H5) -> 66205.883 | I11: =-1*('RC'!H5-'RC'!I5) -> -7062.696 | J11: =-1*('RC'!I5-'RC'!J5) -> 9376.927 | ... L11: =-1*('RC'!K5-'RC'!L5) -> -142030.01
A12: - | B12: (Aumento) diminuzione scorte magazzino | C12: =-1*('RC'!B6-'RC'!C6) -> -13102 | D12: =-1*('RC'!C6-'RC'!D6) -> 35695.143 | E12: =-1*('RC'!D6-'RC'!E6) -> -21276.95 | F12: =-1*('RC'!E6-'RC'!F6) -> -10044.808 | G12: =-1*('RC'!F6-'RC'!G6) -> -3051.458 | H12: =-1*('RC'!G6-'RC'!H6) -> 46549.412 | I12: =-1*('RC'!H6-'RC'!I6) -> -43414.255 | J12: =-1*('RC'!I6-'RC'!J6) -> 8590.164 | ... L12: =-1*('RC'!K6-'RC'!L6) -> -127191.34
A13: - | B13: (Aumento) diminuzione altre attività correnti | C13: =-1*('RC'!B7-'RC'!C7) -> -54161 | D13: =-1*('RC'!C7-'RC'!D7) -> -250170.73 | E13: =-1*('RC'!D7-'RC'!E7) -> 1177.796 | F13: =-1*('RC'!E7-'RC'!F7) -> -10353.605 | G13: =-1*('RC'!F7-'RC'!G7) -> -5883.508 | H13: =-1*('RC'!G7-'RC'!H7) -> 2167.976 | I13: =-1*('RC'!H7-'RC'!I7) -> -699.652 | J13: =-1*('RC'!I7-'RC'!J7) -> -1039.927 | ... L13: =-1*('RC'!K7-'RC'!L7) -> -9881.25
A14: + | B14: Aumento (diminuzione) debiti verso fornitori | C14: ='RC'!B48-'RC'!C48 -> 68013 | D14: ='RC'!C48-'RC'!D48 -> -69875.23 | E14: ='RC'!D48-'RC'!E48 -> 61953.867 | F14: ='RC'!E48-'RC'!F48 -> 55333.239 | G14: ='RC'!F48-'RC'!G48 -> -4922.085 | H14: ='RC'!G48-'RC'!H48 -> -57307.649 | I14: ='RC'!H48-'RC'!I48 -> 54649.144 | J14: ='RC'!I48-'RC'!J48 -> 1552.451 | ... L14: ='RC'!K48-'RC'!L48 -> 154222
A15: + | B15: Aumento (diminuzione) altre passività correnti | C15: ='RC'!B50-'RC'!C50 -> 8265 | D15: ='RC'!C50-'RC'!D50 -> 3030.782 | E15: ='RC'!D50-'RC'!E50 -> 556.815 | F15: ='RC'!E50-'RC'!F50 -> 5737.392 | G15: ='RC'!F50-'RC'!G50 -> -744.099 | H15: ='RC'!G50-'RC'!H50 -> 2756.409 | I15: ='RC'!H50-'RC'!I50 -> -681.304 | J15: ='RC'!I50-'RC'!J50 -> -929.062 | ... L15: ='RC'!K50-'RC'!L50 -> 11889.772
A16: - | B16: (Aumento) diminuzione attività fiscali | C16: =-1*('RC'!B21-'RC'!C21) -> -16515 | D16: =-1*('RC'!C21-'RC'!D21) -> 38157.054 | E16: =-1*('RC'!D21-'RC'!E21) -> -30072.044 | F16: =-1*('RC'!E21-'RC'!F21) -> 3249.688 | G16: =-1*('RC'!F21-'RC'!G21) -> -22732.803 | H16: =-1*('RC'!G21-'RC'!H21) -> -434.079 | I16: =-1*('RC'!H21-'RC'!I21) -> -3056.269 | J16: =-1*('RC'!I21-'RC'!J21) -> -6584.974 | ... L16: =-1*('RC'!K21-'RC'!L21) -> -8894.028
A17: + | B17: Aumento (diminuzione) passività fiscali | C17: ='RC'!B62-'RC'!C62 -> 92954 | D17: ='RC'!C62-'RC'!D62 -> -21855.557 | E17: ='RC'!D62-'RC'!E62 -> 4369.679 | F17: ='RC'!E62-'RC'!F62 -> -24420.619 | G17: ='RC'!F62-'RC'!G62 -> 35385.32 | H17: ='RC'!G62-'RC'!H62 -> 1510.859 | I17: ='RC'!H62-'RC'!I62 -> 5624.407 | J17: ='RC'!I62-'RC'!J62 -> -564.856 | ... L17: ='RC'!K62-'RC'!L62 -> 23945.142
A18: = | B18: (Aumento) diminuzione CCON* | C18: =SUM(C11:C17) -> 73785 | D18: =SUM(D11:D17) -> -331521.82 | E18: =SUM(E11:E17) -> 22716.857 | F18: =SUM(F11:F17) -> 38873.851 | G18: =SUM(G11:G17) -> 19050.019 | H18: =SUM(H11:H17) -> 61448.811 | I18: =SUM(I11:I17) -> 5359.375 | J18: =SUM(J11:J17) -> 10400.723 | ... L18: =SUM(L11:L17) -> -97939.712
A19: + | B19: Aumento (diminuzione) fondo TFR | C19: ='RC'!B53-'RC'!C53 -> -1064 | D19: ='RC'!C53-'RC'!D53 -> -2654.145 | E19: ='RC'!D53-'RC'!E53 -> 39.782 | F19: ='RC'!E53-'RC'!F53 -> -1322.841 | G19: ='RC'!F53-'RC'!G53 -> -2188.46 | H19: ='RC'!G53-'RC'!H53 -> -1299.644 | I19: ='RC'!H53-'RC'!I53 -> -1203.192 | J19: ='RC'!I53-'RC'!J53 -> -1115.942 | ... L19: ='RC'!K53-'RC'!L53 -> 17851.924
A20: - | B20: (Aumento) diminuzione altre attività operative immobilizzate | C20: =-1*('RC'!B15-'RC'!C15) -> 0 | D20: =-1*('RC'!C15-'RC'!D15) -> 10782.128 | E20: =-1*('RC'!D15-'RC'!E15) -> -10438.693 | F20: =-1*('RC'!E15-'RC'!F15) -> 27.25 | G20: =-1*('RC'!F15-'RC'!G15) -> -45.889 | H20: =-1*('RC'!G15-'RC'!H15) -> -42.82 | I20: =-1*('RC'!H15-'RC'!I15) -> -3.718 | J20: =-1*('RC'!I15-'RC'!J15) -> 12.818 | ... L20: =-1*('RC'!K15-'RC'!L15) -> -286.84
A21: + | B21: Aumento (diminuzione) altre passività operative consolidate | C21: ='RC'!B54-'RC'!C54 -> 0 | D21: ='RC'!C54-'RC'!D54 -> 0 | E21: ='RC'!D54-'RC'!E54 -> 0 | F21: ='RC'!E54-'RC'!F54 -> 0 | G21: ='RC'!F54-'RC'!G54 -> 0 | H21: ='RC'!G54-'RC'!H54 -> 0 | I21: ='RC'!H54-'RC'!I54 -> 0 | J21: ='RC'!I54-'RC'!J54 -> 0 | ... L21: ='RC'!K54-'RC'!L54 -> 0
A22: = | B22: Totale rettifiche | C22: =SUM(C18:C21) -> 72721 | D22: =SUM(D18:D21) -> -323393.84 | E22: =SUM(E18:E21) -> 12317.946 | F22: =SUM(F18:F21) -> 37578.26 | G22: =SUM(G18:G21) -> 16815.67 | H22: =SUM(H18:H21) -> 60106.347 | I22: =SUM(I18:I21) -> 4152.465 | J22: =SUM(J18:J21) -> 9297.599 | ... L22: =SUM(L18:L21) -> -80374.628
A23: = | B23: Flussi di cassa netti gestione operativa corrente, acc e straord. | C23: =C8+C22 -> 124117.97 | D23: =D8+D22 -> -244370.29 | E23: =E8+E22 -> 68145.062 | F23: =F8+F22 -> 80402.31 | G23: =G8+G22 -> 52486.434 | H23: =H8+H22 -> 89942.322 | I23: =I8+I22 -> 41875.764 | J23: =J8+J22 -> 96171.359 | ... L23: =L8+L22 -> -14234.384
B24: Flussi di cassa della gestione investimenti
A25: - | B25: (Aumento) diminuzione Immobilizzazioni operative nette | C25: =-1*('RC'!B12-'RC'!C12) -> -1529290 | D25: =-1*('RC'!C12-'RC'!D12) -> 316.013 | E25: =-1*('RC'!D12-'RC'!E12) -> -1516.455 | F25: =-1*('RC'!E12-'RC'!F12) -> -1463.357 | G25: =-1*('RC'!F12-'RC'!G12) -> -140689.15 | H25: =-1*('RC'!G12-'RC'!H12) -> -6066.974 | I25: =-1*('RC'!H12-'RC'!I12) -> 9624.134 | J25: =-1*('RC'!I12-'RC'!J12) -> -11503.925 | ... L25: =-1*('RC'!K12-'RC'!L12) -> -169179.91
A26: - | B26: (Aumento) diminuzione attività accessorie | C26: =-1*('RC'!B27-'RC'!C27) -> -455975 | D26: =-1*('RC'!C27-'RC'!D27) -> 280588.5 | E26: =-1*('RC'!D27-'RC'!E27) -> -171797.09 | F26: =-1*('RC'!E27-'RC'!F27) -> -27650.428 | G26: =-1*('RC'!F27-'RC'!G27) -> -387223.18 | H26: =-1*('RC'!G27-'RC'!H27) -> 28576.895 | I26: =-1*('RC'!H27-'RC'!I27) -> 12974.171 | J26: =-1*('RC'!I27-'RC'!J27) -> 7225.244 | ... L26: =-1*('RC'!K27-'RC'!L27) -> -302513.68
A27: + | B27: Aumento (diminuzione) debiti vs controllate e collegate | C27: ='RC'!B66-'RC'!C66 -> 0 | D27: ='RC'!C66-'RC'!D66 -> -395029.19 | E27: ='RC'!D66-'RC'!E66 -> 220748.76 | F27: ='RC'!E66-'RC'!F66 -> 32754.021 | G27: ='RC'!F66-'RC'!G66 -> 37594.96 | H27: ='RC'!G66-'RC'!H66 -> 35978.454 | I27: ='RC'!H66-'RC'!I66 -> 21451.219 | J27: ='RC'!I66-'RC'!J66 -> -7620.477 | ... L27: ='RC'!K66-'RC'!L66 -> 49593.984
A28: - | B28: (Ammortamenti) | C28: ='RC'!B124 -> -51303 | D28: ='RC'!C124 -> -32661 | E28: ='RC'!D124 -> -35625.263 | F28: ='RC'!E124 -> -31971.207 | G28: ='RC'!F124 -> -26000.365 | H28: ='RC'!G124 -> -21147.856 | I28: ='RC'!H124 -> -26935.278 | J28: ='RC'!I124 -> -31141.093 | ... L28: ='RC'!K124 -> -22820.98
A29: + | B29: Aumento (diminuzione) riserve da rivalutazione | C29: ='RC'!B80-'RC'!C80 -> 0 | D29: ='RC'!C80-'RC'!D80 -> -15208.961 | E29: ='RC'!D80-'RC'!E80 -> -2812.271 | F29: ='RC'!E80-'RC'!F80 -> 3582.652 | G29: ='RC'!F80-'RC'!G80 -> -1033.323 | H29: ='RC'!G80-'RC'!H80 -> 0 | I29: ='RC'!H80-'RC'!I80 -> 0 | J29: ='RC'!I80-'RC'!J80 -> 0 | ... L29: ='RC'!K80-'RC'!L80 -> 15471.903
A30: = | B30: Flussi di cassa netti della gestione investimenti | C30: =SUM(C25:C29) -> -2036568 | D30: =SUM(D25:D29) -> -161994.63 | E30: =SUM(E25:E29) -> 8997.674 | F30: =SUM(F25:F29) -> -24748.319 | G30: =SUM(G25:G29) -> -517351.06 | H30: =SUM(H25:H29) -> 37340.519 | I30: =SUM(I25:I29) -> 17114.246 | J30: =SUM(J25:J29) -> -43040.251 | ... L30: =SUM(L25:L29) -> -429448.69
A31: = | B31: Free cash flow to the firm (FCFF) | C31: =C23+C30 -> -1912450 | D31: =D23+D30 -> -406364.92 | E31: =E23+E30 -> 77142.736 | F31: =F23+F30 -> 55653.991 | G31: =G23+G30 -> -464864.63 | H31: =H23+H30 -> 127282.84 | I31: =I23+I30 -> 58990.01 | J31: =J23+J30 -> 53131.108 | ... L31: =L23+L30 -> -443683.08
B32: Flussi di cassa della gestione finanziaria
B33: Debito e attività finanziarie (esclusa tesoreria)
A34: - | B34: (Oneri finanziari netti) | C34: ='RC'!B140 -> -333886 | D34: ='RC'!C140 -> -113236 | E34: ='RC'!D140 -> -41465.99 | F34: ='RC'!E140 -> -33466.263 | G34: ='RC'!F140 -> -65444.809 | H34: ='RC'!G140 -> -4198.972 | I34: ='RC'!H140 -> -3379.875 | J34: ='RC'!I140 -> -5634.534 | ... L34: ='RC'!K140 -> -3431.708
A35: + | B35: Risparmio fiscale interessi netti | C35: =-'RC'!B157 -> 8875.0313 | D35: =-'RC'!C157 -> 2581.4472 | E35: =-'RC'!D157 -> 39016.608 | F35: =-'RC'!E157 -> 11277.048 | G35: =-'RC'!F157 -> 345.75843 | H35: =-'RC'!G157 -> -4052.8963 | I35: =-'RC'!H157 -> -1500.6165 | J35: =-'RC'!I157 -> -1132.7099 | ... L35: =-'RC'!K157 -> -1013.1259
A36: + | B36: Strumenti derivati: (aumento) diminuzione attivi + aumento (diminuzione) passivi | C36: =-('RC'!B32-'RC'!C32)+('RC'!B72-'RC'!C72) -> -20955 | D36: =-('RC'!C32-'RC'!D32)+('RC'!C72-'RC'!D72) -> 2971.912 | E36: =-('RC'!D32-'RC'!E32)+('RC'!D72-'RC'!E72) -> 18027.567 | F36: =-('RC'!E32-'RC'!F32)+('RC'!E72-'RC'!F72) -> -6513.5 | G36: =-('RC'!F32-'RC'!G32)+('RC'!F72-'RC'!G72) -> 1456.109 | H36: =-('RC'!G32-'RC'!H32)+('RC'!G72-'RC'!H72) -> 403.332 | I36: =-('RC'!H32-'RC'!I32)+('RC'!H72-'RC'!I72) -> -837.062 | J36: =-('RC'!I32-'RC'!J32)+('RC'!I72-'RC'!J72) -> 1941.187 | ... L36: =-('RC'!K32-'RC'!L32)+('RC'!K72-'RC'!L72) -> 0
A37: + | B37: Aumento (diminuzione) debiti struttturali a medio-lungo | C37: ='RC'!B69-'RC'!C69 -> 722110 | D37: ='RC'!C69-'RC'!D69 -> 703519 | E37: ='RC'!D69-'RC'!E69 -> -725617.18 | F37: ='RC'!E69-'RC'!F69 -> -54874.991 | G37: ='RC'!F69-'RC'!G69 -> 780492.17 | H37: ='RC'!G69-'RC'!H69 -> 0 | I37: ='RC'!H69-'RC'!I69 -> -55779.956 | J37: ='RC'!I69-'RC'!J69 -> -24089.8 | ... L37: ='RC'!K69-'RC'!L69 -> 103275.9
A38: + | B38: Aumento (diminuzione) debiti strutturali a breve | C38: ='RC'!B70-'RC'!C70 -> 37027 | D38: ='RC'!C70-'RC'!D70 -> 37414.159 | E38: ='RC'!D70-'RC'!E70 -> 12666.575 | F38: ='RC'!E70-'RC'!F70 -> -6302.069 | G38: ='RC'!F70-'RC'!G70 -> 18706.413 | H38: ='RC'!G70-'RC'!H70 -> -20459.546 | I38: ='RC'!H70-'RC'!I70 -> -79510.883 | J38: ='RC'!I70-'RC'!J70 -> 20497.531 | ... L38: ='RC'!K70-'RC'!L70 -> 100505.1
A39: - | B39: (Aumento) diminuzione riserve strategiche di liquidità | C39: =-('RC'!B30-'RC'!C30) -> 0 | D39: =-('RC'!C30-'RC'!D30) -> 0 | E39: =-('RC'!D30-'RC'!E30) -> 0 | F39: =-('RC'!E30-'RC'!F30) -> 0 | G39: =-('RC'!F30-'RC'!G30) -> 0 | H39: =-('RC'!G30-'RC'!H30) -> 0 | I39: =-('RC'!H30-'RC'!I30) -> 0 | J39: =-('RC'!I30-'RC'!J30) -> 0 | ... L39: =-('RC'!K30-'RC'!L30) -> 0
A40: = | B40: Flussi di cassa netti sul debito netto (esclusa tesoreria) (FCDN) | C40: =SUM(C34:C39) -> 413171.03 | D40: =SUM(D34:D39) -> 633250.52 | E40: =SUM(E34:E39) -> -697372.42 | F40: =SUM(F34:F39) -> -89879.775 | G40: =SUM(G34:G39) -> 735555.64 | H40: =SUM(H34:H39) -> -28308.082 | I40: =SUM(I34:I39) -> -141008.39 | J40: =SUM(J34:J39) -> -8418.3259 | ... L40: =SUM(L34:L39) -> 199336.16
A41: = | B41: Free cash flow to equity (FCFE) | C41: =C31+C40 -> -1499279 | D41: =D31+D40 -> 226885.6 | E41: =E31+E40 -> -620229.68 | F41: =F31+F40 -> -34225.784 | G41: =G31+G40 -> 270691.01 | H41: =H31+H40 -> 98974.759 | I41: =I31+I40 -> -82018.383 | J41: =J31+J40 -> 44712.782 | ... L41: =L31+L40 -> -244346.92
B42: Capitale proprio
A43: - | B43: (Stima utili distribuiti) | C43: ='RC'!B79 -> 1076923 | D43: ='RC'!C79 -> 52270 | E43: ='RC'!D79 -> 3345.615 | F43: ='RC'!E79 -> 10181.987 | G43: ='RC'!F79 -> 65610.639 | H43: ='RC'!G79 -> 237217.2 | I43: ='RC'!H79 -> 235309.67 | J43: ='RC'!I79 -> 214344.4 | ... L43: ='RC'!K79 -> 172816.59
A44: - | B44: (Aumento) diminuzione azioni proprie e partec in controllanti | C44: =-('RC'!B81-'RC'!C81) -> 0 | D44: =-('RC'!C81-'RC'!D81) -> 0 | E44: =-('RC'!D81-'RC'!E81) -> 0 | F44: =-('RC'!E81-'RC'!F81) -> 0 | G44: =-('RC'!F81-'RC'!G81) -> 0 | H44: =-('RC'!G81-'RC'!H81) -> 0 | I44: =-('RC'!H81-'RC'!I81) -> 0 | J44: =-('RC'!I81-'RC'!J81) -> 0 | ... L44: =-('RC'!K81-'RC'!L81) -> 0
A45: + | B45: Aumento (diminuzione) finanziamenti netti da soci e controllanti | C45: ='RC'!B76-'RC'!C76 -> 437975 | D45: ='RC'!C76-'RC'!D76 -> -68969.353 | E45: ='RC'!D76-'RC'!E76 -> 621855.21 | F45: ='RC'!E76-'RC'!F76 -> -2196.273 | G45: ='RC'!F76-'RC'!G76 -> -77071.239 | H45: ='RC'!G76-'RC'!H76 -> -6893.69 | I45: ='RC'!H76-'RC'!I76 -> 80208.762 | J45: ='RC'!I76-'RC'!J76 -> 6933.888 | ... L45: ='RC'!K76-'RC'!L76 -> -11756.08
A46: + | B46: Aumento (diminuzione) di capitale conferito dai soci | C46: ='RC'!B78-'RC'!C78 -> 0 | D46: ='RC'!C78-'RC'!D78 -> -0.674 | E46: ='RC'!D78-'RC'!E78 -> 0 | F46: ='RC'!E78-'RC'!F78 -> 0 | G46: ='RC'!F78-'RC'!G78 -> 8412.316 | H46: ='RC'!G78-'RC'!H78 -> 0 | I46: ='RC'!H78-'RC'!I78 -> 0 | J46: ='RC'!I78-'RC'!J78 -> 0 | ... L46: ='RC'!K78-'RC'!L78 -> 91829.358
A47: + | B47: Aumento (diminuzione) capitale proprio di pertinenza di terzi | C47: ='RC'!B83-'RC'!C83 -> 0 | D47: ='RC'!C83-'RC'!D83 -> 0 | E47: ='RC'!D83-'RC'!E83 -> 0 | F47: ='RC'!E83-'RC'!F83 -> 0 | G47: ='RC'!F83-'RC'!G83 -> 0 | H47: ='RC'!G83-'RC'!H83 -> 0 | I47: ='RC'!H83-'RC'!I83 -> 0 | J47: ='RC'!I83-'RC'!J83 -> 0 | ... L47: ='RC'!K83-'RC'!L83 -> 0
A48: = | B48: Flussi di cassa effettivi sul capitale proprio (FCCP) | C48: =SUM(C43:C47) -> 1514898 | D48: =SUM(D43:D47) -> -16700.027 | E48: =SUM(E43:E47) -> 625200.82 | F48: =SUM(F43:F47) -> 7985.714 | G48: =SUM(G43:G47) -> -3048.284 | H48: =SUM(H43:H47) -> 230323.51 | I48: =SUM(I43:I47) -> 315518.43 | J48: =SUM(J43:J47) -> 221278.29 | ... L48: =SUM(L43:L47) -> 252889.87
A49: = | B49: Flusso di cassa netto (NCF) | C49: =C41+C48 -> 15619 | D49: =D41+D48 -> 210185.57 | E49: =E41+E48 -> 4971.14 | F49: =F41+F48 -> -26240.07 | G49: =G41+G48 -> 267642.73 | H49: =H41+H48 -> 329298.27 | I49: =I41+I48 -> 233500.05 | J49: =J41+J48 -> 265991.07 | ... L49: =L41+L48 -> 8542.951
B51: Check NCF
A52: + | B52: Aumento (diminuzione) attività di tesoreria | C52: ='RC'!B31-'RC'!C31 -> 27641 | D52: ='RC'!C31-'RC'!D31 -> 189087.49 | E52: ='RC'!D31-'RC'!E31 -> 6125.525 | F52: ='RC'!E31-'RC'!F31 -> -36422.057 | G52: ='RC'!F31-'RC'!G31 -> 29989.276 | H52: ='RC'!G31-'RC'!H31 -> 88081.067 | I52: ='RC'!H31-'RC'!I31 -> -29809.775 | J52: ='RC'!I31-'RC'!J31 -> 21646.505 | ... L52: ='RC'!K31-'RC'!L31 -> 8542.951
A53: - | B53: (Aumento) diminuzione debiti di tesoreria | C53: =-('RC'!B71-'RC'!C71) -> 0 | D53: =-('RC'!C71-'RC'!D71) -> 0 | E53: =-('RC'!D71-'RC'!E71) -> 0 | F53: =-('RC'!E71-'RC'!F71) -> 0 | G53: =-('RC'!F71-'RC'!G71) -> 0 | H53: =-('RC'!G71-'RC'!H71) -> 0 | I53: =-('RC'!H71-'RC'!I71) -> 0 | J53: =-('RC'!I71-'RC'!J71) -> 0 | ... L53: =-('RC'!K71-'RC'!L71) -> 0
A54: = | B54: Variazione posizione netta di tesoreria | C54: =C52+C53 -> 27641 | D54: =D52+D53 -> 189087.49 | E54: =E52+E53 -> 6125.525 | F54: =F52+F53 -> -36422.057 | G54: =G52+G53 -> 29989.276 | H54: =H52+H53 -> 88081.067 | I54: =I52+I53 -> -29809.775 | J54: =J52+J53 -> 21646.505 | ... L54: =L52+L53 -> 8542.951
A55: = | B55: NCF | C55: =C49 -> 15619 | D55: =D49 -> 210185.57 | E55: =E49 -> 4971.14 | F55: =F49 -> -26240.07 | G55: =G49 -> 267642.73 | H55: =H49 -> 329298.27 | I55: =I49 -> 233500.05 | J55: =J49 -> 265991.07 | ... L55: =L49 -> 8542.951
B56: Sbilancio check NCF | C56: =C54-C55 -> 12022 | D56: =D54-D55 -> -21098.086 | E56: =E54-E55 -> 1154.385 | F56: =F54-F55 -> -10181.987 | G56: =G54-G55 -> -237653.45 | H56: =H54-H55 -> -241217.2 | I56: =I54-I55 -> -263309.83 | J56: =J54-J55 -> -244344.57 | ... L56: =L54-L55 -> -3.092282e-11
B57: Check FCFF
A58: + | B58: EBITDA al netto delle imposte check | C58: =C8 -> 51396.969 | D58: =D8 -> 79023.553 | E58: =E8 -> 55827.116 | F58: =F8 -> 42824.05 | G58: =G8 -> 35670.764 | H58: =H8 -> 29835.975 | I58: =I8 -> 37723.299 | J58: =J8 -> 86873.76 | ... L58: =L8 -> 66140.244
A59: - | B59: -Ammortamenti check | C59: =-C6 -> -51303 | D59: =-D6 -> -32661 | E59: =-E6 -> -35625.263 | F59: =-F6 -> -31971.207 | G59: =-G6 -> -26000.365 | H59: =-H6 -> -21147.856 | I59: =-I6 -> -26935.278 | J59: =-J6 -> -31141.093 | ... L59: =-L6 -> -22820.98
A60: - | B60: -VAR AON* | C60: =('RC'!B162-'RC'!C162)*-1 -> -1456569 | D60: =('RC'!C162-'RC'!D162)*-1 -> -323077.83 | E60: =('RC'!D162-'RC'!E162)*-1 -> 10801.491 | F60: =('RC'!E162-'RC'!F162)*-1 -> 36114.903 | G60: =('RC'!F162-'RC'!G162)*-1 -> -123873.48 | H60: =('RC'!G162-'RC'!H162)*-1 -> 54039.373 | I60: =('RC'!H162-'RC'!I162)*-1 -> 13776.599 | J60: =('RC'!I162-'RC'!J162)*-1 -> -2206.326 | ... L60: =('RC'!K162-'RC'!L162)*-1 -> -249554.54
A61: - | B61: -VAR AACC | C61: =('RC'!B27-'RC'!C27)*-1 -> -455975 | D61: =('RC'!C27-'RC'!D27)*-1 -> 280588.5 | E61: =('RC'!D27-'RC'!E27)*-1 -> -171797.09 | F61: =('RC'!E27-'RC'!F27)*-1 -> -27650.428 | G61: =('RC'!F27-'RC'!G27)*-1 -> -387223.18 | H61: =('RC'!G27-'RC'!H27)*-1 -> 28576.895 | I61: =('RC'!H27-'RC'!I27)*-1 -> 12974.171 | J61: =('RC'!I27-'RC'!J27)*-1 -> 7225.244 | ... L61: =('RC'!K27-'RC'!L27)*-1 -> -302513.68
A62: + | B62: +VAR P.ACC | C62: ='RC'!B66-'RC'!C66 -> 0 | D62: ='RC'!C66-'RC'!D66 -> -395029.19 | E62: ='RC'!D66-'RC'!E66 -> 220748.76 | F62: ='RC'!E66-'RC'!F66 -> 32754.021 | G62: ='RC'!F66-'RC'!G66 -> 37594.96 | H62: ='RC'!G66-'RC'!H66 -> 35978.454 | I62: ='RC'!H66-'RC'!I66 -> 21451.219 | J62: ='RC'!I66-'RC'!J66 -> -7620.477 | ... L62: ='RC'!K66-'RC'!L66 -> 49593.984
A63: + | B63: +Var. Ris. rivalutazione | C63: ='RC'!B80-'RC'!C80 -> 0 | D63: ='RC'!C80-'RC'!D80 -> -15208.961 | E63: ='RC'!D80-'RC'!E80 -> -2812.271 | F63: ='RC'!E80-'RC'!F80 -> 3582.652 | G63: ='RC'!F80-'RC'!G80 -> -1033.323 | H63: ='RC'!G80-'RC'!H80 -> 0 | I63: ='RC'!H80-'RC'!I80 -> 0 | J63: ='RC'!I80-'RC'!J80 -> 0 | ... L63: ='RC'!K80-'RC'!L80 -> 15471.903
A64: = | B64: = Risultato | C64: =SUM(C58:C63) -> -1912450 | D64: =SUM(D58:D63) -> -406364.92 | E64: =SUM(E58:E63) -> 77142.736 | F64: =SUM(F58:F63) -> 55653.991 | G64: =SUM(G58:G63) -> -464864.63 | H64: =SUM(H58:H63) -> 127282.84 | I64: =SUM(I58:I63) -> 58990.01 | J64: =SUM(J58:J63) -> 53131.108 | ... L64: =SUM(L58:L63) -> -443683.08
A65: = | B65: = FCFF ceck | C65: =C31 -> -1912450 | D65: =D31 -> -406364.92 | E65: =E31 -> 77142.736 | F65: =F31 -> 55653.991 | G65: =G31 -> -464864.63 | H65: =H31 -> 127282.84 | I65: =I31 -> 58990.01 | J65: =J31 -> 53131.108 | ... L65: =L31 -> -443683.08
B66: Sbilancio check FCFF | C66: =C64-C65 -> 0 | D66: =D64-D65 -> 0 | E66: =E64-E65 -> 0 | F66: =F64-F65 -> 0 | G66: =G64-G65 -> 0 | H66: =H64-H65 -> 0 | I66: =I64-I65 -> -1.0913936e-10 | J66: =J64-J65 -> 7.2759576e-11 | ... L66: =L64-L65 -> 0
B67: Check FCFE
A68: + | B68: Reddito netto check | C68: ='RC'!B150 -> -324917 | D68: ='RC'!C150 -> -64292 | E68: ='RC'!D150 -> 17752.471 | F68: ='RC'!E150 -> -11336.372 | G68: ='RC'!F150 -> -55428.652 | H68: ='RC'!G150 -> 436.251 | I68: ='RC'!H150 -> 5907.529 | J68: ='RC'!I150 -> 48965.423 | ... L68: ='RC'!K150 -> 38874.43
A69: - | B69: - Var (AON* + Att acc - Deb contr coll - Ris riv.) check 2 | C69: =SUM(C60:C63) -> -1912544 | D69: =SUM(D60:D63) -> -452727.47 | E69: =SUM(E60:E63) -> 56940.883 | F69: =SUM(F60:F63) -> 44801.148 | G69: =SUM(G60:G63) -> -474535.03 | H69: =SUM(H60:H63) -> 118594.72 | I69: =SUM(I60:I63) -> 48201.989 | J69: =SUM(J60:J63) -> -2601.559 | ... L69: =SUM(L60:L63) -> -487002.34
B70: + Var (Debito strutt + deriv pass - ris strat liq - deriv att ) check | C70: =SUM(C71:C74) -> 738182 | D70: =SUM(D71:D74) -> 743905.07 | E70: =SUM(E71:E74) -> -694923.04 | F70: =SUM(F71:F74) -> -67690.56 | G70: =SUM(G71:G74) -> 800654.69 | H70: =SUM(H71:H74) -> -20056.214 | I70: =SUM(I71:I74) -> -136127.9 | J70: =SUM(J71:J74) -> -1651.082 | ... L70: =SUM(L71:L74) -> 203780.99
B71: +VAR deb strutt m/l + bt | C71: ='RC'!B69+'RC'!B70-'RC'!C69-'RC'!C70 -> 759137 | D71: ='RC'!C69+'RC'!C70-'RC'!D69-'RC'!D70 -> 740933.16 | E71: ='RC'!D69+'RC'!D70-'RC'!E69-'RC'!E70 -> -712950.6 | F71: ='RC'!E69+'RC'!E70-'RC'!F69-'RC'!F70 -> -61177.06 | G71: ='RC'!F69+'RC'!F70-'RC'!G69-'RC'!G70 -> 799198.58 | H71: ='RC'!G69+'RC'!G70-'RC'!H69-'RC'!H70 -> -20459.546 | I71: ='RC'!H69+'RC'!H70-'RC'!I69-'RC'!I70 -> -135290.84 | J71: ='RC'!I69+'RC'!I70-'RC'!J69-'RC'!J70 -> -3592.269 | ... L71: ='RC'!K69+'RC'!K70-'RC'!L69-'RC'!L70 -> 203780.99
B72: +VAR deriv pass | C72: ='RC'!B72-'RC'!C72 -> -14051 | D72: ='RC'!C72-'RC'!D72 -> 1275.268 | E72: ='RC'!D72-'RC'!E72 -> 14114.274 | F72: ='RC'!E72-'RC'!F72 -> -1527.283 | G72: ='RC'!F72-'RC'!G72 -> 2011.728 | H72: ='RC'!G72-'RC'!H72 -> 123.956 | I72: ='RC'!H72-'RC'!I72 -> -520.477 | J72: ='RC'!I72-'RC'!J72 -> 375.062 | ... L72: ='RC'!K72-'RC'!L72 -> 0
B73: -VAR deriv att | C73: =-('RC'!B32-'RC'!C32) -> -6904 | D73: =-('RC'!C32-'RC'!D32) -> 1696.644 | E73: =-('RC'!D32-'RC'!E32) -> 3913.293 | F73: =-('RC'!E32-'RC'!F32) -> -4986.217 | G73: =-('RC'!F32-'RC'!G32) -> -555.619 | H73: =-('RC'!G32-'RC'!H32) -> 279.376 | I73: =-('RC'!H32-'RC'!I32) -> -316.585 | J73: =-('RC'!I32-'RC'!J32) -> 1566.125 | ... L73: =-('RC'!K32-'RC'!L32) -> 0
A74: + | B74: -VAR AON*
B75: = Risultato | C75: =SUM(C68:C70) -> -1499279 | D75: =SUM(D68:D70) -> 226885.6 | E75: =SUM(E68:E70) -> -620229.68 | F75: =SUM(F68:F70) -> -34225.784 | G75: =SUM(G68:G70) -> 270691.01 | H75: =SUM(H68:H70) -> 98974.759 | I75: =SUM(I68:I70) -> -82018.383 | J75: =SUM(J68:J70) -> 44712.782 | ... L75: =SUM(L68:L70) -> -244346.92
A76: = | B76: = FCFE check | C76: =C41 -> -1499279 | D76: =D41 -> 226885.6 | E76: =E41 -> -620229.68 | F76: =F41 -> -34225.784 | G76: =G41 -> 270691.01 | H76: =H41 -> 98974.759 | I76: =I41 -> -82018.383 | J76: =J41 -> 44712.782 | ... L76: =L41 -> -244346.92
B77: Sbilancio check FCFE | C77: =C75-C76 -> 0 | D77: =D75-D76 -> 0 | E77: =E75-E76 -> 0 | F77: =F75-F76 -> 0 | G77: =G75-G76 -> 0 | H77: =H75-H76 -> 0 | I77: =I75-I76 -> 0 | J77: =J75-J76 -> 8.7311491e-11 | ... L77: =L75-L76 -> 0

Sheet ind
A1: INDICATORI FINANZIARI | B1: =RF!C1 -> 31/12/2024 | C1: =RF!D1 -> 31/12/2023 | D1: =RF!E1 -> 31/12/2022 | E1: =RF!F1 -> 31/12/2021 | F1: =RF!G1 -> 31/12/2020 | G1: =RF!H1 -> 31/12/2019 | H1: =RF!I1 -> 31/12/2018 | I1: =RF!J1 -> 31/12/2017 | ... K1: =RF!L1 -> 31/12/2015
A2: valori patrimoniali medie t-1 per attenuare variazioni significativi
A3: RLA (redd. gest OFA) | B3: ='RC'!B131+'RC'!B140+'RC'!B144 -> -271350 | C3: ='RC'!C131+'RC'!C140+'RC'!C144 -> -55571 | D3: ='RC'!D131+'RC'!D140+'RC'!D144 -> 22828.294 | E3: ='RC'!E131+'RC'!E140+'RC'!E144 -> -8349.646 | F3: ='RC'!F131+'RC'!F140+'RC'!F144 -> -54355.359 | G3: ='RC'!G131+'RC'!G140+'RC'!G144 -> 33258.555 | H3: ='RC'!H131+'RC'!H140+'RC'!H144 -> 37150.588 | I3: ='RC'!I131+'RC'!I140+'RC'!I144 -> 79225.107 | ... K3: ='RC'!K131+'RC'!K140+'RC'!K144 -> 54747.826
A4: Reddito operativo | B4: ='RC'!B131 -> 60536 | C4: ='RC'!C131 -> 57190 | D4: ='RC'!D131 -> 11294.284 | E4: ='RC'!E131 -> 9288.812 | F4: ='RC'!F131 -> 3264.182 | G4: ='RC'!G131 -> 30663.78 | H4: ='RC'!H131 -> 33717.566 | I4: ='RC'!I131 -> 77298.709 | ... K4: ='RC'!K131 -> 51933.84
A5: EBITDA(MOL) | B5: ='RC'!B123 -> 119175 | C5: ='RC'!C123 -> 82113 | D5: ='RC'!D123 -> 37444.691 | E5: ='RC'!E123 -> 45295.227 | F5: ='RC'!F123 -> 30724.468 | G5: ='RC'!G123 -> 59292.527 | H5: ='RC'!H123 -> 62458.988 | I5: ='RC'!I123 -> 111262.03 | ... K5: ='RC'!K123 -> 78727.516
A6: Reddito netto | B6: ='RC'!B150 -> -324917 | C6: ='RC'!C150 -> -64292 | D6: ='RC'!D150 -> 17752.471 | E6: ='RC'!E150 -> -11336.372 | F6: ='RC'!F150 -> -55428.652 | G6: ='RC'!G150 -> 436.251 | H6: ='RC'!H150 -> 5907.529 | I6: ='RC'!I150 -> 48965.423 | ... K6: ='RC'!K150 -> 38874.43
A7: Ricavi | B7: ='RC'!B111 -> 700351 | C7: ='RC'!C111 -> 567524 | D7: ='RC'!D111 -> 731617.37 | E7: ='RC'!E111 -> 575309.43 | F7: ='RC'!F111 -> 470766.3 | G7: ='RC'!G111 -> 599353.35 | H7: ='RC'!H111 -> 601111.28 | I7: ='RC'!I111 -> 658456.38 | ... K7: ='RC'!K111 -> 617897.5
A8: Ricavi t-1 | B8: ='RC'!C111 -> 567524 | C8: ='RC'!D111 -> 731617.37 | D8: ='RC'!E111 -> 575309.43 | E8: ='RC'!F111 -> 470766.3 | F8: ='RC'!G111 -> 599353.35 | G8: ='RC'!H111 -> 601111.28 | H8: ='RC'!I111 -> 658456.38 | I8: ='RC'!J111 -> 649016.11 | ... K8: ='RC'!L111 -> 0
A9: Ricavi con IVA gg | B9: =B7*1.22/365 -> 2340.8992 | C9: =C7*1.22/365 -> 1896.9295 | D9: =D7*1.22/365 -> 2445.406 | E9: =E7*1.22/365 -> 1922.9521 | F9: =F7*1.22/365 -> 1573.5202 | G9: =G7*1.22/365 -> 2003.318 | H9: =H7*1.22/365 -> 2009.1939 | I9: =I7*1.22/365 -> 2200.8679 | ... K9: =K7*1.22/365 -> 2065.3012
A10: Acquisti | B10: ='RC'!B116 -> -481014 | C10: ='RC'!C116 -> -384827 | D10: ='RC'!D116 -> -612180.15 | E10: ='RC'!E116 -> -449495.95 | F10: ='RC'!F116 -> -357984.27 | G10: ='RC'!G116 -> -400315.34 | H10: ='RC'!H116 -> -494524.11 | I10: ='RC'!I116 -> -448998.95 | ... K10: ='RC'!K116 -> -453576.4
A11: Acquisti con IVA gg | B11: ='RC'!B116*1.22/365 -> -1607.7728 | C11: ='RC'!C116*1.22/365 -> -1286.2711 | D11: ='RC'!D116*1.22/365 -> -2046.1912 | E11: ='RC'!E116*1.22/365 -> -1502.4248 | F11: ='RC'!F116*1.22/365 -> -1196.5501 | G11: ='RC'!G116*1.22/365 -> -1338.0403 | H11: ='RC'!H116*1.22/365 -> -1652.9299 | I11: ='RC'!I116*1.22/365 -> -1500.7636 | ... K11: ='RC'!K116*1.22/365 -> -1516.0636
A12: Costo del venduto gg medio | B12: =AVERAGE('RC'!B120:C120)/365 -> -1198.6753 | C12: =AVERAGE('RC'!C120:D120)/365 -> -1362.4962 | D12: =AVERAGE('RC'!D120:E120)/365 -> -1398.7047 | E12: =AVERAGE('RC'!E120:F120)/365 -> -1075.4576 | F12: =AVERAGE('RC'!F120:G120)/365 -> -1098.3528 | G12: =AVERAGE('RC'!G120:H120)/365 -> -1230.1022 | H12: =AVERAGE('RC'!H120:I120)/365 -> -1244.7931 | I12: =AVERAGE('RC'!I120:J120)/365 -> -1245.1908 | ... K12: =AVERAGE('RC'!K120:L120)/365 -> -1234.3372
A13: Costo del personale gg medio | B13: =AVERAGE('RC'!B122:C122)/365 -> -262.40274 | C13: =AVERAGE('RC'!C122:D122)/365 -> -253.37189 | D13: =AVERAGE('RC'!D122:E122)/365 -> -278.26363 | E13: =AVERAGE('RC'!E122:F122)/365 -> -253.3863 | F13: =AVERAGE('RC'!F122:G122)/365 -> -244.25356 | G13: =AVERAGE('RC'!G122:H122)/365 -> -247.587 | H13: =AVERAGE('RC'!H122:I122)/365 -> -242.66804 | I13: =AVERAGE('RC'!I122:J122)/365 -> -247.94772 | ... K13: =AVERAGE('RC'!K122:L122)/365 -> -242.84087
A14: AON* medio | B14: =AVERAGE('RC'!B93,'RC'!C93) -> 1292505.5 | C14: =AVERAGE('RC'!C93,'RC'!D93) -> 402682.09 | D14: =AVERAGE('RC'!D93,'RC'!E93) -> 246543.92 | E14: =AVERAGE('RC'!E93,'RC'!F93) -> 270002.12 | F14: =AVERAGE('RC'!F93,'RC'!G93) -> 226122.83 | G14: =AVERAGE('RC'!G93,'RC'!H93) -> 191205.77 | H14: =AVERAGE('RC'!H93,'RC'!I93) -> 225113.76 | I14: =AVERAGE('RC'!I93,'RC'!J93) -> 230898.89 | ... K14: =AVERAGE('RC'!K93,'RC'!L93) -> 249554.54
A15: AON* init | B15: ='RC'!C93 -> 564221 | C15: ='RC'!D93 -> 241143.17 | D15: ='RC'!E93 -> 251944.66 | E15: ='RC'!F93 -> 288059.57 | F15: ='RC'!G93 -> 164186.08 | G15: ='RC'!H93 -> 218225.46 | H15: ='RC'!I93 -> 232002.06 | I15: ='RC'!J93 -> 229795.73 | ... K15: ='RC'!L93 -> 0
A16: AON* fin | B16: ='RC'!B93 -> 2020790 | C16: ='RC'!C93 -> 564221 | D16: ='RC'!D93 -> 241143.17 | E16: ='RC'!E93 -> 251944.66 | F16: ='RC'!F93 -> 288059.57 | G16: ='RC'!G93 -> 164186.08 | H16: ='RC'!H93 -> 218225.46 | I16: ='RC'!I93 -> 232002.06 | ... K16: ='RC'!K93 -> 249554.54
A17: Reddito att.acc (prov-oneri acc) | B17: ='RC'!B144 -> 2000 | C17: ='RC'!C144 -> 475 | D17: ='RC'!D144 -> 53000 | E17: ='RC'!E144 -> 15827.805 | F17: ='RC'!F144 -> 7825.268 | G17: ='RC'!G144 -> 6793.747 | H17: ='RC'!H144 -> 6812.897 | I17: ='RC'!I144 -> 7560.932 | ... K17: ='RC'!K144 -> 6245.694
A18: AACCN media(ris gest acc) | B18: =AVERAGE('RC'!B94,'RC'!C94) -> 787840.5 | C18: =AVERAGE('RC'!C94,'RC'!D94) -> 502632.66 | D18: =AVERAGE('RC'!D94,'RC'!E94) -> 469888.15 | E18: =AVERAGE('RC'!E94,'RC'!F94) -> 496915.78 | F18: =AVERAGE('RC'!F94,'RC'!G94) -> 324653.46 | G18: =AVERAGE('RC'!G94,'RC'!H94) -> 182117.03 | H18: =AVERAGE('RC'!H94,'RC'!I94) -> 231607.4 | I18: =AVERAGE('RC'!I94,'RC'!J94) -> 248622.48 | ... K18: =AVERAGE('RC'!K94,'RC'!L94) -> 252919.7
A19: AACC medie(solo attività) | B19: =AVERAGE('RC'!B27,'RC'!C27) -> 787840.5 | C19: =AVERAGE('RC'!C27,'RC'!D27) -> 700147.25 | D19: =AVERAGE('RC'!D27,'RC'!E27) -> 754542.96 | E19: =AVERAGE('RC'!E27,'RC'!F27) -> 654819.2 | F19: =AVERAGE('RC'!F27,'RC'!G27) -> 447382.39 | G19: =AVERAGE('RC'!G27,'RC'!H27) -> 268059.25 | H19: =AVERAGE('RC'!H27,'RC'!I27) -> 288834.78 | I19: =AVERAGE('RC'!I27,'RC'!J27) -> 298934.49 | ... K19: =AVERAGE('RC'!K27,'RC'!L27) -> 302513.68
A20: AACC finali | B20: ='RC'!B27 -> 1015828 | C20: ='RC'!C27 -> 559853 | D20: ='RC'!D27 -> 840441.5 | E20: ='RC'!E27 -> 668644.41 | F20: ='RC'!F27 -> 640993.98 | G20: ='RC'!G27 -> 253770.8 | H20: ='RC'!H27 -> 282347.7 | I20: ='RC'!I27 -> 295321.87 | ... K20: ='RC'!K27 -> 302513.68
A21: PACC medie (solo passivo) | B21: =AVERAGE('RC'!B66,'RC'!C66) -> 0 | C21: =AVERAGE('RC'!C66,'RC'!D66) -> 197514.59 | D21: =AVERAGE('RC'!D66,'RC'!E66) -> 284654.81 | E21: =AVERAGE('RC'!E66,'RC'!F66) -> 157903.42 | F21: =AVERAGE('RC'!F66,'RC'!G66) -> 122728.93 | G21: =AVERAGE('RC'!G66,'RC'!H66) -> 85942.221 | H21: =AVERAGE('RC'!H66,'RC'!I66) -> 57227.385 | I21: =AVERAGE('RC'!I66,'RC'!J66) -> 50312.014 | ... K21: =AVERAGE('RC'!K66,'RC'!L66) -> 49593.984
A22: PACC finali (solo passivo) | B22: ='RC'!B66 -> 0 | C22: ='RC'!C66 -> 0 | D22: ='RC'!D66 -> 395029.19 | E22: ='RC'!E66 -> 174280.43 | F22: ='RC'!F66 -> 141526.41 | G22: ='RC'!G66 -> 103931.45 | H22: ='RC'!H66 -> 67952.994 | I22: ='RC'!I66 -> 46501.775 | ... K22: ='RC'!K66 -> 49593.984
A23: ris gest str | B23: ='RC'!B145 -> -45154 | C23: ='RC'!C145 -> -7288 | D23: ='RC'!D145 -> -13681.922 | E23: ='RC'!E145 -> -129.521 | F23: ='RC'!F145 -> -781.991 | G23: ='RC'!G145 -> -20718.443 | H23: ='RC'!H145 -> -26525.807 | I23: ='RC'!I145 -> -17939.43 | ... K23: ='RC'!K145 -> 410.812
A24: PFN (ris gest fin) | B24: =B30-B31 -> 840524.5 | C24: =C30-C31 -> 207845.21 | D24: =D30-D31 -> 280960.7 | E24: =E30-E31 -> 647119.23 | F24: =F30-F31 -> 277420.77 | G24: =G30-G31 -> -53843.292 | H24: =H30-H31 -> 53384.411 | I24: =I30-I31 -> 118192.27 | ... K24: =K30-K31 -> 195238.04
A25: DEBn | B25: =IF(B24>0, B24, 0) -> 840524.5 | C25: =IF(C24>0, C24, 0) -> 207845.21 | D25: =IF(D24>0, D24, 0) -> 280960.7 | E25: =IF(E24>0, E24, 0) -> 647119.23 | F25: =IF(F24>0, F24, 0) -> 277420.77 | G25: =IF(G24>0, G24, 0) -> 0 | H25: =IF(H24>0, H24, 0) -> 53384.411 | I25: =IF(I24>0, I24, 0) -> 118192.27 | ... K25: =IF(K24>0, K24, 0) -> 195238.04
A26: LIQn | B26: =IF(B24<0, -B24, 0) -> 0 | C26: =IF(C24<0, C24, 0) -> 0 | D26: =IF(D24<0, D24, 0) -> 0 | E26: =IF(E24<0, E24, 0) -> 0 | F26: =IF(F24<0, F24, 0) -> 0 | G26: =IF(G24<0, G24, 0) -> -53843.292 | H26: =IF(H24<0, H24, 0) -> 0 | I26: =IF(I24<0, I24, 0) -> 0 | J26: =IF(J24<0, J24, 0) -> 0 | K26: =IF(K24<0, K24, 0) -> 0
A27: oneri finanziari | B27: ='RC'!B138 -> -355850 | C27: ='RC'!C138 -> -135795 | D27: ='RC'!D138 -> -57535.862 | E27: ='RC'!E138 -> -41740 | F27: ='RC'!F138 -> -69507.699 | G27: ='RC'!G138 -> -5823.751 | H27: ='RC'!H138 -> -4557.97 | I27: ='RC'!I138 -> -2723.619 | ... K27: ='RC'!K138 -> -4104.179
A28: interessi attivi | B28: ='RC'!B137 -> 29006 | C28: ='RC'!C137 -> 22875 | D28: ='RC'!D137 -> 7976.72 | E28: ='RC'!E137 -> 6455.647 | F28: ='RC'!F137 -> 7773.098 | G28: ='RC'!G137 -> 851.751 | H28: ='RC'!H137 -> 1026.672 | I28: ='RC'!I137 -> 1144.668 | ... K28: ='RC'!K137 -> 1503.171
A29: imposta | B29: ='RC'!B149 -> -8413 | C29: ='RC'!C149 -> -1433 | D29: ='RC'!D149 -> 8606.099 | E29: ='RC'!E149 -> -2857.205 | F29: ='RC'!F149 -> -291.302 | G29: ='RC'!G149 -> -12103.861 | H29: ='RC'!H149 -> -4717.252 | I29: ='RC'!I149 -> -12320.254 | ... K29: ='RC'!K149 -> -16284.208
A30: Debito lordo medio(pass. gest. fin) | B30: =AVERAGE('RC'!B73,'RC'!C73) -> 1154562 | C30: =AVERAGE('RC'!C73,'RC'!D73) -> 410914.79 | D30: =AVERAGE('RC'!D73,'RC'!E73) -> 389228.74 | E30: =AVERAGE('RC'!E73,'RC'!F73) -> 769999.07 | F30: =AVERAGE('RC'!F73,'RC'!G73) -> 400746.09 | G30: =AVERAGE('RC'!G73,'RC'!H73) -> 10308.73 | H30: =AVERAGE('RC'!H73,'RC'!I73) -> 88382.183 | I30: =AVERAGE('RC'!I73,'RC'!J73) -> 157896.44 | ... K30: =AVERAGE('RC'!K73,'RC'!L73) -> 203780.99
A31: Liq. lorda media(att. gest fin) | B31: =AVERAGE('RC'!B33,'RC'!C33) -> 314037.5 | C31: =AVERAGE('RC'!C33,'RC'!D33) -> 203069.58 | D31: =AVERAGE('RC'!D33,'RC'!E33) -> 108268.04 | E31: =AVERAGE('RC'!E33,'RC'!F33) -> 122879.84 | F31: =AVERAGE('RC'!F33,'RC'!G33) -> 123325.32 | G31: =AVERAGE('RC'!G33,'RC'!H33) -> 64152.022 | H31: =AVERAGE('RC'!H33,'RC'!I33) -> 34997.772 | I31: =AVERAGE('RC'!I33,'RC'!J33) -> 39704.177 | ... K31: =AVERAGE('RC'!K33,'RC'!L33) -> 8542.951
A32: Crediti commerciali medi | B32: =AVERAGE('RC'!B5:C5) -> 96044.5 | C32: =AVERAGE('RC'!C5:D5) -> 56958.359 | D32: =AVERAGE('RC'!D5:E5) -> 26710.566 | E32: =AVERAGE('RC'!E5:F5) -> 39400.695 | F32: =AVERAGE('RC'!F5:G5) -> 59586.303 | G32: =AVERAGE('RC'!G5:H5) -> 103188.57 | H32: =AVERAGE('RC'!H5:I5) -> 132760.16 | I32: =AVERAGE('RC'!I5:J5) -> 133917.28 | ... K32: =AVERAGE('RC'!K5:L5) -> 142030.01
A33: Debiti commerciali medi | B33: =AVERAGE('RC'!B48,'RC'!C48) -> 216267.5 | C33: =AVERAGE('RC'!C48,'RC'!D48) -> 217198.61 | D33: =AVERAGE('RC'!D48,'RC'!E48) -> 221159.3 | E33: =AVERAGE('RC'!E48,'RC'!F48) -> 162515.74 | F33: =AVERAGE('RC'!F48,'RC'!G48) -> 137310.17 | G33: =AVERAGE('RC'!G48,'RC'!H48) -> 168425.03 | H33: =AVERAGE('RC'!H48,'RC'!I48) -> 169754.29 | I33: =AVERAGE('RC'!I48,'RC'!J48) -> 141653.49 | ... K33: =AVERAGE('RC'!K48,'RC'!L48) -> 154222
A34: Rimanenze magazzino medie | B34: =AVERAGE('RC'!B6,'RC'!C6) -> 124615 | C34: =AVERAGE('RC'!C6,'RC'!D6) -> 135911.57 | D34: =AVERAGE('RC'!D6,'RC'!E6) -> 143120.67 | E34: =AVERAGE('RC'!E6,'RC'!F6) -> 127459.79 | F34: =AVERAGE('RC'!F6,'RC'!G6) -> 120911.66 | G34: =AVERAGE('RC'!G6,'RC'!H6) -> 142660.63 | H34: =AVERAGE('RC'!H6,'RC'!I6) -> 144228.21 | I34: =AVERAGE('RC'!I6,'RC'!J6) -> 126816.17 | ... K34: =AVERAGE('RC'!K6,'RC'!L6) -> 127191.34
A35: Rimanenze magazzino finali | B35: ='RC'!B6 -> 131166 | C35: ='RC'!C6 -> 118064 | D35: ='RC'!D6 -> 153759.14 | E35: ='RC'!E6 -> 132482.19 | F35: ='RC'!F6 -> 122437.39 | G35: ='RC'!G6 -> 119385.93 | H35: ='RC'!H6 -> 165935.34 | I35: ='RC'!I6 -> 122521.08 | ... K35: ='RC'!K6 -> 127191.34
A36: Attività a BT | B36: =AVERAGE('RC'!B8:C8)+AVERAGE('RC'!B19:C19)+AVERAGE('RC'!B30:C30) -> 524998.5 | C36: =AVERAGE('RC'!C8:D8)+AVERAGE('RC'!C19:D19)+AVERAGE('RC'!C30:D30) -> 365263.36 | D36: =AVERAGE('RC'!D8:E8)+AVERAGE('RC'!D19:E19)+AVERAGE('RC'!D30:E30) -> 226113.39 | E36: =AVERAGE('RC'!E8:F8)+AVERAGE('RC'!E19:F19)+AVERAGE('RC'!E30:F30) -> 206385.4 | F36: =AVERAGE('RC'!F8:G8)+AVERAGE('RC'!F19:G19)+AVERAGE('RC'!F30:G30) -> 201192.46 | G36: =AVERAGE('RC'!G8:H8)+AVERAGE('RC'!G19:H19)+AVERAGE('RC'!G30:H30) -> 253874.74 | H36: =AVERAGE('RC'!H8:I8)+AVERAGE('RC'!H19:I19)+AVERAGE('RC'!H30:I30) -> 285343.9 | I36: =AVERAGE('RC'!I8:J8)+AVERAGE('RC'!I19:J19)+AVERAGE('RC'!I30:J30) -> 266313.68 | ... K36: =AVERAGE('RC'!K8:L8)+AVERAGE('RC'!K19:L19)+AVERAGE('RC'!K30:L30) -> 281017.5
A37: Attività a BT finali | B37: ='RC'!B8+'RC'!B19+'RC'!B30 -> 565393 | C37: ='RC'!C8+'RC'!C19+'RC'!C30 -> 484604 | D37: ='RC'!D8+'RC'!D19+'RC'!D30 -> 245922.71 | E37: ='RC'!E8+'RC'!E19+'RC'!E30 -> 206304.07 | F37: ='RC'!F8+'RC'!F19+'RC'!F30 -> 206466.73 | G37: ='RC'!G8+'RC'!G19+'RC'!G30 -> 195918.2 | H37: ='RC'!H8+'RC'!H19+'RC'!H30 -> 311831.28 | I37: ='RC'!I8+'RC'!I19+'RC'!I30 -> 258856.51 | ... K37: ='RC'!K8+'RC'!K19+'RC'!K30 -> 281017.5
A38: Passività a BT medie | B38: =AVERAGE('RC'!B51:C51)+AVERAGE('RC'!B59:C59)+AVERAGE('RC'!B70:C70) -> 325521 | C38: =AVERAGE('RC'!C51:D51)+AVERAGE('RC'!C59:D59)+AVERAGE('RC'!C70:D70) -> 290790.8 | D38: =AVERAGE('RC'!D51:E51)+AVERAGE('RC'!D59:E59)+AVERAGE('RC'!D70:E70) -> 275177 | E38: =AVERAGE('RC'!E51:F51)+AVERAGE('RC'!E59:F59)+AVERAGE('RC'!E70:F70) -> 220668.01 | F38: =AVERAGE('RC'!F51:G51)+AVERAGE('RC'!F59:G59)+AVERAGE('RC'!F70:G70) -> 185816.17 | G38: =AVERAGE('RC'!G51:H51)+AVERAGE('RC'!G59:H59)+AVERAGE('RC'!G70:H70) -> 205673.93 | H38: =AVERAGE('RC'!H51:I51)+AVERAGE('RC'!H59:I59)+AVERAGE('RC'!H70:I70) -> 256891.31 | I38: =AVERAGE('RC'!I51:J51)+AVERAGE('RC'!I59:J59)+AVERAGE('RC'!I70:J70) -> 264163.13 | ... K38: =AVERAGE('RC'!K51:L51)+AVERAGE('RC'!K59:L59)+AVERAGE('RC'!K70:L70) -> 281006.04
A39: Passività a BT finali | B39: ='RC'!B51+'RC'!B59+'RC'!B70 -> 382681 | C39: ='RC'!C51+'RC'!C59+'RC'!C70 -> 268361 | D39: ='RC'!D51+'RC'!D59+'RC'!D70 -> 313220.59 | E39: ='RC'!E51+'RC'!E59+'RC'!E70 -> 237133.4 | F39: ='RC'!F51+'RC'!F59+'RC'!F70 -> 204202.61 | G39: ='RC'!G51+'RC'!G59+'RC'!G70 -> 167429.73 | H39: ='RC'!H51+'RC'!H59+'RC'!H70 -> 243918.12 | I39: ='RC'!I51+'RC'!I59+'RC'!I70 -> 269864.5 | ... K39: ='RC'!K51+'RC'!K59+'RC'!K70 -> 281006.04
A40: Passività operative consolidate medie | B40: =AVERAGE('RC'!B52,'RC'!C52) -> 0 | C40: =AVERAGE('RC'!C52,'RC'!D52) -> 0 | D40: =AVERAGE('RC'!D52,'RC'!E52) -> 0 | E40: =AVERAGE('RC'!E52,'RC'!F52) -> 0 | F40: =AVERAGE('RC'!F52,'RC'!G52) -> 0 | G40: =AVERAGE('RC'!G52,'RC'!H52) -> 0 | H40: =AVERAGE('RC'!H52,'RC'!I52) -> 0 | I40: =AVERAGE('RC'!I52,'RC'!J52) -> 0 | ... K40: =AVERAGE('RC'!K52,'RC'!L52) -> 0
A41: Passività operative consolidate finali | B41: ='RC'!B52 -> 0 | C41: ='RC'!C52 -> 0 | D41: ='RC'!D52 -> 0 | E41: ='RC'!E52 -> 0 | F41: ='RC'!F52 -> 0 | G41: ='RC'!G52 -> 0 | H41: ='RC'!H52 -> 0 | I41: ='RC'!I52 -> 0 | ... K41: ='RC'!K52 -> 0
A42: debiti strutturali m/l medi | B42: =AVERAGE('RC'!B69,'RC'!C69) -> 1064574 | C42: =AVERAGE('RC'!C69,'RC'!D69) -> 351759.5 | D42: =AVERAGE('RC'!D69,'RC'!E69) -> 362808.59 | E42: =AVERAGE('RC'!E69,'RC'!F69) -> 753054.67 | F42: =AVERAGE('RC'!F69,'RC'!G69) -> 390246.08 | G42: =AVERAGE('RC'!G69,'RC'!H69) -> 0 | H42: =AVERAGE('RC'!H69,'RC'!I69) -> 27889.978 | I42: =AVERAGE('RC'!I69,'RC'!J69) -> 67824.856 | ... K42: =AVERAGE('RC'!K69,'RC'!L69) -> 103275.9
A43: debiti strutturali m/l finali | B43: ='RC'!B69 -> 1425629 | C43: ='RC'!C69 -> 703519 | D43: ='RC'!D69 -> 0 | E43: ='RC'!E69 -> 725617.18 | F43: ='RC'!F69 -> 780492.17 | G43: ='RC'!G69 -> 0 | H43: ='RC'!H69 -> 0 | I43: ='RC'!I69 -> 55779.956 | ... K43: ='RC'!K69 -> 103275.9
A44: immobilizzazioni operative | B44: =(('RC'!B12+'RC'!B15)+'RC'!C12+'RC'!C15)/2 -> 1075360 | C44: =(('RC'!C12+'RC'!C15)+'RC'!D12+'RC'!D15)/2 -> 316264.07 | D44: =(('RC'!D12+'RC'!D15)+'RC'!E12+'RC'!E15)/2 -> 315835.57 | E44: =(('RC'!E12+'RC'!E15)+'RC'!F12+'RC'!F15)/2 -> 309139.94 | F44: =(('RC'!F12+'RC'!F15)+'RC'!G12+'RC'!G15)/2 -> 238054.37 | G44: =(('RC'!G12+'RC'!G15)+'RC'!H12+'RC'!H15)/2 -> 164631.95 | H44: =(('RC'!H12+'RC'!H15)+'RC'!I12+'RC'!I15)/2 -> 166387.26 | I44: =(('RC'!I12+'RC'!I15)+'RC'!J12+'RC'!J15)/2 -> 165451.91 | ... K44: =(('RC'!K12+'RC'!K15)+'RC'!L12+'RC'!L15)/2 -> 84733.377
A45: immobilizzazioni operative finali | B45: ='RC'!B12 -> 1840005 | C45: ='RC'!C12 -> 310715 | D45: ='RC'!D12 -> 311031.01 | E45: ='RC'!E12 -> 309514.56 | F45: ='RC'!F12 -> 308051.2 | G45: ='RC'!G12 -> 167362.05 | H45: ='RC'!H12 -> 161295.08 | I45: ='RC'!I12 -> 170919.21 | ... K45: ='RC'!K12 -> 169179.91
A46: CP capitale proprio medio | B46: =AVERAGE('RC'!B84,'RC'!C84) -> 1239821.5 | C46: =AVERAGE('RC'!C84,'RC'!D84) -> 697469.54 | D46: =AVERAGE('RC'!D84,'RC'!E84) -> 435471.37 | E46: =AVERAGE('RC'!E84,'RC'!F84) -> 119798.66 | F46: =AVERAGE('RC'!F84,'RC'!G84) -> 273355.52 | G46: =AVERAGE('RC'!G84,'RC'!H84) -> 427166.09 | H46: =AVERAGE('RC'!H84,'RC'!I84) -> 403336.74 | I46: =AVERAGE('RC'!I84,'RC'!J84) -> 361329.1 | ... K46: =AVERAGE('RC'!K84,'RC'!L84) -> 307236.2
A47: CP init | B47: ='RC'!C84 -> 638820 | C47: ='RC'!D84 -> 756119.07 | D47: ='RC'!E84 -> 114823.67 | E47: ='RC'!F84 -> 124773.66 | F47: ='RC'!G84 -> 421937.37 | G47: ='RC'!H84 -> 432394.81 | H47: ='RC'!I84 -> 374278.67 | I47: ='RC'!J84 -> 348379.53 | ... K47: ='RC'!L84 -> 0
A48: CP fin | B48: ='RC'!B84 -> 1840823 | C48: ='RC'!C84 -> 638820 | D48: ='RC'!D84 -> 756119.07 | E48: ='RC'!E84 -> 114823.67 | F48: ='RC'!F84 -> 124773.66 | G48: ='RC'!G84 -> 421937.37 | H48: ='RC'!H84 -> 432394.81 | I48: ='RC'!I84 -> 374278.67 | ... K48: ='RC'!K84 -> 307236.2
A49: DIV t | B49: ='RC'!C82+'RC'!C79-'RC'!B79 -> -1088945 | C49: ='RC'!D82+'RC'!D79-'RC'!C79 -> -31171.914 | D49: ='RC'!E82+'RC'!E79-'RC'!D79 -> -4500 | E49: ='RC'!F82+'RC'!F79-'RC'!E79 -> 0 | F49: ='RC'!G82+'RC'!G79-'RC'!F79 -> 172042.81 | G49: ='RC'!H82+'RC'!H79-'RC'!G79 -> 4000.002 | H49: ='RC'!I82+'RC'!I79-'RC'!H79 -> 28000.154 | I49: ='RC'!J82+'RC'!J79-'RC'!I79 -> 30000.165 | ... K49: ='RC'!L82+'RC'!L79-'RC'!K79 -> -172816.59
A50: Aumento finanziamenti netti da soci e controllanti t e t-1 | B50: ='RC'!B76-'RC'!C76 -> 437975 | C50: ='RC'!C76-'RC'!D76 -> -68969.353 | D50: ='RC'!D76-'RC'!E76 -> 621855.21 | E50: ='RC'!E76-'RC'!F76 -> -2196.273 | F50: ='RC'!F76-'RC'!G76 -> -77071.239 | G50: ='RC'!G76-'RC'!H76 -> -6893.69 | H50: ='RC'!H76-'RC'!I76 -> 80208.762 | I50: ='RC'!I76-'RC'!J76 -> 6933.888 | ... K50: ='RC'!K76-'RC'!L76 -> -11756.08
A51: Aumento accantonamenti e perdite precedenti (se neg aumento utile) | B51: =RF!C43-RF!D43 -> 1024653 | C51: =RF!D43-RF!E43 -> 48924.385 | D51: =RF!E43-RF!F43 -> -6836.372 | E51: =RF!F43-RF!G43 -> -55428.652 | F51: =RF!G43-RF!H43 -> -171606.56 | G51: =RF!H43-RF!I43 -> 1907.527 | H51: =RF!I43-RF!J43 -> 20965.269 | I51: =RF!J43-RF!K43 -> 24653.505 | ... K51: =RF!L43-RF!M43 -> 172816.59
A52: var reddito di esercizio | B52: ='RC'!B82-'RC'!C82 -> -260625 | C52: ='RC'!C82-'RC'!D82 -> -82044.471 | D52: ='RC'!D82-'RC'!E82 -> 29088.843 | E52: ='RC'!E82-'RC'!F82 -> 44092.28 | F52: ='RC'!F82-'RC'!G82 -> -55864.903 | G52: ='RC'!G82-'RC'!H82 -> -5471.278 | H52: ='RC'!H82-'RC'!I82 -> -43057.894 | I52: ='RC'!I82-'RC'!J82 -> -5688.247 | ... K52: ='RC'!K82-'RC'!L82 -> 38874.43
A53: var CPn | B53: ='RC'!B77-'RC'!C77 -> 764028 | C53: ='RC'!C77-'RC'!D77 -> -48329.721 | D53: ='RC'!D77-'RC'!E77 -> 19440.2 | E53: ='RC'!E77-'RC'!F77 -> -7753.72 | F53: ='RC'!F77-'RC'!G77 -> -220092.47 | G53: ='RC'!G77-'RC'!H77 -> -3563.751 | H53: ='RC'!H77-'RC'!I77 -> -22092.625 | I53: ='RC'!I77-'RC'!J77 -> 18965.258 | ... K53: ='RC'!K77-'RC'!L77 -> 318992.28
A56: INDICATORI FINANZIARI | B56: =B1 -> 31/12/2024 | C56: =C1 -> 31/12/2023 | D56: =D1 -> 31/12/2022 | E56: =E1 -> 31/12/2021 | F56: =F1 -> 31/12/2020 | G56: =G1 -> 31/12/2019 | H56: =H1 -> 31/12/2018 | I56: =I1 -> 31/12/2017 | ... K56: =K1 -> 31/12/2015
A57: Quozienti di redditività
A58: Reddito operativo | B58: =B4 -> 60536 | C58: =C4 -> 57190 | D58: =D4 -> 11294.284 | E58: =E4 -> 9288.812 | F58: =F4 -> 3264.182 | G58: =G4 -> 30663.78 | H58: =H4 -> 33717.566 | I58: =I4 -> 77298.709 | ... K58: =K4 -> 51933.84
A59: /Ricavi | B59: =B7 -> 700351 | C59: =C7 -> 567524 | D59: =D7 -> 731617.37 | E59: =E7 -> 575309.43 | F59: =F7 -> 470766.3 | G59: =G7 -> 599353.35 | H59: =H7 -> 601111.28 | I59: =I7 -> 658456.38 | ... K59: =K7 -> 617897.5
A60: ROS | B60: =B58/B59 -> 0.086436658 | C60: =C58/C59 -> 0.10077107 | D60: =D58/D59 -> 0.015437419 | E60: =E58/E59 -> 0.016145767 | F60: =F58/F59 -> 0.0069337631 | G60: =G58/G59 -> 0.051161439 | H60: =H58/H59 -> 0.056092053 | I60: =I58/I59 -> 0.11739382 | ... K60: =K58/K59 -> 0.08404928
A62: Reddito operativo | B62: =B4 -> 60536 | C62: =C4 -> 57190 | D62: =D4 -> 11294.284 | E62: =E4 -> 9288.812 | F62: =F4 -> 3264.182 | G62: =G4 -> 30663.78 | H62: =H4 -> 33717.566 | I62: =I4 -> 77298.709 | ... K62: =K4 -> 51933.84
A63: /AON* | B63: =B14 -> 1292505.5 | C63: =C14 -> 402682.09 | D63: =D14 -> 246543.92 | E63: =E14 -> 270002.12 | F63: =F14 -> 226122.83 | G63: =G14 -> 191205.77 | H63: =H14 -> 225113.76 | I63: =I14 -> 230898.89 | ... K63: =K14 -> 249554.54
A64: ROI | B64: =B62/B63 -> 0.046836164 | C64: =C62/C63 -> 0.14202271 | D64: =D62/D63 -> 0.045810434 | E64: =E62/E63 -> 0.034402738 | F64: =F62/F63 -> 0.014435438 | G64: =G62/G63 -> 0.16037058 | H64: =H62/H63 -> 0.14978012 | I64: =I62/I63 -> 0.33477297 | ... K64: =K62/K63 -> 0.20810617
A66: Oneri finanziari | B66: =-B27 -> 355850 | C66: =-C27 -> 135795 | D66: =-D27 -> 57535.862 | E66: =-E27 -> 41740 | F66: =-F27 -> 69507.699 | G66: =-G27 -> 5823.751 | H66: =-H27 -> 4557.97 | I66: =-I27 -> 2723.619 | ... K66: =-K27 -> 4104.179
A67: /Debito lordo | B67: =B30 -> 1154562 | C67: =C30 -> 410914.79 | D67: =D30 -> 389228.74 | E67: =E30 -> 769999.07 | F67: =F30 -> 400746.09 | G67: =G30 -> 10308.73 | H67: =H30 -> 88382.183 | I67: =I30 -> 157896.44 | ... K67: =K30 -> 203780.99
A68: ROD | B68: =B66/B67 -> 0.30821212 | C68: =C66/C67 -> 0.33046998 | D68: =D66/D67 -> 0.14782018 | E68: =E66/E67 -> 0.054207858 | F68: =F66/F67 -> 0.17344573 | G68: =G66/G67 -> 0.5649339 | H68: =H66/H67 -> 0.051571141 | I68: =I66/I67 -> 0.0172494 | ... K68: =K66/K67 -> 0.020140146
A70: Interessi attivi | B70: =B28 -> 29006 | C70: =C28 -> 22875 | D70: =D28 -> 7976.72 | E70: =E28 -> 6455.647 | F70: =F28 -> 7773.098 | G70: =G28 -> 851.751 | H70: =H28 -> 1026.672 | I70: =I28 -> 1144.668 | ... K70: =K28 -> 1503.171
A71: /Liquidità lorda | B71: =B31 -> 314037.5 | C71: =C31 -> 203069.58 | D71: =D31 -> 108268.04 | E71: =E31 -> 122879.84 | F71: =F31 -> 123325.32 | G71: =G31 -> 64152.022 | H71: =H31 -> 34997.772 | I71: =I31 -> 39704.177 | ... K71: =K31 -> 8542.951
A72: ROL | B72: =B70/B71 -> 0.092364765 | C72: =C70/C71 -> 0.11264612 | D72: =D70/D71 -> 0.073675667 | E72: =E70/E71 -> 0.052536257 | F72: =F70/F71 -> 0.063029216 | G72: =G70/G71 -> 0.013277072 | H72: =H70/H71 -> 0.029335353 | I72: =I70/I71 -> 0.028829914 | ... K72: =K70/K71 -> 0.17595454
A74: Reddittività att.acc | B74: =B17 -> 2000 | C74: =C17 -> 475 | D74: =D17 -> 53000 | E74: =E17 -> 15827.805 | F74: =F17 -> 7825.268 | G74: =G17 -> 6793.747 | H74: =H17 -> 6812.897 | I74: =I17 -> 7560.932 | ... K74: =K17 -> 6245.694
A75: /AACCn | B75: =B18 -> 787840.5 | C75: =C18 -> 502632.66 | D75: =D18 -> 469888.15 | E75: =E18 -> 496915.78 | F75: =F18 -> 324653.46 | G75: =G18 -> 182117.03 | H75: =H18 -> 231607.4 | I75: =I18 -> 248622.48 | ... K75: =K18 -> 252919.7
A76: ROAACC | B76: =B74/B75 -> 0.0025385849 | C76: =C74/C75 -> 0.00094502415 | D76: =D74/D75 -> 0.1127928 | E76: =E74/E75 -> 0.031852088 | F76: =F74/F75 -> 0.024103448 | G76: =G74/G75 -> 0.037304293 | H76: =H74/H75 -> 0.029415714 | I76: =I74/I75 -> 0.030411297 | ... K76: =K74/K75 -> 0.024694375
A78: Reddito netto | B78: =B6 -> -324917 | C78: =C6 -> -64292 | D78: =D6 -> 17752.471 | E78: =E6 -> -11336.372 | F78: =F6 -> -55428.652 | G78: =G6 -> 436.251 | H78: =H6 -> 5907.529 | I78: =I6 -> 48965.423 | ... K78: =K6 -> 38874.43
A79: /CP | B79: =B46 -> 1239821.5 | C79: =C46 -> 697469.54 | D79: =D46 -> 435471.37 | E79: =E46 -> 119798.66 | F79: =F46 -> 273355.52 | G79: =G46 -> 427166.09 | H79: =H46 -> 403336.74 | I79: =I46 -> 361329.1 | ... K79: =K46 -> 307236.2
A80: ROE netto | B80: =B78/B79 -> -0.26206756 | C80: =C78/C79 -> -0.092178936 | D80: =D78/D79 -> 0.040766104 | E80: =E78/E79 -> -0.094628534 | F80: =F78/F79 -> -0.2027713 | G80: =G78/G79 -> 0.0010212679 | H80: =H78/H79 -> 0.014646642 | I80: =I78/I79 -> 0.13551475 | ... K80: =K78/K79 -> 0.12652946
A82: RLA | B82: =B3 -> -271350 | C82: =C3 -> -55571 | D82: =D3 -> 22828.294 | E82: =E3 -> -8349.646 | F82: =F3 -> -54355.359 | G82: =G3 -> 33258.555 | H82: =H3 -> 37150.588 | I82: =I3 -> 79225.107 | ... K82: =K3 -> 54747.826
A83: /CP | B83: =B46 -> 1239821.5 | C83: =C46 -> 697469.54 | D83: =D46 -> 435471.37 | E83: =E46 -> 119798.66 | F83: =F46 -> 273355.52 | G83: =G46 -> 427166.09 | H83: =H46 -> 403336.74 | I83: =I46 -> 361329.1 | ... K83: =K46 -> 307236.2
A84: ROE lordo | B84: =B82/B83 -> -0.21886215 | C84: =C82/C83 -> -0.079675164 | D84: =D82/D83 -> 0.052422032 | E84: =E82/E83 -> -0.069697321 | F84: =F82/F83 -> -0.19884493 | G84: =G82/G83 -> 0.077858603 | H84: =H82/H83 -> 0.092108117 | I84: =I82/I83 -> 0.21926024 | ... K84: =K82/K83 -> 0.17819458
A86: Prima scomposizione ROE lordo:
A87: ROI | B87: =B64 -> 0.046836164 | C87: =C64 -> 0.14202271 | D87: =D64 -> 0.045810434 | E87: =E64 -> 0.034402738 | F87: =F64 -> 0.014435438 | G87: =G64 -> 0.16037058 | H87: =H64 -> 0.14978012 | I87: =I64 -> 0.33477297 | ... K87: =K64 -> 0.20810617
A88: +effetto Leva finanziaria | B88: =(B87-B68)*(B30/B46) -> -0.24340177 | C88: =(C87-C68)*(C30/C46) -> -0.11102387 | D88: =(D87-D68)*(D30/D46) -> -0.091177347 | E88: =(E87-E68)*(E30/E46) -> -0.12729628 | F88: =(F87-F68)*(F30/F46) -> -0.23311311 | G88: =(G87-G68)*(G30/G46) -> -0.0097632609 | H88: =(H87-H68)*(H30/H46) -> 0.021520291 | I88: =(I87-I68)*(I30/I46) -> 0.13875396 | ... K88: =(K87-K68)*(K30/K46) -> 0.12467249
A89: +effetto Liquidità | B89: =(B72-B87)*(B31/B46) -> 0.011532054 | C89: =(C72-C87)*(C31/C46) -> -0.008553049 | D89: =(D72-D87)*(D31/D46) -> 0.0069279275 | E89: =(E72-E87)*(E31/E46) -> 0.018599907 | F89: =(F72-F87)*(F31/F46) -> 0.021923256 | G89: =(G72-G87)*(G31/G46) -> -0.022090578 | H89: =(H72-H87)*(H31/H46) -> -0.010451065 | I89: =(I72-I87)*(I31/I46) -> -0.033618154 | ... K89: =(K72-K87)*(K31/K46) -> -0.00089400209
A90: +effetto Attività accessorie | B90: =(B76-B87)*(B75/B46) -> -0.028148751 | C90: =(C76-C87)*(C75/C46) -> -0.10166788 | D90: =(D76-D87)*(D75/D46) -> 0.072276209 | E90: =(E76-E87)*(E75/E46) -> -0.010579903 | F90: =(F76-F87)*(F75/F46) -> 0.011482311 | G90: =(G76-G87)*(G75/G46) -> -0.052467802 | H90: =(H76-H87)*(H75/H46) -> -0.069116656 | I90: =(I76-I87)*(I75/I46) -> -0.20942446 | ... K90: =(K76-K87)*(K75/K46) -> -0.1509863
A91: ROE lordo | B91: =SUM(B87:B90) -> -0.2131823 | C91: =SUM(C87:C90) -> -0.079222098 | D91: =SUM(D87:D90) -> 0.033837223 | E91: =SUM(E87:E90) -> -0.084873534 | F91: =SUM(F87:F90) -> -0.1852721 | G91: =SUM(G87:G90) -> 0.076048937 | H91: =SUM(H87:H90) -> 0.091732691 | I91: =SUM(I87:I90) -> 0.23048431 | ... K91: =SUM(K87:K90) -> 0.18089836
A93: Seconda scomposizione ROE lordo:
A94: +rendimento AON* | B94: =B64*(B14/B46) -> 0.048826383 | C94: =C64*(C14/C46) -> 0.081996413 | D94: =D64*(D14/D46) -> 0.025935767 | E94: =E64*(E14/E46) -> 0.077536858 | F94: =F64*(F14/F46) -> 0.01194116 | G94: =G64*(G14/G46) -> 0.071784209 | H94: =H64*(H14/H46) -> 0.083596564 | I94: =I64*(I14/I46) -> 0.21392882 | ... K94: =K64*(K14/K46) -> 0.16903555
A95: +effetto costo del debito | B95: =-B68*(B30/B46) -> -0.28701712 | C95: =-C68*(C30/C46) -> -0.19469668 | D95: =-D68*(D30/D46) -> -0.13212318 | E95: =-E68*(E30/E46) -> -0.34841791 | F95: =-F68*(F30/F46) -> -0.25427582 | G95: =-G68*(G30/G46) -> -0.013633458 | H95: =-H68*(H30/H46) -> -0.011300657 | I95: =-I68*(I30/I46) -> -0.0075377792 | ... K95: =-K68*(K30/K46) -> -0.013358383
A96: +rendimento liquidità | B96: =B72*(B31/B46) -> 0.023395303 | C96: =C72*(C31/C46) -> 0.032797131 | D96: =D72*(D31/D46) -> 0.018317438 | E96: =E72*(E31/E46) -> 0.053887471 | F96: =F72*(F31/F46) -> 0.028435856 | G96: =G72*(G31/G46) -> 0.0019939574 | H96: =H72*(H31/H46) -> 0.0025454462 | I96: =I72*(I31/I46) -> 0.0031679375 | ... K96: =K72*(K31/K46) -> 0.0048925582
A97: +rendimento att.accessorie | B97: =B76*(B18/B46) -> 0.0016131354 | C97: =C76*(C18/C46) -> 0.00068103333 | D97: =D76*(D18/D46) -> 0.1217072 | E97: =E76*(E18/E46) -> 0.13212005 | F97: =F76*(F18/F46) -> 0.028626706 | G97: =G76*(G18/G46) -> 0.015904228 | H97: =H76*(H18/H46) -> 0.016891337 | I97: =I76*(I18/I46) -> 0.020925334 | ... K97: =K76*(K18/K46) -> 0.02032864
A98: ROE lordo | B98: =SUM(B94:B97) -> -0.2131823 | C98: =SUM(C94:C97) -> -0.079222098 | D98: =SUM(D94:D97) -> 0.033837223 | E98: =SUM(E94:E97) -> -0.084873534 | F98: =SUM(F94:F97) -> -0.1852721 | G98: =SUM(G94:G97) -> 0.076048937 | H98: =SUM(H94:H97) -> 0.091732691 | I98: =SUM(I94:I97) -> 0.23048431 | ... K98: =SUM(K94:K97) -> 0.18089836
A100: check ROE lordo 1: | B100: =B84-B91 -> -0.0056798499 | C100: =C84-C91 -> -0.00045306638 | D100: =D84-D91 -> 0.018584808 | E100: =E84-E91 -> 0.015176213 | F100: =F84-F91 -> -0.01357283 | G100: =G84-G91 -> 0.0018096661 | H100: =H84-H91 -> 0.00037542575 | I100: =I84-I91 -> -0.01122407 | ... K100: =K84-K91 -> -0.0027037829
A101: check ROE lordo 2: | B101: =B84-B98 -> -0.0056798499 | C101: =C84-C98 -> -0.00045306638 | D101: =D84-D98 -> 0.018584808 | E101: =E84-E98 -> 0.015176213 | F101: =F84-F98 -> -0.01357283 | G101: =G84-G98 -> 0.0018096661 | H101: =H84-H98 -> 0.00037542575 | I101: =I84-I98 -> -0.01122407 | ... K101: =K84-K98 -> -0.0027037829
A103: Da lordo a netto:
A104: RLA | B104: =B3 -> -271350 | C104: =C3 -> -55571 | D104: =D3 -> 22828.294 | E104: =E3 -> -8349.646 | F104: =F3 -> -54355.359 | G104: =G3 -> 33258.555 | H104: =H3 -> 37150.588 | I104: =I3 -> 79225.107 | ... K104: =K3 -> 54747.826
A105: /CP | B105: =B46 -> 1239821.5 | C105: =C46 -> 697469.54 | D105: =D46 -> 435471.37 | E105: =E46 -> 119798.66 | F105: =F46 -> 273355.52 | G105: =G46 -> 427166.09 | H105: =H46 -> 403336.74 | I105: =I46 -> 361329.1 | ... K105: =K46 -> 307236.2
A106: x (RLA+ris str)/RLA | B106: =(B104+B23)/B104 -> 1.166405 | C106: =(C104+C23)/C104 -> 1.1311475 | D106: =(D104+D23)/D104 -> 0.40065946 | E106: =(E104+E23)/E104 -> 1.0155122 | F106: =(F104+F23)/F104 -> 1.0143866 | G106: =(G104+G23)/G104 -> 0.37704921 | H106: =(H104+H23)/H104 -> 0.28599227 | I106: =(I104+I23)/I104 -> 0.77356383 | ... K106: =(K104+K23)/K104 -> 1.0075037
A107: x (RL+tax)/RL | B107: =(B3+B23+B29)/(B3+B23) -> 1.026581 | C107: =(C3+C23+C29)/(C3+C23) -> 1.0227971 | D107: =(D3+D23+D29)/(D3+D23) -> 1.9409303 | E107: =(E3+E23+E29)/(E3+E23) -> 1.3369677 | F107: =(F3+F23+F29)/(F3+F23) -> 1.0052832 | G107: =(G3+G23+G29)/(G3+G23) -> 0.034788445 | H107: =(H3+H23+H29)/(H3+H23) -> 0.55601419 | I107: =(I3+I23+I29)/(I3+I23) -> 0.79897009 | ... K107: =(K3+K23+K29)/(K3+K23) -> 0.70477502
A108: '= Reddito netto/CP check | B108: =B6/B46 -> -0.26206756 | C108: =C6/C46 -> -0.092178936 | D108: =D6/D46 -> 0.040766104 | E108: =E6/E46 -> -0.094628534 | F108: =F6/F46 -> -0.2027713 | G108: =G6/G46 -> 0.0010212679 | H108: =H6/H46 -> 0.014646642 | I108: =I6/I46 -> 0.13551475 | ... K108: =K6/K46 -> 0.12652946
A109: ROE netto | B109: =(B104/B105)*B106*B107 -> -0.26206756 | C109: =(C104/C105)*C106*C107 -> -0.092178936 | D109: =(D104/D105)*D106*D107 -> 0.040766104 | E109: =(E104/E105)*E106*E107 -> -0.094628534 | F109: =(F104/F105)*F106*F107 -> -0.2027713 | G109: =(G104/G105)*G106*G107 -> 0.0010212679 | H109: =(H104/H105)*H106*H107 -> 0.014646642 | I109: =(I104/I105)*I106*I107 -> 0.13551475 | ... K109: =(K104/K105)*K106*K107 -> 0.12652946
A110: check ROE netto | B110: =B109-B80 -> 0 | C110: =C109-C80 -> 0 | D110: =D109-D80 -> 0 | E110: =E109-E80 -> 0 | F110: =F109-F80 -> 0 | G110: =G109-G80 -> 8.4567769e-18 | H110: =H109-H80 -> 0 | I110: =I109-I80 -> 0 | ... K110: =K109-K80 -> 0
A113: INDICATORI FINANZIARI
A114: Quozienti di rotazione dell'attivo netto
...

Sheet grph
B3: Quozienti di redditività
B80: Quozienti di rotazione dell'attivo netto
B135: Quozienti di liquidità ed equilibrio fonti/impieghi
B218: Indicatori di robustezza
